Workbook
Name _xlfn_BAHTTEXT: none
Name _xlfn_IFERROR: none
Name _xlfn_SINGLE: none
Name DB: Intro!$D$15:$D$16
Name Excel_BuiltIn__FilterDatabase: Other_SCH09!$A$1:$A$4
Name Excel_BuiltIn__FilterDatabase: Tel_SCH03!$A$1:$A$4
Name month: #REF!
Name PRD: Intro!$D$13
Name Print_Area_MI: #REF!
Name RV: Intro!$D$17
Name YR: Intro!$D$14

Sheet GLAC
A1: GLACNO | B1: GLAC_NAME | C1: GLAC_CRDR | D1: GLAC_BI | E1: GLAC_CBFWD | F1: GLAC_CB01 | G1: GLAC_CB02 | H1: GLAC_CB03 | I1: GLAC_CB04 | J1: GLAC_CB05 | K1: GLAC_CB06 | L1: GLAC_CB07 | M1: GLAC_CB08 | N1: GLAC_CB09 | O1: GLAC_CB10 | P1: GLAC_CB11 | Q1: GLAC_CB12 | R1: GLAC_CB13 | S1: GLAC_CB14 | T1: GLAC_CB15 | U1: GLAC_CB16 | V1: GLAC_CB17 | W1: GLAC_CB18 | X1: GLAC_CB19 | Y1: GLAC_CB20 | Z1: GLAC_CB21 | AA1: GLAC_CB22 | AB1: GLAC_CB23 | AC1: GLAC_CB24 | AD1: GLAC_CB25 | AE1: GLAC_CB26 | AF1: GLAC_PBFWD | AG1: GLAC_PB01 | AH1: GLAC_PB02 | AI1: GLAC_PB03 | AJ1: GLAC_PB04 | AK1: GLAC_PB05 | AL1: GLAC_PB06 | AM1: GLAC_PB07 | AN1: GLAC_PB08 | AO1: GLAC_PB09 | AP1: GLAC_PB10 | AQ1: GLAC_PB11 | AR1: GLAC_PB12 | AS1: GLAC_PB13 | AT1: GLAC_CBG01 | AU1: GLAC_CBG02 | AV1: GLAC_CBG03 | AW1: GLAC_CBG04 | AX1: GLAC_CBG05 | AY1: GLAC_CBG06 | AZ1: GLAC_CBG07 | BA1: GLAC_CBG08 | BB1: GLAC_CBG09 | BC1: GLAC_CBG10 | BD1: GLAC_CBG11 | BE1: GLAC_CBG12 | BF1: GLAC_CBG13 | BG1: GLAC_PBG01 | BH1: GLAC_PBG02 | BI1: GLAC_PBG03 | BJ1: GLAC_PBG04 | BK1: GLAC_PBG05 | BL1: GLAC_PBG06 | BM1: GLAC_PBG07 | BN1: GLAC_PBG08 | BO1: GLAC_PBG09 | BP1: GLAC_PBG10 | BQ1: GLAC_PBG11 | BR1: GLAC_PBG12 | BS1: GLAC_PBG13 | BT1: GLAC_NBG01 | BU1: GLAC_NBG02 | BV1: GLAC_NBG03 | BW1: GLAC_NBG04 | BX1: GLAC_NBG05 | BY1: GLAC_NBG06 | BZ1: GLAC_NBG07 | CA1: GLAC_NBG08 | CB1: GLAC_NBG09 | CC1: GLAC_NBG10 | CD1: GLAC_NBG11 | CE1: GLAC_NBG12 | CF1: GLAC_NBG13 | CG1: CBG01R1 | CH1: CBG02R1 | CI1: CBG03R1 | CJ1: CBG04R1 | CK1: CBG05R1 | CL1: CBG06R1 | CM1: CBG07R1 | CN1: CBG08R1 | CO1: CBG09R1 | CP1: CBG10R1 | CQ1: CBG11R1 | CR1: CBG12R1 | CS1: CBG13R1 | CT1: CBG01R2 | CU1: CBG02R2 | CV1: CBG03R2 | CW1: CBG04R2 | CX1: CBG05R2 | CY1: CBG06R2 | CZ1: CBG07R2 | DB1: CBG09R2 | DC1: CBG10R2 | DD1: CBG11R2 | DE1: CBG12R2 | DF1: CBG13R2 | DG1: CBG01R3 | DH1: CBG02R3 | DI1: CBG03R3 | DJ1: CBG04R3 | DK1: CBG05R3 | DL1: CBG06R3 | DM1: CBG07R3 | DN1: CBG08R3 | DO1: CBG09R3 | DP1: CBG10R3 | DQ1: CBG11R3 | DR1: CBG12R3 | DS1: CBG13R3 | DT1: CBG01R4 | DU1: CBG02R4 | DV1: CBG03R4 | DW1: CBG04R4 | DX1: CBG05R4 | DY1: CBG06R4 | DZ1: CBG07R4 | EA1: CBG08R4 | EB1: CBG09R4 | EC1: CBG10R4 | ED1: CBG11R4 | EE1: CBG12R4 | EF1: CBG13R4
A2: 100*** | B2: ***ASSETS*** | C2: D | D2: H | E2: 0 | F2: 0 | G2: 0 | H2: 0 | I2: 0 | J2: 0 | K2: 0 | L2: 0 | M2: 0 | N2: 0 | O2: 0 | P2: 0 | Q2: 0 | R2: 0 | S2: 0 | T2: 0 | U2: 0 | V2: 0 | W2: 0 | X2: 0 | Y2: 0 | Z2: 0 | AA2: 0 | AB2: 0 | AC2: 0 | AD2: 0 | AE2: 0 | AF2: 0 | AG2: 0 | AH2: 0 | AI2: 0 | AJ2: 0 | AK2: 0 | AL2: 0 | AM2: 0 | AN2: 0 | AO2: 0 | AP2: 0 | AQ2: 0 | AR2: 0 | AS2: 0 | AT2: 0 | AU2: 0 | AV2: 0 | AW2: 0 | AX2: 0 | AY2: 0 | AZ2: 0 | BA2: 0 | BB2: 0 | BC2: 0 | BD2: 0 | BE2: 0 | BF2: 0 | BG2: 0 | BH2: 0 | BI2: 0 | BJ2: 0 | BK2: 0 | BL2: 0 | BM2: 0 | BN2: 0 | BO2: 0 | BP2: 0 | BQ2: 0 | BR2: 0 | BS2: 0 | BT2: 0 | BU2: 0 | BV2: 0 | BW2: 0 | BX2: 0 | BY2: 0 | BZ2: 0 | CA2: 0 | CB2: 0 | CC2: 0 | CD2: 0 | CE2: 0 | CF2: 0 | CG2: 0 | CH2: 0 | CI2: 0 | CJ2: 0 | CK2: 0 | CL2: 0 | CM2: 0 | CN2: 0 | CO2: 0 | CP2: 0 | CQ2: 0 | CR2: 0 | CS2: 0 | CT2: 0 | CU2: 0 | CV2: 0 | CW2: 0 | CX2: 0 | CY2: 0 | CZ2: 0 | DB2: 0 | DC2: 0 | DD2: 0 | DE2: 0 | DF2: 0 | DG2: 0 | DH2: 0 | DI2: 0 | DJ2: 0 | DK2: 0 | DL2: 0 | DM2: 0 | DN2: 0 | DO2: 0 | DP2: 0 | DQ2: 0 | DR2: 0 | DS2: 0 | DT2: 0 | DU2: 0 | DV2: 0 | DW2: 0 | DX2: 0 | DY2: 0 | DZ2: 0 | EA2: 0 | EB2: 0 | EC2: 0 | ED2: 0 | EE2: 0 | EF2: 0
A3: 110*** | B3: ***CURRENT ASSETS*** | C3: D | D3: H | E3: 0 | F3: 0 | G3: 0 | H3: 0 | I3: 0 | J3: 0 | K3: 0 | L3: 0 | M3: 0 | N3: 0 | O3: 0 | P3: 0 | Q3: 0 | R3: 0 | S3: 0 | T3: 0 | U3: 0 | V3: 0 | W3: 0 | X3: 0 | Y3: 0 | Z3: 0 | AA3: 0 | AB3: 0 | AC3: 0 | AD3: 0 | AE3: 0 | AF3: 0 | AG3: 0 | AH3: 0 | AI3: 0 | AJ3: 0 | AK3: 0 | AL3: 0 | AM3: 0 | AN3: 0 | AO3: 0 | AP3: 0 | AQ3: 0 | AR3: 0 | AS3: 0 | AT3: 0 | AU3: 0 | AV3: 0 | AW3: 0 | AX3: 0 | AY3: 0 | AZ3: 0 | BA3: 0 | BB3: 0 | BC3: 0 | BD3: 0 | BE3: 0 | BF3: 0 | BG3: 0 | BH3: 0 | BI3: 0 | BJ3: 0 | BK3: 0 | BL3: 0 | BM3: 0 | BN3: 0 | BO3: 0 | BP3: 0 | BQ3: 0 | BR3: 0 | BS3: 0 | BT3: 0 | BU3: 0 | BV3: 0 | BW3: 0 | BX3: 0 | BY3: 0 | BZ3: 0 | CA3: 0 | CB3: 0 | CC3: 0 | CD3: 0 | CE3: 0 | CF3: 0 | CG3: 0 | CH3: 0 | CI3: 0 | CJ3: 0 | CK3: 0 | CL3: 0 | CM3: 0 | CN3: 0 | CO3: 0 | CP3: 0 | CQ3: 0 | CR3: 0 | CS3: 0 | CT3: 0 | CU3: 0 | CV3: 0 | CW3: 0 | CX3: 0 | CY3: 0 | CZ3: 0 | DB3: 0 | DC3: 0 | DD3: 0 | DE3: 0 | DF3: 0 | DG3: 0 | DH3: 0 | DI3: 0 | DJ3: 0 | DK3: 0 | DL3: 0 | DM3: 0 | DN3: 0 | DO3: 0 | DP3: 0 | DQ3: 0 | DR3: 0 | DS3: 0 | DT3: 0 | DU3: 0 | DV3: 0 | DW3: 0 | DX3: 0 | DY3: 0 | DZ3: 0 | EA3: 0 | EB3: 0 | EC3: 0 | ED3: 0 | EE3: 0 | EF3: 0
A4: 110100 | B4: CASH ON HAND | C4: D | D4: B | E4: 0 | F4: 0 | G4: 0 | H4: 0 | I4: 0 | J4: 0 | K4: 0 | L4: 0 | M4: 0 | N4: 0 | O4: 0 | P4: 0 | Q4: 0 | R4: 0 | S4: 0 | T4: 0 | U4: 0 | V4: 0 | W4: 0 | X4: 0 | Y4: 0 | Z4: 0 | AA4: 0 | AB4: 0 | AC4: 0 | AD4: 0 | AE4: 0 | AF4: 0 | AG4: 0 | AH4: 0 | AI4: 0 | AJ4: 0 | AK4: 0 | AL4: 0 | AM4: 0 | AN4: 0 | AO4: 0 | AP4: 0 | AQ4: 0 | AR4: 0 | AS4: 0 | AT4: 0 | AU4: 0 | AV4: 0 | AW4: 0 | AX4: 0 | AY4: 0 | AZ4: 0 | BA4: 0 | BB4: 0 | BC4: 0 | BD4: 0 | BE4: 0 | BF4: 0 | BG4: 0 | BH4: 0 | BI4: 0 | BJ4: 0 | BK4: 0 | BL4: 0 | BM4: 0 | BN4: 0 | BO4: 0 | BP4: 0 | BQ4: 0 | BR4: 0 | BS4: 0 | BT4: 0 | BU4: 0 | BV4: 0 | BW4: 0 | BX4: 0 | BY4: 0 | BZ4: 0 | CA4: 0 | CB4: 0 | CC4: 0 | CD4: 0 | CE4: 0 | CF4: 0 | CG4: 0 | CH4: 0 | CI4: 0 | CJ4: 0 | CK4: 0 | CL4: 0 | CM4: 0 | CN4: 0 | CO4: 0 | CP4: 0 | CQ4: 0 | CR4: 0 | CS4: 0 | CT4: 0 | CU4: 0 | CV4: 0 | CW4: 0 | CX4: 0 | CY4: 0 | CZ4: 0 | DB4: 0 | DC4: 0 | DD4: 0 | DE4: 0 | DF4: 0 | DG4: 0 | DH4: 0 | DI4: 0 | DJ4: 0 | DK4: 0 | DL4: 0 | DM4: 0 | DN4: 0 | DO4: 0 | DP4: 0 | DQ4: 0 | DR4: 0 | DS4: 0 | DT4: 0 | DU4: 0 | DV4: 0 | DW4: 0 | DX4: 0 | DY4: 0 | DZ4: 0 | EA4: 0 | EB4: 0 | EC4: 0 | ED4: 0 | EE4: 0 | EF4: 0
A5: 110200 | B5: PETTY CASH | C5: D | D5: B | E5: 30000 | F5: 0 | G5: 0 | H5: 0 | I5: 0 | J5: 0 | K5: 0 | L5: 0 | M5: 0 | N5: 0 | O5: 0 | P5: 0 | Q5: 0 | R5: 0 | S5: 0 | T5: 0 | U5: 0 | V5: 0 | W5: 0 | X5: 0 | Y5: 0 | Z5: 0 | AA5: 0 | AB5: 0 | AC5: 0 | AD5: 0 | AE5: 0 | AF5: 30000 | AG5: 0 | AH5: 0 | AI5: 0 | AJ5: 0 | AK5: 0 | AL5: 0 | AM5: 0 | AN5: 0 | AO5: 0 | AP5: 0 | AQ5: 0 | AR5: 0 | AS5: 0 | AT5: 0 | AU5: 0 | AV5: 0 | AW5: 0 | AX5: 0 | AY5: 0 | AZ5: 0 | BA5: 0 | BB5: 0 | BC5: 0 | BD5: 0 | BE5: 0 | BF5: 0 | BG5: 0 | BH5: 0 | BI5: 0 | BJ5: 0 | BK5: 0 | BL5: 0 | BM5: 0 | BN5: 0 | BO5: 0 | BP5: 0 | BQ5: 0 | BR5: 0 | BS5: 0 | BT5: 0 | BU5: 0 | BV5: 0 | BW5: 0 | BX5: 0 | BY5: 0 | BZ5: 0 | CA5: 0 | CB5: 0 | CC5: 0 | CD5: 0 | CE5: 0 | CF5: 0 | CG5: 0 | CH5: 0 | CI5: 0 | CJ5: 0 | CK5: 0 | CL5: 0 | CM5: 0 | CN5: 0 | CO5: 0 | CP5: 0 | CQ5: 0 | CR5: 0 | CS5: 0 | CT5: 0 | CU5: 0 | CV5: 0 | CW5: 0 | CX5: 0 | CY5: 0 | CZ5: 0 | DB5: 0 | DC5: 0 | DD5: 0 | DE5: 0 | DF5: 0 | DG5: 0 | DH5: 0 | DI5: 0 | DJ5: 0 | DK5: 0 | DL5: 0 | DM5: 0 | DN5: 0 | DO5: 0 | DP5: 0 | DQ5: 0 | DR5: 0 | DS5: 0 | DT5: 0 | DU5: 0 | DV5: 0 | DW5: 0 | DX5: 0 | DY5: 0 | DZ5: 0 | EA5: 0 | EB5: 0 | EC5: 0 | ED5: 0 | EE5: 0 | EF5: 0
A6: 110310 | B6: HOUSE FUND - FRONT OFFICE | C6: D | D6: B | E6: 40000 | F6: 0 | G6: 0 | H6: 0 | I6: 0 | J6: 0 | K6: 0 | L6: 0 | M6: 0 | N6: 0 | O6: 0 | P6: 0 | Q6: 0 | R6: 0 | S6: 0 | T6: 0 | U6: 0 | V6: 0 | W6: 0 | X6: 0 | Y6: 0 | Z6: 0 | AA6: 0 | AB6: 0 | AC6: 0 | AD6: 0 | AE6: 0 | AF6: 40000 | AG6: 0 | AH6: 0 | AI6: 0 | AJ6: 0 | AK6: 0 | AL6: 0 | AM6: 0 | AN6: 0 | AO6: 0 | AP6: 0 | AQ6: 0 | AR6: 0 | AS6: 0 | AT6: 0 | AU6: 0 | AV6: 0 | AW6: 0 | AX6: 0 | AY6: 0 | AZ6: 0 | BA6: 0 | BB6: 0 | BC6: 0 | BD6: 0 | BE6: 0 | BF6: 0 | BG6: 0 | BH6: 0 | BI6: 0 | BJ6: 0 | BK6: 0 | BL6: 0 | BM6: 0 | BN6: 0 | BO6: 0 | BP6: 0 | BQ6: 0 | BR6: 0 | BS6: 0 | BT6: 0 | BU6: 0 | BV6: 0 | BW6: 0 | BX6: 0 | BY6: 0 | BZ6: 0 | CA6: 0 | CB6: 0 | CC6: 0 | CD6: 0 | CE6: 0 | CF6: 0 | CG6: 0 | CH6: 0 | CI6: 0 | CJ6: 0 | CK6: 0 | CL6: 0 | CM6: 0 | CN6: 0 | CO6: 0 | CP6: 0 | CQ6: 0 | CR6: 0 | CS6: 0 | CT6: 0 | CU6: 0 | CV6: 0 | CW6: 0 | CX6: 0 | CY6: 0 | CZ6: 0 | DB6: 0 | DC6: 0 | DD6: 0 | DE6: 0 | DF6: 0 | DG6: 0 | DH6: 0 | DI6: 0 | DJ6: 0 | DK6: 0 | DL6: 0 | DM6: 0 | DN6: 0 | DO6: 0 | DP6: 0 | DQ6: 0 | DR6: 0 | DS6: 0 | DT6: 0 | DU6: 0 | DV6: 0 | DW6: 0 | DX6: 0 | DY6: 0 | DZ6: 0 | EA6: 0 | EB6: 0 | EC6: 0 | ED6: 0 | EE6: 0 | EF6: 0
A7: 110320 | B7: HOUSE FUND - RESTAURANT | C7: D | D7: B | E7: 8000 | F7: 0 | G7: 0 | H7: 0 | I7: 0 | J7: 0 | K7: 0 | L7: 0 | M7: 0 | N7: 0 | O7: 0 | P7: 0 | Q7: 0 | R7: 0 | S7: 0 | T7: 0 | U7: 0 | V7: 0 | W7: 0 | X7: 0 | Y7: 0 | Z7: 0 | AA7: 0 | AB7: 0 | AC7: 0 | AD7: 0 | AE7: 0 | AF7: 5000 | AG7: 0 | AH7: 0 | AI7: 0 | AJ7: 0 | AK7: 0 | AL7: 0 | AM7: 0 | AN7: 0 | AO7: 0 | AP7: 0 | AQ7: 0 | AR7: 3000 | AS7: 0 | AT7: 0 | AU7: 0 | AV7: 0 | AW7: 0 | AX7: 0 | AY7: 0 | AZ7: 0 | BA7: 0 | BB7: 0 | BC7: 0 | BD7: 0 | BE7: 0 | BF7: 0 | BG7: 0 | BH7: 0 | BI7: 0 | BJ7: 0 | BK7: 0 | BL7: 0 | BM7: 0 | BN7: 0 | BO7: 0 | BP7: 0 | BQ7: 0 | BR7: 0 | BS7: 0 | BT7: 0 | BU7: 0 | BV7: 0 | BW7: 0 | BX7: 0 | BY7: 0 | BZ7: 0 | CA7: 0 | CB7: 0 | CC7: 0 | CD7: 0 | CE7: 0 | CF7: 0 | CG7: 0 | CH7: 0 | CI7: 0 | CJ7: 0 | CK7: 0 | CL7: 0 | CM7: 0 | CN7: 0 | CO7: 0 | CP7: 0 | CQ7: 0 | CR7: 0 | CS7: 0 | CT7: 0 | CU7: 0 | CV7: 0 | CW7: 0 | CX7: 0 | CY7: 0 | CZ7: 0 | DB7: 0 | DC7: 0 | DD7: 0 | DE7: 0 | DF7: 0 | DG7: 0 | DH7: 0 | DI7: 0 | DJ7: 0 | DK7: 0 | DL7: 0 | DM7: 0 | DN7: 0 | DO7: 0 | DP7: 0 | DQ7: 0 | DR7: 0 | DS7: 0 | DT7: 0 | DU7: 0 | DV7: 0 | DW7: 0 | DX7: 0 | DY7: 0 | DZ7: 0 | EA7: 0 | EB7: 0 | EC7: 0 | ED7: 0 | EE7: 0 | EF7: 0
A8: 110330 | B8: HOUSE FUND - EXCHANGE | C8: D | D8: B | E8: 0 | F8: 0 | G8: 0 | H8: 0 | I8: 0 | J8: 0 | K8: 0 | L8: 0 | M8: 0 | N8: 0 | O8: 0 | P8: 0 | Q8: 0 | R8: 0 | S8: 0 | T8: 0 | U8: 0 | V8: 0 | W8: 0 | X8: 0 | Y8: 0 | Z8: 0 | AA8: 0 | AB8: 0 | AC8: 0 | AD8: 0 | AE8: 0 | AF8: 0 | AG8: 0 | AH8: 0 | AI8: 0 | AJ8: 0 | AK8: 0 | AL8: 0 | AM8: 0 | AN8: 0 | AO8: 0 | AP8: 0 | AQ8: 0 | AR8: 0 | AS8: 0 | AT8: 0 | AU8: 0 | AV8: 0 | AW8: 0 | AX8: 0 | AY8: 0 | AZ8: 0 | BA8: 0 | BB8: 0 | BC8: 0 | BD8: 0 | BE8: 0 | BF8: 0 | BG8: 0 | BH8: 0 | BI8: 0 | BJ8: 0 | BK8: 0 | BL8: 0 | BM8: 0 | BN8: 0 | BO8: 0 | BP8: 0 | BQ8: 0 | BR8: 0 | BS8: 0 | BT8: 0 | BU8: 0 | BV8: 0 | BW8: 0 | BX8: 0 | BY8: 0 | BZ8: 0 | CA8: 0 | CB8: 0 | CC8: 0 | CD8: 0 | CE8: 0 | CF8: 0 | CG8: 0 | CH8: 0 | CI8: 0 | CJ8: 0 | CK8: 0 | CL8: 0 | CM8: 0 | CN8: 0 | CO8: 0 | CP8: 0 | CQ8: 0 | CR8: 0 | CS8: 0 | CT8: 0 | CU8: 0 | CV8: 0 | CW8: 0 | CX8: 0 | CY8: 0 | CZ8: 0 | DB8: 0 | DC8: 0 | DD8: 0 | DE8: 0 | DF8: 0 | DG8: 0 | DH8: 0 | DI8: 0 | DJ8: 0 | DK8: 0 | DL8: 0 | DM8: 0 | DN8: 0 | DO8: 0 | DP8: 0 | DQ8: 0 | DR8: 0 | DS8: 0 | DT8: 0 | DU8: 0 | DV8: 0 | DW8: 0 | DX8: 0 | DY8: 0 | DZ8: 0 | EA8: 0 | EB8: 0 | EC8: 0 | ED8: 0 | EE8: 0 | EF8: 0
A9: 110340 | B9: HOUSE FUND - PURCHASING | C9: D | D9: B | E9: 0 | F9: 0 | G9: 0 | H9: 0 | I9: 0 | J9: 0 | K9: 0 | L9: 0 | M9: 0 | N9: 0 | O9: 0 | P9: 0 | Q9: 0 | R9: 0 | S9: 0 | T9: 0 | U9: 0 | V9: 0 | W9: 0 | X9: 0 | Y9: 0 | Z9: 0 | AA9: 0 | AB9: 0 | AC9: 0 | AD9: 0 | AE9: 0 | AF9: 0 | AG9: 0 | AH9: 0 | AI9: 0 | AJ9: 0 | AK9: 0 | AL9: 0 | AM9: 0 | AN9: 0 | AO9: 0 | AP9: 0 | AQ9: 0 | AR9: 0 | AS9: 0 | AT9: 0 | AU9: 0 | AV9: 0 | AW9: 0 | AX9: 0 | AY9: 0 | AZ9: 0 | BA9: 0 | BB9: 0 | BC9: 0 | BD9: 0 | BE9: 0 | BF9: 0 | BG9: 0 | BH9: 0 | BI9: 0 | BJ9: 0 | BK9: 0 | BL9: 0 | BM9: 0 | BN9: 0 | BO9: 0 | BP9: 0 | BQ9: 0 | BR9: 0 | BS9: 0 | BT9: 0 | BU9: 0 | BV9: 0 | BW9: 0 | BX9: 0 | BY9: 0 | BZ9: 0 | CA9: 0 | CB9: 0 | CC9: 0 | CD9: 0 | CE9: 0 | CF9: 0 | CG9: 0 | CH9: 0 | CI9: 0 | CJ9: 0 | CK9: 0 | CL9: 0 | CM9: 0 | CN9: 0 | CO9: 0 | CP9: 0 | CQ9: 0 | CR9: 0 | CS9: 0 | CT9: 0 | CU9: 0 | CV9: 0 | CW9: 0 | CX9: 0 | CY9: 0 | CZ9: 0 | DB9: 0 | DC9: 0 | DD9: 0 | DE9: 0 | DF9: 0 | DG9: 0 | DH9: 0 | DI9: 0 | DJ9: 0 | DK9: 0 | DL9: 0 | DM9: 0 | DN9: 0 | DO9: 0 | DP9: 0 | DQ9: 0 | DR9: 0 | DS9: 0 | DT9: 0 | DU9: 0 | DV9: 0 | DW9: 0 | DX9: 0 | DY9: 0 | DZ9: 0 | EA9: 0 | EB9: 0 | EC9: 0 | ED9: 0 | EE9: 0 | EF9: 0
A10: 110350 | B10: HOUSE FUND - SPA | C10: D | D10: B | E10: 3000 | F10: 0 | G10: 0 | H10: 0 | I10: 0 | J10: 0 | K10: 0 | L10: 0 | M10: 0 | N10: 0 | O10: 0 | P10: 0 | Q10: 0 | R10: 0 | S10: 0 | T10: 0 | U10: 0 | V10: 0 | W10: 0 | X10: 0 | Y10: 0 | Z10: 0 | AA10: 0 | AB10: 0 | AC10: 0 | AD10: 0 | AE10: 0 | AF10: 3000 | AG10: 0 | AH10: 0 | AI10: 0 | AJ10: 0 | AK10: 0 | AL10: 0 | AM10: 0 | AN10: 0 | AO10: 0 | AP10: 0 | AQ10: 0 | AR10: 0 | AS10: 0 | AT10: 0 | AU10: 0 | AV10: 0 | AW10: 0 | AX10: 0 | AY10: 0 | AZ10: 0 | BA10: 0 | BB10: 0 | BC10: 0 | BD10: 0 | BE10: 0 | BF10: 0 | BG10: 0 | BH10: 0 | BI10: 0 | BJ10: 0 | BK10: 0 | BL10: 0 | BM10: 0 | BN10: 0 | BO10: 0 | BP10: 0 | BQ10: 0 | BR10: 0 | BS10: 0 | BT10: 0 | BU10: 0 | BV10: 0 | BW10: 0 | BX10: 0 | BY10: 0 | BZ10: 0 | CA10: 0 | CB10: 0 | CC10: 0 | CD10: 0 | CE10: 0 | CF10: 0 | CG10: 0 | CH10: 0 | CI10: 0 | CJ10: 0 | CK10: 0 | CL10: 0 | CM10: 0 | CN10: 0 | CO10: 0 | CP10: 0 | CQ10: 0 | CR10: 0 | CS10: 0 | CT10: 0 | CU10: 0 | CV10: 0 | CW10: 0 | CX10: 0 | CY10: 0 | CZ10: 0 | DB10: 0 | DC10: 0 | DD10: 0 | DE10: 0 | DF10: 0 | DG10: 0 | DH10: 0 | DI10: 0 | DJ10: 0 | DK10: 0 | DL10: 0 | DM10: 0 | DN10: 0 | DO10: 0 | DP10: 0 | DQ10: 0 | DR10: 0 | DS10: 0 | DT10: 0 | DU10: 0 | DV10: 0 | DW10: 0 | DX10: 0 | DY10: 0 | DZ10: 0 | EA10: 0 | EB10: 0 | EC10: 0 | ED10: 0 | EE10: 0 | EF10: 0
A11: 110360 | B11: HOUSE FUND - S&M BANGKOK OFFICE | C11: D | D11: B | E11: 0 | F11: 0 | G11: 0 | H11: 0 | I11: 0 | J11: 0 | K11: 0 | L11: 0 | M11: 0 | N11: 0 | O11: 0 | P11: 0 | Q11: 0 | R11: 0 | S11: 0 | T11: 0 | U11: 0 | V11: 0 | W11: 0 | X11: 0 | Y11: 0 | Z11: 0 | AA11: 0 | AB11: 0 | AC11: 0 | AD11: 0 | AE11: 0 | AF11: 0 | AG11: 0 | AH11: 0 | AI11: 0 | AJ11: 0 | AK11: 0 | AL11: 0 | AM11: 0 | AN11: 0 | AO11: 0 | AP11: 0 | AQ11: 0 | AR11: 0 | AS11: 0 | AT11: 0 | AU11: 0 | AV11: 0 | AW11: 0 | AX11: 0 | AY11: 0 | AZ11: 0 | BA11: 0 | BB11: 0 | BC11: 0 | BD11: 0 | BE11: 0 | BF11: 0 | BG11: 0 | BH11: 0 | BI11: 0 | BJ11: 0 | BK11: 0 | BL11: 0 | BM11: 0 | BN11: 0 | BO11: 0 | BP11: 0 | BQ11: 0 | BR11: 0 | BS11: 0 | BT11: 0 | BU11: 0 | BV11: 0 | BW11: 0 | BX11: 0 | BY11: 0 | BZ11: 0 | CA11: 0 | CB11: 0 | CC11: 0 | CD11: 0 | CE11: 0 | CF11: 0 | CG11: 0 | CH11: 0 | CI11: 0 | CJ11: 0 | CK11: 0 | CL11: 0 | CM11: 0 | CN11: 0 | CO11: 0 | CP11: 0 | CQ11: 0 | CR11: 0 | CS11: 0 | CT11: 0 | CU11: 0 | CV11: 0 | CW11: 0 | CX11: 0 | CY11: 0 | CZ11: 0 | DB11: 0 | DC11: 0 | DD11: 0 | DE11: 0 | DF11: 0 | DG11: 0 | DH11: 0 | DI11: 0 | DJ11: 0 | DK11: 0 | DL11: 0 | DM11: 0 | DN11: 0 | DO11: 0 | DP11: 0 | DQ11: 0 | DR11: 0 | DS11: 0 | DT11: 0 | DU11: 0 | DV11: 0 | DW11: 0 | DX11: 0 | DY11: 0 | DZ11: 0 | EA11: 0 | EB11: 0 | EC11: 0 | ED11: 0 | EE11: 0 | EF11: 0
A12: 110400 | B12: CASH SALES CLEARANCE | C12: D | D12: B | E12: 370812 | F12: -351166 | G12: 169090 | H12: -99232.65 | I12: -65630.71 | J12: -17418.93 | K12: 1838.82 | L12: 2499.47 | M12: 14958.84 | N12: -25750.84 | O12: 0 | P12: 0 | Q12: 0 | R12: 0 | S12: 0 | T12: 0 | U12: 0 | V12: 0 | W12: 0 | X12: 0 | Y12: 0 | Z12: 0 | AA12: 0 | AB12: 0 | AC12: 0 | AD12: 0 | AE12: 0 | AF12: 30571 | AG12: -23437 | AH12: 7915 | AI12: -4503 | AJ12: 46104.6 | AK12: -52070.6 | AL12: 12024 | AM12: -6696 | AN12: -8428 | AO12: -405 | AP12: 10255 | AQ12: 5005.08 | AR12: 354476.92 | AS12: 0 | AT12: 0 | AU12: 0 | AV12: 0 | AW12: 0 | AX12: 0 | AY12: 0 | AZ12: 0 | BA12: 0 | BB12: 0 | BC12: 0 | BD12: 0 | BE12: 0 | BF12: 0 | BG12: 0 | BH12: 0 | BI12: 0 | BJ12: 0 | BK12: 0 | BL12: 0 | BM12: 0 | BN12: 0 | BO12: 0 | BP12: 0 | BQ12: 0 | BR12: 0 | BS12: 0 | BT12: 0 | BU12: 0 | BV12: 0 | BW12: 0 | BX12: 0 | BY12: 0 | BZ12: 0 | CA12: 0 | CB12: 0 | CC12: 0 | CD12: 0 | CE12: 0 | CF12: 0 | CG12: 0 | CH12: 0 | CI12: 0 | CJ12: 0 | CK12: 0 | CL12: 0 | CM12: 0 | CN12: 0 | CO12: 0 | CP12: 0 | CQ12: 0 | CR12: 0 | CS12: 0 | CT12: 0 | CU12: 0 | CV12: 0 | CW12: 0 | CX12: 0 | CY12: 0 | CZ12: 0 | DB12: 0 | DC12: 0 | DD12: 0 | DE12: 0 | DF12: 0 | DG12: 0 | DH12: 0 | DI12: 0 | DJ12: 0 | DK12: 0 | DL12: 0 | DM12: 0 | DN12: 0 | DO12: 0 | DP12: 0 | DQ12: 0 | DR12: 0 | DS12: 0 | DT12: 0 | DU12: 0 | DV12: 0 | DW12: 0 | DX12: 0 | DY12: 0 | DZ12: 0 | EA12: 0 | EB12: 0 | EC12: 0 | ED12: 0 | EE12: 0 | EF12: 0
A13: 110510 | B13: CHEQUE ON HAND | C13: D | D13: B | E13: 0 | F13: 0 | G13: 0 | H13: 0 | I13: 0 | J13: 0 | K13: 0 | L13: 0 | M13: 0 | N13: 0 | O13: 0 | P13: 0 | Q13: 0 | R13: 0 | S13: 0 | T13: 0 | U13: 0 | V13: 0 | W13: 0 | X13: 0 | Y13: 0 | Z13: 0 | AA13: 0 | AB13: 0 | AC13: 0 | AD13: 0 | AE13: 0 | AF13: 0 | AG13: 0 | AH13: 0 | AI13: 0 | AJ13: 0 | AK13: 0 | AL13: 0 | AM13: 0 | AN13: 0 | AO13: 0 | AP13: 0 | AQ13: 0 | AR13: 0 | AS13: 0 | AT13: 0 | AU13: 0 | AV13: 0 | AW13: 0 | AX13: 0 | AY13: 0 | AZ13: 0 | BA13: 0 | BB13: 0 | BC13: 0 | BD13: 0 | BE13: 0 | BF13: 0 | BG13: 0 | BH13: 0 | BI13: 0 | BJ13: 0 | BK13: 0 | BL13: 0 | BM13: 0 | BN13: 0 | BO13: 0 | BP13: 0 | BQ13: 0 | BR13: 0 | BS13: 0 | BT13: 0 | BU13: 0 | BV13: 0 | BW13: 0 | BX13: 0 | BY13: 0 | BZ13: 0 | CA13: 0 | CB13: 0 | CC13: 0 | CD13: 0 | CE13: 0 | CF13: 0 | CG13: 0 | CH13: 0 | CI13: 0 | CJ13: 0 | CK13: 0 | CL13: 0 | CM13: 0 | CN13: 0 | CO13: 0 | CP13: 0 | CQ13: 0 | CR13: 0 | CS13: 0 | CT13: 0 | CU13: 0 | CV13: 0 | CW13: 0 | CX13: 0 | CY13: 0 | CZ13: 0 | DB13: 0 | DC13: 0 | DD13: 0 | DE13: 0 | DF13: 0 | DG13: 0 | DH13: 0 | DI13: 0 | DJ13: 0 | DK13: 0 | DL13: 0 | DM13: 0 | DN13: 0 | DO13: 0 | DP13: 0 | DQ13: 0 | DR13: 0 | DS13: 0 | DT13: 0 | DU13: 0 | DV13: 0 | DW13: 0 | DX13: 0 | DY13: 0 | DZ13: 0 | EA13: 0 | EB13: 0 | EC13: 0 | ED13: 0 | EE13: 0 | EF13: 0
... A1384: N/A | B1384: Not Available | C1384: D | D1384: S | E1384: 0 | F1384: 0 | G1384: 0 | H1384: 0 | I1384: 0 | J1384: 0 | K1384: 0 | L1384: 0 | M1384: 0 | N1384: 0 | O1384: 0 | P1384: 0 | Q1384: 0 | R1384: 0 | S1384: 0 | T1384: 0 | U1384: 0 | V1384: 0 | W1384: 0 | X1384: 0 | Y1384: 0 | Z1384: 0 | AA1384: 0 | AB1384: 0 | AC1384: 0 | AD1384: 0 | AE1384: 0 | AF1384: 0 | AG1384: 0 | AH1384: 0 | AI1384: 0 | AJ1384: 0 | AK1384: 0 | AL1384: 0 | AM1384: 0 | AN1384: 0 | AO1384: 0 | AP1384: 0 | AQ1384: 0 | AR1384: 0 | AS1384: 0 | AT1384: 0 | AU1384: 0 | AV1384: 0 | AW1384: 0 | AX1384: 0 | AY1384: 0 | AZ1384: 0 | BA1384: 0 | BB1384: 0 | BC1384: 0 | BD1384: 0 | BE1384: 0 | BF1384: 0 | BG1384: 0 | BH1384: 0 | BI1384: 0 | BJ1384: 0 | BK1384: 0 | BL1384: 0 | BM1384: 0 | BN1384: 0 | BO1384: 0 | BP1384: 0 | BQ1384: 0 | BR1384: 0 | BS1384: 0 | BT1384: 0 | BU1384: 0 | BV1384: 0 | BW1384: 0 | BX1384: 0 | BY1384: 0 | BZ1384: 0 | CA1384: 0 | CB1384: 0 | CC1384: 0 | CD1384: 0 | CE1384: 0 | CF1384: 0 | CG1384: 0 | CH1384: 0 | CI1384: 0 | CJ1384: 0 | CK1384: 0 | CL1384: 0 | CM1384: 0 | CN1384: 0 | CO1384: 0 | CP1384: 0 | CQ1384: 0 | CR1384: 0 | CS1384: 0 | CT1384: 0 | CU1384: 0 | CV1384: 0 | CW1384: 0 | CX1384: 0 | CY1384: 0 | CZ1384: 0 | DB1384: 0 | DC1384: 0 | DD1384: 0 | DE1384: 0 | DF1384: 0 | DG1384: 0 | DH1384: 0 | DI1384: 0 | DJ1384: 0 | DK1384: 0 | DL1384: 0 | DM1384: 0 | DN1384: 0 | DO1384: 0 | DP1384: 0 | DQ1384: 0 | DR1384: 0 | DS1384: 0 | DT1384: 0 | DU1384: 0 | DV1384: 0 | DW1384: 0 | DX1384: 0 | DY1384: 0 | DZ1384: 0 | EA1384: 0 | EB1384: 0 | EC1384: 0 | ED1384: 0 | EE1384: 0 | EF1384: 0

Sheet Intro
B7: CONFIDENTAL
B10: Financial Statement Report
B11: Ramada Resort Kho Lak
B12: Profit & ( Loss ) Statement
C13: Period | D13: 6
C14: Year | D14: 2026
C15: Database | D15: ramadakhaolak
C16: Database | D16: stwasset
C17: Budget | D17: 0
D23: {=_xll.GetBusinessUnitList()} -> ramadakhaolak
D24: ramadakhaolak_training
D25: stwasset

Sheet Cover
B2: Ramada Resort Khao Lak, Phang Nga
B4: Financial Reports
B7: Table of Contents
B12: Sch
C13: Trend of Operations
B14: 00 | C14: Summary Statement of Income
B15: 00A | C15: Supplementary Statement of Income
B17: Sch | C17: Operating Departments | D17: Sch | E17: Non-Operating Departments
B18: 01 | C18: Room Division | D18: 11 | E18: Administrative and General
B19: 02 | C19: Minibar | D19: 12 | E19: Human Resources
B20: 03 | C20: Telecommunications | D20: 13 | E20: Marketing
B21: 04 | C21: Guest Laundry | D21: 14 | E21: POMEC
B22: 05 | C22: Food & Beverage Division
B23: 06 | C23: The Spa
B24: 09 | C24: Other Income

Sheet SCH00A
A2: SUPPLEMENTARY STATEMENT OF INCOME
A3: =SCH00!J3 -> For the PRD of June 2026
R4: Schedule 00A
R5: MTD ACTUAL
R6: Local currency
F8: NET REVENUE | H8: COST | I8: % | K8: PAYROLL | L8: % | N8: OTHER EXPENSE | O8: % | Q8: INCOME (LOSS) | R8: %
A10: OPERATED DEPARTMENTS
B11: Rooms | F11: =+Room_SCH01!G26 -> 2893701.6 | H11: 0 | I11: =IF(H11=0,0,(H11*100/$F$11)) -> 0 | K11: =+Room_SCH01!G33 -> 1604568.5 | L11: =IF(K11=0,0,(K11*100/$F$11)) -> 55.45038 | N11: =+Room_SCH01!G63 -> 650238.08 | O11: =IF(N11=0,0,(N11*100/$F$11)) -> 22.470807 | Q11: =F11-H11-K11-N11 -> 638894.98 | R11: =IF(Q11=0,0,(Q11*100/$F$11)) -> 22.078814 | T11: 8620349.5 | U11: =+F11-T11 -> -5726648
B12: Food & Beverage | F12: =+'SCH05'!G24 -> 4907832.8 | H12: =+'SCH05'!G31 -> 1652253.4 | I12: =IF(H12=0,0,(H12*100/$F$12)) -> 33.665642 | K12: =+'SCH05'!G36 -> 899492.44 | L12: =IF(K12=0,0,(K12*100/$F$12)) -> 18.327691 | N12: ='SCH05'!G68 -> 501612.24 | O12: =IF(N12=0,0,(N12*100/$F$12)) -> 10.220647 | Q12: =F12-H12-K12-N12 -> 1854474.7 | R12: =IF(Q12=0,0,(Q12*100/$F$12)) -> 37.78602 | T12: 4194273.9 | U12: =+F12-T12 -> 713558.89 | V12: 146165.83 | W12: =+U12+V12 -> 859724.72
B13: Telecommunications | F13: =+Tel_SCH03!I14 -> 184.22 | H13: =+Tel_SCH03!I20 -> 0 | I13: =IF(OR(H13=0,F13=0),0,(H13*100/$F$13)) -> 0 | K13: =+Tel_SCH03!I29 -> 0 | L13: =IF(K13=0,0,(K13*100/$F$13)) -> 0 | N13: =Tel_SCH03!I33 -> 0 | O13: =IF(N13=0,0,(N13*100/$F$13)) -> 0 | Q13: =F13-H13-K13-N13 -> 184.22 | R13: =IF(OR(Q13=0,F13=0),0,(Q13*100/$F$13)) -> 100
B14: Guest Laundry | F14: =+Lau_SCH04!I12 -> 9736.6 | H14: =+Lau_SCH04!I14 -> 2372.8 | I14: =IF(H14=0,0,(H14*100/$F$14)) -> 24.369903 | K14: =+Lau_SCH04!I21 -> 0 | L14: =IF(K14=0,0,(K14*100/$F$14)) -> 0 | N14: =Lau_SCH04!I33 -> 0 | O14: =IF(N14=0,0,(N14*100/$F$14)) -> 0 | Q14: =F14-H14-K14-N14 -> 7363.8 | R14: =IF(Q14=0,0,(Q14*100/$F$14)) -> 75.630097
B15: The Spa | F15: =+Spa_SCH06!I13 -> 208086.72 | H15: =+Spa_SCH06!I15 -> 10930.9 | I15: =IF(H15=0,0,(H15*100/$F$15)) -> 5.2530503 | K15: =+Spa_SCH06!I22 -> 198894.12 | L15: =IF(K15=0,0,(K15*100/$F$15)) -> 95.582323 | N15: =Spa_SCH06!I49 -> 19523.58 | O15: =IF(N15=0,0,(N15*100/$F$15)) -> 9.3824248 | Q15: =F15-H15-K15-N15 -> -21261.88 | R15: =IF(Q15=0,0,(Q15*100/$F$15)) -> -10.217798
B16: Other Operated Departments | F16: ='Mini Bar_SCH02'!I14 -> 19329 | H16: ='Mini Bar_SCH02'!I17 -> 2998.46 | I16: =IF(H16=0,0,(H16*100/$F$16)) -> 15.512753 | K16: 0 | L16: =IF(K16=0,0,(K16*100/$F$16)) -> 0 | N16: ='Mini Bar_SCH02'!I35 -> 0 | O16: =IF(N16=0,0,(N16*100/$F$16)) -> 0 | Q16: =F16-H16-K16-N16 -> 16330.54 | R16: =IF(Q16=0,0,(Q16*100/$F$16)) -> 84.487247
B17: Rentals & Other Income | F17: =Other_SCH09!J17 -> 322055.52 | H17: =Other_SCH09!J24 -> 196079.24 | I17: =IF(H17=0,0,(H17*100/$F$17)) -> 60.883676 | K17: 0 | L17: =IF(K17=0,0,(K17*100/$F$17)) -> 0 | N17: 0 | O17: =IF(N17=0,0,(N17*100/$F$17)) -> 0 | Q17: =F17-H17-K17-N17 -> 125976.28 | R17: =IF(Q17=0,0,(Q17*100/$F$17)) -> 39.116324 | T17: 216907.13 | U17: =SUM(F13:F17)-T17 -> 342484.93
B18: Extraordinary items | F18: =+Room_SCH01!G27 -> 0 | H18: 0 | I18: =IF(H18=0,0,(H18*100/$F$18)) -> 0 | K18: 0 | L18: =IF(K18=0,0,(K18*100/$F$18)) -> 0 | N18: 0 | O18: =IF(N18=0,0,(N18*100/$F$18)) -> 0 | Q18: =F18-H18-K18-N18 -> 0 | R18: =IF(Q18=0,0,(Q18*100/$F$18)) -> 0
B19: Total Operated Departments | F19: =SUM(F11:F18) -> 8360926.4 | H19: =SUM(H11:H18) -> 1864634.8 | I19: =IF(H19=0,0,(H19*100/$F$19)) -> 22.301773 | K19: =SUM(K11:K18) -> 2702955.1 | L19: =IF(K19=0,0,(K19*100/$F$19)) -> 32.328416 | N19: =SUM(N11:N18) -> 1171373.9 | O19: =IF(N19=0,0,(N19*100/$F$19)) -> 14.010097 | Q19: =SUM(Q11:Q18) -> 2621962.6 | R19: =IF(Q19=0,0,(Q19*100/$F$19)) -> 31.359714 | T19: =SUM(T11:T18) -> 13031531 | U19: =SUM(U11:U18) -> -4670604.1 | V19: =+F19-T19-U19 -> 0
A21: UNDISTRIBUTED OPERATING EXPENSES
B22: Administrative & General | K22: =+AG_SCH11!I13 -> 1345878.1 | L22: =IF(K22=0,0,(K22*100/$F$19)) -> 16.097236 | N22: =AG_SCH11!I56 -> 1776195.2 | O22: =IF(N22=0,0,(N22*100/$F$19)) -> 21.244 | Q22: =K22+N22 -> 3122073.2 | R22: =IF(Q22=0,0,(Q22*100/$F$19)) -> 37.341236
B23: Human Resources | K23: =+HR_SCH12!I12 -> 297905.08 | L23: =IF(K23=0,0,(K23*100/$F$19)) -> 3.5630631 | N23: =HR_SCH12!I35 -> 65874.38 | O23: =IF(N23=0,0,(N23*100/$F$19)) -> 0.78788375 | Q23: =K23+N23 -> 363779.46 | R23: =IF(Q23=0,0,(Q23*100/$F$19)) -> 4.3509468
B24: Marketing | K24: =+SM_SCH13!I19 -> 475536.84 | L24: =IF(K24=0,0,(K24*100/$F$19)) -> 5.6876095 | N24: =SM_SCH13!I55+SM_SCH13!I13 -> 812205.5 | O24: =IF(N24=0,0,(N24*100/$F$19)) -> 9.7143003 | Q24: =K24+N24 -> 1287742.3 | R24: =IF(Q24=0,0,(Q24*100/$F$19)) -> 15.40191
B25: Energy | L25: =IF(K25=0,0,(K25*100/$F$19)) -> 0 | N25: =RM_SCH14!I21 -> 1074147.8 | O25: =IF(N25=0,0,(N25*100/$F$19)) -> 12.847234 | Q25: =K25+N25 -> 1074147.8 | R25: =IF(Q25=0,0,(Q25*100/$F$19)) -> 12.847234
B26: Repair & Maintenance | K26: =+RM_SCH14!I26 -> 743919.6 | L26: =IF(K26=0,0,(K26*100/$F$19)) -> 8.8975739 | N26: =RM_SCH14!I67 -> 863867.36 | O26: =IF(N26=0,0,(N26*100/$F$19)) -> 10.332197 | Q26: =K26+N26 -> 1607787 | R26: =IF(Q26=0,0,(Q26*100/$F$19)) -> 19.229771
B27: Total Undistributed Operating Expenses | K27: =SUM(K22:K26) -> 2863239.6 | L27: =IF(K27=0,0,(K27*100/$F$19)) -> 34.245483 | N27: =SUM(N22:N26) -> 4592290.2 | O27: =IF(N27=0,0,(N27*100/$F$19)) -> 54.925614 | Q27: =SUM(Q22:Q26) -> 7455529.8 | R27: =IF(Q27=0,0,(Q27*100/$F$19)) -> 89.171097
A29: TOTALS | F29: =F19 -> 8360926.4 | H29: =H19 -> 1864634.8 | K29: =K19+K27 -> 5566194.7 | N29: =N19+N27 -> 5763664.1
A31: GROSS OPERATING PROFIT | Q31: =Q19-Q27 -> -4833567.1 | R31: =IF(Q31=0,0,(Q31*100/$F$19)) -> -57.811383
B33: Other Income | Q33: =SCH00!A56 -> 816951.68 | R33: =IF(Q33=0,0,(Q33*100/$F$19)) -> 9.7710665
B34: less:
B35: Management Fee - Incentive | N35: =SCH00!A59 -> 0
B36: Rent Property Taxes and Insurance | N36: 0
B37: Interest Expense | N37: =SCH00!A64 -> 0
B38: Depreciation and Amortisation | N38: =SCH00!A58 -> 2647017.5
B39: Other Additions/Deductions | N39: =SCH00!A60 -> 6281885
Q40: =SUM(N35:N39) -> 8928902.5
A42: PROFIT BEFORE INCOME TAX | Q42: =Q31-Q40 -> -13762470
B44: less : Income Taxes | Q44: 0
B45: Royalty to Main Office | Q45: 0
A47: NET PROFIT (NET LOSS) | Q47: =Q42-Q44-Q45 -> -13762470 | R47: =IF(Q47=0,0,(Q47*100/$F$19)) -> -164.6046

Sheet SCH00
J1: =Cover!B2 -> Ramada Resort Khao Lak, Phang Nga | Q1: =+BS!J1 -> 6
E2: SUMMARY STATEMENT OF INCOME | P2: Schedule 00
J3: ="For the PRD of"&" "&TEXT(DATE(YR, PRD, 1), "[$-409]mmmm yyyy") -> For the PRD of June 2026 | P3: Local Currency
A5: CURRENT MONTH | J5: DESCRIPTION | L5: YEAR TO DATE | S5: THIS MONTH | U5: Y-T-D | X5: LAST MONTH
A6: Actual | C6: vs Plan | E6: vs Last Year | G6: vs BRM | L6: Actual | N6: vs Plan | P6: vs Last Year | S6: Budget This monthPlan | T6: Actual Last Year | U6: Budge YTD Plan | V6: Actual Last Year | X6: Actual | Y6: Plan | Z6: Last Year
C7: Better / (Worse) | N7: Better / (Worse)
J9: OPERATED DEPARTMENTS
J10: INCOME
A11: =+Room_SCH01!G26 -> 2893701.6 | C11: =+A11-S11 -> 2893701.6 | E11: =+A11-T11 -> 1614090.2 | G11: 20175813 | J11: Rooms | L11: =+Room_SCH01!J26 -> 83040602 | N11: =+L11-U11 -> 83040602 | P11: =+L11-V11 -> 5286513.3 | S11: =+Room_SCH01!Q26 -> 0 | T11: =+Room_SCH01!R26 -> 1279611.4 | U11: =+Room_SCH01!S26 -> 0 | V11: =+Room_SCH01!T26 -> 77754089 | X11: =+Room_SCH01!V26 -> 77754089 | Y11: =+Room_SCH01!W26 -> 0 | Z11: =+Room_SCH01!X26 -> 70530593
A12: =+'SCH05'!G24 -> 4907832.8 | C12: =+A12-S12 -> 4907832.8 | E12: =+A12-T12 -> 2461271.3 | G12: 13423812 | J12: Food & Beverage | L12: =+'SCH05'!J24 -> 26933045 | N12: =+L12-U12 -> 26933045 | P12: =+L12-V12 -> 2636572.7 | S12: =+'SCH05'!Q24 -> 0 | T12: =+'SCH05'!R24 -> 2446561.4 | U12: =+'SCH05'!S24 -> 0 | V12: =+'SCH05'!T24 -> 24296473 | X12: =+'SCH05'!V24 -> 24296473 | Y12: =+'SCH05'!W24 -> 0 | Z12: =+'SCH05'!X24 -> 24772181
A13: =+Lau_SCH04!I12+Spa_SCH06!I13+'Mini Bar_SCH02'!I14+Tel_SCH03!I14 -> 237336.54 | C13: =+A13-S13 -> 237336.54 | E13: =+A13-T13 -> 95445.7 | J13: Other Operated Departments (OOD ) | L13: =Lau_SCH04!L12+Spa_SCH06!L13+'Mini Bar_SCH02'!L14+Tel_SCH03!L14 -> 2034561.3 | N13: =+L13-U13 -> 2034561.3 | P13: =+L13-V13 -> 625508.35 | S13: =+Lau_SCH04!S12+Spa_SCH06!S13+'Mini Bar_SCH02'!S14+Tel_SCH03!S14 -> 0 | T13: =+Lau_SCH04!T12+Spa_SCH06!T13+'Mini Bar_SCH02'!T14+Tel_SCH03!T14 -> 141890.84 | U13: =Lau_SCH04!U12+Spa_SCH06!U13+'Mini Bar_SCH02'!U14+Tel_SCH03!U14 -> 0 | V13: =+Lau_SCH04!V12+Spa_SCH06!V13+'Mini Bar_SCH02'!V14+Tel_SCH03!V14 -> 1409052.9 | X13: =+Lau_SCH04!X12+Spa_SCH06!X13+'Mini Bar_SCH02'!X14+Tel_SCH03!X14 -> 1967199.7 | Y13: =+Lau_SCH04!Y12+Spa_SCH06!Y13+'Mini Bar_SCH02'!Y14+Tel_SCH03!Y14 -> 0 | Z13: =+Lau_SCH04!Z12+Spa_SCH06!Z13+'Mini Bar_SCH02'!Z14++Tel_SCH03!Z14 -> 1327434.7
A14: =+Other_SCH09!J17 -> 322055.52 | C14: =+A14-S14 -> 322055.52 | E14: =+A14-T14 -> 199216.02 | G14: 611386.81 | J14: Other Income | L14: =+Other_SCH09!M17 -> 1635266.3 | N14: =+L14-U14 -> 1635266.3 | P14: =+L14-V14 -> -188339.68 | S14: =+Other_SCH09!T17 -> 0 | T14: =+Other_SCH09!U17 -> 122839.5 | U14: =+Other_SCH09!V17 -> 0 | V14: =+Other_SCH09!W17 -> 1823605.9 | X14: =+Other_SCH09!Y17 -> 1823605.9 | Y14: =+Other_SCH09!Z17 -> 0 | Z14: =+Other_SCH09!AA17 -> 2013707.2
A15: =+Room_SCH01!G27 -> 0 | C15: =+A15-S15 -> 0 | E15: =+A15-T15 -> 0 | J15: Extraordinary items | L15: =+Room_SCH01!J27 -> 0 | N15: =+L15-U15 -> 0 | P15: =+L15-V15 -> 0 | S15: =+Room_SCH01!Q27 -> 0 | T15: =+Room_SCH01!R27 -> 0 | U15: =+Room_SCH01!S27 -> 0 | V15: =+Room_SCH01!T27 -> 0 | X15: =+Room_SCH01!V27 -> 0 | Y15: =+Room_SCH01!W27 -> 0 | Z15: =+Room_SCH01!X27 -> 0
A16: =SUM(A11:A15) -> 8360926.4 | C16: =SUM(C11:C15) -> 8360926.4 | E16: =SUM(E11:E15) -> 4370023.3 | J16: Total Income | L16: =SUM(L11:L15) -> 1.1364348e+08 | N16: =SUM(N11:N15) -> 1.1364348e+08 | P16: =SUM(P11:P15) -> 8360254.6 | S16: =SUM(S11:S15) -> 0 | T16: =SUM(T11:T15) -> 3990903.1 | U16: =SUM(U11:U15) -> 0 | V16: =SUM(V11:V15) -> 1.0528322e+08 | X16: =SUM(X11:X15) -> 1.0584137e+08 | Y16: =SUM(Y11:Y15) -> 0 | Z16: =SUM(Z11:Z15) -> 98643916
J18: COST OF SALES
A19: =+'SCH05'!G27 -> 1259305.8 | C19: =+A19-S19 -> 1259305.8 | E19: =+A19-T19 -> 652524.25 | G19: -2377556.3 | J19: Food | L19: =+'SCH05'!J27 -> 5823021 | N19: =+L19-U19 -> 5823021 | P19: =+L19-V19 -> 355455.87 | S19: =+'SCH05'!Q27 -> 0 | T19: =+'SCH05'!R27 -> 606781.59 | U19: =+'SCH05'!S27 -> 0 | V19: =+'SCH05'!T27 -> 5467565.1 | X19: =+'SCH05'!V27 -> 5467565.1 | Y19: =+'SCH05'!W27 -> 0 | Z19: =+'SCH05'!X27 -> 5512254.8
A20: =+'SCH05'!G28 -> 390456.68 | C20: =+A20-S20 -> 390456.68 | E20: =+A20-T20 -> 161648.14 | G20: -1551714.5 | J20: Beverage | L20: =+'SCH05'!J28 -> 2278435.5 | N20: =+L20-U20 -> 2278435.5 | P20: =+L20-V20 -> 278209.06 | S20: =+'SCH05'!Q28 -> 0 | T20: =+'SCH05'!R28 -> 228808.54 | U20: =+'SCH05'!S28 -> 0 | V20: =+'SCH05'!T28 -> 2000226.5 | X20: =+'SCH05'!V28 -> 2000226.5 | Y20: =+'SCH05'!W28 -> 0 | Z20: =+'SCH05'!X28 -> 2038291.4
A21: =+'SCH05'!G30+'SCH05'!G29 -> 2490.88 | C21: =+A21-S21 -> 2490.88 | E21: =+A21-T21 -> 1790.88 | G21: -1551714.5 | J21: Cigar & Cigarette | L21: =+'SCH05'!J30+'SCH05'!J29 -> 51539.28 | N21: =+L21-U21 -> 51539.28 | P21: =+L21-V21 -> -20113.27 | S21: =+'SCH05'!Q30+'SCH05'!Q29 -> 0 | T21: =+'SCH05'!R30+'SCH05'!R29 -> 700 | U21: =+'SCH05'!S30+'SCH05'!S29 -> 0 | V21: =+'SCH05'!T30+'SCH05'!T29 -> 71652.55 | X21: =+'SCH05'!V30+'SCH05'!V29 -> 71652.55 | Y21: =+'SCH05'!W30+'SCH05'!W29 -> 0 | Z21: =+'SCH05'!X30+'SCH05'!X29 -> 119122.83
A22: =+Other_SCH09!J24+Lau_SCH04!I14+Spa_SCH06!I15+'Mini Bar_SCH02'!I18+Tel_SCH03!I20 -> 212381.4 | C22: =+A22-S22 -> 212381.4 | E22: =+A22-T22 -> 125657.95 | J22: Other Operated Departments (OOD ) | L22: =+Other_SCH09!M24+Lau_SCH04!L14+Spa_SCH06!L15+'Mini Bar_SCH02'!L18+Tel_SCH03!L20 -> 1008730.8 | N22: =+L22-U22 -> 1008730.8 | P22: =+L22-V22 -> 97218.03 | S22: =+Other_SCH09!T24+Lau_SCH04!S14+Spa_SCH06!S15+'Mini Bar_SCH02'!S18+Tel_SCH03!S20 -> 0 | T22: =+Other_SCH09!U24+Lau_SCH04!T14+Spa_SCH06!T15+'Mini Bar_SCH02'!T18++Tel_SCH03!T20 -> 86723.45 | U22: =+Other_SCH09!V24+Lau_SCH04!U14+Spa_SCH06!U15+'Mini Bar_SCH02'!U18++Tel_SCH03!U20 -> 0 | V22: =+Other_SCH09!W24+Lau_SCH04!V14+Spa_SCH06!V15+'Mini Bar_SCH02'!V18++Tel_SCH03!V20 -> 911512.73 | X22: =+Other_SCH09!Y24+Lau_SCH04!X14+Spa_SCH06!X15+'Mini Bar_SCH02'!X18++Tel_SCH03!X20 -> 992672.82 | Y22: =+Other_SCH09!Z24+Lau_SCH04!Y14+Spa_SCH06!Y15+'Mini Bar_SCH02'!Y18++Tel_SCH03!Y20 -> 0 | Z22: =+Other_SCH09!AA24+Lau_SCH04!Z14+Spa_SCH06!Z15+'Mini Bar_SCH02'!Z18++Tel_SCH03!Z20 -> 1138329.9
A23: =SUM(A19:A22) -> 1864634.8 | C23: =SUM(C19:C22) -> 1864634.8 | E23: =SUM(E19:E22) -> 941621.22 | J23: Total Cost of Sales | L23: =SUM(L19:L22) -> 9161726.6 | N23: =+L23-U23 -> 9161726.6 | P23: =+L23-V23 -> 710769.69 | S23: =SUM(S19:S22) -> 0 | T23: =SUM(T19:T22) -> 923013.58 | U23: =SUM(U19:U22) -> 0 | V23: =SUM(V19:V22) -> 8450956.9 | X23: =SUM(X19:X22) -> 8532116.9 | Y23: =SUM(Y19:Y22) -> 0 | Z23: =SUM(Z19:Z22) -> 8807999
J25: PAYROLL
A26: =+Room_SCH01!G33 -> 1604568.5 | C26: =+A26-S26 -> 1604568.5 | E26: =+A26-T26 -> 845313.05 | G26: -1331611.2 | J26: Rooms | L26: =+Room_SCH01!J33 -> 8930942.2 | N26: =+L26-U26 -> 8930942.2 | P26: =+L26-V26 -> 3401653.9 | S26: =+Room_SCH01!Q33 -> 0 | T26: =+Room_SCH01!R33 -> 759255.45 | U26: =+Room_SCH01!S33 -> 0 | V26: =+Room_SCH01!T33 -> 5529288.3 | X26: =+Room_SCH01!V33 -> 5529288.3 | Y26: =+Room_SCH01!W33 -> 0 | Z26: =+Room_SCH01!X33 -> 3628145.2
A27: =+'SCH05'!G36 -> 899492.44 | C27: =+A27-S27 -> 899492.44 | E27: =+A27-T27 -> 555030.75 | G27: -2474920.3 | J27: Food & Beverage | L27: =+'SCH05'!J36 -> 4631688.3 | N27: =+L27-U27 -> 4631688.3 | P27: =+L27-V27 -> 2157872.6 | S27: =+'SCH05'!Q36 -> 0 | T27: =+'SCH05'!R36 -> 344461.69 | U27: =+'SCH05'!S36 -> 0 | V27: =+'SCH05'!T36 -> 2473815.7 | X27: =+'SCH05'!V36 -> 2473815.7 | Y27: =+'SCH05'!W36 -> 0 | Z27: =+'SCH05'!X36 -> 2485772
A28: =+Other_SCH09!J31+Lau_SCH04!I21+Spa_SCH06!I22 -> 198894.12 | C28: =+A28-S28 -> 198894.12 | E28: =+A28-T28 -> 76585.41 | J28: Other Operated Departments (OOD ) | L28: =+Other_SCH09!M31+Lau_SCH04!L21+Spa_SCH06!L22 -> 938741.12 | N28: =+L28-U28 -> 938741.12 | P28: =+L28-V28 -> 211565.37 | S28: =+Other_SCH09!T31+Lau_SCH04!S21+Spa_SCH06!S22 -> 0 | T28: =+Other_SCH09!U31+Lau_SCH04!T21+Spa_SCH06!T22 -> 122308.71 | U28: =+Other_SCH09!V31+Lau_SCH04!U21+Spa_SCH06!U22 -> 0 | V28: =+Other_SCH09!W31+Lau_SCH04!V21+Spa_SCH06!V22 -> 727175.75 | X28: =+Other_SCH09!Y31+Lau_SCH04!X21+Spa_SCH06!X22 -> 727175.75 | Y28: =+Other_SCH09!Z31+Lau_SCH04!Y21+Spa_SCH06!Y22 -> 0 | Z28: =+Other_SCH09!AA31+Lau_SCH04!Z21+Spa_SCH06!Z22 -> 491000.9
A29: =SUM(A26:A28) -> 2702955.1 | C29: =SUM(C26:C28) -> 2702955.1 | E29: =SUM(E26:E28) -> 1476929.2 | J29: Total Payroll | L29: =SUM(L26:L28) -> 14501372 | N29: =SUM(N26:N28) -> 14501372 | P29: =SUM(P26:P28) -> 5771091.9 | S29: =SUM(S26:S28) -> 0 | T29: =SUM(T26:T28) -> 1226025.8 | U29: =SUM(U26:U28) -> 0 | V29: =SUM(V26:V28) -> 8730279.8 | X29: =SUM(X26:X28) -> 8730279.8 | Y29: =SUM(Y26:Y28) -> 0 | Z29: =SUM(Z26:Z28) -> 6604918.1
J31: OTHER EXPENSES
A32: =+Room_SCH01!G63 -> 650238.08 | C32: =+A32-S32 -> 650238.08 | E32: =+A32-T32 -> 294751.29 | G32: -1272560.5 | J32: Rooms | L32: =+Room_SCH01!J63 -> 6823040.2 | N32: =+L32-U32 -> 6823040.2 | P32: =+L32-V32 -> 852316.77 | S32: =+Room_SCH01!Q63 -> 0 | T32: =+Room_SCH01!R63 -> 355486.79 | U32: =+Room_SCH01!S63 -> 0 | V32: =+Room_SCH01!T63 -> 5970723.5 | X32: =+Room_SCH01!V63 -> 5970723.5 | Y32: =+Room_SCH01!W63 -> 0 | Z32: =+Room_SCH01!X63 -> 6101740.6
A33: =+'SCH05'!G68 -> 501612.24 | C33: =+A33-S33 -> 501612.24 | E33: =+A33-T33 -> 357652.44 | G33: -1195673.2 | J33: Food & Beverage | L33: =+'SCH05'!J68 -> 2050878.5 | N33: =+L33-U33 -> 2050878.5 | P33: =+L33-V33 -> 560347.56 | S33: =+'SCH05'!Q68 -> 0 | T33: =+'SCH05'!R68 -> 143959.8 | U33: =+'SCH05'!S68 -> 0 | V33: =+'SCH05'!T68 -> 1490531 | X33: =+'SCH05'!V68 -> 1490531 | Y33: =+'SCH05'!W68 -> 0 | Z33: =+'SCH05'!X68 -> 1652793.3
A34: =+Lau_SCH04!I33+Spa_SCH06!I49+'Mini Bar_SCH02'!I33+Tel_SCH03!I34 -> 19523.58 | C34: =+A34-S34 -> 19523.58 | E34: =+A34-T34 -> 4302.71 | J34: Other Operated Departments (OOD ) | L34: =+Lau_SCH04!L33+Spa_SCH06!L49+'Mini Bar_SCH02'!L33+Tel_SCH03!L34 -> 79845.43 | N34: =+L34-U34 -> 79845.43 | P34: =+L34-V34 -> -74069.16 | S34: =+'Mini Bar_SCH02'!S35+Tel_SCH03!S34+Lau_SCH04!S33+Spa_SCH06!S49 -> 0 | T34: =+'Mini Bar_SCH02'!T35+Tel_SCH03!T34+Lau_SCH04!T33+Spa_SCH06!T49 -> 15220.87 | U34: =+'Mini Bar_SCH02'!U35+Tel_SCH03!U34+Lau_SCH04!U33+Spa_SCH06!U49 -> 0 | V34: =+'Mini Bar_SCH02'!V35+Tel_SCH03!V34+Lau_SCH04!V33+Spa_SCH06!V49 -> 153914.59 | X34: =+'Mini Bar_SCH02'!X35+Tel_SCH03!X34+Lau_SCH04!X33+Spa_SCH06!X49 -> 153897.22 | Y34: =+'Mini Bar_SCH02'!Y35+Tel_SCH03!Y34+Lau_SCH04!Y33+Spa_SCH06!Y49 -> 0 | Z34: =+'Mini Bar_SCH02'!Z35+Tel_SCH03!Z34+Lau_SCH04!Z33+Spa_SCH06!Z49 -> 80657.3
A35: =SUM(A32:A34) -> 1171373.9 | C35: =SUM(C32:C34) -> 1171373.9 | E35: =SUM(E32:E34) -> 656706.44 | J35: Total Other Expenses | L35: =SUM(L32:L34) -> 8953764.2 | N35: =SUM(N32:N34) -> 8953764.2 | P35: =SUM(P32:P34) -> 1338595.2 | S35: =SUM(S32:S34) -> 0 | T35: =SUM(T32:T34) -> 514667.46 | U35: =SUM(U32:U34) -> 0 | V35: =SUM(V32:V34) -> 7615169 | X35: =SUM(X32:X34) -> 7615151.7 | Y35: =SUM(Y32:Y34) -> 0 | Z35: =SUM(Z32:Z34) -> 7835191.2
J37: OPERATING DEPT. PROFIT
A38: =+A11+A15-A26-A32 -> 638894.98 | C38: =+A38-S38 -> 638894.98 | E38: =+A38-T38 -> 474025.85 | G38: 17571642 | J38: Rooms | L38: =+L11+L15-L26-L32 -> 67286620 | N38: =+N11-N26-N32 -> 67286620 | P38: =+P11-P26-P32 -> 1032542.6 | S38: =+S11-S26-S32 -> 0 | T38: =+T11-T26-T32 -> 164869.13 | U38: =+U11-U26-U32 -> 0 | V38: =+V11-V26-V32 -> 66254077 | X38: =+X11-X26-X32 -> 66254077 | Y38: =+Y11-Y26-Y32 -> 0 | Z38: =+Z11-Z26-Z32 -> 60800707
A39: =+A12-A19-A20-A27-A33-A21 -> 1854474.7 | C39: =+A39-S39 -> 1854474.7 | E39: =+A39-T39 -> 732624.89 | G39: 5823947.9 | J39: Food & Beverage | L39: =+L12-L19-L20-L27-L33-L21 -> 12097483 | N39: =+N12-N19-N20-N27-N33-N21 -> 12097483 | P39: =+P12-P19-P20-P27-P33-P21 -> -695199.2 | S39: =+S12-S19-S20-S27-S33-S21 -> 0 | T39: =+T12-T19-T20-T27-T33-T21 -> 1121849.8 | U39: =+U12-U19-U20-U27-U33-U21 -> 0 | V39: =+V12-V19-V20-V27-V33-V21 -> 12792682 | X39: =+X12-X19-X20-X27-X33-X21 -> 12792682 | Y39: =+Y12-Y19-Y20-Y27-Y33-Y21 -> 0 | Z39: =+Z12-Z19-Z20-Z27-Z33-Z21 -> 12963947
A40: =+A13-A22-A28-A34 -> -193462.56 | C40: =+A40-S40 -> -193462.56 | E40: =+A40-T40 -> -111100.37 | J40: Other Operated Departments (OOD ) | L40: =+L13-L22-L28-L34 -> 7243.96 | N40: =+L40-U40 -> 7243.96 | P40: =+L40-V40 -> 390794.11 | S40: =+S13-S22-S28-S34 -> 0 | T40: =+T13-T22-T28-T34 -> -82362.19 | U40: =+U13-U22-U28-U34 -> 0 | V40: =+V13-V22-V28-V34 -> -383550.15 | X40: =+X13-X22-X28-X34 -> 93453.9 | Y40: =+Y13-Y22-Y28-Y34 -> 0 | Z40: =+Z13-Z22-Z28-Z34 -> -382553.34
A41: =+A14 -> 322055.52 | C41: =+A41-S41 -> 322055.52 | E41: =+A41-T41 -> 199216.02 | G41: 611386.81 | L41: =+L14 -> 1635266.3 | N41: =+L41-U41 -> 1635266.3 | P41: =+L41-V41 -> -188339.68 | S41: =+S14 -> 0 | T41: =+T14 -> 122839.5 | U41: =+U14 -> 0 | V41: =+V14 -> 1823605.9 | X41: =+X14 -> 1823605.9 | Y41: =+Y14 -> 0 | Z41: =+Z14 -> 2013707.2
A42: =SUM(A38:A41) -> 2621962.6 | C42: =SUM(C38:C41) -> 2621962.6 | E42: =SUM(E38:E41) -> 1294766.4 | J42: Total Op. Dept. Profit | L42: =SUM(L38:L41) -> 81026613 | N42: =+L42-U42 -> 81026613 | P42: =+L42-V42 -> 539797.87 | S42: =SUM(S38:S41) -> 0 | T42: =SUM(T38:T41) -> 1327196.2 | U42: =SUM(U38:U41) -> 0 | V42: =SUM(V38:V41) -> 80486815 | X42: =SUM(X38:X41) -> 80963819 | Y42: =SUM(Y38:Y41) -> 0 | Z42: =SUM(Z38:Z41) -> 75395808
I44: Op. Dept. Profit b/f
J46: NON-OPERATED DEPTS.
A47: =+AG_SCH11!I58 -> 3122073.2 | C47: =+A47-S47 -> 3122073.2 | E47: =+A47-T47 -> 1712858.4 | G47: -1860798 | J47: Hotel Administration | L47: =+AG_SCH11!L58 -> 11867446 | N47: =+L47-U47 -> 11867446 | P47: =+L47-V47 -> 1160677.2 | S47: =+AG_SCH11!S58 -> 0 | T47: =+AG_SCH11!T58 -> 1409214.8 | U47: =+AG_SCH11!U58 -> 0 | V47: =+AG_SCH11!V58 -> 10706769 | X47: =+AG_SCH11!X58 -> 11867446 | Y47: =+AG_SCH11!Y58 -> 0 | Z47: =+AG_SCH11!Z58 -> 10706769
A48: =+HR_SCH12!I37 -> 363779.46 | C48: =+A48-S48 -> 363779.46 | E48: =+A48-T48 -> 169839.26 | G48: -453630.28 | J48: Human Resources | L48: =+HR_SCH12!L37 -> 1635471 | N48: =+L48-U48 -> 1635471 | P48: =+L48-V48 -> 426835.75 | S48: =+HR_SCH12!S37 -> 0 | T48: =+HR_SCH12!T37 -> 193940.2 | U48: =+HR_SCH12!U37 -> 0 | V48: =+HR_SCH12!V37 -> 1208635.2 | X48: =+HR_SCH12!X37 -> 1208635.2 | Y48: =+HR_SCH12!Y37 -> 0 | Z48: =+HR_SCH12!Z37 -> 933468.52
A49: =+SM_SCH13!I59 -> 1287742.3 | C49: =+A49-S49 -> 1287742.3 | E49: =+A49-T49 -> 797001.87 | G49: -1200653.9 | J49: Marketing | L49: =+SM_SCH13!L59 -> 8295787.6 | N49: =+L49-U49 -> 8295787.6 | P49: =+L49-V49 -> 1259691.8 | S49: =+SM_SCH13!S59 -> 0 | T49: =+SM_SCH13!T59 -> 490740.47 | U49: =+SM_SCH13!U59 -> 0 | V49: =+SM_SCH13!V59 -> 7036095.8 | X49: =+SM_SCH13!X59 -> 7036095.8 | Y49: =+SM_SCH13!Y59 -> 0 | Z49: =+SM_SCH13!Z59 -> 6840774
A50: =+RM_SCH14!I71 -> 2681934.7 | C50: =+A50-S50 -> 2681934.7 | E50: =+A50-T50 -> 1569810 | G50: -3472520.3 | J50: POMEC | L50: =+RM_SCH14!L71 -> 11147340 | N50: =+L50-U50 -> 11147340 | P50: =+L50-V50 -> 3721393 | S50: =+RM_SCH14!S71 -> 0 | T50: =+RM_SCH14!T71 -> 1112124.8 | U50: =+RM_SCH14!U71 -> 0 | V50: =+RM_SCH14!V71 -> 7425947.1 | X50: =+RM_SCH14!X71 -> 7425947.1 | Y50: =+RM_SCH14!Y71 -> 0 | Z50: =+RM_SCH14!Z71 -> 9274638.5
A52: =SUM(A47:A51) -> 7455529.8 | C52: =SUM(C47:C51) -> 7455529.8 | E52: =SUM(E47:E51) -> 4249509.5 | G52: -7957251.6 | J52: Total Undistributed Op. Exps | L52: =SUM(L47:L51) -> 32946045 | N52: =+L52-U52 -> 32946045 | P52: =+L52-V52 -> 6568597.8 | S52: =SUM(S47:S51) -> 0 | T52: =SUM(T47:T51) -> 3206020.2 | U52: =SUM(U47:U51) -> 0 | V52: =SUM(V47:V51) -> 26377447 | X52: =SUM(X47:X51) -> 27538124 | Y52: =SUM(Y47:Y51) -> 0 | Z52: =SUM(Z47:Z51) -> 27755650
A54: =+A42-A52 -> -4833567.1 | C54: =+A54-S54 -> -4833567.1 | E54: =+A54-T54 -> -2954743.1 | J54: GROSS OPERATING PROFIT | L54: =+L42-L52 -> 48080568 | N54: =+L54-U54 -> 48080568 | P54: =+L54-V54 -> -6028799.9 | S54: =+S42-S52 -> 0 | T54: =+T42-T52 -> -1878824 | U54: =+U42-U52 -> 0 | V54: =+V42-V52 -> 54109368 | X54: =+X42-X52 -> 53425695 | Y54: =+Y42-Y52 -> 0 | Z54: =+Z42-Z52 -> 47640158
A56: ='Add&Deduct'!I9 -> 816951.68 | C56: =+A56-S56 -> 816951.68 | E56: =+A56-T56 -> 429594.23 | G56: 0 | J56: Other Income | L56: ='Add&Deduct'!L9 -> 11188869 | N56: =+L56-U56 -> 11188869 | P56: =+L56-V56 -> 838005.66 | S56: ='Add&Deduct'!S9 -> 0 | T56: ='Add&Deduct'!T9 -> 387357.45 | U56: ='Add&Deduct'!U9 -> 0 | V56: ='Add&Deduct'!V9 -> 10350863 | X56: ='Add&Deduct'!X9 -> 10350863 | Y56: ='Add&Deduct'!Y9 -> 0 | Z56: ='Add&Deduct'!Z9 -> 9708402.6
A57: 0 | C57: =+A57-S57 -> 0 | E57: =+A57-T57 -> 0 | G57: -13042921 | J57: Rental & Owners Return | L57: 0 | N57: =+L57-U57 -> 0 | P57: =+L57-V57 -> 0 | S57: 0 | T57: 0 | U57: 0 | V57: 0 | X57: 0 | Y57: 0 | Z57: 0
A58: ='Add&Deduct'!I15 -> 2647017.5 | C58: =+A58-S58 -> 2647017.5 | E58: =+A58-T58 -> 2180476.5 | G58: 0 | J58: Depreciation & Amortisation | L58: ='Add&Deduct'!L15 -> 9248398.9 | N58: =+L58-U58 -> 9248398.9 | P58: =+L58-V58 -> 6466145.2 | S58: ='Add&Deduct'!S15 -> 0 | T58: ='Add&Deduct'!T15 -> 466541.02 | U58: ='Add&Deduct'!U15 -> 0 | V58: ='Add&Deduct'!V15 -> 2782253.7 | X58: ='Add&Deduct'!X15 -> 2782253.7 | Y58: ='Add&Deduct'!Y15 -> 0 | Z58: ='Add&Deduct'!Z15 -> 2694371.8
A59: ='Add&Deduct'!I13 -> 0 | C59: =+A59-S59 -> 0 | E59: =+A59-T59 -> 0 | G59: 1449213.4 | J59: Management Fee - Incentive | L59: ='Add&Deduct'!L13 -> 0 | N59: =+L59-U59 -> 0 | P59: =+L59-V59 -> 0 | S59: ='Add&Deduct'!S13 -> 0 | T59: ='Add&Deduct'!T13 -> 0 | U59: ='Add&Deduct'!U13 -> 0 | V59: ='Add&Deduct'!V13 -> 0 | X59: ='Add&Deduct'!X13 -> 0 | Y59: ='Add&Deduct'!Y13 -> 0 | Z59: ='Add&Deduct'!Z13 -> 0
A60: ='Add&Deduct'!I11 -> 6281885 | C60: =+A60-S60 -> 6281885 | E60: =+A60-T60 -> 4779426 | G60: 1086442.9 | J60: Other Additions/Deductions | L60: ='Add&Deduct'!L11 -> 12915129 | N60: =+L60-U60 -> 12915129 | P60: =+L60-V60 -> 402119.53 | S60: ='Add&Deduct'!S11 -> 0 | T60: ='Add&Deduct'!T11 -> 1502459.1 | U60: ='Add&Deduct'!U11 -> 0 | V60: ='Add&Deduct'!V11 -> 12513010 | X60: ='Add&Deduct'!X11 -> 12513010 | Y60: ='Add&Deduct'!Y11 -> 0 | Z60: ='Add&Deduct'!Z11 -> 10315865
A62: =A54-A57-A58-A59-A60 -> -13762470 | C62: =+A62-S62 -> -13762470 | E62: =+A62-T62 -> -9914645.6 | J62: RAMADA KHAO LAK PBIT | L62: =L54-L57-L58-L59-L60 -> 25917040 | N62: =+L62-U62 -> 25917040 | P62: =+L62-V62 -> -12897065 | S62: =S54-S57-S58-S59-S60 -> 0 | T62: =T54-T57-T58-T59-T60 -> -3847824.1 | U62: =U54-U57-U58-U59-U60 -> 0 | V62: =V54-V57-V58-V59-V60 -> 38814104 | X62: =X54-X57-X58-X59-X60 -> 38130431 | Y62: =Y54-Y57-Y58-Y59-Y60 -> 0 | Z62: =Z54-Z57-Z58-Z59-Z60 -> 34629921
A64: ='Add&Deduct'!I14 -> 0 | C64: =+A64-S64 -> 0 | E64: =+A64-T64 -> 0 | G64: 0 | J64: Interest Expense | L64: ='Add&Deduct'!L14 -> 0 | N64: =+L64-U64 -> 0 | P64: =+L64-V64 -> 0 | S64: ='Add&Deduct'!S14 -> 0 | T64: ='Add&Deduct'!T14 -> 0 | U64: ='Add&Deduct'!U14 -> 0 | V64: ='Add&Deduct'!V14 -> 0 | X64: 0 | Y64: 0 | Z64: 0
A65: 0 | C65: =+A65-S65 -> 0 | E65: =+A65-T65 -> 0 | G65: 0 | J65: Income Taxes | L65: 0 | N65: =+L65-U65 -> 0 | P65: =+L65-V65 -> 0 | S65: 0 | T65: 0 | U65: 0 | V65: 0 | X65: 0 | Y65: 0 | Z65: 0
A66: 0 | C66: =+A66-S66 -> 0 | E66: =+A66-T66 -> 0 | G66: 0 | J66: Head Office Royalties | L66: 0 | N66: =+L66-U66 -> 0 | P66: =+L66-V66 -> 0 | S66: 0 | T66: 0 | U66: 0 | V66: 0 | X66: 0 | Y66: 0 | Z66: 0
A68: =+A62-A64-A65-A66 -> -13762470 | C68: =+C62-C64-C65-C66 -> -13762470 | E68: =+E62-E64-E65-E66 -> -9914645.6 | J68: NET PROFIT | L68: =+L62-L64-L65-L66 -> 25917040 | N68: =+L68-U68 -> 25917040 | P68: =+L68-V68 -> -12897065 | S68: =+S62-S64-S65-S66 -> 0 | T68: =+T62-T64-T65-T66 -> -3847824.1 | U68: =+U62-U64-U65-U66 -> 0 | V68: =+V62-V64-V65-V66 -> 38814104 | X68: =+X62-X64-X65-X66 -> 38130431 | Y68: =+Y62-Y64-Y65-Y66 -> 0 | Z68: =+Z62-Z64-Z65-Z66 -> 34629921
J72: KPI's
A73: =116*30 -> 3480 | C73: =+A73-S73 -> 0 | E73: =+A73-T73 -> 0 | G73: 9176 | J73: Available Rooms | L73: =3596+3364+3596+3480+3596+3480+3596+A73 -> 28188 | N73: =+L73-U73 -> 7192 | P73: =+L73-V73 -> 7192 | S73: 3480 | T73: =116*30 -> 3480 | U73: 20996 | V73: 20996 | X73: 3596
A74: 1399 | C74: 1762 | E74: =+A74-T74 -> 32 | G74: 7640 | J74: Occupied Rooms | L74: =3191+3156+3230+2969+2351+1461+1960+A74 -> 19717 | N74: =+L74-U74 -> 3619 | P74: =+L74-V74 -> 6017 | S74: 1760 | T74: 1367 | U74: 16098 | V74: 13700 | X74: 1888
A75: =+A74/A73*100 -> 40.201149 | C75: =+A75-S75 -> -10.373563 | E75: =+A75-T75 -> 0.91954023 | G75: 0.8326068 | J75: Occupancy % | L75: =+L74/L73*100 -> 69.948205 | N75: =+L75-U75 -> -6.7235421 | P75: =+L75-V75 -> 4.697681 | S75: =+S74/S73*100 -> 50.574713 | T75: =+T74/T73*100 -> 39.281609 | U75: =+U74/U73*100 -> 76.671747 | V75: =+V74/V73*100 -> 65.250524
A76: 2876 | C76: =+A76-S76 -> -644 | E76: =+A76-T76 -> -10 | G76: 7640 | J76: Number of Guest | L76: =6763+6629+7036+6521+4802+2904+4420+A76 -> 41951 | N76: =+L76-U76 -> 9755 | P76: =+L76-V76 -> 14864 | S76: 3520 | T76: 2886 | U76: 32196 | V76: 27087 | X76: 3855
A77: =+A11/A74 -> 2068.4071 | C77: =+A77-S77 -> 2068.4071 | E77: =+A77-T77 -> 1132.3344 | G77: 2618.0091 | J77: Average Room Rate | L77: =+L11/L74 -> 4211.6246 | N77: =+L77-U77 -> 4211.6246 | P77: =+L77-V77 -> -1463.8563 | S77: =+S11/S74 -> 0 | T77: =+T11/T74 -> 936.07269 | U77: =+U11/U74 -> 0 | V77: =+V11/V74 -> 5675.4809
A78: =+A77*A75/100 -> 831.52344 | C78: =+A78-S78 -> 831.52344 | E78: =+A78-T78 -> 463.81902 | G78: 2179.7722 | J78: RevPar | L78: =+L77*L75/100 -> 2945.9558 | N78: =+L78-U78 -> 2945.9558 | P78: =+L78-V78 -> -757.32525 | S78: =+S77*S75/100 -> 0 | T78: =+T77*T75/100 -> 367.70442 | U78: =+U77*U75/100 -> 0 | V78: =+V77*V75/100 -> 3703.2811
A79: =A74/222 -> 6.3018018 | C79: =+A79-S79 -> 6.3018018 | E79: =+A79-T79 -> -0.46552493 | G79: -174.29466 | J79: Average Length Stay | L79: =20450/28304 -> 0.72251272 | N79: =+L79-U79 -> 0.72251272 | P79: =+L79-V79 -> -2.0078294 | S79: 0 | T79: =T74/202 -> 6.7673267 | U79: 0 | V79: 2.7303421 | X79: =X74/295 -> 6.4
A80: =+A115/A74 -> 972.48924 | C80: =+A80-S80 -> 972.48924 | E80: =+A80-T80 -> 417.07193 | G80: -174.29466 | J80: Rooms Payroll per Occ Room | L80: =+L115/L74 -> 303.15518 | N80: =+L80-U80 -> 303.15518 | P80: =+L80-V80 -> -100.4425 | S80: =+S115/S74 -> 0 | T80: =+T115/T74 -> 555.4173 | U80: =+U115/U74 -> 0 | V80: =+V115/V74 -> 403.59769
A81: =+A32/A74 -> 464.78776 | C81: =+A81-S81 -> 464.78776 | E81: =+A81-T81 -> 204.7389 | G81: -166.56551 | J81: Rooms Other Exp per Occ Room | L81: =+L32/L74 -> 346.0486 | N81: =+L81-U81 -> 346.0486 | P81: =+L81-V81 -> -89.770632 | S81: =+S32/S74 -> 0 | T81: =+T32/T74 -> 260.04886 | U81: =+U32/U74 -> 0 | V81: =+V32/V74 -> 435.81923
A82: =+A38/A42*100 -> 24.367051 | C82: =+A82-S82 -> #DIV/0! | E82: =+A82-T82 -> 11.944689 | G82: 0.87092606 | J82: Rooms Profit % Total Profit | L82: =+L38/L42*100 -> 83.042617 | N82: =+L82-U82 -> #DIV/0! | P82: =+L82-V82 -> 0.72593301 | S82: =+S38/S42*100 -> #DIV/0! | T82: =+T38/T42*100 -> 12.422363 | U82: =+U38/U42*100 -> #DIV/0! | V82: =+V38/V42*100 -> 82.316684
A83: 11788 | C83: =+A83-S83 -> 2564 | E83: =+A83-T83 -> 4668 | G83: 26951 | J83: Total Food Cover | L83: =14190+12281+14352+14585+11423+8570+11636+A83 -> 98825 | N83: =+L83-U83 -> 44079.5 | P83: =+L83-V83 -> 65610 | S83: 9224 | T83: 7120 | U83: 54745.5 | V83: 33215 | X83: 8723
A84: 6560 | C84: =+A84-S84 -> -2664 | E84: =+A84-T84 -> 2169 | J84: Total Beverage Cover | L84: =7553+5708+7456+8182+6388+5900+7137+A84 -> 54884 | N84: =+L84-U84 -> 138.5 | P84: =+L84-V84 -> 21915 | S84: 9224 | T84: 4391 | U84: 54745.5 | V84: 32969 | X84: 4890
A85: =+A110/A83 -> 280.25121 | C85: =+A85-S85 -> 280.25121 | E85: =+A85-T85 -> 59.860779 | G85: 254.71673 | J85: Average Food Check | L85: =+L110/L83 -> 192.81788 | N85: =+L85-U85 -> 192.81788 | P85: =+L85-V85 -> -330.08746 | S85: =+S110/S83 -> 0 | T85: =+T110/T83 -> 220.39043 | U85: =+U110/U83 -> 0 | V85: =+V110/V83 -> 522.90534
A86: =+A111/A84 -> 194.52161 | C86: =+A86-S86 -> 194.52161 | E86: =+A86-T86 -> 40.324602 | J86: Average Beverage Check | L86: =+L111/L84 -> 124.60764 | N86: =+L86-U86 -> 124.60764 | P86: =+L86-V86 -> -57.587225 | S86: =+S111/S84 -> 0 | T86: =+T111/T84 -> 154.19701 | U86: =+U111/U84 -> 0 | V86: =+V111/V84 -> 182.19486
A87: =+A19/A110*100 -> 38.119183 | C87: =+A87-S87 -> #DIV/0! | E87: =+A87-T87 -> -0.54952457 | G87: -0.34633665 | J87: COS Food % | L87: =+L19/L110*100 -> 30.558655 | N87: =+L87-U87 -> #DIV/0! | P87: =+L87-V87 -> -0.92148366 | S87: =+S19/S110*100 -> #DIV/0! | T87: =+T19/T110*100 -> 38.668708 | U87: =+U19/U110*100 -> #DIV/0! | V87: =+V19/V110*100 -> 31.480138
A88: =+A20/A111*100 -> 30.598572 | C88: =+A88-S88 -> #DIV/0! | E88: =+A88-T88 -> -3.1949023 | G88: -0.24395368 | J88: COS Beverage % | L88: =+L20/L111*100 -> 33.315499 | N88: =+L88-U88 -> #DIV/0! | P88: =+L88-V88 -> 0.016033265 | S88: =+S20/S111*100 -> #DIV/0! | T88: =+T20/T111*100 -> 33.793475 | U88: =+U20/U111*100 -> #DIV/0! | V88: =+V20/V111*100 -> 33.299465
A89: =+A116/A12*100 -> 15.541823 | C89: =+A89-S89 -> #DIV/0! | E89: =+A89-T89 -> 1.4624012 | G89: -0.18436792 | J89: F&B Payroll % per Total F&B Revenue | L89: =+L116/L12*100 -> 11.671865 | N89: =+L89-U89 -> #DIV/0! | P89: =+L89-V89 -> 1.4900756 | S89: =+S116/S12*100 -> #DIV/0! | T89: =+T116/T12*100 -> 14.079421 | U89: =+U116/U12*100 -> #DIV/0! | V89: =+V116/V12*100 -> 10.181789
A90: =A33/A12*100 -> 10.220647 | C90: =+A90-S90 -> #DIV/0! | E90: =+A90-T90 -> 4.3364779 | G90: -0.08907106 | J90: F&B Other Expenses % | L90: =L33/L12*100 -> 7.6147294 | N90: =+L90-U90 -> #DIV/0! | P90: =+L90-V90 -> 1.4799666 | S90: =S33/S12*100 -> #DIV/0! | T90: =T33/T12*100 -> 5.8841687 | U90: =U33/U12*100 -> #DIV/0! | V90: =V33/V12*100 -> 6.1347628
A91: =+A39/A12*100 -> 37.78602 | C91: =+A91-S91 -> #DIV/0! | E91: =+A91-T91 -> -8.0681237 | G91: 0.43385201 | J91: F&B Profit % Total F&B Revenue | L91: =+L39/L12*100 -> 44.916877 | N91: =+L91-U91 -> #DIV/0! | P91: =+L91-V91 -> -7.7355479 | S91: =+S39/S12*100 -> #DIV/0! | T91: =+T39/T12*100 -> 45.854144 | U91: =+U39/U12*100 -> #DIV/0! | V91: =+V39/V12*100 -> 52.652424
A92: =+A117/A122*100 -> 3.6604064 | C92: =+A92-S92 -> #DIV/0! | E92: =+A92-T92 -> -1.4149088 | J92: OOD Payroll % Total Payroll | L92: =+L117/L122*100 -> 3.7613505 | N92: =+L92-U92 -> #DIV/0! | P92: =+L92-V92 -> -0.64430545 | S92: =+S117/S122*100 -> #DIV/0! | T92: =+T117/T122*100 -> 5.0753152 | U92: =+U117/U122*100 -> #DIV/0! | V92: =+V117/V122*100 -> 4.405656
A93: =+A40/A42*100 -> -7.37854 | C93: =+A93-S93 -> #DIV/0! | E93: =+A93-T93 -> -1.1728118 | J93: OOD Profit % Total Profit | L93: =+L40/L42*100 -> 0.0089402232 | N93: =+L93-U93 -> #DIV/0! | P93: =+L93-V93 -> 0.48547809 | S93: =+S40/S42*100 -> #DIV/0! | T93: =+T40/T42*100 -> -6.2057281 | U93: =+U40/U42*100 -> #DIV/0! | V93: =+V40/V42*100 -> -0.47653787
A94: =+A47/A73 -> 897.14748 | C94: =+A94-S94 -> 897.14748 | E94: =+A94-T94 -> 492.2007 | G94: -202.78967 | J94: Hotel Admin per Avail Room | L94: =+L47/L73 -> 421.01058 | N94: =+L94-U94 -> 421.01058 | P94: =+L94-V94 -> -88.932694 | S94: =+S47/S73 -> 0 | T94: =+T47/T73 -> 404.94678 | U94: =+U47/U73 -> 0 | V94: =+V47/V73 -> 509.94327
A95: =+A49/A73 -> 370.0409 | C95: =+A95-S95 -> 370.0409 | E95: =+A95-T95 -> 229.02353 | G95: -130.8472 | J95: Marketing per Avail Room | L95: =+L49/L73 -> 294.3021 | N95: =+L95-U95 -> 294.3021 | P95: =+L95-V95 -> -40.813911 | S95: =+S49/S73 -> 0 | T95: =+T49/T73 -> 141.01738 | U95: =+U49/U73 -> 0 | V95: =+V49/V73 -> 335.11601
A96: =+A113/A73 -> 308.66315 | C96: =+A96-S96 -> 308.66315 | E96: =+A96-T96 -> 186.58242 | G96: -257.41096 | J96: Energy per Avail Room | L96: =+L113/L73 -> 144.43654 | N96: =+L96-U96 -> 144.43654 | P96: =+L96-V96 -> -15.372995 | S96: =+S113/S73 -> 0 | T96: =+T113/T73 -> 122.08073 | U96: =+U113/U73 -> 0 | V96: =+V113/V73 -> 159.80954
A97: =+(A50-A113)/A73 -> 462.00775 | C97: =+A97-S97 -> 462.00775 | E97: =+A97-T97 -> 264.51239 | G97: -121.02412 | J97: POM per Avail Room | L97: =+(L50-L113)/L73 -> 251.02749 | N97: =+L97-U97 -> 251.02749 | P97: =+L97-V97 -> 57.153129 | S97: =+(S50-S113)/S73 -> 0 | T97: =+(T50-T113)/T73 -> 197.49535 | U97: =+(U50-U113)/U73 -> 0 | V97: =+(V50-V113)/V73 -> 193.87436
J98: Total Non Op Dept %
A99: =+A54/A16*100 -> -57.811383 | C99: =+A99-S99 -> #DIV/0! | E99: =+A99-T99 -> -10.733718 | J99: GOP % | L99: =+L54/L16*100 -> 42.308252 | N99: =+L99-U99 -> #DIV/0! | P99: =+L99-V99 -> -9.085852 | S99: =+S54/S16*100 -> #DIV/0! | T99: =+T54/T16*100 -> -47.077665 | U99: =+U54/U16*100 -> #DIV/0! | V99: =+V54/V16*100 -> 51.394104
A100: =+A122 -> 4733354.2 | C100: =+A100-S100 -> 4733354.2 | E100: =+A100-T100 -> 2323480 | G100: -6886865.3 | J100: Total Hotel Payroll | L100: =+L122 -> 18546796 | N100: =+L100-U100 -> 18546796 | P100: =+L100-V100 -> 2041291.2 | S100: =+S122 -> 0 | T100: =+T122 -> 2409874.2 | U100: =+U122 -> 0 | V100: =+V122 -> 16505505
A101: =+A122/A16*100 -> 56.612796 | C101: =+A101-S101 -> #DIV/0! | E101: =+A101-T101 -> -3.7713851 | J101: Total Hotel Payroll % to Revenue | L101: =+L122/L16*100 -> 16.320159 | N101: =+L101-U101 -> #DIV/0! | P101: =+L101-V101 -> 0.64291756 | S101: =+S122/S16*100 -> #DIV/0! | T101: =+T122/T16*100 -> 60.384181 | U101: =+U122/U16*100 -> #DIV/0! | V101: =+V122/V16*100 -> 15.677241
J102: Conversion ratios
G103: 0.87092606 | J103: Rooms Division
G104: 0.43385201 | J104: Food & Beverage Department
J105: Other Operated Departments
J106: Gross Operating Profit
A110: =+'SCH05'!G13 -> 3303601.3 | C110: =+A110-S110 -> 3303601.3 | E110: =+A110-T110 -> 1734421.4 | J110: Food Revenue | L110: =+'SCH05'!J13 -> 19055227 | N110: =+L110-U110 -> 19055227 | P110: =+L110-V110 -> 1686926.1 | S110: =+'SCH05'!Q13 -> 0 | T110: ='SCH05'!R13 -> 1569179.9 | U110: =+'SCH05'!S13 -> 0 | V110: ='SCH05'!T13 -> 17368301
A111: =+'SCH05'!G17 -> 1276061.8 | C111: =+A111-S111 -> 1276061.8 | E111: =+A111-T111 -> 598982.7 | J111: Beverage Revenue | L111: =+'SCH05'!J17 -> 6838965.7 | N111: =+L111-U111 -> 6838965.7 | P111: =+L111-V111 -> 832183.18 | S111: =+'SCH05'!Q17 -> 0 | T111: ='SCH05'!R17 -> 677079.06 | U111: =+'SCH05'!S17 -> 0 | V111: ='SCH05'!T17 -> 6006782.5
A113: =+RM_SCH14!I14 -> 1074147.8 | C113: =+A113-S113 -> 1074147.8 | E113: =+A113-T113 -> 649306.82 | J113: Electricity | L113: =+RM_SCH14!L14 -> 4071377.2 | N113: =+L113-U113 -> 4071377.2 | P113: =+L113-V113 -> 716016.2 | S113: =+RM_SCH14!S14 -> 0 | T113: =RM_SCH14!T11 -> 424840.94 | U113: =+RM_SCH14!U14 -> 0 | V113: =RM_SCH14!V11 -> 3355361
A115: =+Room_SCH01!G31 -> 1360512.4 | C115: =+A115-S115 -> 1360512.4 | E115: =+A115-T115 -> 601256.99 | J115: Room Payroll | L115: =+Room_SCH01!J31 -> 5977310.8 | N115: =+L115-U115 -> 5977310.8 | P115: =+L115-V115 -> 448022.43 | S115: =Room_SCH01!Q31 -> 0 | T115: =Room_SCH01!R33 -> 759255.45 | U115: =Room_SCH01!S31 -> 0 | V115: =Room_SCH01!T33 -> 5529288.3
A116: =+'SCH05'!G34 -> 762766.66 | C116: =+A116-S116 -> 762766.66 | E116: =+A116-T116 -> 418304.97 | J116: F&B Payroll | L116: =+'SCH05'!J34 -> 3143588.7 | N116: =+L116-U116 -> 3143588.7 | P116: =+L116-V116 -> 669773.02 | S116: =+'SCH05'!Q34 -> 0 | T116: ='SCH05'!R36 -> 344461.69 | U116: =+'SCH05'!S34 -> 0 | V116: ='SCH05'!T36 -> 2473815.7
A117: =+Lau_SCH04!I19+Spa_SCH06!I20 -> 173260 | C117: =+A117-S117 -> 173260 | E117: =+A117-T117 -> 50951.29 | J117: Other Payroll | L117: =+Lau_SCH04!L19+Spa_SCH06!L20 -> 697610 | N117: =+L117-U117 -> 697610 | P117: =+L117-V117 -> -29565.75 | S117: =+Lau_SCH04!S19+Spa_SCH06!S20 -> 0 | T117: ='Mini Bar_SCH02'!T23+Tel_SCH03!T27+Lau_SCH04!T21+Spa_SCH06!T22 -> 122308.71 | U117: =+Lau_SCH04!U19+Spa_SCH06!U20 -> 0 | V117: ='Mini Bar_SCH02'!V23+Tel_SCH03!V27+Lau_SCH04!V21+Spa_SCH06!V22 -> 727175.75
A118: =+AG_SCH11!I11 -> 1162840 | C118: =+A118-S118 -> 1162840 | E118: =+A118-T118 -> 610001.65 | J118: A&G Payroll | L118: =+AG_SCH11!L11 -> 3911710.8 | N118: =+L118-U118 -> 3911710.8 | P118: =+L118-V118 -> 187731.35 | S118: =+AG_SCH11!S11 -> 0 | T118: =AG_SCH11!T13 -> 552838.35 | U118: =+AG_SCH11!U11 -> 0 | V118: =AG_SCH11!V13 -> 3723979.5
A119: =+HR_SCH12!I10 -> 196400 | C119: =+A119-S119 -> 196400 | E119: =+A119-T119 -> 60077.12 | J119: HR Payroll | L119: =+HR_SCH12!L10 -> 740525 | N119: =+L119-U119 -> 740525 | P119: =+L119-V119 -> -175830.58 | S119: =+HR_SCH12!S10 -> 0 | T119: =HR_SCH12!T12 -> 136322.88 | U119: =+HR_SCH12!U10 -> 0 | V119: =HR_SCH12!V12 -> 916355.58
A120: =+SM_SCH13!I17 -> 452000 | C120: =+A120-S120 -> 452000 | E120: =+A120-T120 -> 279254.15 | J120: Mkt Payroll | L120: =+SM_SCH13!L17 -> 1594000 | N120: =+L120-U120 -> 1594000 | P120: =+L120-V120 -> 557772.6 | S120: =+SM_SCH13!S17 -> 0 | T120: =SM_SCH13!T19 -> 172745.85 | U120: =+SM_SCH13!U17 -> 0 | V120: =SM_SCH13!V19 -> 1036227.4
A121: =+RM_SCH14!I24 -> 625575.12 | C121: =+A121-S121 -> 625575.12 | E121: =+A121-T121 -> 303633.87 | J121: R&M Payroll | L121: =+RM_SCH14!L24 -> 2482050.5 | N121: =+L121-U121 -> 2482050.5 | P121: =+L121-V121 -> 383388.09 | S121: =+RM_SCH14!S24 -> 0 | T121: =RM_SCH14!T26 -> 321941.25 | U121: =+RM_SCH14!U24 -> 0 | V121: =RM_SCH14!V26 -> 2098662.4
A122: =SUM(A115:A121) -> 4733354.2 | C122: =+A122-S122 -> 4733354.2 | E122: =+A122-T122 -> 2323480 | J122: Total Payroll | L122: =SUM(L115:L121) -> 18546796 | N122: =+L122-U122 -> 18546796 | P122: =+L122-V122 -> 2041291.2 | S122: =SUM(S115:S121) -> 0 | T122: =SUM(T115:T121) -> 2409874.2 | U122: =SUM(U115:U121) -> 0 | V122: =SUM(V115:V121) -> 16505505
...

Sheet Room_SCH01
A2: =Cover!B2 -> Ramada Resort Khao Lak, Phang Nga
A3: Room Division | B3: Income Statement | O3: Schedule 01 | P3: =+BS!J1 -> 6 | BA3: Mapping Area
A4: =SCH00!J3 -> For the PRD of June 2026 | O4: Local Currency : Thai Baht | BA4: *Department Code | BG4: *Account Code | CB4: Dimension
BA5: Dept 1 | BB5: Dept 2 | BC5: Dept 3 | BD5: Dept 4 | BE5: Dept 5 | BG5: 1st Range | BI5: 2nd Range | BK5: 3rd Range | BM5: 4rd Range | BO5: 5rd Range | BQ5: 6rd Range | BS5: 7rd Range | BU5: 8rd Range | BW5: 9rd Range | BY5: 10th Range
A6: Current Month | I6: Description | J6: Year To Date | Q6: THIS MONTH | S6: Y-T-D | V6: LAST Y-T-D | AC6: MTD | AG6: YTD | BG6: From | BH6: To | BI6: From | BJ6: To | BK6: From | BL6: To | BM6: From | BN6: To | BO6: From | BP6: To | BQ6: From | BR6: To | BS6: From | BT6: To | BU6: From | BV6: To | BW6: From | BX6: To | BY6: From | BZ6: To | CB6: A/O | CC6: Field Name | CD6: Operator | CE6: Value
A7: vs Last Year | B7: % | C7: vs Last Month | D7: % | E7: vs Plan | F7: % | G7: Actual | H7: % | J7: Actual | K7: % | L7: vs Plan | M7: % | N7: vs Last Year | O7: % | Q7: Plan | R7: Last Year | S7: Plan | T7: Last Year | V7: Actual | W7: Plan | X7: Last Year | Z7: Actual Last Month | AA7: Plan | AC7: Plan | AD7: Last Year | AE7: Actual Last Month | AG7: Plan | AH7: Last Year
A8: Better/(worse) | L8: Better/(worse)
I9: REVENUE
A10: =+G10-R10 -> 1367474.6 | B10: =IF(G10=0,0,(A10*100/G10)) -> 100 | C10: =G10-Z10 -> 1367474.6 | D10: =IF(G10=0,0,(C10*100/G10)) -> 100 | E10: =+G10-Q10 -> 1367474.6 | F10: =IF(G10=0,0,(E10*100/G10)) -> 100 | G10: =IFERROR(_xll.AC_BU(_xll.ArrayBU(DB),_xll.ArrayDPT($BA10:$BE10),_xll.ArrayCOA($BG10:$BZ10),YR,PRD,_xll.ArrayDIM($CB10:$CE10)),0) -> 1367474.6 | H10: =G10/G$21*100 -> 43.851476 | I10: Rooms Revenue - Incentive | J10: =IFERROR(_xll.ACC_BU(_xll.ArrayBU(DB),_xll.ArrayDPT($BA10:$BE10),_xll.ArrayCOA($BG10:$BZ10),YR,PRD,_xll.ArrayDIM($CB10:$CE10)),0) -> 1367474.6 | K10: =J10/J$21*100 -> 1.6406136 | L10: =+J10-S10 -> 1367474.6 | M10: =IF(S10<>0,L10/S10*100,0) -> 0 | N10: =+J10-T10 -> 1367474.6 | O10: =IF(T10<>0,N10/T10*100,0) -> 0 | Q10: =IFERROR(_xll.BC_BU(_xll.ArrayBU(DB),_xll.ArrayDPT($BA10:$BE10),_xll.ArrayCOA($BG10:$BZ10),YR,PRD,RV,_xll.ArrayDIM($CB10:$CE10)),0) -> 0 | R10: =IFERROR(_xll.AC_BU(_xll.ArrayBU(DB),_xll.ArrayDPT($BA10:$BE10),_xll.ArrayCOA($BG10:$BZ10),YR-1,PRD,_xll.ArrayDIM($CB10:$CE10)),0) -> 0 | S10: =IFERROR(_xll.BCC_BU(_xll.ArrayBU(DB),_xll.ArrayDPT($BA10:$BE10),_xll.ArrayCOA($BG10:$BZ10),YR,PRD,RV,_xll.ArrayDIM($CB10:$CE10)),0) -> 0 | T10: =IFERROR(_xll.ACC_BU(_xll.ArrayBU(DB),_xll.ArrayDPT($BA10:$BE10),_xll.ArrayCOA($BG10:$BZ10),YR-1,PRD,_xll.ArrayDIM($CB10:$CE10)),0) -> 0 | V10: =IFERROR(_xll.ACC_BU(_xll.ArrayBU(DB),_xll.ArrayDPT($BA10:$BE10),_xll.ArrayCOA($BG10:$BZ10),YR-1,PRD,_xll.ArrayDIM($CB10:$CE10)),0) -> 0 | W10: =IFERROR(_xll.BCC_BU(_xll.ArrayBU(DB),_xll.ArrayDPT($BA10:$BE10),_xll.ArrayCOA($BG10:$BZ10),YR-1,PRD,RV,_xll.ArrayDIM($CB10:$CE10)),0) -> 0 | X10: =IFERROR(_xll.ACC_BU(_xll.ArrayBU(DB),_xll.ArrayDPT($BA10:$BE10),_xll.ArrayCOA($BG10:$BZ10),YR-1-1,PRD,_xll.ArrayDIM($CB10:$CE10)),0) -> 0 | Z10: =IFERROR(_xll.AC_BU(_xll.ArrayBU(DB),_xll.ArrayDPT($BA10:$BE10),_xll.ArrayCOA($BG10:$BZ10),YR,PRD-1,_xll.ArrayDIM($CB10:$CE10)),0) -> 0 | AA10: =IFERROR(_xll.BC_BU(_xll.ArrayBU(DB),_xll.ArrayDPT($BA10:$BE10),_xll.ArrayCOA($BG10:$BZ10),YR,PRD-1,RV,_xll.ArrayDIM($CB10:$CE10)),0) -> 0 | AC10: =Q10/Q$21*100 -> #DIV/0! | AD10: =R10/R$21*100 -> 0 | AE10: =Z10/Z$21*100 -> 0 | AG10: =S10/S$21*100 -> #DIV/0! | AH10: =T10/T$21*100 -> 0 | BG10: 414010
A11: =+G11-R11 -> -121195.4 | B11: =IF(G11=0,0,(A11*100/G11)) -> -15.528787 | C11: =G11-Z11 -> -1082007.6 | D11: =IF(G11=0,0,(C11*100/G11)) -> -138.63781 | E11: =+G11-Q11 -> 780456.34 | F11: =IF(G11=0,0,(E11*100/G11)) -> 100 | G11: =IFERROR(_xll.AC_BU(_xll.ArrayBU(DB),_xll.ArrayDPT($BA11:$BE11),_xll.ArrayCOA($BG11:$BZ11),YR,PRD,_xll.ArrayDIM($CB11:$CE11)),0) -> 780456.34 | H11: =G11/G$21*100 -> 25.027275 | I11: Rooms Revenue - Travel Agent | J11: =IFERROR(_xll.ACC_BU(_xll.ArrayBU(DB),_xll.ArrayDPT($BA11:$BE11),_xll.ArrayCOA($BG11:$BZ11),YR,PRD,_xll.ArrayDIM($CB11:$CE11)),0) -> 58539037 | K11: =J11/J$21*100 -> 70.231609 | L11: =+J11-S11 -> 58539037 | M11: =IF(S11<>0,L11/S11*100,0) -> 0 | N11: =+J11-T11 -> -2561240.9 | O11: =IF(T11<>0,N11/T11*100,0) -> -4.1918647 | Q11: =IFERROR(_xll.BC_BU(_xll.ArrayBU(DB),_xll.ArrayDPT($BA11:$BE11),_xll.ArrayCOA($BG11:$BZ11),YR,PRD,RV,_xll.ArrayDIM($CB11:$CE11)),0) -> 0 | R11: =IFERROR(_xll.AC_BU(_xll.ArrayBU(DB),_xll.ArrayDPT($BA11:$BE11),_xll.ArrayCOA($BG11:$BZ11),YR-1,PRD,_xll.ArrayDIM($CB11:$CE11)),0) -> 901651.74 | S11: =IFERROR(_xll.BCC_BU(_xll.ArrayBU(DB),_xll.ArrayDPT($BA11:$BE11),_xll.ArrayCOA($BG11:$BZ11),YR,PRD,RV,_xll.ArrayDIM($CB11:$CE11)),0) -> 0 | T11: =IFERROR(_xll.ACC_BU(_xll.ArrayBU(DB),_xll.ArrayDPT($BA11:$BE11),_xll.ArrayCOA($BG11:$BZ11),YR-1,PRD,_xll.ArrayDIM($CB11:$CE11)),0) -> 61100278 | V11: =IFERROR(_xll.ACC_BU(_xll.ArrayBU(DB),_xll.ArrayDPT($BA11:$BE11),_xll.ArrayCOA($BG11:$BZ11),YR-1,PRD,_xll.ArrayDIM($CB11:$CE11)),0) -> 61100278 | W11: =IFERROR(_xll.BCC_BU(_xll.ArrayBU(DB),_xll.ArrayDPT($BA11:$BE11),_xll.ArrayCOA($BG11:$BZ11),YR-1,PRD,RV,_xll.ArrayDIM($CB11:$CE11)),0) -> 0 | X11: =IFERROR(_xll.ACC_BU(_xll.ArrayBU(DB),_xll.ArrayDPT($BA11:$BE11),_xll.ArrayCOA($BG11:$BZ11),YR-1-1,PRD,_xll.ArrayDIM($CB11:$CE11)),0) -> 65023901 | Z11: =IFERROR(_xll.AC_BU(_xll.ArrayBU(DB),_xll.ArrayDPT($BA11:$BE11),_xll.ArrayCOA($BG11:$BZ11),YR,PRD-1,_xll.ArrayDIM($CB11:$CE11)),0) -> 1862463.9 | AA11: =IFERROR(_xll.BC_BU(_xll.ArrayBU(DB),_xll.ArrayDPT($BA11:$BE11),_xll.ArrayCOA($BG11:$BZ11),YR,PRD-1,RV,_xll.ArrayDIM($CB11:$CE11)),0) -> 0 | AC11: =Q11/Q$21*100 -> #DIV/0! | AD11: =R11/R$21*100 -> 70.301911 | AE11: =Z11/Z$21*100 -> 64.818164 | AG11: =S11/S$21*100 -> #DIV/0! | AH11: =T11/T$21*100 -> 78.494214 | BG11: 414020
A12: =+G12-R12 -> 337526.12 | B12: =IF(G12=0,0,(A12*100/G12)) -> 53.08748 | C12: =G12-Z12 -> -277076.78 | D12: =IF(G12=0,0,(C12*100/G12)) -> -43.579762 | E12: =+G12-Q12 -> 635792.32 | F12: =IF(G12=0,0,(E12*100/G12)) -> 100 | G12: =IFERROR(_xll.AC_BU(_xll.ArrayBU(DB),_xll.ArrayDPT($BA12:$BE12),_xll.ArrayCOA($BG12:$BZ12),YR,PRD,_xll.ArrayDIM($CB12:$CE12)),0) -> 635792.32 | H12: =G12/G$21*100 -> 20.388263 | I12: Rooms Revenue - Web Site (OTA) | J12: =IFERROR(_xll.ACC_BU(_xll.ArrayBU(DB),_xll.ArrayDPT($BA12:$BE12),_xll.ArrayCOA($BG12:$BZ12),YR,PRD,_xll.ArrayDIM($CB12:$CE12)),0) -> 22047965 | K12: =J12/J$21*100 -> 26.45182 | L12: =+J12-S12 -> 22047965 | M12: =IF(S12<>0,L12/S12*100,0) -> 0 | N12: =+J12-T12 -> 7109145.5 | O12: =IF(T12<>0,N12/T12*100,0) -> 47.588402 | Q12: =IFERROR(_xll.BC_BU(_xll.ArrayBU(DB),_xll.ArrayDPT($BA12:$BE12),_xll.ArrayCOA($BG12:$BZ12),YR,PRD,RV,_xll.ArrayDIM($CB12:$CE12)),0) -> 0 | R12: =IFERROR(_xll.AC_BU(_xll.ArrayBU(DB),_xll.ArrayDPT($BA12:$BE12),_xll.ArrayCOA($BG12:$BZ12),YR-1,PRD,_xll.ArrayDIM($CB12:$CE12)),0) -> 298266.2 | S12: =IFERROR(_xll.BCC_BU(_xll.ArrayBU(DB),_xll.ArrayDPT($BA12:$BE12),_xll.ArrayCOA($BG12:$BZ12),YR,PRD,RV,_xll.ArrayDIM($CB12:$CE12)),0) -> 0 | T12: =IFERROR(_xll.ACC_BU(_xll.ArrayBU(DB),_xll.ArrayDPT($BA12:$BE12),_xll.ArrayCOA($BG12:$BZ12),YR-1,PRD,_xll.ArrayDIM($CB12:$CE12)),0) -> 14938820 | V12: =IFERROR(_xll.ACC_BU(_xll.ArrayBU(DB),_xll.ArrayDPT($BA12:$BE12),_xll.ArrayCOA($BG12:$BZ12),YR-1,PRD,_xll.ArrayDIM($CB12:$CE12)),0) -> 14938820 | W12: =IFERROR(_xll.BCC_BU(_xll.ArrayBU(DB),_xll.ArrayDPT($BA12:$BE12),_xll.ArrayCOA($BG12:$BZ12),YR-1,PRD,RV,_xll.ArrayDIM($CB12:$CE12)),0) -> 0 | X12: =IFERROR(_xll.ACC_BU(_xll.ArrayBU(DB),_xll.ArrayDPT($BA12:$BE12),_xll.ArrayCOA($BG12:$BZ12),YR-1-1,PRD,_xll.ArrayDIM($CB12:$CE12)),0) -> 3956920.1 | Z12: =IFERROR(_xll.AC_BU(_xll.ArrayBU(DB),_xll.ArrayDPT($BA12:$BE12),_xll.ArrayCOA($BG12:$BZ12),YR,PRD-1,_xll.ArrayDIM($CB12:$CE12)),0) -> 912869.1 | AA12: =IFERROR(_xll.BC_BU(_xll.ArrayBU(DB),_xll.ArrayDPT($BA12:$BE12),_xll.ArrayCOA($BG12:$BZ12),YR,PRD-1,RV,_xll.ArrayDIM($CB12:$CE12)),0) -> 0 | AC12: =Q12/Q$21*100 -> #DIV/0! | AD12: =R12/R$21*100 -> 23.255857 | AE12: =Z12/Z$21*100 -> 31.770011 | AG12: =S12/S$21*100 -> #DIV/0! | AH12: =T12/T$21*100 -> 19.191581 | BG12: 414030
A13: =+G13-R13 -> 0 | B13: =IF(G13=0,0,(A13*100/G13)) -> 0 | C13: =G13-Z13 -> 0 | D13: =IF(G13=0,0,(C13*100/G13)) -> 0 | E13: =+G13-Q13 -> 0 | F13: =IF(G13=0,0,(E13*100/G13)) -> 0 | G13: =IFERROR(_xll.AC_BU(_xll.ArrayBU(DB),_xll.ArrayDPT($BA13:$BE13),_xll.ArrayCOA($BG13:$BZ13),YR,PRD,_xll.ArrayDIM($CB13:$CE13)),0) -> 0 | H13: =G13/G$21*100 -> 0 | I13: Rooms Revenue - Airline/Hotelier | J13: =IFERROR(_xll.ACC_BU(_xll.ArrayBU(DB),_xll.ArrayDPT($BA13:$BE13),_xll.ArrayCOA($BG13:$BZ13),YR,PRD,_xll.ArrayDIM($CB13:$CE13)),0) -> 0 | K13: =J13/J$21*100 -> 0 | L13: =+J13-S13 -> 0 | M13: =IF(S13<>0,L13/S13*100,0) -> 0 | N13: =+J13-T13 -> 0 | O13: =IF(T13<>0,N13/T13*100,0) -> 0 | Q13: =IFERROR(_xll.BC_BU(_xll.ArrayBU(DB),_xll.ArrayDPT($BA13:$BE13),_xll.ArrayCOA($BG13:$BZ13),YR,PRD,RV,_xll.ArrayDIM($CB13:$CE13)),0) -> 0 | R13: =IFERROR(_xll.AC_BU(_xll.ArrayBU(DB),_xll.ArrayDPT($BA13:$BE13),_xll.ArrayCOA($BG13:$BZ13),YR-1,PRD,_xll.ArrayDIM($CB13:$CE13)),0) -> 0 | S13: =IFERROR(_xll.BCC_BU(_xll.ArrayBU(DB),_xll.ArrayDPT($BA13:$BE13),_xll.ArrayCOA($BG13:$BZ13),YR,PRD,RV,_xll.ArrayDIM($CB13:$CE13)),0) -> 0 | T13: =IFERROR(_xll.ACC_BU(_xll.ArrayBU(DB),_xll.ArrayDPT($BA13:$BE13),_xll.ArrayCOA($BG13:$BZ13),YR-1,PRD,_xll.ArrayDIM($CB13:$CE13)),0) -> 0 | V13: =IFERROR(_xll.ACC_BU(_xll.ArrayBU(DB),_xll.ArrayDPT($BA13:$BE13),_xll.ArrayCOA($BG13:$BZ13),YR-1,PRD,_xll.ArrayDIM($CB13:$CE13)),0) -> 0 | W13: =IFERROR(_xll.BCC_BU(_xll.ArrayBU(DB),_xll.ArrayDPT($BA13:$BE13),_xll.ArrayCOA($BG13:$BZ13),YR-1,PRD,RV,_xll.ArrayDIM($CB13:$CE13)),0) -> 0 | X13: =IFERROR(_xll.ACC_BU(_xll.ArrayBU(DB),_xll.ArrayDPT($BA13:$BE13),_xll.ArrayCOA($BG13:$BZ13),YR-1-1,PRD,_xll.ArrayDIM($CB13:$CE13)),0) -> 0 | Z13: =IFERROR(_xll.AC_BU(_xll.ArrayBU(DB),_xll.ArrayDPT($BA13:$BE13),_xll.ArrayCOA($BG13:$BZ13),YR,PRD-1,_xll.ArrayDIM($CB13:$CE13)),0) -> 0 | AA13: =IFERROR(_xll.BC_BU(_xll.ArrayBU(DB),_xll.ArrayDPT($BA13:$BE13),_xll.ArrayCOA($BG13:$BZ13),YR,PRD-1,RV,_xll.ArrayDIM($CB13:$CE13)),0) -> 0 | AC13: =Q13/Q$21*100 -> #DIV/0! | AD13: =R13/R$21*100 -> 0 | AE13: =Z13/Z$21*100 -> 0 | AG13: =S13/S$21*100 -> #DIV/0! | AH13: =T13/T$21*100 -> 0 | BG13: 414040
A14: =+G14-R14 -> 0 | B14: =IF(G14=0,0,(A14*100/G14)) -> 0 | C14: =G14-Z14 -> 0 | D14: =IF(G14=0,0,(C14*100/G14)) -> 0 | E14: =+G14-Q14 -> 0 | F14: =IF(G14=0,0,(E14*100/G14)) -> 0 | G14: =IFERROR(_xll.AC_BU(_xll.ArrayBU(DB),_xll.ArrayDPT($BA14:$BE14),_xll.ArrayCOA($BG14:$BZ14),YR,PRD,_xll.ArrayDIM($CB14:$CE14)),0) -> 0 | H14: =G14/G$21*100 -> 0 | I14: Rooms Revenue - Direct Booking | J14: =IFERROR(_xll.ACC_BU(_xll.ArrayBU(DB),_xll.ArrayDPT($BA14:$BE14),_xll.ArrayCOA($BG14:$BZ14),YR,PRD,_xll.ArrayDIM($CB14:$CE14)),0) -> 0 | K14: =J14/J$21*100 -> 0 | L14: =+J14-S14 -> 0 | M14: =IF(S14<>0,L14/S14*100,0) -> 0 | N14: =+J14-T14 -> 0 | O14: =IF(T14<>0,N14/T14*100,0) -> 0 | Q14: =IFERROR(_xll.BC_BU(_xll.ArrayBU(DB),_xll.ArrayDPT($BA14:$BE14),_xll.ArrayCOA($BG14:$BZ14),YR,PRD,RV,_xll.ArrayDIM($CB14:$CE14)),0) -> 0 | R14: =IFERROR(_xll.AC_BU(_xll.ArrayBU(DB),_xll.ArrayDPT($BA14:$BE14),_xll.ArrayCOA($BG14:$BZ14),YR-1,PRD,_xll.ArrayDIM($CB14:$CE14)),0) -> 0 | S14: =IFERROR(_xll.BCC_BU(_xll.ArrayBU(DB),_xll.ArrayDPT($BA14:$BE14),_xll.ArrayCOA($BG14:$BZ14),YR,PRD,RV,_xll.ArrayDIM($CB14:$CE14)),0) -> 0 | T14: =IFERROR(_xll.ACC_BU(_xll.ArrayBU(DB),_xll.ArrayDPT($BA14:$BE14),_xll.ArrayCOA($BG14:$BZ14),YR-1,PRD,_xll.ArrayDIM($CB14:$CE14)),0) -> 0 | V14: =IFERROR(_xll.ACC_BU(_xll.ArrayBU(DB),_xll.ArrayDPT($BA14:$BE14),_xll.ArrayCOA($BG14:$BZ14),YR-1,PRD,_xll.ArrayDIM($CB14:$CE14)),0) -> 0 | W14: =IFERROR(_xll.BCC_BU(_xll.ArrayBU(DB),_xll.ArrayDPT($BA14:$BE14),_xll.ArrayCOA($BG14:$BZ14),YR-1,PRD,RV,_xll.ArrayDIM($CB14:$CE14)),0) -> 0 | X14: =IFERROR(_xll.ACC_BU(_xll.ArrayBU(DB),_xll.ArrayDPT($BA14:$BE14),_xll.ArrayCOA($BG14:$BZ14),YR-1-1,PRD,_xll.ArrayDIM($CB14:$CE14)),0) -> 359360.96 | Z14: =IFERROR(_xll.AC_BU(_xll.ArrayBU(DB),_xll.ArrayDPT($BA14:$BE14),_xll.ArrayCOA($BG14:$BZ14),YR,PRD-1,_xll.ArrayDIM($CB14:$CE14)),0) -> 0 | AA14: =IFERROR(_xll.BC_BU(_xll.ArrayBU(DB),_xll.ArrayDPT($BA14:$BE14),_xll.ArrayCOA($BG14:$BZ14),YR,PRD-1,RV,_xll.ArrayDIM($CB14:$CE14)),0) -> 0 | AC14: =Q14/Q$21*100 -> #DIV/0! | AD14: =R14/R$21*100 -> 0 | AE14: =Z14/Z$21*100 -> 0 | AG14: =S14/S$21*100 -> #DIV/0! | AH14: =T14/T$21*100 -> 0 | BG14: 414050
A15: =+G15-R15 -> 0 | B15: =IF(G15=0,0,(A15*100/G15)) -> 0 | C15: =G15-Z15 -> 0 | D15: =IF(G15=0,0,(C15*100/G15)) -> 0 | E15: =+G15-Q15 -> 0 | F15: =IF(G15=0,0,(E15*100/G15)) -> 0 | G15: =IFERROR(_xll.AC_BU(_xll.ArrayBU(DB),_xll.ArrayDPT($BA15:$BE15),_xll.ArrayCOA($BG15:$BZ15),YR,PRD,_xll.ArrayDIM($CB15:$CE15)),0) -> 0 | H15: =G15/G$21*100 -> 0 | I15: Rooms Revenue - Walk In | J15: =IFERROR(_xll.ACC_BU(_xll.ArrayBU(DB),_xll.ArrayDPT($BA15:$BE15),_xll.ArrayCOA($BG15:$BZ15),YR,PRD,_xll.ArrayDIM($CB15:$CE15)),0) -> 0 | K15: =J15/J$21*100 -> 0 | L15: =+J15-S15 -> 0 | M15: =IF(S15<>0,L15/S15*100,0) -> 0 | N15: =+J15-T15 -> 0 | O15: =IF(T15<>0,N15/T15*100,0) -> 0 | Q15: =IFERROR(_xll.BC_BU(_xll.ArrayBU(DB),_xll.ArrayDPT($BA15:$BE15),_xll.ArrayCOA($BG15:$BZ15),YR,PRD,RV,_xll.ArrayDIM($CB15:$CE15)),0) -> 0 | R15: =IFERROR(_xll.AC_BU(_xll.ArrayBU(DB),_xll.ArrayDPT($BA15:$BE15),_xll.ArrayCOA($BG15:$BZ15),YR-1,PRD,_xll.ArrayDIM($CB15:$CE15)),0) -> 0 | S15: =IFERROR(_xll.BCC_BU(_xll.ArrayBU(DB),_xll.ArrayDPT($BA15:$BE15),_xll.ArrayCOA($BG15:$BZ15),YR,PRD,RV,_xll.ArrayDIM($CB15:$CE15)),0) -> 0 | T15: =IFERROR(_xll.ACC_BU(_xll.ArrayBU(DB),_xll.ArrayDPT($BA15:$BE15),_xll.ArrayCOA($BG15:$BZ15),YR-1,PRD,_xll.ArrayDIM($CB15:$CE15)),0) -> 0 | V15: =IFERROR(_xll.ACC_BU(_xll.ArrayBU(DB),_xll.ArrayDPT($BA15:$BE15),_xll.ArrayCOA($BG15:$BZ15),YR-1,PRD,_xll.ArrayDIM($CB15:$CE15)),0) -> 0 | W15: =IFERROR(_xll.BCC_BU(_xll.ArrayBU(DB),_xll.ArrayDPT($BA15:$BE15),_xll.ArrayCOA($BG15:$BZ15),YR-1,PRD,RV,_xll.ArrayDIM($CB15:$CE15)),0) -> 0 | X15: =IFERROR(_xll.ACC_BU(_xll.ArrayBU(DB),_xll.ArrayDPT($BA15:$BE15),_xll.ArrayCOA($BG15:$BZ15),YR-1-1,PRD,_xll.ArrayDIM($CB15:$CE15)),0) -> 0 | Z15: =IFERROR(_xll.AC_BU(_xll.ArrayBU(DB),_xll.ArrayDPT($BA15:$BE15),_xll.ArrayCOA($BG15:$BZ15),YR,PRD-1,_xll.ArrayDIM($CB15:$CE15)),0) -> 0 | AA15: =IFERROR(_xll.BC_BU(_xll.ArrayBU(DB),_xll.ArrayDPT($BA15:$BE15),_xll.ArrayCOA($BG15:$BZ15),YR,PRD-1,RV,_xll.ArrayDIM($CB15:$CE15)),0) -> 0 | AC15: =Q15/Q$21*100 -> #DIV/0! | AD15: =R15/R$21*100 -> 0 | AE15: =Z15/Z$21*100 -> 0 | AG15: =S15/S$21*100 -> #DIV/0! | AH15: =T15/T$21*100 -> 0 | BG15: 414060
A16: =+G16-R16 -> 0 | B16: =IF(G16=0,0,(A16*100/G16)) -> 0 | C16: =G16-Z16 -> 0 | D16: =IF(G16=0,0,(C16*100/G16)) -> 0 | E16: =+G16-Q16 -> 0 | F16: =IF(G16=0,0,(E16*100/G16)) -> 0 | G16: =IFERROR(_xll.AC_BU(_xll.ArrayBU(DB),_xll.ArrayDPT($BA16:$BE16),_xll.ArrayCOA($BG16:$BZ16),YR,PRD,_xll.ArrayDIM($CB16:$CE16)),0) -> 0 | H16: =G16/G$21*100 -> 0 | I16: Rooms Revenue - Website RKL | J16: =IFERROR(_xll.ACC_BU(_xll.ArrayBU(DB),_xll.ArrayDPT($BA16:$BE16),_xll.ArrayCOA($BG16:$BZ16),YR,PRD,_xll.ArrayDIM($CB16:$CE16)),0) -> 0 | K16: =J16/J$21*100 -> 0 | L16: =+J16-S16 -> 0 | M16: =IF(S16<>0,L16/S16*100,0) -> 0 | N16: =+J16-T16 -> 0 | O16: =IF(T16<>0,N16/T16*100,0) -> 0 | Q16: =IFERROR(_xll.BC_BU(_xll.ArrayBU(DB),_xll.ArrayDPT($BA16:$BE16),_xll.ArrayCOA($BG16:$BZ16),YR,PRD,RV,_xll.ArrayDIM($CB16:$CE16)),0) -> 0 | R16: =IFERROR(_xll.AC_BU(_xll.ArrayBU(DB),_xll.ArrayDPT($BA16:$BE16),_xll.ArrayCOA($BG16:$BZ16),YR-1,PRD,_xll.ArrayDIM($CB16:$CE16)),0) -> 0 | S16: =IFERROR(_xll.BCC_BU(_xll.ArrayBU(DB),_xll.ArrayDPT($BA16:$BE16),_xll.ArrayCOA($BG16:$BZ16),YR,PRD,RV,_xll.ArrayDIM($CB16:$CE16)),0) -> 0 | T16: =IFERROR(_xll.ACC_BU(_xll.ArrayBU(DB),_xll.ArrayDPT($BA16:$BE16),_xll.ArrayCOA($BG16:$BZ16),YR-1,PRD,_xll.ArrayDIM($CB16:$CE16)),0) -> 0 | V16: =IFERROR(_xll.ACC_BU(_xll.ArrayBU(DB),_xll.ArrayDPT($BA16:$BE16),_xll.ArrayCOA($BG16:$BZ16),YR-1,PRD,_xll.ArrayDIM($CB16:$CE16)),0) -> 0 | W16: =IFERROR(_xll.BCC_BU(_xll.ArrayBU(DB),_xll.ArrayDPT($BA16:$BE16),_xll.ArrayCOA($BG16:$BZ16),YR-1,PRD,RV,_xll.ArrayDIM($CB16:$CE16)),0) -> 0 | X16: =IFERROR(_xll.ACC_BU(_xll.ArrayBU(DB),_xll.ArrayDPT($BA16:$BE16),_xll.ArrayCOA($BG16:$BZ16),YR-1-1,PRD,_xll.ArrayDIM($CB16:$CE16)),0) -> 212003.28 | Z16: =IFERROR(_xll.AC_BU(_xll.ArrayBU(DB),_xll.ArrayDPT($BA16:$BE16),_xll.ArrayCOA($BG16:$BZ16),YR,PRD-1,_xll.ArrayDIM($CB16:$CE16)),0) -> 0 | AA16: =IFERROR(_xll.BC_BU(_xll.ArrayBU(DB),_xll.ArrayDPT($BA16:$BE16),_xll.ArrayCOA($BG16:$BZ16),YR,PRD-1,RV,_xll.ArrayDIM($CB16:$CE16)),0) -> 0 | AC16: =Q16/Q$21*100 -> #DIV/0! | AD16: =R16/R$21*100 -> 0 | AE16: =Z16/Z$21*100 -> 0 | AG16: =S16/S$21*100 -> #DIV/0! | AH16: =T16/T$21*100 -> 0 | BG16: 414070
A17: =+G17-R17 -> 0 | B17: =IF(G17=0,0,(A17*100/G17)) -> 0 | C17: =G17-Z17 -> 0 | D17: =IF(G17=0,0,(C17*100/G17)) -> 0 | E17: =+G17-Q17 -> 0 | F17: =IF(G17=0,0,(E17*100/G17)) -> 0 | G17: =IFERROR(_xll.AC_BU(_xll.ArrayBU(DB),_xll.ArrayDPT($BA17:$BE17),_xll.ArrayCOA($BG17:$BZ17),YR,PRD,_xll.ArrayDIM($CB17:$CE17)),0) -> 0 | H17: =G17/G$21*100 -> 0 | I17: Rooms Revenue - Special Package | J17: =IFERROR(_xll.ACC_BU(_xll.ArrayBU(DB),_xll.ArrayDPT($BA17:$BE17),_xll.ArrayCOA($BG17:$BZ17),YR,PRD,_xll.ArrayDIM($CB17:$CE17)),0) -> 0 | K17: =J17/J$21*100 -> 0 | L17: =+J17-S17 -> 0 | M17: =IF(S17<>0,L17/S17*100,0) -> 0 | N17: =+J17-T17 -> 0 | O17: =IF(T17<>0,N17/T17*100,0) -> 0 | Q17: =IFERROR(_xll.BC_BU(_xll.ArrayBU(DB),_xll.ArrayDPT($BA17:$BE17),_xll.ArrayCOA($BG17:$BZ17),YR,PRD,RV,_xll.ArrayDIM($CB17:$CE17)),0) -> 0 | R17: =IFERROR(_xll.AC_BU(_xll.ArrayBU(DB),_xll.ArrayDPT($BA17:$BE17),_xll.ArrayCOA($BG17:$BZ17),YR-1,PRD,_xll.ArrayDIM($CB17:$CE17)),0) -> 0 | S17: =IFERROR(_xll.BCC_BU(_xll.ArrayBU(DB),_xll.ArrayDPT($BA17:$BE17),_xll.ArrayCOA($BG17:$BZ17),YR,PRD,RV,_xll.ArrayDIM($CB17:$CE17)),0) -> 0 | T17: =IFERROR(_xll.ACC_BU(_xll.ArrayBU(DB),_xll.ArrayDPT($BA17:$BE17),_xll.ArrayCOA($BG17:$BZ17),YR-1,PRD,_xll.ArrayDIM($CB17:$CE17)),0) -> 0 | V17: =IFERROR(_xll.ACC_BU(_xll.ArrayBU(DB),_xll.ArrayDPT($BA17:$BE17),_xll.ArrayCOA($BG17:$BZ17),YR-1,PRD,_xll.ArrayDIM($CB17:$CE17)),0) -> 0 | W17: =IFERROR(_xll.BCC_BU(_xll.ArrayBU(DB),_xll.ArrayDPT($BA17:$BE17),_xll.ArrayCOA($BG17:$BZ17),YR-1,PRD,RV,_xll.ArrayDIM($CB17:$CE17)),0) -> 0 | X17: =IFERROR(_xll.ACC_BU(_xll.ArrayBU(DB),_xll.ArrayDPT($BA17:$BE17),_xll.ArrayCOA($BG17:$BZ17),YR-1-1,PRD,_xll.ArrayDIM($CB17:$CE17)),0) -> 0 | Z17: =IFERROR(_xll.AC_BU(_xll.ArrayBU(DB),_xll.ArrayDPT($BA17:$BE17),_xll.ArrayCOA($BG17:$BZ17),YR,PRD-1,_xll.ArrayDIM($CB17:$CE17)),0) -> 0 | AA17: =IFERROR(_xll.BC_BU(_xll.ArrayBU(DB),_xll.ArrayDPT($BA17:$BE17),_xll.ArrayCOA($BG17:$BZ17),YR,PRD-1,RV,_xll.ArrayDIM($CB17:$CE17)),0) -> 0 | AC17: =Q17/Q$21*100 -> #DIV/0! | AD17: =R17/R$21*100 -> 0 | AE17: =Z17/Z$21*100 -> 0 | AG17: =S17/S$21*100 -> #DIV/0! | AH17: =T17/T$21*100 -> 0 | BG17: 414080
A18: =+G18-R18 -> 100673.96 | B18: =IF(G18=0,0,(A18*100/G18)) -> 82.413839 | C18: =G18-Z18 -> 107708.43 | D18: =IF(G18=0,0,(C18*100/G18)) -> 88.172405 | E18: =+G18-Q18 -> 122156.62 | F18: =IF(G18=0,0,(E18*100/G18)) -> 100 | G18: =IFERROR(_xll.AC_BU(_xll.ArrayBU(DB),_xll.ArrayDPT($BA18:$BE18),_xll.ArrayCOA($BG18:$BZ18),YR,PRD,_xll.ArrayDIM($CB18:$CE18)),0) -> 122156.62 | H18: =G18/G$21*100 -> 3.9172561 | I18: Rooms Revenue - Room Upselling | J18: =IFERROR(_xll.ACC_BU(_xll.ArrayBU(DB),_xll.ArrayDPT($BA18:$BE18),_xll.ArrayCOA($BG18:$BZ18),YR,PRD,_xll.ArrayDIM($CB18:$CE18)),0) -> 379991.26 | K18: =J18/J$21*100 -> 0.45589062 | L18: =+J18-S18 -> 379991.26 | M18: =IF(S18<>0,L18/S18*100,0) -> 0 | N18: =+J18-T18 -> 136744.79 | O18: =IF(T18<>0,N18/T18*100,0) -> 56.216557 | Q18: =IFERROR(_xll.BC_BU(_xll.ArrayBU(DB),_xll.ArrayDPT($BA18:$BE18),_xll.ArrayCOA($BG18:$BZ18),YR,PRD,RV,_xll.ArrayDIM($CB18:$CE18)),0) -> 0 | R18: =IFERROR(_xll.AC_BU(_xll.ArrayBU(DB),_xll.ArrayDPT($BA18:$BE18),_xll.ArrayCOA($BG18:$BZ18),YR-1,PRD,_xll.ArrayDIM($CB18:$CE18)),0) -> 21482.66 | S18: =IFERROR(_xll.BCC_BU(_xll.ArrayBU(DB),_xll.ArrayDPT($BA18:$BE18),_xll.ArrayCOA($BG18:$BZ18),YR,PRD,RV,_xll.ArrayDIM($CB18:$CE18)),0) -> 0 | T18: =IFERROR(_xll.ACC_BU(_xll.ArrayBU(DB),_xll.ArrayDPT($BA18:$BE18),_xll.ArrayCOA($BG18:$BZ18),YR-1,PRD,_xll.ArrayDIM($CB18:$CE18)),0) -> 243246.47 | V18: =IFERROR(_xll.ACC_BU(_xll.ArrayBU(DB),_xll.ArrayDPT($BA18:$BE18),_xll.ArrayCOA($BG18:$BZ18),YR-1,PRD,_xll.ArrayDIM($CB18:$CE18)),0) -> 243246.47 | W18: =IFERROR(_xll.BCC_BU(_xll.ArrayBU(DB),_xll.ArrayDPT($BA18:$BE18),_xll.ArrayCOA($BG18:$BZ18),YR-1,PRD,RV,_xll.ArrayDIM($CB18:$CE18)),0) -> 0 | X18: =IFERROR(_xll.ACC_BU(_xll.ArrayBU(DB),_xll.ArrayDPT($BA18:$BE18),_xll.ArrayCOA($BG18:$BZ18),YR-1-1,PRD,_xll.ArrayDIM($CB18:$CE18)),0) -> 221794.31 | Z18: =IFERROR(_xll.AC_BU(_xll.ArrayBU(DB),_xll.ArrayDPT($BA18:$BE18),_xll.ArrayCOA($BG18:$BZ18),YR,PRD-1,_xll.ArrayDIM($CB18:$CE18)),0) -> 14448.19 | AA18: =IFERROR(_xll.BC_BU(_xll.ArrayBU(DB),_xll.ArrayDPT($BA18:$BE18),_xll.ArrayCOA($BG18:$BZ18),YR,PRD-1,RV,_xll.ArrayDIM($CB18:$CE18)),0) -> 0 | AC18: =Q18/Q$21*100 -> #DIV/0! | AD18: =R18/R$21*100 -> 1.675006 | AE18: =Z18/Z$21*100 -> 0.5028313 | AG18: =S18/S$21*100 -> #DIV/0! | AH18: =T18/T$21*100 -> 0.31249351 | BG18: 414091
A19: =+G19-R19 -> 54970.52 | B19: =IF(G19=0,0,(A19*100/G19)) -> 75.129531 | C19: =G19-Z19 -> 33376.59 | D19: =IF(G19=0,0,(C19*100/G19)) -> 45.616588 | E19: =+G19-Q19 -> 73167.66 | F19: =IF(G19=0,0,(E19*100/G19)) -> 100 | G19: =IFERROR(_xll.AC_BU(_xll.ArrayBU(DB),_xll.ArrayDPT($BA19:$BE19),_xll.ArrayCOA($BG19:$BZ19),YR,PRD,_xll.ArrayDIM($CB19:$CE19)),0) -> 73167.66 | H19: =G19/G$21*100 -> 2.3463031 | I19: Rooms Revenue - Other Room Revenue | J19: =IFERROR(_xll.ACC_BU(_xll.ArrayBU(DB),_xll.ArrayDPT($BA19:$BE19),_xll.ArrayCOA($BG19:$BZ19),YR,PRD,_xll.ArrayDIM($CB19:$CE19)),0) -> 493163.95 | K19: =J19/J$21*100 -> 0.59166839 | L19: =+J19-S19 -> 493163.95 | M19: =IF(S19<>0,L19/S19*100,0) -> 0 | N19: =+J19-T19 -> -175814.2 | O19: =IF(T19<>0,N19/T19*100,0) -> -26.281008 | Q19: =IFERROR(_xll.BC_BU(_xll.ArrayBU(DB),_xll.ArrayDPT($BA19:$BE19),_xll.ArrayCOA($BG19:$BZ19),YR,PRD,RV,_xll.ArrayDIM($CB19:$CE19)),0) -> 0 | R19: =IFERROR(_xll.AC_BU(_xll.ArrayBU(DB),_xll.ArrayDPT($BA19:$BE19),_xll.ArrayCOA($BG19:$BZ19),YR-1,PRD,_xll.ArrayDIM($CB19:$CE19)),0) -> 18197.14 | S19: =IFERROR(_xll.BCC_BU(_xll.ArrayBU(DB),_xll.ArrayDPT($BA19:$BE19),_xll.ArrayCOA($BG19:$BZ19),YR,PRD,RV,_xll.ArrayDIM($CB19:$CE19)),0) -> 0 | T19: =IFERROR(_xll.ACC_BU(_xll.ArrayBU(DB),_xll.ArrayDPT($BA19:$BE19),_xll.ArrayCOA($BG19:$BZ19),YR-1,PRD,_xll.ArrayDIM($CB19:$CE19)),0) -> 668978.15 | V19: =IFERROR(_xll.ACC_BU(_xll.ArrayBU(DB),_xll.ArrayDPT($BA19:$BE19),_xll.ArrayCOA($BG19:$BZ19),YR-1,PRD,_xll.ArrayDIM($CB19:$CE19)),0) -> 668978.15 | W19: =IFERROR(_xll.BCC_BU(_xll.ArrayBU(DB),_xll.ArrayDPT($BA19:$BE19),_xll.ArrayCOA($BG19:$BZ19),YR-1,PRD,RV,_xll.ArrayDIM($CB19:$CE19)),0) -> 0 | X19: =IFERROR(_xll.ACC_BU(_xll.ArrayBU(DB),_xll.ArrayDPT($BA19:$BE19),_xll.ArrayCOA($BG19:$BZ19),YR-1-1,PRD,_xll.ArrayDIM($CB19:$CE19)),0) -> 160674.05 | Z19: =IFERROR(_xll.AC_BU(_xll.ArrayBU(DB),_xll.ArrayDPT($BA19:$BE19),_xll.ArrayCOA($BG19:$BZ19),YR,PRD-1,_xll.ArrayDIM($CB19:$CE19)),0) -> 39791.07 | AA19: =IFERROR(_xll.BC_BU(_xll.ArrayBU(DB),_xll.ArrayDPT($BA19:$BE19),_xll.ArrayCOA($BG19:$BZ19),YR,PRD-1,RV,_xll.ArrayDIM($CB19:$CE19)),0) -> 0 | AC19: =Q19/Q$21*100 -> #DIV/0! | AD19: =R19/R$21*100 -> 1.4188335 | AE19: =Z19/Z$21*100 -> 1.3848237 | AG19: =S19/S$21*100 -> #DIV/0! | AH19: =T19/T$21*100 -> 0.85942186 | BG19: 414099
A20: =+G20-R20 -> 96431.07 | B20: =IF(G20=0,0,(A20*100/G20)) -> 69.187904 | C20: =G20-Z20 -> 95580.6 | D20: =IF(G20=0,0,(C20*100/G20)) -> 68.577704 | E20: =+G20-Q20 -> 139375.62 | F20: =IF(G20=0,0,(E20*100/G20)) -> 100 | G20: =IFERROR(_xll.AC_BU(_xll.ArrayBU(DB),_xll.ArrayDPT($BA20:$BE20),_xll.ArrayCOA($BG20:$BZ20),YR,PRD,_xll.ArrayDIM($CB20:$CE20)),0) -> 139375.62 | H20: =G20/G$21*100 -> 4.4694262 | I20: Room Day Use/Extra Bed/late Check out | J20: =IFERROR(_xll.ACC_BU(_xll.ArrayBU(DB),_xll.ArrayDPT($BA20:$BE20),_xll.ArrayCOA($BG20:$BZ20),YR,PRD,_xll.ArrayDIM($CB20:$CE20)),0) -> 523779.23 | K20: =J20/J$21*100 -> 0.62839876 | L20: =+J20-S20 -> 523779.23 | M20: =IF(S20<>0,L20/S20*100,0) -> 0 | N20: =+J20-T20 -> -365384.88 | O20: =IF(T20<>0,N20/T20*100,0) -> -41.093076 | Q20: =IFERROR(_xll.BC_BU(_xll.ArrayBU(DB),_xll.ArrayDPT($BA20:$BE20),_xll.ArrayCOA($BG20:$BZ20),YR,PRD,RV,_xll.ArrayDIM($CB20:$CE20)),0) -> 0 | R20: =IFERROR(_xll.AC_BU(_xll.ArrayBU(DB),_xll.ArrayDPT($BA20:$BE20),_xll.ArrayCOA($BG20:$BZ20),YR-1,PRD,_xll.ArrayDIM($CB20:$CE20)),0) -> 42944.55 | S20: =IFERROR(_xll.BCC_BU(_xll.ArrayBU(DB),_xll.ArrayDPT($BA20:$BE20),_xll.ArrayCOA($BG20:$BZ20),YR,PRD,RV,_xll.ArrayDIM($CB20:$CE20)),0) -> 0 | T20: =IFERROR(_xll.ACC_BU(_xll.ArrayBU(DB),_xll.ArrayDPT($BA20:$BE20),_xll.ArrayCOA($BG20:$BZ20),YR-1,PRD,_xll.ArrayDIM($CB20:$CE20)),0) -> 889164.11 | V20: =IFERROR(_xll.ACC_BU(_xll.ArrayBU(DB),_xll.ArrayDPT($BA20:$BE20),_xll.ArrayCOA($BG20:$BZ20),YR-1,PRD,_xll.ArrayDIM($CB20:$CE20)),0) -> 889164.11 | W20: =IFERROR(_xll.BCC_BU(_xll.ArrayBU(DB),_xll.ArrayDPT($BA20:$BE20),_xll.ArrayCOA($BG20:$BZ20),YR-1,PRD,RV,_xll.ArrayDIM($CB20:$CE20)),0) -> 0 | X20: =IFERROR(_xll.ACC_BU(_xll.ArrayBU(DB),_xll.ArrayDPT($BA20:$BE20),_xll.ArrayCOA($BG20:$BZ20),YR-1-1,PRD,_xll.ArrayDIM($CB20:$CE20)),0) -> 654314.64 | Z20: =IFERROR(_xll.AC_BU(_xll.ArrayBU(DB),_xll.ArrayDPT($BA20:$BE20),_xll.ArrayCOA($BG20:$BZ20),YR,PRD-1,_xll.ArrayDIM($CB20:$CE20)),0) -> 43795.02 | AA20: =IFERROR(_xll.BC_BU(_xll.ArrayBU(DB),_xll.ArrayDPT($BA20:$BE20),_xll.ArrayCOA($BG20:$BZ20),YR,PRD-1,RV,_xll.ArrayDIM($CB20:$CE20)),0) -> 0 | AC20: =Q20/Q$21*100 -> #DIV/0! | AD20: =R20/R$21*100 -> 3.3483925 | AE20: =Z20/Z$21*100 -> 1.5241706 | AG20: =S20/S$21*100 -> #DIV/0! | AH20: =T20/T$21*100 -> 1.14229 | BG20: 414090
A21: =SUM(A10:A20) -> 1835880.9 | B21: =IF(G21=0,0,(A21*100/G21)) -> 58.872089 | C21: =SUM(C10:C20) -> 245055.85 | D21: =IF(G21=0,0,(C21*100/G21)) -> 7.8583258 | E21: =SUM(E10:E20) -> 3118423.1 | F21: =IF(G21=0,0,(E21*100/G21)) -> 100 | G21: =SUM(G10:G20) -> 3118423.1 | H21: =G21/G$21*100 -> 100 | I21: Rooms Revenue | J21: =SUM(J10:J20) -> 83351411 | K21: =J21/J$21*100 -> 100 | L21: =SUM(L10:L20) -> 83351411 | M21: =IF(S21<>0,L21/S21*100,0) -> 0 | N21: =SUM(N10:N20) -> 5510924.8 | O21: =IF(T21<>0,N21/T21*100,0) -> 7.0797667 | Q21: =SUM(Q10:Q20) -> 0 | R21: =SUM(R10:R20) -> 1282542.3 | S21: =SUM(S10:S20) -> 0 | T21: =SUM(T10:T20) -> 77840486 | V21: =SUM(V10:V20) -> 77840486 | W21: =SUM(W10:W20) -> 0 | X21: =SUM(X10:X20) -> 70588969 | Z21: =SUM(Z10:Z20) -> 2873367.3 | AA21: =SUM(AA10:AA20) -> 0 | AC21: =Q21/Q$21*100 -> #DIV/0! | AD21: =R21/R$21*100 -> 100 | AE21: =Z21/Z$21*100 -> 100 | AG21: =S21/S$21*100 -> #DIV/0! | AH21: =T21/T$21*100 -> 100
A22: =+G22-R22 -> 0 | B22: =IF(G22=0,0,(A22*100/G22)) -> 0 | C22: =G22-Z22 -> 0 | D22: =IF(G22=0,0,(C22*100/G22)) -> 0 | E22: =+G22-Q22 -> 0 | F22: =IF(G22=0,0,(E22*100/G22)) -> 0 | G22: =IFERROR(_xll.AC_BU(_xll.ArrayBU(DB),_xll.ArrayDPT($BA22:$BE22),_xll.ArrayCOA($BG22:$BZ22),YR,PRD,_xll.ArrayDIM($CB22:$CE22)),0) -> 0 | H22: =G22/$G$26*100 -> 0 | I22: Overbooking Expenses | J22: =IFERROR(_xll.ACC_BU(_xll.ArrayBU(DB),_xll.ArrayDPT($BA22:$BE22),_xll.ArrayCOA($BG22:$BZ22),YR,PRD,_xll.ArrayDIM($CB22:$CE22)),0) -> 0 | K22: =J22/$J$26*100 -> 0 | L22: =+J22-S22 -> 0 | M22: =IF(S22=0,0,(L22*100/S22)) -> 0 | N22: =+J22-T22 -> 0 | O22: =IF(J22=0,0,(N22*100/J22)) -> 0 | Q22: =IFERROR(_xll.BC_BU(_xll.ArrayBU(DB),_xll.ArrayDPT($BA22:$BE22),_xll.ArrayCOA($BG22:$BZ22),YR,PRD,RV,_xll.ArrayDIM($CB22:$CE22)),0) -> 0 | R22: =IFERROR(_xll.AC_BU(_xll.ArrayBU(DB),_xll.ArrayDPT($BA22:$BE22),_xll.ArrayCOA($BG22:$BZ22),YR-1,PRD,_xll.ArrayDIM($CB22:$CE22)),0) -> 0 | S22: =IFERROR(_xll.BCC_BU(_xll.ArrayBU(DB),_xll.ArrayDPT($BA22:$BE22),_xll.ArrayCOA($BG22:$BZ22),YR,PRD,RV,_xll.ArrayDIM($CB22:$CE22)),0) -> 0 | T22: =IFERROR(_xll.ACC_BU(_xll.ArrayBU(DB),_xll.ArrayDPT($BA22:$BE22),_xll.ArrayCOA($BG22:$BZ22),YR-1,PRD,_xll.ArrayDIM($CB22:$CE22)),0) -> 0 | V22: =IFERROR(_xll.ACC_BU(_xll.ArrayBU(DB),_xll.ArrayDPT($BA22:$BE22),_xll.ArrayCOA($BG22:$BZ22),YR-1,PRD,_xll.ArrayDIM($CB22:$CE22)),0) -> 0 | W22: =IFERROR(_xll.BCC_BU(_xll.ArrayBU(DB),_xll.ArrayDPT($BA22:$BE22),_xll.ArrayCOA($BG22:$BZ22),YR-1,PRD,RV,_xll.ArrayDIM($CB22:$CE22)),0) -> 0 | X22: =IFERROR(_xll.ACC_BU(_xll.ArrayBU(DB),_xll.ArrayDPT($BA22:$BE22),_xll.ArrayCOA($BG22:$BZ22),YR-1-1,PRD,_xll.ArrayDIM($CB22:$CE22)),0) -> 0 | Z22: =IFERROR(_xll.AC_BU(_xll.ArrayBU(DB),_xll.ArrayDPT($BA22:$BE22),_xll.ArrayCOA($BG22:$BZ22),YR,PRD-1,_xll.ArrayDIM($CB22:$CE22)),0) -> 0 | AA22: =IFERROR(_xll.BC_BU(_xll.ArrayBU(DB),_xll.ArrayDPT($BA22:$BE22),_xll.ArrayCOA($BG22:$BZ22),YR,PRD-1,RV,_xll.ArrayDIM($CB22:$CE22)),0) -> 0 | AC22: =Q22/Q$21*100 -> #DIV/0! | AD22: =R22/R$21*100 -> 0 | AE22: =Z22/Z$21*100 -> 0 | AG22: =S22/S$21*100 -> #DIV/0! | AH22: =T22/T$21*100 -> 0 | BG22: 415772
A23: =+G23-R23 -> 221790.66 | B23: =IF(G23=0,0,(A23*100/G23)) -> 98.695755 | C23: =G23-Z23 -> 222404.82 | D23: =IF(G23=0,0,(C23*100/G23)) -> 98.969053 | E23: =+G23-Q23 -> 224721.58 | F23: =IF(G23=0,0,(E23*100/G23)) -> 100 | G23: =IFERROR(_xll.AC_BU(_xll.ArrayBU(DB),_xll.ArrayDPT($BA23:$BE23),_xll.ArrayCOA($BG23:$BZ23),YR,PRD,_xll.ArrayDIM($CB23:$CE23)),0) -> 224721.58 | H23: =G23/$G$21*100 -> 7.2062568 | I23: Allowances | J23: =IFERROR(_xll.ACC_BU(_xll.ArrayBU(DB),_xll.ArrayDPT($BA23:$BE23),_xll.ArrayCOA($BG23:$BZ23),YR,PRD,_xll.ArrayDIM($CB23:$CE23)),0) -> 310808.38 | K23: =J23/$J$21*100 -> 0.37288917 | L23: =+J23-S23 -> 310808.38 | M23: =IF(S23=0,0,(L23*100/S23)) -> 0 | N23: =+J23-T23 -> 224411.52 | O23: =K23-AH23 -> 0.26189698 | Q23: =IFERROR(_xll.BC_BU(_xll.ArrayBU(DB),_xll.ArrayDPT($BA23:$BE23),_xll.ArrayCOA($BG23:$BZ23),YR,PRD,RV,_xll.ArrayDIM($CB23:$CE23)),0) -> 0 | R23: =IFERROR(_xll.AC_BU(_xll.ArrayBU(DB),_xll.ArrayDPT($BA23:$BE23),_xll.ArrayCOA($BG23:$BZ23),YR-1,PRD,_xll.ArrayDIM($CB23:$CE23)),0) -> 2930.92 | S23: =IFERROR(_xll.BCC_BU(_xll.ArrayBU(DB),_xll.ArrayDPT($BA23:$BE23),_xll.ArrayCOA($BG23:$BZ23),YR,PRD,RV,_xll.ArrayDIM($CB23:$CE23)),0) -> 0 | T23: =IFERROR(_xll.ACC_BU(_xll.ArrayBU(DB),_xll.ArrayDPT($BA23:$BE23),_xll.ArrayCOA($BG23:$BZ23),YR-1,PRD,_xll.ArrayDIM($CB23:$CE23)),0) -> 86396.86 | V23: =IFERROR(_xll.ACC_BU(_xll.ArrayBU(DB),_xll.ArrayDPT($BA23:$BE23),_xll.ArrayCOA($BG23:$BZ23),YR-1,PRD,_xll.ArrayDIM($CB23:$CE23)),0) -> 86396.86 | W23: =IFERROR(_xll.BCC_BU(_xll.ArrayBU(DB),_xll.ArrayDPT($BA23:$BE23),_xll.ArrayCOA($BG23:$BZ23),YR-1,PRD,RV,_xll.ArrayDIM($CB23:$CE23)),0) -> 0 | X23: =IFERROR(_xll.ACC_BU(_xll.ArrayBU(DB),_xll.ArrayDPT($BA23:$BE23),_xll.ArrayCOA($BG23:$BZ23),YR-1-1,PRD,_xll.ArrayDIM($CB23:$CE23)),0) -> 58375.78 | Z23: =IFERROR(_xll.AC_BU(_xll.ArrayBU(DB),_xll.ArrayDPT($BA23:$BE23),_xll.ArrayCOA($BG23:$BZ23),YR,PRD-1,_xll.ArrayDIM($CB23:$CE23)),0) -> 2316.76 | AA23: =IFERROR(_xll.BC_BU(_xll.ArrayBU(DB),_xll.ArrayDPT($BA23:$BE23),_xll.ArrayCOA($BG23:$BZ23),YR,PRD-1,RV,_xll.ArrayDIM($CB23:$CE23)),0) -> 0 | AC23: =Q23/Q$21*100 -> #DIV/0! | AD23: =R23/R$21*100 -> 0.22852424 | AE23: =Z23/Z$21*100 -> 0.080628746 | AG23: =S23/S$21*100 -> #DIV/0! | AH23: =T23/T$21*100 -> 0.11099219 | BG23: 414910
A24: =+G24-R24 -> 1614090.2 | B24: =IF(G24=0,0,(A24*100/G24)) -> 55.779428 | C24: =G24-Z24 -> 22651.03 | D24: =IF(G24=0,0,(C24*100/G24)) -> 0.78277008 | E24: =+G24-Q24 -> 2893701.6 | F24: =IF(G24=0,0,(E24*100/G24)) -> 100 | G24: =SUM(G21-G22-G23) -> 2893701.6 | H24: =G24/$G$21*100 -> 92.793743 | I24: Net Rooms Revenue | J24: =SUM(J21-J22-J23) -> 83040602 | K24: =J24/$J$21*100 -> 99.627111 | L24: =+J24-S24 -> 83040602 | M24: =IF(S24=0,0,(L24*100/S24)) -> 0 | N24: =+J24-T24 -> 5286513.3 | O24: =K24-AH24 -> -0.26189698 | Q24: =SUM(Q21-Q22-Q23) -> 0 | R24: =SUM(R21-R22-R23) -> 1279611.4 | S24: =SUM(S21-S22-S23) -> 0 | T24: =SUM(T21-T22-T23) -> 77754089 | V24: =SUM(V21-V22-V23) -> 77754089 | W24: =SUM(W21-W22-W23) -> 0 | X24: =SUM(X21-X22-X23) -> 70530593 | Z24: =SUM(Z21-Z22-Z23) -> 2871050.5 | AA24: =SUM(AA21-AA22-AA23) -> 0 | AC24: =Q24/Q$21*100 -> #DIV/0! | AD24: =R24/R$21*100 -> 99.771476 | AE24: =Z24/Z$21*100 -> 99.919371 | AG24: =S24/S$21*100 -> #DIV/0! | AH24: =T24/T$21*100 -> 99.889008
A25: =+G25-R25 -> 0 | B25: =IF(G25=0,0,(A25*100/G25)) -> 0 | C25: =G25-Z25 -> 0 | D25: =IF(G25=0,0,(C25*100/G25)) -> 0 | E25: =+G25-Q25 -> 0 | F25: =IF(G25=0,0,(E25*100/G25)) -> 0 | H25: =G25/$G$26*100 -> 0 | I25: Sundry Revenue | K25: =J25/$J$21*100 -> 0 | L25: =+J25-S25 -> 0 | M25: =IF(S25=0,0,(L25*100/S25)) -> 0 | N25: =+J25-T25 -> 0 | O25: =K25-AH25 -> 0 | AC25: =Q25/Q$21*100 -> #DIV/0! | AD25: =R25/R$21*100 -> 0 | AE25: =Z25/Z$21*100 -> 0 | AG25: =S25/S$21*100 -> #DIV/0! | AH25: =T25/T$21*100 -> 0
A26: =SUM(A24:A25) -> 1614090.2 | B26: =IF(G26=0,0,(A26*100/G26)) -> 55.779428 | C26: =SUM(C24:C25) -> 22651.03 | D26: =IF(G26=0,0,(C26*100/G26)) -> 0.78277008 | E26: =SUM(E24:E25) -> 2893701.6 | F26: =IF(G26=0,0,(E26*100/G26)) -> 100 | G26: =SUM(G24:G25) -> 2893701.6 | H26: =G26/$G$21*100 -> 92.793743 | I26: Total | J26: =SUM(J24:J25) -> 83040602 | K26: =J26/$J$21*100 -> 99.627111 | L26: =SUM(L24:L25) -> 83040602 | M26: =IF(S26=0,0,(L26*100/S26)) -> 0 | N26: =SUM(N24:N25) -> 5286513.3 | O26: =K26-AH26 -> -0.26189698 | Q26: =SUM(Q24:Q25) -> 0 | R26: =SUM(R24:R25) -> 1279611.4 | S26: =SUM(S24:S25) -> 0 | T26: =SUM(T24:T25) -> 77754089 | V26: =SUM(V24:V25) -> 77754089 | W26: =SUM(W24:W25) -> 0 | X26: =SUM(X24:X25) -> 70530593 | Z26: =SUM(Z24:Z25) -> 2871050.5 | AA26: =SUM(AA24:AA25) -> 0 | AC26: =Q26/Q$21*100 -> #DIV/0! | AD26: =R26/R$21*100 -> 99.771476 | AE26: =Z26/Z$21*100 -> 99.919371 | AG26: =S26/S$21*100 -> #DIV/0! | AH26: =T26/T$21*100 -> 99.889008
A27: =+G27-R27 -> 0 | B27: =IF(G27=0,0,(A27*100/G27)) -> 0 | C27: =G27-Z27 -> 0 | D27: =IF(G27=0,0,(C27*100/G27)) -> 0 | E27: =+G27-Q27 -> 0 | F27: =IF(G27=0,0,(E27*100/G27)) -> 0 | G27: =IFERROR(_xll.AC_BU(_xll.ArrayBU(DB),_xll.ArrayDPT($BA27:$BE27),_xll.ArrayCOA($BG27:$BZ27),YR,PRD,_xll.ArrayDIM($CB27:$CE27)),0) -> 0 | H27: =G27/G$21*100 -> 0 | I27: Extraordinary items | J27: =IFERROR(_xll.ACC_BU(_xll.ArrayBU(DB),_xll.ArrayDPT($BA27:$BE27),_xll.ArrayCOA($BG27:$BZ27),YR,PRD,_xll.ArrayDIM($CB27:$CE27)),0) -> 0 | K27: =J27/J$21*100 -> 0 | L27: =+J27-S27 -> 0 | M27: =IF(S27=0,0,(L27*100/S27)) -> 0 | N27: =+J27-T27 -> 0 | O27: =IF(T27<>0,N27/T27*100,0) -> 0 | Q27: =IFERROR(_xll.BC_BU(_xll.ArrayBU(DB),_xll.ArrayDPT($BA27:$BE27),_xll.ArrayCOA($BG27:$BZ27),YR,PRD,RV,_xll.ArrayDIM($CB27:$CE27)),0) -> 0 | R27: =IFERROR(_xll.AC_BU(_xll.ArrayBU(DB),_xll.ArrayDPT($BA27:$BE27),_xll.ArrayCOA($BG27:$BZ27),YR-1,PRD,_xll.ArrayDIM($CB27:$CE27)),0) -> 0 | S27: =IFERROR(_xll.BCC_BU(_xll.ArrayBU(DB),_xll.ArrayDPT($BA27:$BE27),_xll.ArrayCOA($BG27:$BZ27),YR,PRD,RV,_xll.ArrayDIM($CB27:$CE27)),0) -> 0 | T27: =IFERROR(_xll.ACC_BU(_xll.ArrayBU(DB),_xll.ArrayDPT($BA27:$BE27),_xll.ArrayCOA($BG27:$BZ27),YR-1,PRD,_xll.ArrayDIM($CB27:$CE27)),0) -> 0 | V27: =IFERROR(_xll.ACC_BU(_xll.ArrayBU(DB),_xll.ArrayDPT($BA27:$BE27),_xll.ArrayCOA($BG27:$BZ27),YR-1,PRD,_xll.ArrayDIM($CB27:$CE27)),0) -> 0 | W27: =IFERROR(_xll.BCC_BU(_xll.ArrayBU(DB),_xll.ArrayDPT($BA27:$BE27),_xll.ArrayCOA($BG27:$BZ27),YR-1,PRD,RV,_xll.ArrayDIM($CB27:$CE27)),0) -> 0 | X27: =IFERROR(_xll.ACC_BU(_xll.ArrayBU(DB),_xll.ArrayDPT($BA27:$BE27),_xll.ArrayCOA($BG27:$BZ27),YR-1-1,PRD,_xll.ArrayDIM($CB27:$CE27)),0) -> 0 | Z27: =IFERROR(_xll.AC_BU(_xll.ArrayBU(DB),_xll.ArrayDPT($BA27:$BE27),_xll.ArrayCOA($BG27:$BZ27),YR,PRD-1,_xll.ArrayDIM($CB27:$CE27)),0) -> 0 | AA27: =IFERROR(_xll.BC_BU(_xll.ArrayBU(DB),_xll.ArrayDPT($BA27:$BE27),_xll.ArrayCOA($BG27:$BZ27),YR,PRD-1,RV,_xll.ArrayDIM($CB27:$CE27)),0) -> 0 | AC27: =Q27/Q$21*100 -> #DIV/0! | AD27: =R27/R$21*100 -> 0 | AE27: =Z27/Z$21*100 -> 0 | AG27: =S27/S$21*100 -> #DIV/0! | AH27: =T27/T$21*100 -> 0 | BG27: 414999
A28: =SUM(A26:A27) -> 1614090.2 | B28: =IF(G28=0,0,(A28*100/G28)) -> 55.779428 | C28: =SUM(C26:C27) -> 22651.03 | D28: =IF(G28=0,0,(C28*100/G28)) -> 0.78277008 | E28: =SUM(E26:E27) -> 2893701.6 | F28: =IF(G28=0,0,(E28*100/G28)) -> 100 | G28: =SUM(G26:G27) -> 2893701.6 | H28: =G28/$G$21*100 -> 92.793743 | I28: Total Revenue | J28: =SUM(J26:J27) -> 83040602 | K28: =J28/$J$21*100 -> 99.627111 | L28: =SUM(L26:L27) -> 83040602 | M28: =IF(S28=0,0,(L28*100/S28)) -> 0 | N28: =SUM(N26:N27) -> 5286513.3 | O28: =K28-AH28 -> -0.26189698 | Q28: =SUM(Q26:Q27) -> 0 | R28: =SUM(R26:R27) -> 1279611.4 | S28: =SUM(S26:S27) -> 0 | T28: =SUM(T26:T27) -> 77754089 | V28: =SUM(V26:V27) -> 77754089 | W28: =SUM(W26:W27) -> 0 | X28: =SUM(X26:X27) -> 70530593 | Z28: =SUM(Z26:Z27) -> 2871050.5 | AA28: =SUM(AA26:AA27) -> 0 | AC28: =Q28/Q$21*100 -> #DIV/0! | AD28: =R28/R$21*100 -> 99.771476 | AE28: =Z28/Z$21*100 -> 99.919371 | AG28: =S28/S$21*100 -> #DIV/0! | AH28: =T28/T$21*100 -> 99.889008
I30: PAYROLL
A31: =+G31-R31 -> 712146.22 | B31: =IF(G31=0,0,(A31*100/G31)) -> 52.34397 | C31: =G31-Z31 -> 464262.91 | D31: =IF(G31=0,0,(C31*100/G31)) -> 34.124121 | E31: =+G31-Q31 -> 1360512.4 | F31: =IF(G31=0,0,(E31*100/G31)) -> 100 | G31: =IFERROR(_xll.AC_BU(_xll.ArrayBU(DB),_xll.ArrayDPT($BA31:$BE31),_xll.ArrayCOA($BG31:$BZ31),YR,PRD,_xll.ArrayDIM($CB31:$CE31)),0) -> 1360512.4 | H31: =G31/$G$26*100 -> 47.016336 | I31: Salaries & Wages | J31: =IFERROR(_xll.ACC_BU(_xll.ArrayBU(DB),_xll.ArrayDPT($BA31:$BE31),_xll.ArrayCOA($BG31:$BZ31),YR,PRD,_xll.ArrayDIM($CB31:$CE31)),0) -> 5977310.8 | K31: =J31/$J$26*100 -> 7.1980581 | L31: =+J31-S31 -> 5977310.8 | M31: =IF(S31=0,0,(L31*100/S31)) -> 0 | N31: =+J31-T31 -> 1987197.1 | O31: =IF(J31=0,0,(N31*100/J31)) -> 33.245671 | Q31: =IFERROR(_xll.BC_BU(_xll.ArrayBU(DB),_xll.ArrayDPT($BA31:$BE31),_xll.ArrayCOA($BG31:$BZ31),YR,PRD,RV,_xll.ArrayDIM($CB31:$CE31)),0) -> 0 | R31: =IFERROR(_xll.AC_BU(_xll.ArrayBU(DB),_xll.ArrayDPT($BA31:$BE31),_xll.ArrayCOA($BG31:$BZ31),YR-1,PRD,_xll.ArrayDIM($CB31:$CE31)),0) -> 648366.22 | S31: =IFERROR(_xll.BCC_BU(_xll.ArrayBU(DB),_xll.ArrayDPT($BA31:$BE31),_xll.ArrayCOA($BG31:$BZ31),YR,PRD,RV,_xll.ArrayDIM($CB31:$CE31)),0) -> 0 | T31: =IFERROR(_xll.ACC_BU(_xll.ArrayBU(DB),_xll.ArrayDPT($BA31:$BE31),_xll.ArrayCOA($BG31:$BZ31),YR-1,PRD,_xll.ArrayDIM($CB31:$CE31)),0) -> 3990113.7 | V31: =IFERROR(_xll.ACC_BU(_xll.ArrayBU(DB),_xll.ArrayDPT($BA31:$BE31),_xll.ArrayCOA($BG31:$BZ31),YR-1,PRD,_xll.ArrayDIM($CB31:$CE31)),0) -> 3990113.7 | W31: =IFERROR(_xll.BCC_BU(_xll.ArrayBU(DB),_xll.ArrayDPT($BA31:$BE31),_xll.ArrayCOA($BG31:$BZ31),YR-1,PRD,RV,_xll.ArrayDIM($CB31:$CE31)),0) -> 0 | X31: =IFERROR(_xll.ACC_BU(_xll.ArrayBU(DB),_xll.ArrayDPT($BA31:$BE31),_xll.ArrayCOA($BG31:$BZ31),YR-1-1,PRD,_xll.ArrayDIM($CB31:$CE31)),0) -> 2814338.3 | Z31: =IFERROR(_xll.AC_BU(_xll.ArrayBU(DB),_xll.ArrayDPT($BA31:$BE31),_xll.ArrayCOA($BG31:$BZ31),YR,PRD-1,_xll.ArrayDIM($CB31:$CE31)),0) -> 896249.53 | AA31: =IFERROR(_xll.BC_BU(_xll.ArrayBU(DB),_xll.ArrayDPT($BA31:$BE31),_xll.ArrayCOA($BG31:$BZ31),YR,PRD-1,RV,_xll.ArrayDIM($CB31:$CE31)),0) -> 0 | AC31: =Q31/Q$26*100 -> #DIV/0! | AD31: =R31/R$26*100 -> 50.668995 | AE31: =Z31/Z$26*100 -> 31.21678 | AG31: =S31/S$26*100 -> #DIV/0! | AH31: =T31/T$26*100 -> 5.1317091 | BG31: 415210 | BH31: 415212 | BI31: 425210 | BJ31: 425212
A32: =+G32-R32 -> 133166.83 | B32: =IF(G32=0,0,(A32*100/G32)) -> 54.564033 | C32: =G32-Z32 -> 13689.56 | D32: =IF(G32=0,0,(C32*100/G32)) -> 5.6091867 | E32: =+G32-Q32 -> 244056.06 | F32: =IF(G32=0,0,(E32*100/G32)) -> 100 | G32: =IFERROR(_xll.AC_BU(_xll.ArrayBU(DB),_xll.ArrayDPT($BA32:$BE32),_xll.ArrayCOA($BG32:$BZ32),YR,PRD,_xll.ArrayDIM($CB32:$CE32)),0) -> 244056.06 | H32: =G32/$G$26*100 -> 8.4340439 | I32: Employee Benefits | J32: =IFERROR(_xll.ACC_BU(_xll.ArrayBU(DB),_xll.ArrayDPT($BA32:$BE32),_xll.ArrayCOA($BG32:$BZ32),YR,PRD,_xll.ArrayDIM($CB32:$CE32)),0) -> 2953631.5 | K32: =J32/$J$26*100 -> 3.5568522 | L32: =+J32-S32 -> 2953631.5 | M32: =IF(S32=0,0,(L32*100/S32)) -> 0 | N32: =+J32-T32 -> 1414456.8 | O32: =IF(J32=0,0,(N32*100/J32)) -> 47.888737 | Q32: =IFERROR(_xll.BC_BU(_xll.ArrayBU(DB),_xll.ArrayDPT($BA32:$BE32),_xll.ArrayCOA($BG32:$BZ32),YR,PRD,RV,_xll.ArrayDIM($CB32:$CE32)),0) -> 0 | R32: =IFERROR(_xll.AC_BU(_xll.ArrayBU(DB),_xll.ArrayDPT($BA32:$BE32),_xll.ArrayCOA($BG32:$BZ32),YR-1,PRD,_xll.ArrayDIM($CB32:$CE32)),0) -> 110889.23 | S32: =IFERROR(_xll.BCC_BU(_xll.ArrayBU(DB),_xll.ArrayDPT($BA32:$BE32),_xll.ArrayCOA($BG32:$BZ32),YR,PRD,RV,_xll.ArrayDIM($CB32:$CE32)),0) -> 0 | T32: =IFERROR(_xll.ACC_BU(_xll.ArrayBU(DB),_xll.ArrayDPT($BA32:$BE32),_xll.ArrayCOA($BG32:$BZ32),YR-1,PRD,_xll.ArrayDIM($CB32:$CE32)),0) -> 1539174.7 | V32: =IFERROR(_xll.ACC_BU(_xll.ArrayBU(DB),_xll.ArrayDPT($BA32:$BE32),_xll.ArrayCOA($BG32:$BZ32),YR-1,PRD,_xll.ArrayDIM($CB32:$CE32)),0) -> 1539174.7 | W32: =IFERROR(_xll.BCC_BU(_xll.ArrayBU(DB),_xll.ArrayDPT($BA32:$BE32),_xll.ArrayCOA($BG32:$BZ32),YR-1,PRD,RV,_xll.ArrayDIM($CB32:$CE32)),0) -> 0 | X32: =IFERROR(_xll.ACC_BU(_xll.ArrayBU(DB),_xll.ArrayDPT($BA32:$BE32),_xll.ArrayCOA($BG32:$BZ32),YR-1-1,PRD,_xll.ArrayDIM($CB32:$CE32)),0) -> 813806.87 | Z32: =IFERROR(_xll.AC_BU(_xll.ArrayBU(DB),_xll.ArrayDPT($BA32:$BE32),_xll.ArrayCOA($BG32:$BZ32),YR,PRD-1,_xll.ArrayDIM($CB32:$CE32)),0) -> 230366.5 | AA32: =IFERROR(_xll.BC_BU(_xll.ArrayBU(DB),_xll.ArrayDPT($BA32:$BE32),_xll.ArrayCOA($BG32:$BZ32),YR,PRD-1,RV,_xll.ArrayDIM($CB32:$CE32)),0) -> 0 | AC32: =Q32/Q$26*100 -> #DIV/0! | AD32: =R32/R$26*100 -> 8.6658522 | AE32: =Z32/Z$26*100 -> 8.0237703 | AG32: =S32/S$26*100 -> #DIV/0! | AH32: =T32/T$26*100 -> 1.9795418 | BG32: 415213 | BH32: 415270 | BI32: 425213 | BJ32: 425270
A33: =SUM(A31:A32) -> 845313.05 | B33: =IF(G33=0,0,(A33*100/G33)) -> 52.681643 | C33: =SUM(C31:C32) -> 477952.47 | D33: =IF(G33=0,0,(C33*100/G33)) -> 29.786978 | E33: =SUM(E31:E32) -> 1604568.5 | F33: =IF(G33=0,0,(E33*100/G33)) -> 100 | G33: =SUM(G31:G32) -> 1604568.5 | H33: =G33/$G$26*100 -> 55.45038 | I33: Total Payroll Expenses | J33: =SUM(J31:J32) -> 8930942.2 | K33: =J33/$J$26*100 -> 10.75491 | L33: =SUM(L31:L32) -> 8930942.2 | M33: =IF(S33=0,0,(L33*100/S33)) -> 0 | N33: =SUM(N31:N32) -> 3401653.9 | O33: =IF(J33=0,0,(N33*100/J33)) -> 38.08841 | Q33: =SUM(Q31:Q32) -> 0 | R33: =SUM(R31:R32) -> 759255.45 | S33: =SUM(S31:S32) -> 0 | T33: =SUM(T31:T32) -> 5529288.3 | V33: =SUM(V31:V32) -> 5529288.3 | W33: =SUM(W31:W32) -> 0 | X33: =SUM(X31:X32) -> 3628145.2 | Z33: =SUM(Z31:Z32) -> 1126616 | AA33: =SUM(AA31:AA32) -> 0 | AC33: =Q33/Q$26*100 -> #DIV/0! | AD33: =R33/R$26*100 -> 59.334847 | AE33: =Z33/Z$26*100 -> 39.24055 | AG33: =S33/S$26*100 -> #DIV/0! | AH33: =T33/T$26*100 -> 7.1112509
I35: OTHER EXPENSES
A36: =+G36-R36 -> 0 | B36: =IF(G36=0,0,(A36*100/G36)) -> 0 | C36: =G36-Z36 -> 0 | D36: =IF(G36=0,0,(C36*100/G36)) -> 0 | E36: =+G36-Q36 -> 0 | F36: =IF(G36=0,0,(E36*100/G36)) -> 0 | G36: =IFERROR(_xll.AC_BU(_xll.ArrayBU(DB),_xll.ArrayDPT($BA36:$BE36),_xll.ArrayCOA($BG36:$BZ36),YR,PRD,_xll.ArrayDIM($CB36:$CE36)),0) -> 0 | H36: =G36/$G$26*100 -> 0 | I36: Paper Supply Expenses | J36: =IFERROR(_xll.ACC_BU(_xll.ArrayBU(DB),_xll.ArrayDPT($BA36:$BE36),_xll.ArrayCOA($BG36:$BZ36),YR,PRD,_xll.ArrayDIM($CB36:$CE36)),0) -> 0 | K36: =J36/$J$26*100 -> 0 | L36: =+J36-S36 -> 0 | M36: =IF(S36=0,0,(L36*100/S36)) -> 0 | N36: =+J36-T36 -> 0 | O36: =IF(J36=0,0,(N36*100/J36)) -> 0 | Q36: =IFERROR(_xll.BC_BU(_xll.ArrayBU(DB),_xll.ArrayDPT($BA36:$BE36),_xll.ArrayCOA($BG36:$BZ36),YR,PRD,RV,_xll.ArrayDIM($CB36:$CE36)),0) -> 0 | R36: =IFERROR(_xll.AC_BU(_xll.ArrayBU(DB),_xll.ArrayDPT($BA36:$BE36),_xll.ArrayCOA($BG36:$BZ36),YR-1,PRD,_xll.ArrayDIM($CB36:$CE36)),0) -> 0 | S36: =IFERROR(_xll.BCC_BU(_xll.ArrayBU(DB),_xll.ArrayDPT($BA36:$BE36),_xll.ArrayCOA($BG36:$BZ36),YR,PRD,RV,_xll.ArrayDIM($CB36:$CE36)),0) -> 0 | T36: =IFERROR(_xll.ACC_BU(_xll.ArrayBU(DB),_xll.ArrayDPT($BA36:$BE36),_xll.ArrayCOA($BG36:$BZ36),YR-1,PRD,_xll.ArrayDIM($CB36:$CE36)),0) -> 0 | V36: =IFERROR(_xll.ACC_BU(_xll.ArrayBU(DB),_xll.ArrayDPT($BA36:$BE36),_xll.ArrayCOA($BG36:$BZ36),YR-1,PRD,_xll.ArrayDIM($CB36:$CE36)),0) -> 0 | W36: =IFERROR(_xll.BCC_BU(_xll.ArrayBU(DB),_xll.ArrayDPT($BA36:$BE36),_xll.ArrayCOA($BG36:$BZ36),YR-1,PRD,RV,_xll.ArrayDIM($CB36:$CE36)),0) -> 0 | X36: =IFERROR(_xll.ACC_BU(_xll.ArrayBU(DB),_xll.ArrayDPT($BA36:$BE36),_xll.ArrayCOA($BG36:$BZ36),YR-1-1,PRD,_xll.ArrayDIM($CB36:$CE36)),0) -> 3060 | Z36: =IFERROR(_xll.AC_BU(_xll.ArrayBU(DB),_xll.ArrayDPT($BA36:$BE36),_xll.ArrayCOA($BG36:$BZ36),YR,PRD-1,_xll.ArrayDIM($CB36:$CE36)),0) -> 0 | AA36: =IFERROR(_xll.BC_BU(_xll.ArrayBU(DB),_xll.ArrayDPT($BA36:$BE36),_xll.ArrayCOA($BG36:$BZ36),YR,PRD-1,RV,_xll.ArrayDIM($CB36:$CE36)),0) -> 0 | BG36: 425411 | BH36: 425411 | BI36: 415411 | BJ36: 415411
A37: =+G37-R37 -> 0 | B37: =IF(G37=0,0,(A37*100/G37)) -> 0 | C37: =G37-Z37 -> 0 | D37: =IF(G37=0,0,(C37*100/G37)) -> 0 | E37: =+G37-Q37 -> 0 | F37: =IF(G37=0,0,(E37*100/G37)) -> 0 | G37: =IFERROR(_xll.AC_BU(_xll.ArrayBU(DB),_xll.ArrayDPT($BA37:$BE37),_xll.ArrayCOA($BG37:$BZ37),YR,PRD,_xll.ArrayDIM($CB37:$CE37)),0) -> 0 | H37: =G37/$G$26*100 -> 0 | I37: F&B Supply Expenses | J37: =IFERROR(_xll.ACC_BU(_xll.ArrayBU(DB),_xll.ArrayDPT($BA37:$BE37),_xll.ArrayCOA($BG37:$BZ37),YR,PRD,_xll.ArrayDIM($CB37:$CE37)),0) -> 0 | K37: =J37/$J$26*100 -> 0 | L37: =+J37-S37 -> 0 | M37: =IF(S37=0,0,(L37*100/S37)) -> 0 | N37: =+J37-T37 -> 0 | O37: =IF(J37=0,0,(N37*100/J37)) -> 0 | Q37: =IFERROR(_xll.BC_BU(_xll.ArrayBU(DB),_xll.ArrayDPT($BA37:$BE37),_xll.ArrayCOA($BG37:$BZ37),YR,PRD,RV,_xll.ArrayDIM($CB37:$CE37)),0) -> 0 | R37: =IFERROR(_xll.AC_BU(_xll.ArrayBU(DB),_xll.ArrayDPT($BA37:$BE37),_xll.ArrayCOA($BG37:$BZ37),YR-1,PRD,_xll.ArrayDIM($CB37:$CE37)),0) -> 0 | S37: =IFERROR(_xll.BCC_BU(_xll.ArrayBU(DB),_xll.ArrayDPT($BA37:$BE37),_xll.ArrayCOA($BG37:$BZ37),YR,PRD,RV,_xll.ArrayDIM($CB37:$CE37)),0) -> 0 | T37: =IFERROR(_xll.ACC_BU(_xll.ArrayBU(DB),_xll.ArrayDPT($BA37:$BE37),_xll.ArrayCOA($BG37:$BZ37),YR-1,PRD,_xll.ArrayDIM($CB37:$CE37)),0) -> 0 | V37: =IFERROR(_xll.ACC_BU(_xll.ArrayBU(DB),_xll.ArrayDPT($BA37:$BE37),_xll.ArrayCOA($BG37:$BZ37),YR-1,PRD,_xll.ArrayDIM($CB37:$CE37)),0) -> 0 | W37: =IFERROR(_xll.BCC_BU(_xll.ArrayBU(DB),_xll.ArrayDPT($BA37:$BE37),_xll.ArrayCOA($BG37:$BZ37),YR-1,PRD,RV,_xll.ArrayDIM($CB37:$CE37)),0) -> 0 | X37: =IFERROR(_xll.ACC_BU(_xll.ArrayBU(DB),_xll.ArrayDPT($BA37:$BE37),_xll.ArrayCOA($BG37:$BZ37),YR-1-1,PRD,_xll.ArrayDIM($CB37:$CE37)),0) -> 0 | Z37: =IFERROR(_xll.AC_BU(_xll.ArrayBU(DB),_xll.ArrayDPT($BA37:$BE37),_xll.ArrayCOA($BG37:$BZ37),YR,PRD-1,_xll.ArrayDIM($CB37:$CE37)),0) -> 0 | AA37: =IFERROR(_xll.BC_BU(_xll.ArrayBU(DB),_xll.ArrayDPT($BA37:$BE37),_xll.ArrayCOA($BG37:$BZ37),YR,PRD-1,RV,_xll.ArrayDIM($CB37:$CE37)),0) -> 0 | BG37: 425420 | BH37: 425420 | BI37: 415420 | BJ37: 415420
A38: =+G38-R38 -> 35617.05 | B38: =IF(G38=0,0,(A38*100/G38)) -> 48.157427 | C38: =G38-Z38 -> 46391.06 | D38: =IF(G38=0,0,(C38*100/G38)) -> 62.724849 | E38: =+G38-Q38 -> 73959.62 | F38: =IF(G38=0,0,(E38*100/G38)) -> 100 | G38: =IFERROR(_xll.AC_BU(_xll.ArrayBU(DB),_xll.ArrayDPT($BA38:$BE38),_xll.ArrayCOA($BG38:$BZ38),YR,PRD,_xll.ArrayDIM($CB38:$CE38)),0) -> 73959.62 | H38: =G38/$G$26*100 -> 2.5558828 | I38: Guest Supplies | J38: =IFERROR(_xll.ACC_BU(_xll.ArrayBU(DB),_xll.ArrayDPT($BA38:$BE38),_xll.ArrayCOA($BG38:$BZ38),YR,PRD,_xll.ArrayDIM($CB38:$CE38)),0) -> 282149.05 | K38: =J38/$J$26*100 -> 0.3397724 | L38: =+J38-S38 -> 282149.05 | M38: =IF(S38=0,0,(L38*100/S38)) -> 0 | N38: =+J38-T38 -> -21536.36 | O38: =IF(J38=0,0,(N38*100/J38)) -> -7.6329727 | Q38: =IFERROR(_xll.BC_BU(_xll.ArrayBU(DB),_xll.ArrayDPT($BA38:$BE38),_xll.ArrayCOA($BG38:$BZ38),YR,PRD,RV,_xll.ArrayDIM($CB38:$CE38)),0) -> 0 | R38: =IFERROR(_xll.AC_BU(_xll.ArrayBU(DB),_xll.ArrayDPT($BA38:$BE38),_xll.ArrayCOA($BG38:$BZ38),YR-1,PRD,_xll.ArrayDIM($CB38:$CE38)),0) -> 38342.57 | S38: =IFERROR(_xll.BCC_BU(_xll.ArrayBU(DB),_xll.ArrayDPT($BA38:$BE38),_xll.ArrayCOA($BG38:$BZ38),YR,PRD,RV,_xll.ArrayDIM($CB38:$CE38)),0) -> 0 | T38: =IFERROR(_xll.ACC_BU(_xll.ArrayBU(DB),_xll.ArrayDPT($BA38:$BE38),_xll.ArrayCOA($BG38:$BZ38),YR-1,PRD,_xll.ArrayDIM($CB38:$CE38)),0) -> 303685.41 | V38: =IFERROR(_xll.ACC_BU(_xll.ArrayBU(DB),_xll.ArrayDPT($BA38:$BE38),_xll.ArrayCOA($BG38:$BZ38),YR-1,PRD,_xll.ArrayDIM($CB38:$CE38)),0) -> 303685.41 | W38: =IFERROR(_xll.BCC_BU(_xll.ArrayBU(DB),_xll.ArrayDPT($BA38:$BE38),_xll.ArrayCOA($BG38:$BZ38),YR-1,PRD,RV,_xll.ArrayDIM($CB38:$CE38)),0) -> 0 | X38: =IFERROR(_xll.ACC_BU(_xll.ArrayBU(DB),_xll.ArrayDPT($BA38:$BE38),_xll.ArrayCOA($BG38:$BZ38),YR-1-1,PRD,_xll.ArrayDIM($CB38:$CE38)),0) -> 278351.79 | Z38: =IFERROR(_xll.AC_BU(_xll.ArrayBU(DB),_xll.ArrayDPT($BA38:$BE38),_xll.ArrayCOA($BG38:$BZ38),YR,PRD-1,_xll.ArrayDIM($CB38:$CE38)),0) -> 27568.56 | AA38: =IFERROR(_xll.BC_BU(_xll.ArrayBU(DB),_xll.ArrayDPT($BA38:$BE38),_xll.ArrayCOA($BG38:$BZ38),YR,PRD-1,RV,_xll.ArrayDIM($CB38:$CE38)),0) -> 0 | BG38: 415410 | BH38: 415410 | BI38: 425410 | BJ38: 425410
A39: =+G39-R39 -> 23187.03 | B39: =IF(G39=0,0,(A39*100/G39)) -> 69.152468 | C39: =G39-Z39 -> 15394.29 | D39: =IF(G39=0,0,(C39*100/G39)) -> 45.911578 | E39: =+G39-Q39 -> 33530.3 | F39: =IF(G39=0,0,(E39*100/G39)) -> 100 | G39: =IFERROR(_xll.AC_BU(_xll.ArrayBU(DB),_xll.ArrayDPT($BA39:$BE39),_xll.ArrayCOA($BG39:$BZ39),YR,PRD,_xll.ArrayDIM($CB39:$CE39)),0) -> 33530.3 | H39: =G39/$G$26*100 -> 1.1587339 | I39: Cleaning Supplies | J39: =IFERROR(_xll.ACC_BU(_xll.ArrayBU(DB),_xll.ArrayDPT($BA39:$BE39),_xll.ArrayCOA($BG39:$BZ39),YR,PRD,_xll.ArrayDIM($CB39:$CE39)),0) -> 142774.41 | K39: =J39/$J$26*100 -> 0.17193325 | L39: =+J39-S39 -> 142774.41 | M39: =IF(S39=0,0,(L39*100/S39)) -> 0 | N39: =+J39-T39 -> 55753.31 | O39: =IF(J39=0,0,(N39*100/J39)) -> 39.049932 | Q39: =IFERROR(_xll.BC_BU(_xll.ArrayBU(DB),_xll.ArrayDPT($BA39:$BE39),_xll.ArrayCOA($BG39:$BZ39),YR,PRD,RV,_xll.ArrayDIM($CB39:$CE39)),0) -> 0 | R39: =IFERROR(_xll.AC_BU(_xll.ArrayBU(DB),_xll.ArrayDPT($BA39:$BE39),_xll.ArrayCOA($BG39:$BZ39),YR-1,PRD,_xll.ArrayDIM($CB39:$CE39)),0) -> 10343.27 | S39: =IFERROR(_xll.BCC_BU(_xll.ArrayBU(DB),_xll.ArrayDPT($BA39:$BE39),_xll.ArrayCOA($BG39:$BZ39),YR,PRD,RV,_xll.ArrayDIM($CB39:$CE39)),0) -> 0 | T39: =IFERROR(_xll.ACC_BU(_xll.ArrayBU(DB),_xll.ArrayDPT($BA39:$BE39),_xll.ArrayCOA($BG39:$BZ39),YR-1,PRD,_xll.ArrayDIM($CB39:$CE39)),0) -> 87021.1 | V39: =IFERROR(_xll.ACC_BU(_xll.ArrayBU(DB),_xll.ArrayDPT($BA39:$BE39),_xll.ArrayCOA($BG39:$BZ39),YR-1,PRD,_xll.ArrayDIM($CB39:$CE39)),0) -> 87021.1 | W39: =IFERROR(_xll.BCC_BU(_xll.ArrayBU(DB),_xll.ArrayDPT($BA39:$BE39),_xll.ArrayCOA($BG39:$BZ39),YR-1,PRD,RV,_xll.ArrayDIM($CB39:$CE39)),0) -> 0 | X39: =IFERROR(_xll.ACC_BU(_xll.ArrayBU(DB),_xll.ArrayDPT($BA39:$BE39),_xll.ArrayCOA($BG39:$BZ39),YR-1-1,PRD,_xll.ArrayDIM($CB39:$CE39)),0) -> 91425.94 | Z39: =IFERROR(_xll.AC_BU(_xll.ArrayBU(DB),_xll.ArrayDPT($BA39:$BE39),_xll.ArrayCOA($BG39:$BZ39),YR,PRD-1,_xll.ArrayDIM($CB39:$CE39)),0) -> 18136.01 | AA39: =IFERROR(_xll.BC_BU(_xll.ArrayBU(DB),_xll.ArrayDPT($BA39:$BE39),_xll.ArrayCOA($BG39:$BZ39),YR,PRD-1,RV,_xll.ArrayDIM($CB39:$CE39)),0) -> 0 | BG39: 415430 | BH39: 415430 | BI39: 425430 | BJ39: 425430
A40: =+G40-R40 -> 20403.22 | B40: =IF(G40=0,0,(A40*100/G40)) -> 51.055225 | C40: =G40-Z40 -> 23284.8 | D40: =IF(G40=0,0,(C40*100/G40)) -> 58.265838 | E40: =+G40-Q40 -> 39963.04 | F40: =IF(G40=0,0,(E40*100/G40)) -> 100 | G40: =IFERROR(_xll.AC_BU(_xll.ArrayBU(DB),_xll.ArrayDPT($BA40:$BE40),_xll.ArrayCOA($BG40:$BZ40),YR,PRD,_xll.ArrayDIM($CB40:$CE40)),0) -> 39963.04 | H40: =G40/$G$26*100 -> 1.3810353 | I40: Printing & Stationery | J40: =IFERROR(_xll.ACC_BU(_xll.ArrayBU(DB),_xll.ArrayDPT($BA40:$BE40),_xll.ArrayCOA($BG40:$BZ40),YR,PRD,_xll.ArrayDIM($CB40:$CE40)),0) -> 170864.03 | K40: =J40/$J$26*100 -> 0.20575962 | L40: =+J40-S40 -> 170864.03 | M40: =IF(S40=0,0,(L40*100/S40)) -> 0 | N40: =+J40-T40 -> 44265.05 | O40: =IF(J40=0,0,(N40*100/J40)) -> 25.906594 | Q40: =IFERROR(_xll.BC_BU(_xll.ArrayBU(DB),_xll.ArrayDPT($BA40:$BE40),_xll.ArrayCOA($BG40:$BZ40),YR,PRD,RV,_xll.ArrayDIM($CB40:$CE40)),0) -> 0 | R40: =IFERROR(_xll.AC_BU(_xll.ArrayBU(DB),_xll.ArrayDPT($BA40:$BE40),_xll.ArrayCOA($BG40:$BZ40),YR-1,PRD,_xll.ArrayDIM($CB40:$CE40)),0) -> 19559.82 | S40: =IFERROR(_xll.BCC_BU(_xll.ArrayBU(DB),_xll.ArrayDPT($BA40:$BE40),_xll.ArrayCOA($BG40:$BZ40),YR,PRD,RV,_xll.ArrayDIM($CB40:$CE40)),0) -> 0 | T40: =IFERROR(_xll.ACC_BU(_xll.ArrayBU(DB),_xll.ArrayDPT($BA40:$BE40),_xll.ArrayCOA($BG40:$BZ40),YR-1,PRD,_xll.ArrayDIM($CB40:$CE40)),0) -> 126598.98 | V40: =IFERROR(_xll.ACC_BU(_xll.ArrayBU(DB),_xll.ArrayDPT($BA40:$BE40),_xll.ArrayCOA($BG40:$BZ40),YR-1,PRD,_xll.ArrayDIM($CB40:$CE40)),0) -> 126598.98 | W40: =IFERROR(_xll.BCC_BU(_xll.ArrayBU(DB),_xll.ArrayDPT($BA40:$BE40),_xll.ArrayCOA($BG40:$BZ40),YR-1,PRD,RV,_xll.ArrayDIM($CB40:$CE40)),0) -> 0 | X40: =IFERROR(_xll.ACC_BU(_xll.ArrayBU(DB),_xll.ArrayDPT($BA40:$BE40),_xll.ArrayCOA($BG40:$BZ40),YR-1-1,PRD,_xll.ArrayDIM($CB40:$CE40)),0) -> 143278.36 | Z40: =IFERROR(_xll.AC_BU(_xll.ArrayBU(DB),_xll.ArrayDPT($BA40:$BE40),_xll.ArrayCOA($BG40:$BZ40),YR,PRD-1,_xll.ArrayDIM($CB40:$CE40)),0) -> 16678.24 | AA40: =IFERROR(_xll.BC_BU(_xll.ArrayBU(DB),_xll.ArrayDPT($BA40:$BE40),_xll.ArrayCOA($BG40:$BZ40),YR,PRD-1,RV,_xll.ArrayDIM($CB40:$CE40)),0) -> 0 | BG40: 415440 | BH40: 415440 | BI40: 425440 | BJ40: 425440
A41: =+G41-R41 -> 20088.23 | B41: =IF(G41=0,0,(A41*100/G41)) -> 94.214159 | C41: =G41-Z41 -> 19893.38 | D41: =IF(G41=0,0,(C41*100/G41)) -> 93.300309 | E41: =+G41-Q41 -> 21321.88 | F41: =IF(G41=0,0,(E41*100/G41)) -> 100 | G41: =IFERROR(_xll.AC_BU(_xll.ArrayBU(DB),_xll.ArrayDPT($BA41:$BE41),_xll.ArrayCOA($BG41:$BZ41),YR,PRD,_xll.ArrayDIM($CB41:$CE41)),0) -> 21321.88 | H41: =G41/$G$26*100 -> 0.73683756 | I41: Other Supplies | J41: =IFERROR(_xll.ACC_BU(_xll.ArrayBU(DB),_xll.ArrayDPT($BA41:$BE41),_xll.ArrayCOA($BG41:$BZ41),YR,PRD,_xll.ArrayDIM($CB41:$CE41)),0) -> 50722.87 | K41: =J41/$J$26*100 -> 0.061082011 | L41: =+J41-S41 -> 50722.87 | M41: =IF(S41=0,0,(L41*100/S41)) -> 0 | N41: =+J41-T41 -> 44499.68 | O41: =IF(J41=0,0,(N41*100/J41)) -> 87.730998 | Q41: =IFERROR(_xll.BC_BU(_xll.ArrayBU(DB),_xll.ArrayDPT($BA41:$BE41),_xll.ArrayCOA($BG41:$BZ41),YR,PRD,RV,_xll.ArrayDIM($CB41:$CE41)),0) -> 0 | R41: =IFERROR(_xll.AC_BU(_xll.ArrayBU(DB),_xll.ArrayDPT($BA41:$BE41),_xll.ArrayCOA($BG41:$BZ41),YR-1,PRD,_xll.ArrayDIM($CB41:$CE41)),0) -> 1233.65 | S41: =IFERROR(_xll.BCC_BU(_xll.ArrayBU(DB),_xll.ArrayDPT($BA41:$BE41),_xll.ArrayCOA($BG41:$BZ41),YR,PRD,RV,_xll.ArrayDIM($CB41:$CE41)),0) -> 0 | T41: =IFERROR(_xll.ACC_BU(_xll.ArrayBU(DB),_xll.ArrayDPT($BA41:$BE41),_xll.ArrayCOA($BG41:$BZ41),YR-1,PRD,_xll.ArrayDIM($CB41:$CE41)),0) -> 6223.19 | V41: =IFERROR(_xll.ACC_BU(_xll.ArrayBU(DB),_xll.ArrayDPT($BA41:$BE41),_xll.ArrayCOA($BG41:$BZ41),YR-1,PRD,_xll.ArrayDIM($CB41:$CE41)),0) -> 6223.19 | W41: =IFERROR(_xll.BCC_BU(_xll.ArrayBU(DB),_xll.ArrayDPT($BA41:$BE41),_xll.ArrayCOA($BG41:$BZ41),YR-1,PRD,RV,_xll.ArrayDIM($CB41:$CE41)),0) -> 0 | X41: =IFERROR(_xll.ACC_BU(_xll.ArrayBU(DB),_xll.ArrayDPT($BA41:$BE41),_xll.ArrayCOA($BG41:$BZ41),YR-1-1,PRD,_xll.ArrayDIM($CB41:$CE41)),0) -> 981.68 | Z41: =IFERROR(_xll.AC_BU(_xll.ArrayBU(DB),_xll.ArrayDPT($BA41:$BE41),_xll.ArrayCOA($BG41:$BZ41),YR,PRD-1,_xll.ArrayDIM($CB41:$CE41)),0) -> 1428.5 | AA41: =IFERROR(_xll.BC_BU(_xll.ArrayBU(DB),_xll.ArrayDPT($BA41:$BE41),_xll.ArrayCOA($BG41:$BZ41),YR,PRD-1,RV,_xll.ArrayDIM($CB41:$CE41)),0) -> 0 | BG41: 415490 | BH41: 415490 | BI41: 425490 | BJ41: 425490
A42: =+G42-R42 -> 6708 | B42: =IF(G42=0,0,(A42*100/G42)) -> 45.663717 | C42: =G42-Z42 -> 7345 | D42: =IF(G42=0,0,(C42*100/G42)) -> 50 | E42: =+G42-Q42 -> 14690 | F42: =IF(G42=0,0,(E42*100/G42)) -> 100 | G42: =IFERROR(_xll.AC_BU(_xll.ArrayBU(DB),_xll.ArrayDPT($BA42:$BE42),_xll.ArrayCOA($BG42:$BZ42),YR,PRD,_xll.ArrayDIM($CB42:$CE42)),0) -> 14690 | H42: =G42/$G$26*100 -> 0.50765429 | I42: TV Network (True & Cable) | J42: =IFERROR(_xll.ACC_BU(_xll.ArrayBU(DB),_xll.ArrayDPT($BA42:$BE42),_xll.ArrayCOA($BG42:$BZ42),YR,PRD,_xll.ArrayDIM($CB42:$CE42)),0) -> 51415 | K42: =J42/$J$26*100 -> 0.061915495 | L42: =+J42-S42 -> 51415 | M42: =IF(S42=0,0,(L42*100/S42)) -> 0 | N42: =+J42-T42 -> 3523 | O42: =IF(J42=0,0,(N42*100/J42)) -> 6.852086 | Q42: =IFERROR(_xll.BC_BU(_xll.ArrayBU(DB),_xll.ArrayDPT($BA42:$BE42),_xll.ArrayCOA($BG42:$BZ42),YR,PRD,RV,_xll.ArrayDIM($CB42:$CE42)),0) -> 0 | R42: =IFERROR(_xll.AC_BU(_xll.ArrayBU(DB),_xll.ArrayDPT($BA42:$BE42),_xll.ArrayCOA($BG42:$BZ42),YR-1,PRD,_xll.ArrayDIM($CB42:$CE42)),0) -> 7982 | S42: =IFERROR(_xll.BCC_BU(_xll.ArrayBU(DB),_xll.ArrayDPT($BA42:$BE42),_xll.ArrayCOA($BG42:$BZ42),YR,PRD,RV,_xll.ArrayDIM($CB42:$CE42)),0) -> 0 | T42: =IFERROR(_xll.ACC_BU(_xll.ArrayBU(DB),_xll.ArrayDPT($BA42:$BE42),_xll.ArrayCOA($BG42:$BZ42),YR-1,PRD,_xll.ArrayDIM($CB42:$CE42)),0) -> 47892 | V42: =IFERROR(_xll.ACC_BU(_xll.ArrayBU(DB),_xll.ArrayDPT($BA42:$BE42),_xll.ArrayCOA($BG42:$BZ42),YR-1,PRD,_xll.ArrayDIM($CB42:$CE42)),0) -> 47892 | W42: =IFERROR(_xll.BCC_BU(_xll.ArrayBU(DB),_xll.ArrayDPT($BA42:$BE42),_xll.ArrayCOA($BG42:$BZ42),YR-1,PRD,RV,_xll.ArrayDIM($CB42:$CE42)),0) -> 0 | X42: =IFERROR(_xll.ACC_BU(_xll.ArrayBU(DB),_xll.ArrayDPT($BA42:$BE42),_xll.ArrayCOA($BG42:$BZ42),YR-1-1,PRD,_xll.ArrayDIM($CB42:$CE42)),0) -> 45985.33 | Z42: =IFERROR(_xll.AC_BU(_xll.ArrayBU(DB),_xll.ArrayDPT($BA42:$BE42),_xll.ArrayCOA($BG42:$BZ42),YR,PRD-1,_xll.ArrayDIM($CB42:$CE42)),0) -> 7345 | AA42: =IFERROR(_xll.BC_BU(_xll.ArrayBU(DB),_xll.ArrayDPT($BA42:$BE42),_xll.ArrayCOA($BG42:$BZ42),YR,PRD-1,RV,_xll.ArrayDIM($CB42:$CE42)),0) -> 0 | BG42: 415820 | BH42: 415820 | BI42: 425820 | BJ42: 425820
A43: =+G43-R43 -> -3504.76 | B43: =IF(G43=0,0,(A43*100/G43)) -> 0 | C43: =G43-Z43 -> 0 | D43: =IF(G43=0,0,(C43*100/G43)) -> 0 | E43: =+G43-Q43 -> 0 | F43: =IF(G43=0,0,(E43*100/G43)) -> 0 | G43: =IFERROR(_xll.AC_BU(_xll.ArrayBU(DB),_xll.ArrayDPT($BA43:$BE43),_xll.ArrayCOA($BG43:$BZ43),YR,PRD,_xll.ArrayDIM($CB43:$CE43)),0) -> 0 | H43: =G43/$G$26*100 -> 0 | I43: Magazine&News paper | J43: =IFERROR(_xll.ACC_BU(_xll.ArrayBU(DB),_xll.ArrayDPT($BA43:$BE43),_xll.ArrayCOA($BG43:$BZ43),YR,PRD,_xll.ArrayDIM($CB43:$CE43)),0) -> 14018.99 | K43: =J43/$J$26*100 -> 0.016882091 | L43: =+J43-S43 -> 14018.99 | M43: =IF(S43=0,0,(L43*100/S43)) -> 0 | N43: =+J43-T43 -> -8008 | O43: =IF(J43=0,0,(N43*100/J43)) -> -57.122517 | Q43: =IFERROR(_xll.BC_BU(_xll.ArrayBU(DB),_xll.ArrayDPT($BA43:$BE43),_xll.ArrayCOA($BG43:$BZ43),YR,PRD,RV,_xll.ArrayDIM($CB43:$CE43)),0) -> 0 | R43: =IFERROR(_xll.AC_BU(_xll.ArrayBU(DB),_xll.ArrayDPT($BA43:$BE43),_xll.ArrayCOA($BG43:$BZ43),YR-1,PRD,_xll.ArrayDIM($CB43:$CE43)),0) -> 3504.76 | S43: =IFERROR(_xll.BCC_BU(_xll.ArrayBU(DB),_xll.ArrayDPT($BA43:$BE43),_xll.ArrayCOA($BG43:$BZ43),YR,PRD,RV,_xll.ArrayDIM($CB43:$CE43)),0) -> 0 | T43: =IFERROR(_xll.ACC_BU(_xll.ArrayBU(DB),_xll.ArrayDPT($BA43:$BE43),_xll.ArrayCOA($BG43:$BZ43),YR-1,PRD,_xll.ArrayDIM($CB43:$CE43)),0) -> 22026.99 | V43: =IFERROR(_xll.ACC_BU(_xll.ArrayBU(DB),_xll.ArrayDPT($BA43:$BE43),_xll.ArrayCOA($BG43:$BZ43),YR-1,PRD,_xll.ArrayDIM($CB43:$CE43)),0) -> 22026.99 | W43: =IFERROR(_xll.BCC_BU(_xll.ArrayBU(DB),_xll.ArrayDPT($BA43:$BE43),_xll.ArrayCOA($BG43:$BZ43),YR-1,PRD,RV,_xll.ArrayDIM($CB43:$CE43)),0) -> 0 | X43: =IFERROR(_xll.ACC_BU(_xll.ArrayBU(DB),_xll.ArrayDPT($BA43:$BE43),_xll.ArrayCOA($BG43:$BZ43),YR-1-1,PRD,_xll.ArrayDIM($CB43:$CE43)),0) -> 21583.21 | Z43: =IFERROR(_xll.AC_BU(_xll.ArrayBU(DB),_xll.ArrayDPT($BA43:$BE43),_xll.ArrayCOA($BG43:$BZ43),YR,PRD-1,_xll.ArrayDIM($CB43:$CE43)),0) -> 0 | AA43: =IFERROR(_xll.BC_BU(_xll.ArrayBU(DB),_xll.ArrayDPT($BA43:$BE43),_xll.ArrayCOA($BG43:$BZ43),YR,PRD-1,RV,_xll.ArrayDIM($CB43:$CE43)),0) -> 0 | BG43: 415821 | BH43: 415821 | BI43: 425821 | BJ43: 425821
A44: =+G44-R44 -> 0 | B44: =IF(G44=0,0,(A44*100/G44)) -> 0 | C44: =G44-Z44 -> 0 | D44: =IF(G44=0,0,(C44*100/G44)) -> 0 | E44: =+G44-Q44 -> 0 | F44: =IF(G44=0,0,(E44*100/G44)) -> 0 | G44: =IFERROR(_xll.AC_BU(_xll.ArrayBU(DB),_xll.ArrayDPT($BA44:$BE44),_xll.ArrayCOA($BG44:$BZ44),YR,PRD,_xll.ArrayDIM($CB44:$CE44)),0) -> 0 | H44: =G44/$G$26*100 -> 0 | I44: Travelling Expenses | J44: =IFERROR(_xll.ACC_BU(_xll.ArrayBU(DB),_xll.ArrayDPT($BA44:$BE44),_xll.ArrayCOA($BG44:$BZ44),YR,PRD,_xll.ArrayDIM($CB44:$CE44)),0) -> 0 | K44: =J44/$J$26*100 -> 0 | L44: =+J44-S44 -> 0 | M44: =IF(S44=0,0,(L44*100/S44)) -> 0 | N44: =+J44-T44 -> 0 | O44: =IF(J44=0,0,(N44*100/J44)) -> 0 | Q44: =IFERROR(_xll.BC_BU(_xll.ArrayBU(DB),_xll.ArrayDPT($BA44:$BE44),_xll.ArrayCOA($BG44:$BZ44),YR,PRD,RV,_xll.ArrayDIM($CB44:$CE44)),0) -> 0 | R44: =IFERROR(_xll.AC_BU(_xll.ArrayBU(DB),_xll.ArrayDPT($BA44:$BE44),_xll.ArrayCOA($BG44:$BZ44),YR-1,PRD,_xll.ArrayDIM($CB44:$CE44)),0) -> 0 | S44: =IFERROR(_xll.BCC_BU(_xll.ArrayBU(DB),_xll.ArrayDPT($BA44:$BE44),_xll.ArrayCOA($BG44:$BZ44),YR,PRD,RV,_xll.ArrayDIM($CB44:$CE44)),0) -> 0 | T44: =IFERROR(_xll.ACC_BU(_xll.ArrayBU(DB),_xll.ArrayDPT($BA44:$BE44),_xll.ArrayCOA($BG44:$BZ44),YR-1,PRD,_xll.ArrayDIM($CB44:$CE44)),0) -> 0 | V44: =IFERROR(_xll.ACC_BU(_xll.ArrayBU(DB),_xll.ArrayDPT($BA44:$BE44),_xll.ArrayCOA($BG44:$BZ44),YR-1,PRD,_xll.ArrayDIM($CB44:$CE44)),0) -> 0 | W44: =IFERROR(_xll.BCC_BU(_xll.ArrayBU(DB),_xll.ArrayDPT($BA44:$BE44),_xll.ArrayCOA($BG44:$BZ44),YR-1,PRD,RV,_xll.ArrayDIM($CB44:$CE44)),0) -> 0 | X44: =IFERROR(_xll.ACC_BU(_xll.ArrayBU(DB),_xll.ArrayDPT($BA44:$BE44),_xll.ArrayCOA($BG44:$BZ44),YR-1-1,PRD,_xll.ArrayDIM($CB44:$CE44)),0) -> 0 | Z44: =IFERROR(_xll.AC_BU(_xll.ArrayBU(DB),_xll.ArrayDPT($BA44:$BE44),_xll.ArrayCOA($BG44:$BZ44),YR,PRD-1,_xll.ArrayDIM($CB44:$CE44)),0) -> 0 | AA44: =IFERROR(_xll.BC_BU(_xll.ArrayBU(DB),_xll.ArrayDPT($BA44:$BE44),_xll.ArrayCOA($BG44:$BZ44),YR,PRD-1,RV,_xll.ArrayDIM($CB44:$CE44)),0) -> 0 | BG44: 415740 | BH44: 415740 | BI44: 425740 | BJ44: 425740
A45: =+G45-R45 -> 10217.74 | B45: =IF(G45=0,0,(A45*100/G45)) -> 55.090115 | C45: =G45-Z45 -> 1060.89 | D45: =IF(G45=0,0,(C45*100/G45)) -> 5.7199099 | E45: =+G45-Q45 -> 18547.32 | F45: =IF(G45=0,0,(E45*100/G45)) -> 100 | G45: =IFERROR(_xll.AC_BU(_xll.ArrayBU(DB),_xll.ArrayDPT($BA45:$BE45),_xll.ArrayCOA($BG45:$BZ45),YR,PRD,_xll.ArrayDIM($CB45:$CE45)),0) -> 18547.32 | H45: =G45/$G$26*100 -> 0.64095483 | I45: Reservation Expenses | J45: =IFERROR(_xll.ACC_BU(_xll.ArrayBU(DB),_xll.ArrayDPT($BA45:$BE45),_xll.ArrayCOA($BG45:$BZ45),YR,PRD,_xll.ArrayDIM($CB45:$CE45)),0) -> 508616.64 | K45: =J45/$J$26*100 -> 0.61249151 | L45: =+J45-S45 -> 508616.64 | M45: =IF(S45=0,0,(L45*100/S45)) -> 0 | N45: =+J45-T45 -> 256822.72 | O45: =IF(J45=0,0,(N45*100/J45)) -> 50.494361 | Q45: =IFERROR(_xll.BC_BU(_xll.ArrayBU(DB),_xll.ArrayDPT($BA45:$BE45),_xll.ArrayCOA($BG45:$BZ45),YR,PRD,RV,_xll.ArrayDIM($CB45:$CE45)),0) -> 0 | R45: =IFERROR(_xll.AC_BU(_xll.ArrayBU(DB),_xll.ArrayDPT($BA45:$BE45),_xll.ArrayCOA($BG45:$BZ45),YR-1,PRD,_xll.ArrayDIM($CB45:$CE45)),0) -> 8329.58 | S45: =IFERROR(_xll.BCC_BU(_xll.ArrayBU(DB),_xll.ArrayDPT($BA45:$BE45),_xll.ArrayCOA($BG45:$BZ45),YR,PRD,RV,_xll.ArrayDIM($CB45:$CE45)),0) -> 0 | T45: =IFERROR(_xll.ACC_BU(_xll.ArrayBU(DB),_xll.ArrayDPT($BA45:$BE45),_xll.ArrayCOA($BG45:$BZ45),YR-1,PRD,_xll.ArrayDIM($CB45:$CE45)),0) -> 251793.92 | V45: =IFERROR(_xll.ACC_BU(_xll.ArrayBU(DB),_xll.ArrayDPT($BA45:$BE45),_xll.ArrayCOA($BG45:$BZ45),YR-1,PRD,_xll.ArrayDIM($CB45:$CE45)),0) -> 251793.92 | W45: =IFERROR(_xll.BCC_BU(_xll.ArrayBU(DB),_xll.ArrayDPT($BA45:$BE45),_xll.ArrayCOA($BG45:$BZ45),YR-1,PRD,RV,_xll.ArrayDIM($CB45:$CE45)),0) -> 0 | X45: =IFERROR(_xll.ACC_BU(_xll.ArrayBU(DB),_xll.ArrayDPT($BA45:$BE45),_xll.ArrayCOA($BG45:$BZ45),YR-1-1,PRD,_xll.ArrayDIM($CB45:$CE45)),0) -> 169739.03 | Z45: =IFERROR(_xll.AC_BU(_xll.ArrayBU(DB),_xll.ArrayDPT($BA45:$BE45),_xll.ArrayCOA($BG45:$BZ45),YR,PRD-1,_xll.ArrayDIM($CB45:$CE45)),0) -> 17486.43 | AA45: =IFERROR(_xll.BC_BU(_xll.ArrayBU(DB),_xll.ArrayDPT($BA45:$BE45),_xll.ArrayCOA($BG45:$BZ45),YR,PRD-1,RV,_xll.ArrayDIM($CB45:$CE45)),0) -> 0 | BG45: 415771 | BH45: 415771 | BI45: 425771 | BJ45: 425771
A46: =+G46-R46 -> 820 | B46: =IF(G46=0,0,(A46*100/G46)) -> 80.392157 | C46: =G46-Z46 -> 600 | D46: =IF(G46=0,0,(C46*100/G46)) -> 58.823529 | E46: =+G46-Q46 -> 1020 | F46: =IF(G46=0,0,(E46*100/G46)) -> 100 | G46: =IFERROR(_xll.AC_BU(_xll.ArrayBU(DB),_xll.ArrayDPT($BA46:$BE46),_xll.ArrayCOA($BG46:$BZ46),YR,PRD,_xll.ArrayDIM($CB46:$CE46)),0) -> 1020 | H46: =G46/$G$26*100 -> 0.03524897 | I46: Local Transportation | J46: =IFERROR(_xll.ACC_BU(_xll.ArrayBU(DB),_xll.ArrayDPT($BA46:$BE46),_xll.ArrayCOA($BG46:$BZ46),YR,PRD,_xll.ArrayDIM($CB46:$CE46)),0) -> 5720 | K46: =J46/$J$26*100 -> 0.0068881967 | L46: =+J46-S46 -> 5720 | M46: =IF(S46=0,0,(L46*100/S46)) -> 0 | N46: =+J46-T46 -> 720.72 | O46: =IF(J46=0,0,(N46*100/J46)) -> 12.6 | Q46: =IFERROR(_xll.BC_BU(_xll.ArrayBU(DB),_xll.ArrayDPT($BA46:$BE46),_xll.ArrayCOA($BG46:$BZ46),YR,PRD,RV,_xll.ArrayDIM($CB46:$CE46)),0) -> 0 | R46: =IFERROR(_xll.AC_BU(_xll.ArrayBU(DB),_xll.ArrayDPT($BA46:$BE46),_xll.ArrayCOA($BG46:$BZ46),YR-1,PRD,_xll.ArrayDIM($CB46:$CE46)),0) -> 200 | S46: =IFERROR(_xll.BCC_BU(_xll.ArrayBU(DB),_xll.ArrayDPT($BA46:$BE46),_xll.ArrayCOA($BG46:$BZ46),YR,PRD,RV,_xll.ArrayDIM($CB46:$CE46)),0) -> 0 | T46: =IFERROR(_xll.ACC_BU(_xll.ArrayBU(DB),_xll.ArrayDPT($BA46:$BE46),_xll.ArrayCOA($BG46:$BZ46),YR-1,PRD,_xll.ArrayDIM($CB46:$CE46)),0) -> 4999.28 | V46: =IFERROR(_xll.ACC_BU(_xll.ArrayBU(DB),_xll.ArrayDPT($BA46:$BE46),_xll.ArrayCOA($BG46:$BZ46),YR-1,PRD,_xll.ArrayDIM($CB46:$CE46)),0) -> 4999.28 | W46: =IFERROR(_xll.BCC_BU(_xll.ArrayBU(DB),_xll.ArrayDPT($BA46:$BE46),_xll.ArrayCOA($BG46:$BZ46),YR-1,PRD,RV,_xll.ArrayDIM($CB46:$CE46)),0) -> 0 | X46: =IFERROR(_xll.ACC_BU(_xll.ArrayBU(DB),_xll.ArrayDPT($BA46:$BE46),_xll.ArrayCOA($BG46:$BZ46),YR-1-1,PRD,_xll.ArrayDIM($CB46:$CE46)),0) -> 5470.69 | Z46: =IFERROR(_xll.AC_BU(_xll.ArrayBU(DB),_xll.ArrayDPT($BA46:$BE46),_xll.ArrayCOA($BG46:$BZ46),YR,PRD-1,_xll.ArrayDIM($CB46:$CE46)),0) -> 420 | AA46: =IFERROR(_xll.BC_BU(_xll.ArrayBU(DB),_xll.ArrayDPT($BA46:$BE46),_xll.ArrayCOA($BG46:$BZ46),YR,PRD-1,RV,_xll.ArrayDIM($CB46:$CE46)),0) -> 0 | BG46: 415730 | BH46: 415730 | BI46: 425730 | BJ46: 425730
A47: =+G47-R47 -> 0 | B47: =IF(G47=0,0,(A47*100/G47)) -> 0 | C47: =G47-Z47 -> 0 | D47: =IF(G47=0,0,(C47*100/G47)) -> 0 | E47: =+G47-Q47 -> 0 | F47: =IF(G47=0,0,(E47*100/G47)) -> 0 | G47: =IFERROR(_xll.AC_BU(_xll.ArrayBU(DB),_xll.ArrayDPT($BA47:$BE47),_xll.ArrayCOA($BG47:$BZ47),YR,PRD,_xll.ArrayDIM($CB47:$CE47)),0) -> 0 | H47: =G47/$G$26*100 -> 0 | I47: Gasoline | J47: =IFERROR(_xll.ACC_BU(_xll.ArrayBU(DB),_xll.ArrayDPT($BA47:$BE47),_xll.ArrayCOA($BG47:$BZ47),YR,PRD,_xll.ArrayDIM($CB47:$CE47)),0) -> 0 | K47: =J47/$J$26*100 -> 0 | L47: =+J47-S47 -> 0 | M47: =IF(S47=0,0,(L47*100/S47)) -> 0 | N47: =+J47-T47 -> 0 | O47: =IF(J47=0,0,(N47*100/J47)) -> 0 | Q47: =IFERROR(_xll.BC_BU(_xll.ArrayBU(DB),_xll.ArrayDPT($BA47:$BE47),_xll.ArrayCOA($BG47:$BZ47),YR,PRD,RV,_xll.ArrayDIM($CB47:$CE47)),0) -> 0 | R47: =IFERROR(_xll.AC_BU(_xll.ArrayBU(DB),_xll.ArrayDPT($BA47:$BE47),_xll.ArrayCOA($BG47:$BZ47),YR-1,PRD,_xll.ArrayDIM($CB47:$CE47)),0) -> 0 | S47: =IFERROR(_xll.BCC_BU(_xll.ArrayBU(DB),_xll.ArrayDPT($BA47:$BE47),_xll.ArrayCOA($BG47:$BZ47),YR,PRD,RV,_xll.ArrayDIM($CB47:$CE47)),0) -> 0 | T47: =IFERROR(_xll.ACC_BU(_xll.ArrayBU(DB),_xll.ArrayDPT($BA47:$BE47),_xll.ArrayCOA($BG47:$BZ47),YR-1,PRD,_xll.ArrayDIM($CB47:$CE47)),0) -> 0 | V47: =IFERROR(_xll.ACC_BU(_xll.ArrayBU(DB),_xll.ArrayDPT($BA47:$BE47),_xll.ArrayCOA($BG47:$BZ47),YR-1,PRD,_xll.ArrayDIM($CB47:$CE47)),0) -> 0 | W47: =IFERROR(_xll.BCC_BU(_xll.ArrayBU(DB),_xll.ArrayDPT($BA47:$BE47),_xll.ArrayCOA($BG47:$BZ47),YR-1,PRD,RV,_xll.ArrayDIM($CB47:$CE47)),0) -> 0 | X47: =IFERROR(_xll.ACC_BU(_xll.ArrayBU(DB),_xll.ArrayDPT($BA47:$BE47),_xll.ArrayCOA($BG47:$BZ47),YR-1-1,PRD,_xll.ArrayDIM($CB47:$CE47)),0) -> 5094.51 | Z47: =IFERROR(_xll.AC_BU(_xll.ArrayBU(DB),_xll.ArrayDPT($BA47:$BE47),_xll.ArrayCOA($BG47:$BZ47),YR,PRD-1,_xll.ArrayDIM($CB47:$CE47)),0) -> 0 | AA47: =IFERROR(_xll.BC_BU(_xll.ArrayBU(DB),_xll.ArrayDPT($BA47:$BE47),_xll.ArrayCOA($BG47:$BZ47),YR,PRD-1,RV,_xll.ArrayDIM($CB47:$CE47)),0) -> 0 | BG47: 415590 | BH47: 415590 | BI47: 425590 | BJ47: 425590
A48: =+G48-R48 -> -4028.97 | B48: =IF(G48=0,0,(A48*100/G48)) -> -107.4392 | C48: =G48-Z48 -> 2600 | D48: =IF(G48=0,0,(C48*100/G48)) -> 69.333333 | E48: =+G48-Q48 -> 3750 | F48: =IF(G48=0,0,(E48*100/G48)) -> 100 | G48: =IFERROR(_xll.AC_BU(_xll.ArrayBU(DB),_xll.ArrayDPT($BA48:$BE48),_xll.ArrayCOA($BG48:$BZ48),YR,PRD,_xll.ArrayDIM($CB48:$CE48)),0) -> 3750 | H48: =G48/$G$26*100 -> 0.1295918 | I48: Decoration | J48: =IFERROR(_xll.ACC_BU(_xll.ArrayBU(DB),_xll.ArrayDPT($BA48:$BE48),_xll.ArrayCOA($BG48:$BZ48),YR,PRD,_xll.ArrayDIM($CB48:$CE48)),0) -> 8380 | K48: =J48/$J$26*100 -> 0.010091449 | L48: =+J48-S48 -> 8380 | M48: =IF(S48=0,0,(L48*100/S48)) -> 0 | N48: =+J48-T48 -> -17845.94 | O48: =IF(J48=0,0,(N48*100/J48)) -> -212.95871 | Q48: =IFERROR(_xll.BC_BU(_xll.ArrayBU(DB),_xll.ArrayDPT($BA48:$BE48),_xll.ArrayCOA($BG48:$BZ48),YR,PRD,RV,_xll.ArrayDIM($CB48:$CE48)),0) -> 0 | R48: =IFERROR(_xll.AC_BU(_xll.ArrayBU(DB),_xll.ArrayDPT($BA48:$BE48),_xll.ArrayCOA($BG48:$BZ48),YR-1,PRD,_xll.ArrayDIM($CB48:$CE48)),0) -> 7778.97 | S48: =IFERROR(_xll.BCC_BU(_xll.ArrayBU(DB),_xll.ArrayDPT($BA48:$BE48),_xll.ArrayCOA($BG48:$BZ48),YR,PRD,RV,_xll.ArrayDIM($CB48:$CE48)),0) -> 0 | T48: =IFERROR(_xll.ACC_BU(_xll.ArrayBU(DB),_xll.ArrayDPT($BA48:$BE48),_xll.ArrayCOA($BG48:$BZ48),YR-1,PRD,_xll.ArrayDIM($CB48:$CE48)),0) -> 26225.94 | V48: =IFERROR(_xll.ACC_BU(_xll.ArrayBU(DB),_xll.ArrayDPT($BA48:$BE48),_xll.ArrayCOA($BG48:$BZ48),YR-1,PRD,_xll.ArrayDIM($CB48:$CE48)),0) -> 26225.94 | W48: =IFERROR(_xll.BCC_BU(_xll.ArrayBU(DB),_xll.ArrayDPT($BA48:$BE48),_xll.ArrayCOA($BG48:$BZ48),YR-1,PRD,RV,_xll.ArrayDIM($CB48:$CE48)),0) -> 0 | X48: =IFERROR(_xll.ACC_BU(_xll.ArrayBU(DB),_xll.ArrayDPT($BA48:$BE48),_xll.ArrayCOA($BG48:$BZ48),YR-1-1,PRD,_xll.ArrayDIM($CB48:$CE48)),0) -> 11850 | Z48: =IFERROR(_xll.AC_BU(_xll.ArrayBU(DB),_xll.ArrayDPT($BA48:$BE48),_xll.ArrayCOA($BG48:$BZ48),YR,PRD-1,_xll.ArrayDIM($CB48:$CE48)),0) -> 1150 | AA48: =IFERROR(_xll.BC_BU(_xll.ArrayBU(DB),_xll.ArrayDPT($BA48:$BE48),_xll.ArrayCOA($BG48:$BZ48),YR,PRD-1,RV,_xll.ArrayDIM($CB48:$CE48)),0) -> 0 | BG48: 415580 | BH48: 415580 | BI48: 425580 | BJ48: 425580
A49: =+G49-R49 -> 98.59 | B49: =IF(G49=0,0,(A49*100/G49)) -> 39.253862 | C49: =G49-Z49 -> 78.68 | D49: =IF(G49=0,0,(C49*100/G49)) -> 31.326644 | E49: =+G49-Q49 -> 251.16 | F49: =IF(G49=0,0,(E49*100/G49)) -> 100 | G49: =IFERROR(_xll.AC_BU(_xll.ArrayBU(DB),_xll.ArrayDPT($BA49:$BE49),_xll.ArrayCOA($BG49:$BZ49),YR,PRD,_xll.ArrayDIM($CB49:$CE49)),0) -> 251.16 | H49: =G49/$G$26*100 -> 0.0086795405 | I49: Entertainment | J49: =IFERROR(_xll.ACC_BU(_xll.ArrayBU(DB),_xll.ArrayDPT($BA49:$BE49),_xll.ArrayCOA($BG49:$BZ49),YR,PRD,_xll.ArrayDIM($CB49:$CE49)),0) -> 1277.94 | K49: =J49/$J$26*100 -> 0.0015389339 | L49: =+J49-S49 -> 1277.94 | M49: =IF(S49=0,0,(L49*100/S49)) -> 0 | N49: =+J49-T49 -> -2085.27 | O49: =IF(J49=0,0,(N49*100/J49)) -> -163.17433 | Q49: =IFERROR(_xll.BC_BU(_xll.ArrayBU(DB),_xll.ArrayDPT($BA49:$BE49),_xll.ArrayCOA($BG49:$BZ49),YR,PRD,RV,_xll.ArrayDIM($CB49:$CE49)),0) -> 0 | R49: =IFERROR(_xll.AC_BU(_xll.ArrayBU(DB),_xll.ArrayDPT($BA49:$BE49),_xll.ArrayCOA($BG49:$BZ49),YR-1,PRD,_xll.ArrayDIM($CB49:$CE49)),0) -> 152.57 | S49: =IFERROR(_xll.BCC_BU(_xll.ArrayBU(DB),_xll.ArrayDPT($BA49:$BE49),_xll.ArrayCOA($BG49:$BZ49),YR,PRD,RV,_xll.ArrayDIM($CB49:$CE49)),0) -> 0 | T49: =IFERROR(_xll.ACC_BU(_xll.ArrayBU(DB),_xll.ArrayDPT($BA49:$BE49),_xll.ArrayCOA($BG49:$BZ49),YR-1,PRD,_xll.ArrayDIM($CB49:$CE49)),0) -> 3363.21 | V49: =IFERROR(_xll.ACC_BU(_xll.ArrayBU(DB),_xll.ArrayDPT($BA49:$BE49),_xll.ArrayCOA($BG49:$BZ49),YR-1,PRD,_xll.ArrayDIM($CB49:$CE49)),0) -> 3363.21 | W49: =IFERROR(_xll.BCC_BU(_xll.ArrayBU(DB),_xll.ArrayDPT($BA49:$BE49),_xll.ArrayCOA($BG49:$BZ49),YR-1,PRD,RV,_xll.ArrayDIM($CB49:$CE49)),0) -> 0 | X49: =IFERROR(_xll.ACC_BU(_xll.ArrayBU(DB),_xll.ArrayDPT($BA49:$BE49),_xll.ArrayCOA($BG49:$BZ49),YR-1-1,PRD,_xll.ArrayDIM($CB49:$CE49)),0) -> 704.32 | Z49: =IFERROR(_xll.AC_BU(_xll.ArrayBU(DB),_xll.ArrayDPT($BA49:$BE49),_xll.ArrayCOA($BG49:$BZ49),YR,PRD-1,_xll.ArrayDIM($CB49:$CE49)),0) -> 172.48 | AA49: =IFERROR(_xll.BC_BU(_xll.ArrayBU(DB),_xll.ArrayDPT($BA49:$BE49),_xll.ArrayCOA($BG49:$BZ49),YR,PRD-1,RV,_xll.ArrayDIM($CB49:$CE49)),0) -> 0 | BG49: 415750 | BH49: 415750 | BI49: 425750 | BJ49: 425750
A50: =+G50-R50 -> 0 | B50: =IF(G50=0,0,(A50*100/G50)) -> 0 | C50: =G50-Z50 -> 0 | D50: =IF(G50=0,0,(C50*100/G50)) -> 0 | E50: =+G50-Q50 -> 0 | F50: =IF(G50=0,0,(E50*100/G50)) -> 0 | G50: =IFERROR(_xll.AC_BU(_xll.ArrayBU(DB),_xll.ArrayDPT($BA50:$BE50),_xll.ArrayCOA($BG50:$BZ50),YR,PRD,_xll.ArrayDIM($CB50:$CE50)),0) -> 0 | H50: =G50/$G$26*100 -> 0 | I50: Postage | J50: =IFERROR(_xll.ACC_BU(_xll.ArrayBU(DB),_xll.ArrayDPT($BA50:$BE50),_xll.ArrayCOA($BG50:$BZ50),YR,PRD,_xll.ArrayDIM($CB50:$CE50)),0) -> 139 | K50: =J50/$J$26*100 -> 0.000167388 | L50: =+J50-S50 -> 139 | M50: =IF(S50=0,0,(L50*100/S50)) -> 0 | N50: =+J50-T50 -> 139 | O50: =IF(J50=0,0,(N50*100/J50)) -> 100 | Q50: =IFERROR(_xll.BC_BU(_xll.ArrayBU(DB),_xll.ArrayDPT($BA50:$BE50),_xll.ArrayCOA($BG50:$BZ50),YR,PRD,RV,_xll.ArrayDIM($CB50:$CE50)),0) -> 0 | R50: =IFERROR(_xll.AC_BU(_xll.ArrayBU(DB),_xll.ArrayDPT($BA50:$BE50),_xll.ArrayCOA($BG50:$BZ50),YR-1,PRD,_xll.ArrayDIM($CB50:$CE50)),0) -> 0 | S50: =IFERROR(_xll.BCC_BU(_xll.ArrayBU(DB),_xll.ArrayDPT($BA50:$BE50),_xll.ArrayCOA($BG50:$BZ50),YR,PRD,RV,_xll.ArrayDIM($CB50:$CE50)),0) -> 0 | T50: =IFERROR(_xll.ACC_BU(_xll.ArrayBU(DB),_xll.ArrayDPT($BA50:$BE50),_xll.ArrayCOA($BG50:$BZ50),YR-1,PRD,_xll.ArrayDIM($CB50:$CE50)),0) -> 0 | V50: =IFERROR(_xll.ACC_BU(_xll.ArrayBU(DB),_xll.ArrayDPT($BA50:$BE50),_xll.ArrayCOA($BG50:$BZ50),YR-1,PRD,_xll.ArrayDIM($CB50:$CE50)),0) -> 0 | W50: =IFERROR(_xll.BCC_BU(_xll.ArrayBU(DB),_xll.ArrayDPT($BA50:$BE50),_xll.ArrayCOA($BG50:$BZ50),YR-1,PRD,RV,_xll.ArrayDIM($CB50:$CE50)),0) -> 0 | X50: =IFERROR(_xll.ACC_BU(_xll.ArrayBU(DB),_xll.ArrayDPT($BA50:$BE50),_xll.ArrayCOA($BG50:$BZ50),YR-1-1,PRD,_xll.ArrayDIM($CB50:$CE50)),0) -> 0 | Z50: =IFERROR(_xll.AC_BU(_xll.ArrayBU(DB),_xll.ArrayDPT($BA50:$BE50),_xll.ArrayCOA($BG50:$BZ50),YR,PRD-1,_xll.ArrayDIM($CB50:$CE50)),0) -> 0 | AA50: =IFERROR(_xll.BC_BU(_xll.ArrayBU(DB),_xll.ArrayDPT($BA50:$BE50),_xll.ArrayCOA($BG50:$BZ50),YR,PRD-1,RV,_xll.ArrayDIM($CB50:$CE50)),0) -> 0 | BG50: 415840 | BH50: 415840 | BI50: 425840 | BJ50: 425840
A51: =+G51-R51 -> 8460.37 | B51: =IF(G51=0,0,(A51*100/G51)) -> 53.535803 | C51: =G51-Z51 -> 8061.26 | D51: =IF(G51=0,0,(C51*100/G51)) -> 51.010302 | E51: =+G51-Q51 -> 15803.2 | F51: =IF(G51=0,0,(E51*100/G51)) -> 100 | G51: =IFERROR(_xll.AC_BU(_xll.ArrayBU(DB),_xll.ArrayDPT($BA51:$BE51),_xll.ArrayCOA($BG51:$BZ51),YR,PRD,_xll.ArrayDIM($CB51:$CE51)),0) -> 15803.2 | H51: =G51/$G$26*100 -> 0.54612404 | I51: Communication Charge | J51: =IFERROR(_xll.ACC_BU(_xll.ArrayBU(DB),_xll.ArrayDPT($BA51:$BE51),_xll.ArrayCOA($BG51:$BZ51),YR,PRD,_xll.ArrayDIM($CB51:$CE51)),0) -> 60033.02 | K51: =J51/$J$26*100 -> 0.072293575 | L51: =+J51-S51 -> 60033.02 | M51: =IF(S51=0,0,(L51*100/S51)) -> 0 | N51: =+J51-T51 -> 14657.19 | O51: =IF(J51=0,0,(N51*100/J51)) -> 24.415213 | Q51: =IFERROR(_xll.BC_BU(_xll.ArrayBU(DB),_xll.ArrayDPT($BA51:$BE51),_xll.ArrayCOA($BG51:$BZ51),YR,PRD,RV,_xll.ArrayDIM($CB51:$CE51)),0) -> 0 | R51: =IFERROR(_xll.AC_BU(_xll.ArrayBU(DB),_xll.ArrayDPT($BA51:$BE51),_xll.ArrayCOA($BG51:$BZ51),YR-1,PRD,_xll.ArrayDIM($CB51:$CE51)),0) -> 7342.83 | S51: =IFERROR(_xll.BCC_BU(_xll.ArrayBU(DB),_xll.ArrayDPT($BA51:$BE51),_xll.ArrayCOA($BG51:$BZ51),YR,PRD,RV,_xll.ArrayDIM($CB51:$CE51)),0) -> 0 | T51: =IFERROR(_xll.ACC_BU(_xll.ArrayBU(DB),_xll.ArrayDPT($BA51:$BE51),_xll.ArrayCOA($BG51:$BZ51),YR-1,PRD,_xll.ArrayDIM($CB51:$CE51)),0) -> 45375.83 | V51: =IFERROR(_xll.ACC_BU(_xll.ArrayBU(DB),_xll.ArrayDPT($BA51:$BE51),_xll.ArrayCOA($BG51:$BZ51),YR-1,PRD,_xll.ArrayDIM($CB51:$CE51)),0) -> 45375.83 | W51: =IFERROR(_xll.BCC_BU(_xll.ArrayBU(DB),_xll.ArrayDPT($BA51:$BE51),_xll.ArrayCOA($BG51:$BZ51),YR-1,PRD,RV,_xll.ArrayDIM($CB51:$CE51)),0) -> 0 | X51: =IFERROR(_xll.ACC_BU(_xll.ArrayBU(DB),_xll.ArrayDPT($BA51:$BE51),_xll.ArrayCOA($BG51:$BZ51),YR-1-1,PRD,_xll.ArrayDIM($CB51:$CE51)),0) -> 44747.2 | Z51: =IFERROR(_xll.AC_BU(_xll.ArrayBU(DB),_xll.ArrayDPT($BA51:$BE51),_xll.ArrayCOA($BG51:$BZ51),YR,PRD-1,_xll.ArrayDIM($CB51:$CE51)),0) -> 7741.94 | AA51: =IFERROR(_xll.BC_BU(_xll.ArrayBU(DB),_xll.ArrayDPT($BA51:$BE51),_xll.ArrayCOA($BG51:$BZ51),YR,PRD-1,RV,_xll.ArrayDIM($CB51:$CE51)),0) -> 0 | BG51: 415520 | BH51: 415520 | BI51: 425520 | BJ51: 425520
A52: =+G52-R52 -> 109589 | B52: =IF(G52=0,0,(A52*100/G52)) -> 49.04452 | C52: =G52-Z52 -> 92079 | D52: =IF(G52=0,0,(C52*100/G52)) -> 41.208245 | E52: =+G52-Q52 -> 223448 | F52: =IF(G52=0,0,(E52*100/G52)) -> 100 | G52: =IFERROR(_xll.AC_BU(_xll.ArrayBU(DB),_xll.ArrayDPT($BA52:$BE52),_xll.ArrayCOA($BG52:$BZ52),YR,PRD,_xll.ArrayDIM($CB52:$CE52)),0) -> 223448 | H52: =G52/$G$26*100 -> 7.7218744 | I52: Laundry Expenses | J52: =IFERROR(_xll.ACC_BU(_xll.ArrayBU(DB),_xll.ArrayDPT($BA52:$BE52),_xll.ArrayCOA($BG52:$BZ52),YR,PRD,_xll.ArrayDIM($CB52:$CE52)),0) -> 1022622 | K52: =J52/$J$26*100 -> 1.2314723 | L52: =+J52-S52 -> 1022622 | M52: =IF(S52=0,0,(L52*100/S52)) -> 0 | N52: =+J52-T52 -> 47057 | O52: =IF(J52=0,0,(N52*100/J52)) -> 4.6016025 | Q52: =IFERROR(_xll.BC_BU(_xll.ArrayBU(DB),_xll.ArrayDPT($BA52:$BE52),_xll.ArrayCOA($BG52:$BZ52),YR,PRD,RV,_xll.ArrayDIM($CB52:$CE52)),0) -> 0 | R52: =IFERROR(_xll.AC_BU(_xll.ArrayBU(DB),_xll.ArrayDPT($BA52:$BE52),_xll.ArrayCOA($BG52:$BZ52),YR-1,PRD,_xll.ArrayDIM($CB52:$CE52)),0) -> 113859 | S52: =IFERROR(_xll.BCC_BU(_xll.ArrayBU(DB),_xll.ArrayDPT($BA52:$BE52),_xll.ArrayCOA($BG52:$BZ52),YR,PRD,RV,_xll.ArrayDIM($CB52:$CE52)),0) -> 0 | T52: =IFERROR(_xll.ACC_BU(_xll.ArrayBU(DB),_xll.ArrayDPT($BA52:$BE52),_xll.ArrayCOA($BG52:$BZ52),YR-1,PRD,_xll.ArrayDIM($CB52:$CE52)),0) -> 975565 | V52: =IFERROR(_xll.ACC_BU(_xll.ArrayBU(DB),_xll.ArrayDPT($BA52:$BE52),_xll.ArrayCOA($BG52:$BZ52),YR-1,PRD,_xll.ArrayDIM($CB52:$CE52)),0) -> 975565 | W52: =IFERROR(_xll.BCC_BU(_xll.ArrayBU(DB),_xll.ArrayDPT($BA52:$BE52),_xll.ArrayCOA($BG52:$BZ52),YR-1,PRD,RV,_xll.ArrayDIM($CB52:$CE52)),0) -> 0 | X52: =IFERROR(_xll.ACC_BU(_xll.ArrayBU(DB),_xll.ArrayDPT($BA52:$BE52),_xll.ArrayCOA($BG52:$BZ52),YR-1-1,PRD,_xll.ArrayDIM($CB52:$CE52)),0) -> 919407 | Z52: =IFERROR(_xll.AC_BU(_xll.ArrayBU(DB),_xll.ArrayDPT($BA52:$BE52),_xll.ArrayCOA($BG52:$BZ52),YR,PRD-1,_xll.ArrayDIM($CB52:$CE52)),0) -> 131369 | AA52: =IFERROR(_xll.BC_BU(_xll.ArrayBU(DB),_xll.ArrayDPT($BA52:$BE52),_xll.ArrayCOA($BG52:$BZ52),YR,PRD-1,RV,_xll.ArrayDIM($CB52:$CE52)),0) -> 0 | BG52: 415635 | BH52: 415635 | BI52: 425635 | BJ52: 425635
A53: =+G53-R53 -> 27196.5 | B53: =IF(G53=0,0,(A53*100/G53)) -> 47.102478 | C53: =G53-Z53 -> 20704.03 | D53: =IF(G53=0,0,(C53*100/G53)) -> 35.857964 | E53: =+G53-Q53 -> 57739 | F53: =IF(G53=0,0,(E53*100/G53)) -> 100 | G53: =IFERROR(_xll.AC_BU(_xll.ArrayBU(DB),_xll.ArrayDPT($BA53:$BE53),_xll.ArrayCOA($BG53:$BZ53),YR,PRD,_xll.ArrayDIM($CB53:$CE53)),0) -> 57739 | H53: =G53/$G$26*100 -> 1.9953336 | I53: Complimentary Services | J53: =IFERROR(_xll.ACC_BU(_xll.ArrayBU(DB),_xll.ArrayDPT($BA53:$BE53),_xll.ArrayCOA($BG53:$BZ53),YR,PRD,_xll.ArrayDIM($CB53:$CE53)),0) -> 419680.8 | K53: =J53/$J$26*100 -> 0.50539229 | L53: =+J53-S53 -> 419680.8 | M53: =IF(S53=0,0,(L53*100/S53)) -> 0 | N53: =+J53-T53 -> 45421.05 | O53: =IF(J53=0,0,(N53*100/J53)) -> 10.822761 | Q53: =IFERROR(_xll.BC_BU(_xll.ArrayBU(DB),_xll.ArrayDPT($BA53:$BE53),_xll.ArrayCOA($BG53:$BZ53),YR,PRD,RV,_xll.ArrayDIM($CB53:$CE53)),0) -> 0 | R53: =IFERROR(_xll.AC_BU(_xll.ArrayBU(DB),_xll.ArrayDPT($BA53:$BE53),_xll.ArrayCOA($BG53:$BZ53),YR-1,PRD,_xll.ArrayDIM($CB53:$CE53)),0) -> 30542.5 | S53: =IFERROR(_xll.BCC_BU(_xll.ArrayBU(DB),_xll.ArrayDPT($BA53:$BE53),_xll.ArrayCOA($BG53:$BZ53),YR,PRD,RV,_xll.ArrayDIM($CB53:$CE53)),0) -> 0 | T53: =IFERROR(_xll.ACC_BU(_xll.ArrayBU(DB),_xll.ArrayDPT($BA53:$BE53),_xll.ArrayCOA($BG53:$BZ53),YR-1,PRD,_xll.ArrayDIM($CB53:$CE53)),0) -> 374259.75 | V53: =IFERROR(_xll.ACC_BU(_xll.ArrayBU(DB),_xll.ArrayDPT($BA53:$BE53),_xll.ArrayCOA($BG53:$BZ53),YR-1,PRD,_xll.ArrayDIM($CB53:$CE53)),0) -> 374259.75 | W53: =IFERROR(_xll.BCC_BU(_xll.ArrayBU(DB),_xll.ArrayDPT($BA53:$BE53),_xll.ArrayCOA($BG53:$BZ53),YR-1,PRD,RV,_xll.ArrayDIM($CB53:$CE53)),0) -> 0 | X53: =IFERROR(_xll.ACC_BU(_xll.ArrayBU(DB),_xll.ArrayDPT($BA53:$BE53),_xll.ArrayCOA($BG53:$BZ53),YR-1-1,PRD,_xll.ArrayDIM($CB53:$CE53)),0) -> 347821.75 | Z53: =IFERROR(_xll.AC_BU(_xll.ArrayBU(DB),_xll.ArrayDPT($BA53:$BE53),_xll.ArrayCOA($BG53:$BZ53),YR,PRD-1,_xll.ArrayDIM($CB53:$CE53)),0) -> 37034.97 | AA53: =IFERROR(_xll.BC_BU(_xll.ArrayBU(DB),_xll.ArrayDPT($BA53:$BE53),_xll.ArrayCOA($BG53:$BZ53),YR,PRD-1,RV,_xll.ArrayDIM($CB53:$CE53)),0) -> 0 | BG53: 415760 | BH53: 415760
A54: =+G54-R54 -> 65259.45 | B54: =IF(G54=0,0,(A54*100/G54)) -> 45.55126 | C54: =G54-Z54 -> -97775.79 | D54: =IF(G54=0,0,(C54*100/G54)) -> -68.247747 | E54: =+G54-Q54 -> 143265.96 | F54: =IF(G54=0,0,(E54*100/G54)) -> 100 | G54: =IFERROR(_xll.AC_BU(_xll.ArrayBU(DB),_xll.ArrayDPT($BA54:$BE54),_xll.ArrayCOA($BG54:$BZ54),YR,PRD,_xll.ArrayDIM($CB54:$CE54)),0) -> 143265.96 | H54: =G54/$G$26*100 -> 4.9509584 | I54: Travel Agent Commission | J54: =IFERROR(_xll.ACC_BU(_xll.ArrayBU(DB),_xll.ArrayDPT($BA54:$BE54),_xll.ArrayCOA($BG54:$BZ54),YR,PRD,_xll.ArrayDIM($CB54:$CE54)),0) -> 4049382.2 | K54: =J54/$J$26*100 -> 4.8763882 | L54: =+J54-S54 -> 4049382.2 | M54: =IF(S54=0,0,(L54*100/S54)) -> 0 | N54: =+J54-T54 -> 405562.2 | O54: =IF(J54=0,0,(N54*100/J54)) -> 10.015409 | Q54: =IFERROR(_xll.BC_BU(_xll.ArrayBU(DB),_xll.ArrayDPT($BA54:$BE54),_xll.ArrayCOA($BG54:$BZ54),YR,PRD,RV,_xll.ArrayDIM($CB54:$CE54)),0) -> 0 | R54: =IFERROR(_xll.AC_BU(_xll.ArrayBU(DB),_xll.ArrayDPT($BA54:$BE54),_xll.ArrayCOA($BG54:$BZ54),YR-1,PRD,_xll.ArrayDIM($CB54:$CE54)),0) -> 78006.51 | S54: =IFERROR(_xll.BCC_BU(_xll.ArrayBU(DB),_xll.ArrayDPT($BA54:$BE54),_xll.ArrayCOA($BG54:$BZ54),YR,PRD,RV,_xll.ArrayDIM($CB54:$CE54)),0) -> 0 | T54: =IFERROR(_xll.ACC_BU(_xll.ArrayBU(DB),_xll.ArrayDPT($BA54:$BE54),_xll.ArrayCOA($BG54:$BZ54),YR-1,PRD,_xll.ArrayDIM($CB54:$CE54)),0) -> 3643820 | V54: =IFERROR(_xll.ACC_BU(_xll.ArrayBU(DB),_xll.ArrayDPT($BA54:$BE54),_xll.ArrayCOA($BG54:$BZ54),YR-1,PRD,_xll.ArrayDIM($CB54:$CE54)),0) -> 3643820 | W54: =IFERROR(_xll.BCC_BU(_xll.ArrayBU(DB),_xll.ArrayDPT($BA54:$BE54),_xll.ArrayCOA($BG54:$BZ54),YR-1,PRD,RV,_xll.ArrayDIM($CB54:$CE54)),0) -> 0 | X54: =IFERROR(_xll.ACC_BU(_xll.ArrayBU(DB),_xll.ArrayDPT($BA54:$BE54),_xll.ArrayCOA($BG54:$BZ54),YR-1-1,PRD,_xll.ArrayDIM($CB54:$CE54)),0) -> 3981176.4 | Z54: =IFERROR(_xll.AC_BU(_xll.ArrayBU(DB),_xll.ArrayDPT($BA54:$BE54),_xll.ArrayCOA($BG54:$BZ54),YR,PRD-1,_xll.ArrayDIM($CB54:$CE54)),0) -> 241041.75 | AA54: =IFERROR(_xll.BC_BU(_xll.ArrayBU(DB),_xll.ArrayDPT($BA54:$BE54),_xll.ArrayCOA($BG54:$BZ54),YR,PRD-1,RV,_xll.ArrayDIM($CB54:$CE54)),0) -> 0 | BG54: 415770 | BH54: 415770
A55: =+G55-R55 -> 0 | B55: =IF(G55=0,0,(A55*100/G55)) -> 0 | C55: =G55-Z55 -> 0 | D55: =IF(G55=0,0,(C55*100/G55)) -> 0 | E55: =+G55-Q55 -> 0 | F55: =IF(G55=0,0,(E55*100/G55)) -> 0 | G55: =IFERROR(_xll.AC_BU(_xll.ArrayBU(DB),_xll.ArrayDPT($BA55:$BE55),_xll.ArrayCOA($BG55:$BZ55),YR,PRD,_xll.ArrayDIM($CB55:$CE55)),0) -> 0 | H55: =G55/$G$26*100 -> 0 | I55: Linen | J55: =IFERROR(_xll.ACC_BU(_xll.ArrayBU(DB),_xll.ArrayDPT($BA55:$BE55),_xll.ArrayCOA($BG55:$BZ55),YR,PRD,_xll.ArrayDIM($CB55:$CE55)),0) -> 0 | K55: =J55/$J$26*100 -> 0 | L55: =+J55-S55 -> 0 | M55: =IF(S55=0,0,(L55*100/S55)) -> 0 | N55: =+J55-T55 -> 0 | O55: =IF(J55=0,0,(N55*100/J55)) -> 0 | Q55: =IFERROR(_xll.BC_BU(_xll.ArrayBU(DB),_xll.ArrayDPT($BA55:$BE55),_xll.ArrayCOA($BG55:$BZ55),YR,PRD,RV,_xll.ArrayDIM($CB55:$CE55)),0) -> 0 | R55: =IFERROR(_xll.AC_BU(_xll.ArrayBU(DB),_xll.ArrayDPT($BA55:$BE55),_xll.ArrayCOA($BG55:$BZ55),YR-1,PRD,_xll.ArrayDIM($CB55:$CE55)),0) -> 0 | S55: =IFERROR(_xll.BCC_BU(_xll.ArrayBU(DB),_xll.ArrayDPT($BA55:$BE55),_xll.ArrayCOA($BG55:$BZ55),YR,PRD,RV,_xll.ArrayDIM($CB55:$CE55)),0) -> 0 | T55: =IFERROR(_xll.ACC_BU(_xll.ArrayBU(DB),_xll.ArrayDPT($BA55:$BE55),_xll.ArrayCOA($BG55:$BZ55),YR-1,PRD,_xll.ArrayDIM($CB55:$CE55)),0) -> 0 | V55: =IFERROR(_xll.ACC_BU(_xll.ArrayBU(DB),_xll.ArrayDPT($BA55:$BE55),_xll.ArrayCOA($BG55:$BZ55),YR-1,PRD,_xll.ArrayDIM($CB55:$CE55)),0) -> 0 | W55: =IFERROR(_xll.BCC_BU(_xll.ArrayBU(DB),_xll.ArrayDPT($BA55:$BE55),_xll.ArrayCOA($BG55:$BZ55),YR-1,PRD,RV,_xll.ArrayDIM($CB55:$CE55)),0) -> 0 | X55: =IFERROR(_xll.ACC_BU(_xll.ArrayBU(DB),_xll.ArrayDPT($BA55:$BE55),_xll.ArrayCOA($BG55:$BZ55),YR-1-1,PRD,_xll.ArrayDIM($CB55:$CE55)),0) -> 168 | Z55: =IFERROR(_xll.AC_BU(_xll.ArrayBU(DB),_xll.ArrayDPT($BA55:$BE55),_xll.ArrayCOA($BG55:$BZ55),YR,PRD-1,_xll.ArrayDIM($CB55:$CE55)),0) -> 0 | AA55: =IFERROR(_xll.BC_BU(_xll.ArrayBU(DB),_xll.ArrayDPT($BA55:$BE55),_xll.ArrayCOA($BG55:$BZ55),YR,PRD-1,RV,_xll.ArrayDIM($CB55:$CE55)),0) -> 0 | BG55: 415320 | BH55: 415320 | BI55: 425320 | BJ55: 425320
A56: =+G56-R56 -> 0 | B56: =IF(G56=0,0,(A56*100/G56)) -> 0 | C56: =G56-Z56 -> 0 | D56: =IF(G56=0,0,(C56*100/G56)) -> 0 | E56: =+G56-Q56 -> 0 | F56: =IF(G56=0,0,(E56*100/G56)) -> 0 | G56: =IFERROR(_xll.AC_BU(_xll.ArrayBU(DB),_xll.ArrayDPT($BA56:$BE56),_xll.ArrayCOA($BG56:$BZ56),YR,PRD,_xll.ArrayDIM($CB56:$CE56)),0) -> 0 | H56: =G56/$G$26*100 -> 0 | I56: Uniform Cleaning | J56: =IFERROR(_xll.ACC_BU(_xll.ArrayBU(DB),_xll.ArrayDPT($BA56:$BE56),_xll.ArrayCOA($BG56:$BZ56),YR,PRD,_xll.ArrayDIM($CB56:$CE56)),0) -> 0 | K56: =J56/$J$26*100 -> 0 | L56: =+J56-S56 -> 0 | M56: =IF(S56=0,0,(L56*100/S56)) -> 0 | N56: =+J56-T56 -> 0 | O56: =IF(J56=0,0,(N56*100/J56)) -> 0 | Q56: =IFERROR(_xll.BC_BU(_xll.ArrayBU(DB),_xll.ArrayDPT($BA56:$BE56),_xll.ArrayCOA($BG56:$BZ56),YR,PRD,RV,_xll.ArrayDIM($CB56:$CE56)),0) -> 0 | R56: =IFERROR(_xll.AC_BU(_xll.ArrayBU(DB),_xll.ArrayDPT($BA56:$BE56),_xll.ArrayCOA($BG56:$BZ56),YR-1,PRD,_xll.ArrayDIM($CB56:$CE56)),0) -> 0 | S56: =IFERROR(_xll.BCC_BU(_xll.ArrayBU(DB),_xll.ArrayDPT($BA56:$BE56),_xll.ArrayCOA($BG56:$BZ56),YR,PRD,RV,_xll.ArrayDIM($CB56:$CE56)),0) -> 0 | T56: =IFERROR(_xll.ACC_BU(_xll.ArrayBU(DB),_xll.ArrayDPT($BA56:$BE56),_xll.ArrayCOA($BG56:$BZ56),YR-1,PRD,_xll.ArrayDIM($CB56:$CE56)),0) -> 0 | V56: =IFERROR(_xll.ACC_BU(_xll.ArrayBU(DB),_xll.ArrayDPT($BA56:$BE56),_xll.ArrayCOA($BG56:$BZ56),YR-1,PRD,_xll.ArrayDIM($CB56:$CE56)),0) -> 0 | W56: =IFERROR(_xll.BCC_BU(_xll.ArrayBU(DB),_xll.ArrayDPT($BA56:$BE56),_xll.ArrayCOA($BG56:$BZ56),YR-1,PRD,RV,_xll.ArrayDIM($CB56:$CE56)),0) -> 0 | X56: =IFERROR(_xll.ACC_BU(_xll.ArrayBU(DB),_xll.ArrayDPT($BA56:$BE56),_xll.ArrayCOA($BG56:$BZ56),YR-1-1,PRD,_xll.ArrayDIM($CB56:$CE56)),0) -> 45 | Z56: =IFERROR(_xll.AC_BU(_xll.ArrayBU(DB),_xll.ArrayDPT($BA56:$BE56),_xll.ArrayCOA($BG56:$BZ56),YR,PRD-1,_xll.ArrayDIM($CB56:$CE56)),0) -> 0 | AA56: =IFERROR(_xll.BC_BU(_xll.ArrayBU(DB),_xll.ArrayDPT($BA56:$BE56),_xll.ArrayCOA($BG56:$BZ56),YR,PRD-1,RV,_xll.ArrayDIM($CB56:$CE56)),0) -> 0 | BG56: 415630 | BH56: 415630 | BI56: 425630 | BJ56: 425630
A57: =+G57-R57 -> 0 | B57: =IF(G57=0,0,(A57*100/G57)) -> 0 | C57: =G57-Z57 -> 0 | D57: =IF(G57=0,0,(C57*100/G57)) -> 0 | E57: =+G57-Q57 -> 0 | F57: =IF(G57=0,0,(E57*100/G57)) -> 0 | G57: =IFERROR(_xll.AC_BU(_xll.ArrayBU(DB),_xll.ArrayDPT($BA57:$BE57),_xll.ArrayCOA($BG57:$BZ57),YR,PRD,_xll.ArrayDIM($CB57:$CE57)),0) -> 0 | H57: =G57/$G$26*100 -> 0 | I57: Uniform | J57: =IFERROR(_xll.ACC_BU(_xll.ArrayBU(DB),_xll.ArrayDPT($BA57:$BE57),_xll.ArrayCOA($BG57:$BZ57),YR,PRD,_xll.ArrayDIM($CB57:$CE57)),0) -> 17480 | K57: =J57/$J$26*100 -> 0.021049944 | L57: =+J57-S57 -> 17480 | M57: =IF(S57=0,0,(L57*100/S57)) -> 0 | N57: =+J57-T57 -> 17180 | O57: =IF(J57=0,0,(N57*100/J57)) -> 98.283753 | Q57: =IFERROR(_xll.BC_BU(_xll.ArrayBU(DB),_xll.ArrayDPT($BA57:$BE57),_xll.ArrayCOA($BG57:$BZ57),YR,PRD,RV,_xll.ArrayDIM($CB57:$CE57)),0) -> 0 | R57: =IFERROR(_xll.AC_BU(_xll.ArrayBU(DB),_xll.ArrayDPT($BA57:$BE57),_xll.ArrayCOA($BG57:$BZ57),YR-1,PRD,_xll.ArrayDIM($CB57:$CE57)),0) -> 0 | S57: =IFERROR(_xll.BCC_BU(_xll.ArrayBU(DB),_xll.ArrayDPT($BA57:$BE57),_xll.ArrayCOA($BG57:$BZ57),YR,PRD,RV,_xll.ArrayDIM($CB57:$CE57)),0) -> 0 | T57: =IFERROR(_xll.ACC_BU(_xll.ArrayBU(DB),_xll.ArrayDPT($BA57:$BE57),_xll.ArrayCOA($BG57:$BZ57),YR-1,PRD,_xll.ArrayDIM($CB57:$CE57)),0) -> 300 | V57: =IFERROR(_xll.ACC_BU(_xll.ArrayBU(DB),_xll.ArrayDPT($BA57:$BE57),_xll.ArrayCOA($BG57:$BZ57),YR-1,PRD,_xll.ArrayDIM($CB57:$CE57)),0) -> 300 | W57: =IFERROR(_xll.BCC_BU(_xll.ArrayBU(DB),_xll.ArrayDPT($BA57:$BE57),_xll.ArrayCOA($BG57:$BZ57),YR-1,PRD,RV,_xll.ArrayDIM($CB57:$CE57)),0) -> 0 | X57: =IFERROR(_xll.ACC_BU(_xll.ArrayBU(DB),_xll.ArrayDPT($BA57:$BE57),_xll.ArrayCOA($BG57:$BZ57),YR-1-1,PRD,_xll.ArrayDIM($CB57:$CE57)),0) -> 19290 | Z57: =IFERROR(_xll.AC_BU(_xll.ArrayBU(DB),_xll.ArrayDPT($BA57:$BE57),_xll.ArrayCOA($BG57:$BZ57),YR,PRD-1,_xll.ArrayDIM($CB57:$CE57)),0) -> 0 | AA57: =IFERROR(_xll.BC_BU(_xll.ArrayBU(DB),_xll.ArrayDPT($BA57:$BE57),_xll.ArrayCOA($BG57:$BZ57),YR,PRD-1,RV,_xll.ArrayDIM($CB57:$CE57)),0) -> 0 | BG57: 415310 | BH57: 415310 | BI57: 425310 | BJ57: 425310
A58: =+G58-R58 -> 0 | B58: =IF(G58=0,0,(A58*100/G58)) -> 0 | C58: =G58-Z58 -> -1572 | D58: =IF(G58=0,0,(C58*100/G58)) -> 0 | E58: =+G58-Q58 -> 0 | F58: =IF(G58=0,0,(E58*100/G58)) -> 0 | G58: =IFERROR(_xll.AC_BU(_xll.ArrayBU(DB),_xll.ArrayDPT($BA58:$BE58),_xll.ArrayCOA($BG58:$BZ58),YR,PRD,_xll.ArrayDIM($CB58:$CE58)),0) -> 0 | H58: =G58/$G$26*100 -> 0 | I58: Chaina ware/Glass ware/Silver ware | J58: =IFERROR(_xll.ACC_BU(_xll.ArrayBU(DB),_xll.ArrayDPT($BA58:$BE58),_xll.ArrayCOA($BG58:$BZ58),YR,PRD,_xll.ArrayDIM($CB58:$CE58)),0) -> 2635.67 | K58: =J58/$J$26*100 -> 0.0031739534 | L58: =+J58-S58 -> 2635.67 | M58: =IF(S58=0,0,(L58*100/S58)) -> 0 | N58: =+J58-T58 -> 37.75 | O58: =IF(J58=0,0,(N58*100/J58)) -> 1.4322734 | Q58: =IFERROR(_xll.BC_BU(_xll.ArrayBU(DB),_xll.ArrayDPT($BA58:$BE58),_xll.ArrayCOA($BG58:$BZ58),YR,PRD,RV,_xll.ArrayDIM($CB58:$CE58)),0) -> 0 | R58: =IFERROR(_xll.AC_BU(_xll.ArrayBU(DB),_xll.ArrayDPT($BA58:$BE58),_xll.ArrayCOA($BG58:$BZ58),YR-1,PRD,_xll.ArrayDIM($CB58:$CE58)),0) -> 0 | S58: =IFERROR(_xll.BCC_BU(_xll.ArrayBU(DB),_xll.ArrayDPT($BA58:$BE58),_xll.ArrayCOA($BG58:$BZ58),YR,PRD,RV,_xll.ArrayDIM($CB58:$CE58)),0) -> 0 | T58: =IFERROR(_xll.ACC_BU(_xll.ArrayBU(DB),_xll.ArrayDPT($BA58:$BE58),_xll.ArrayCOA($BG58:$BZ58),YR-1,PRD,_xll.ArrayDIM($CB58:$CE58)),0) -> 2597.92 | V58: =IFERROR(_xll.ACC_BU(_xll.ArrayBU(DB),_xll.ArrayDPT($BA58:$BE58),_xll.ArrayCOA($BG58:$BZ58),YR-1,PRD,_xll.ArrayDIM($CB58:$CE58)),0) -> 2597.92 | W58: =IFERROR(_xll.BCC_BU(_xll.ArrayBU(DB),_xll.ArrayDPT($BA58:$BE58),_xll.ArrayCOA($BG58:$BZ58),YR-1,PRD,RV,_xll.ArrayDIM($CB58:$CE58)),0) -> 0 | X58: =IFERROR(_xll.ACC_BU(_xll.ArrayBU(DB),_xll.ArrayDPT($BA58:$BE58),_xll.ArrayCOA($BG58:$BZ58),YR-1-1,PRD,_xll.ArrayDIM($CB58:$CE58)),0) -> 854.41 | Z58: =IFERROR(_xll.AC_BU(_xll.ArrayBU(DB),_xll.ArrayDPT($BA58:$BE58),_xll.ArrayCOA($BG58:$BZ58),YR,PRD-1,_xll.ArrayDIM($CB58:$CE58)),0) -> 1572 | AA58: =IFERROR(_xll.BC_BU(_xll.ArrayBU(DB),_xll.ArrayDPT($BA58:$BE58),_xll.ArrayCOA($BG58:$BZ58),YR,PRD-1,RV,_xll.ArrayDIM($CB58:$CE58)),0) -> 0 | BG58: 415330 | BH58: 415360 | BI58: 425330 | BJ58: 425360
A59: =+G59-R59 -> 0 | B59: =IF(G59=0,0,(A59*100/G59)) -> 0 | C59: =G59-Z59 -> 0 | D59: =IF(G59=0,0,(C59*100/G59)) -> 0 | E59: =+G59-Q59 -> 0 | F59: =IF(G59=0,0,(E59*100/G59)) -> 0 | G59: =IFERROR(_xll.AC_BU(_xll.ArrayBU(DB),_xll.ArrayDPT($BA59:$BE59),_xll.ArrayCOA($BG59:$BZ59),YR,PRD,_xll.ArrayDIM($CB59:$CE59)),0) -> 0 | H59: =G59/$G$26*100 -> 0 | I59: Loyalty Program | J59: =IFERROR(_xll.ACC_BU(_xll.ArrayBU(DB),_xll.ArrayDPT($BA59:$BE59),_xll.ArrayCOA($BG59:$BZ59),YR,PRD,_xll.ArrayDIM($CB59:$CE59)),0) -> 0 | K59: =J59/$J$26*100 -> 0 | L59: =+J59-S59 -> 0 | M59: =IF(S59=0,0,(L59*100/S59)) -> 0 | N59: =+J59-T59 -> 0 | O59: =IF(J59=0,0,(N59*100/J59)) -> 0 | Q59: =IFERROR(_xll.BC_BU(_xll.ArrayBU(DB),_xll.ArrayDPT($BA59:$BE59),_xll.ArrayCOA($BG59:$BZ59),YR,PRD,RV,_xll.ArrayDIM($CB59:$CE59)),0) -> 0 | R59: =IFERROR(_xll.AC_BU(_xll.ArrayBU(DB),_xll.ArrayDPT($BA59:$BE59),_xll.ArrayCOA($BG59:$BZ59),YR-1,PRD,_xll.ArrayDIM($CB59:$CE59)),0) -> 0 | S59: =IFERROR(_xll.BCC_BU(_xll.ArrayBU(DB),_xll.ArrayDPT($BA59:$BE59),_xll.ArrayCOA($BG59:$BZ59),YR,PRD,RV,_xll.ArrayDIM($CB59:$CE59)),0) -> 0 | T59: =IFERROR(_xll.ACC_BU(_xll.ArrayBU(DB),_xll.ArrayDPT($BA59:$BE59),_xll.ArrayCOA($BG59:$BZ59),YR-1,PRD,_xll.ArrayDIM($CB59:$CE59)),0) -> 0 | V59: =IFERROR(_xll.ACC_BU(_xll.ArrayBU(DB),_xll.ArrayDPT($BA59:$BE59),_xll.ArrayCOA($BG59:$BZ59),YR-1,PRD,_xll.ArrayDIM($CB59:$CE59)),0) -> 0 | W59: =IFERROR(_xll.BCC_BU(_xll.ArrayBU(DB),_xll.ArrayDPT($BA59:$BE59),_xll.ArrayCOA($BG59:$BZ59),YR-1,PRD,RV,_xll.ArrayDIM($CB59:$CE59)),0) -> 0 | X59: =IFERROR(_xll.ACC_BU(_xll.ArrayBU(DB),_xll.ArrayDPT($BA59:$BE59),_xll.ArrayCOA($BG59:$BZ59),YR-1-1,PRD,_xll.ArrayDIM($CB59:$CE59)),0) -> 0 | Z59: =IFERROR(_xll.AC_BU(_xll.ArrayBU(DB),_xll.ArrayDPT($BA59:$BE59),_xll.ArrayCOA($BG59:$BZ59),YR,PRD-1,_xll.ArrayDIM($CB59:$CE59)),0) -> 0 | AA59: =IFERROR(_xll.BC_BU(_xll.ArrayBU(DB),_xll.ArrayDPT($BA59:$BE59),_xll.ArrayCOA($BG59:$BZ59),YR,PRD-1,RV,_xll.ArrayDIM($CB59:$CE59)),0) -> 0 | BG59: 415773 | BH59: 415773
A60: =+G60-R60 -> 1874.46 | B60: =IF(G60=0,0,(A60*100/G60)) -> 63.571186 | C60: =G60-Z60 -> 2226.19 | D60: =IF(G60=0,0,(C60*100/G60)) -> 75.499898 | E60: =+G60-Q60 -> 2948.6 | F60: =IF(G60=0,0,(E60*100/G60)) -> 100 | G60: =IFERROR(_xll.AC_BU(_xll.ArrayBU(DB),_xll.ArrayDPT($BA60:$BE60),_xll.ArrayCOA($BG60:$BZ60),YR,PRD,_xll.ArrayDIM($CB60:$CE60)),0) -> 2948.6 | H60: =G60/$G$26*100 -> 0.10189717 | I60: Incentive Payment | J60: =IFERROR(_xll.ACC_BU(_xll.ArrayBU(DB),_xll.ArrayDPT($BA60:$BE60),_xll.ArrayCOA($BG60:$BZ60),YR,PRD,_xll.ArrayDIM($CB60:$CE60)),0) -> 13723.65 | K60: =J60/$J$26*100 -> 0.016526434 | L60: =+J60-S60 -> 13723.65 | M60: =IF(S60=0,0,(L60*100/S60)) -> 0 | N60: =+J60-T60 -> 1571.17 | O60: =IF(J60=0,0,(N60*100/J60)) -> 11.448631 | Q60: =IFERROR(_xll.BC_BU(_xll.ArrayBU(DB),_xll.ArrayDPT($BA60:$BE60),_xll.ArrayCOA($BG60:$BZ60),YR,PRD,RV,_xll.ArrayDIM($CB60:$CE60)),0) -> 0 | R60: =IFERROR(_xll.AC_BU(_xll.ArrayBU(DB),_xll.ArrayDPT($BA60:$BE60),_xll.ArrayCOA($BG60:$BZ60),YR-1,PRD,_xll.ArrayDIM($CB60:$CE60)),0) -> 1074.14 | S60: =IFERROR(_xll.BCC_BU(_xll.ArrayBU(DB),_xll.ArrayDPT($BA60:$BE60),_xll.ArrayCOA($BG60:$BZ60),YR,PRD,RV,_xll.ArrayDIM($CB60:$CE60)),0) -> 0 | T60: =IFERROR(_xll.ACC_BU(_xll.ArrayBU(DB),_xll.ArrayDPT($BA60:$BE60),_xll.ArrayCOA($BG60:$BZ60),YR-1,PRD,_xll.ArrayDIM($CB60:$CE60)),0) -> 12152.48 | V60: =IFERROR(_xll.ACC_BU(_xll.ArrayBU(DB),_xll.ArrayDPT($BA60:$BE60),_xll.ArrayCOA($BG60:$BZ60),YR-1,PRD,_xll.ArrayDIM($CB60:$CE60)),0) -> 12152.48 | W60: =IFERROR(_xll.BCC_BU(_xll.ArrayBU(DB),_xll.ArrayDPT($BA60:$BE60),_xll.ArrayCOA($BG60:$BZ60),YR-1,PRD,RV,_xll.ArrayDIM($CB60:$CE60)),0) -> 0 | X60: =IFERROR(_xll.ACC_BU(_xll.ArrayBU(DB),_xll.ArrayDPT($BA60:$BE60),_xll.ArrayCOA($BG60:$BZ60),YR-1-1,PRD,_xll.ArrayDIM($CB60:$CE60)),0) -> 10705.98 | Z60: =IFERROR(_xll.AC_BU(_xll.ArrayBU(DB),_xll.ArrayDPT($BA60:$BE60),_xll.ArrayCOA($BG60:$BZ60),YR,PRD-1,_xll.ArrayDIM($CB60:$CE60)),0) -> 722.41 | AA60: =IFERROR(_xll.BC_BU(_xll.ArrayBU(DB),_xll.ArrayDPT($BA60:$BE60),_xll.ArrayCOA($BG60:$BZ60),YR,PRD-1,RV,_xll.ArrayDIM($CB60:$CE60)),0) -> 0 | BG60: 415774 | BH60: 415774
A61: =+G61-R61 -> -27234.62 | B61: =IF(G61=0,0,(A61*100/G61)) -> 0 | C61: =G61-Z61 -> -490 | D61: =IF(G61=0,0,(C61*100/G61)) -> 0 | E61: =+G61-Q61 -> 0 | F61: =IF(G61=0,0,(E61*100/G61)) -> 0 | G61: =IFERROR(_xll.AC_BU(_xll.ArrayBU(DB),_xll.ArrayDPT($BA61:$BE61),_xll.ArrayCOA($BG61:$BZ61),YR,PRD,_xll.ArrayDIM($CB61:$CE61)),0) -> 0 | H61: =G61/$G$26*100 -> 0 | I61: Guest Compensation | J61: =IFERROR(_xll.ACC_BU(_xll.ArrayBU(DB),_xll.ArrayDPT($BA61:$BE61),_xll.ArrayCOA($BG61:$BZ61),YR,PRD,_xll.ArrayDIM($CB61:$CE61)),0) -> 665 | K61: =J61/$J$26*100 -> 0.00080081307 | L61: =+J61-S61 -> 665 | M61: =IF(S61=0,0,(L61*100/S61)) -> 0 | N61: =+J61-T61 -> -34187.5 | O61: =IF(J61=0,0,(N61*100/J61)) -> -5140.9774 | Q61: =IFERROR(_xll.BC_BU(_xll.ArrayBU(DB),_xll.ArrayDPT($BA61:$BE61),_xll.ArrayCOA($BG61:$BZ61),YR,PRD,RV,_xll.ArrayDIM($CB61:$CE61)),0) -> 0 | R61: =IFERROR(_xll.AC_BU(_xll.ArrayBU(DB),_xll.ArrayDPT($BA61:$BE61),_xll.ArrayCOA($BG61:$BZ61),YR-1,PRD,_xll.ArrayDIM($CB61:$CE61)),0) -> 27234.62 | S61: =IFERROR(_xll.BCC_BU(_xll.ArrayBU(DB),_xll.ArrayDPT($BA61:$BE61),_xll.ArrayCOA($BG61:$BZ61),YR,PRD,RV,_xll.ArrayDIM($CB61:$CE61)),0) -> 0 | T61: =IFERROR(_xll.ACC_BU(_xll.ArrayBU(DB),_xll.ArrayDPT($BA61:$BE61),_xll.ArrayCOA($BG61:$BZ61),YR-1,PRD,_xll.ArrayDIM($CB61:$CE61)),0) -> 34852.5 | V61: =IFERROR(_xll.ACC_BU(_xll.ArrayBU(DB),_xll.ArrayDPT($BA61:$BE61),_xll.ArrayCOA($BG61:$BZ61),YR-1,PRD,_xll.ArrayDIM($CB61:$CE61)),0) -> 34852.5 | W61: =IFERROR(_xll.BCC_BU(_xll.ArrayBU(DB),_xll.ArrayDPT($BA61:$BE61),_xll.ArrayCOA($BG61:$BZ61),YR-1,PRD,RV,_xll.ArrayDIM($CB61:$CE61)),0) -> 0 | X61: =IFERROR(_xll.ACC_BU(_xll.ArrayBU(DB),_xll.ArrayDPT($BA61:$BE61),_xll.ArrayCOA($BG61:$BZ61),YR-1-1,PRD,_xll.ArrayDIM($CB61:$CE61)),0) -> 0 | Z61: =IFERROR(_xll.AC_BU(_xll.ArrayBU(DB),_xll.ArrayDPT($BA61:$BE61),_xll.ArrayCOA($BG61:$BZ61),YR,PRD-1,_xll.ArrayDIM($CB61:$CE61)),0) -> 490 | AA61: =IFERROR(_xll.BC_BU(_xll.ArrayBU(DB),_xll.ArrayDPT($BA61:$BE61),_xll.ArrayCOA($BG61:$BZ61),YR,PRD-1,RV,_xll.ArrayDIM($CB61:$CE61)),0) -> 0 | BG61: 415775 | BH61: 415775
A62: =+G62-R62 -> 0 | B62: =IF(G62=0,0,(A62*100/G62)) -> 0 | C62: =G62-Z62 -> -740 | D62: =IF(G62=0,0,(C62*100/G62)) -> 0 | E62: =+G62-Q62 -> 0 | F62: =IF(G62=0,0,(E62*100/G62)) -> 0 | G62: =IFERROR(_xll.AC_BU(_xll.ArrayBU(DB),_xll.ArrayDPT($BA62:$BE62),_xll.ArrayCOA($BG62:$BZ62),YR,PRD,_xll.ArrayDIM($CB62:$CE62)),0) -> 0 | H62: =G62/$G$26*100 -> 0 | I62: Miscellaneous Expenses | J62: =IFERROR(_xll.ACC_BU(_xll.ArrayBU(DB),_xll.ArrayDPT($BA62:$BE62),_xll.ArrayCOA($BG62:$BZ62),YR,PRD,_xll.ArrayDIM($CB62:$CE62)),0) -> 740 | K62: =J62/$J$26*100 -> 0.00089113034 | L62: =+J62-S62 -> 740 | M62: =IF(S62=0,0,(L62*100/S62)) -> 0 | N62: =+J62-T62 -> -1230 | O62: =IF(J62=0,0,(N62*100/J62)) -> -166.21622 | Q62: =IFERROR(_xll.BC_BU(_xll.ArrayBU(DB),_xll.ArrayDPT($BA62:$BE62),_xll.ArrayCOA($BG62:$BZ62),YR,PRD,RV,_xll.ArrayDIM($CB62:$CE62)),0) -> 0 | R62: =IFERROR(_xll.AC_BU(_xll.ArrayBU(DB),_xll.ArrayDPT($BA62:$BE62),_xll.ArrayCOA($BG62:$BZ62),YR-1,PRD,_xll.ArrayDIM($CB62:$CE62)),0) -> 0 | S62: =IFERROR(_xll.BCC_BU(_xll.ArrayBU(DB),_xll.ArrayDPT($BA62:$BE62),_xll.ArrayCOA($BG62:$BZ62),YR,PRD,RV,_xll.ArrayDIM($CB62:$CE62)),0) -> 0 | T62: =IFERROR(_xll.ACC_BU(_xll.ArrayBU(DB),_xll.ArrayDPT($BA62:$BE62),_xll.ArrayCOA($BG62:$BZ62),YR-1,PRD,_xll.ArrayDIM($CB62:$CE62)),0) -> 1970 | V62: =IFERROR(_xll.ACC_BU(_xll.ArrayBU(DB),_xll.ArrayDPT($BA62:$BE62),_xll.ArrayCOA($BG62:$BZ62),YR-1,PRD,_xll.ArrayDIM($CB62:$CE62)),0) -> 1970 | W62: =IFERROR(_xll.BCC_BU(_xll.ArrayBU(DB),_xll.ArrayDPT($BA62:$BE62),_xll.ArrayCOA($BG62:$BZ62),YR-1,PRD,RV,_xll.ArrayDIM($CB62:$CE62)),0) -> 0 | X62: =IFERROR(_xll.ACC_BU(_xll.ArrayBU(DB),_xll.ArrayDPT($BA62:$BE62),_xll.ArrayCOA($BG62:$BZ62),YR-1-1,PRD,_xll.ArrayDIM($CB62:$CE62)),0) -> 0 | Z62: =IFERROR(_xll.AC_BU(_xll.ArrayBU(DB),_xll.ArrayDPT($BA62:$BE62),_xll.ArrayCOA($BG62:$BZ62),YR,PRD-1,_xll.ArrayDIM($CB62:$CE62)),0) -> 740 | AA62: =IFERROR(_xll.BC_BU(_xll.ArrayBU(DB),_xll.ArrayDPT($BA62:$BE62),_xll.ArrayCOA($BG62:$BZ62),YR,PRD-1,RV,_xll.ArrayDIM($CB62:$CE62)),0) -> 0 | BG62: 415990 | BH62: 415990 | BI62: 425990 | BJ62: 425990 | BK62: 415360 | BL62: 415360 | BM62: 425360 | BN62: 425360
A63: =SUM(A36:A62) -> 294751.29 | B63: =IF(G63=0,0,(A63*100/G63)) -> 45.329749 | C63: =SUM(C36:C62) -> 139140.79 | D63: =IF(G63=0,0,(C63*100/G63)) -> 21.398438 | E63: =SUM(E36:E62) -> 650238.08 | F63: =IF(G63=0,0,(E63*100/G63)) -> 100 | G63: =SUM(G36:G62) -> 650238.08 | H63: =G63/$G$26*100 -> 22.470807 | I63: Total Other Expenses | J63: =SUM(J36:J62) -> 6823040.2 | K63: =J63/$J$26*100 -> 8.216511 | L63: =SUM(L36:L62) -> 6823040.2 | M63: =IF(S63=0,0,(L63*100/S63)) -> 0 | N63: =SUM(N36:N62) -> 852316.77 | O63: =IF(J63=0,0,(N63*100/J63)) -> 12.491745 | Q63: =SUM(Q36:Q62) -> 0 | R63: =SUM(R36:R62) -> 355486.79 | S63: =SUM(S36:S62) -> 0 | T63: =SUM(T36:T62) -> 5970723.5 | V63: =SUM(V36:V62) -> 5970723.5 | W63: =SUM(W36:W62) -> 0 | X63: =SUM(X36:X62) -> 6101740.6 | Z63: =SUM(Z36:Z62) -> 511097.29 | AA63: =SUM(AA36:AA62) -> 0
A64: =A33+A63 -> 1140064.3 | B64: =IF(G64=0,0,(A64*100/G64)) -> 50.561514 | C64: =C33+C63 -> 617093.26 | D64: =IF(G64=0,0,(C64*100/G64)) -> 27.367902 | E64: =E33+E63 -> 2254806.6 | F64: =IF(G64=0,0,(E64*100/G64)) -> 100 | G64: =G33+G63 -> 2254806.6 | H64: =G64/$G$26*100 -> 77.921186 | I64: TOTAL EXPENSES | J64: =J33+J63 -> 15753982 | K64: =J64/$J$26*100 -> 18.971421 | L64: =L33+L63 -> 15753982 | M64: =IF(S64=0,0,(L64*100/S64)) -> 0 | N64: =N33+N63 -> 4253970.7 | O64: =IF(J64=0,0,(N64*100/J64)) -> 27.00251 | Q64: =Q33+Q63 -> 0 | R64: =R33+R63 -> 1114742.2 | S64: =S33+S63 -> 0 | T64: =T33+T63 -> 11500012 | V64: =V33+V63 -> 11500012 | W64: =W33+W63 -> 0 | X64: =X33+X63 -> 9729885.8 | Z64: =Z33+Z63 -> 1637713.3 | AA64: =AA33+AA63 -> 0
A65: =A26-A64 -> 474025.85 | B65: =IF(G65=0,0,(A65*100/G65)) -> 74.194643 | C65: =C26-C64 -> -594442.23 | D65: =IF(G65=0,0,(C65*100/G65)) -> -93.042245 | E65: =E26-E64 -> 638894.98 | F65: =IF(G65=0,0,(E65*100/G65)) -> 100 | G65: =G26-G64 -> 638894.98 | H65: =G65/$G$26*100 -> 22.078814 | I65: DIVISION INCOME (LOSS) | J65: =J26-J64 -> 67286620 | K65: =J65/$J$26*100 -> 81.028579 | L65: =L26-L64 -> 67286620 | M65: =IF(S65=0,0,(L65*100/S65)) -> 0 | N65: =N26-N64 -> 1032542.6 | O65: =IF(J65=0,0,(N65*100/J65)) -> 1.5345438 | Q65: =Q26-Q64 -> 0 | R65: =R26-R64 -> 164869.13 | S65: =S26-S64 -> 0 | T65: =T26-T64 -> 66254077 | V65: =V26-V64 -> 66254077 | W65: =W26-W64 -> 0 | X65: =X26-X64 -> 60800707 | Z65: =Z26-Z64 -> 1233337.2 | AA65: =AA26-AA64 -> 0
A66: =AG_SCH11!A96 -> 402266.77 | B66: =IF(G66=0,0,(A66*100/G66)) -> 60.642946 | C66: =AG_SCH11!C96 -> 329234.69 | D66: =IF(G66=0,0,(C66*100/G66)) -> 49.633136 | E66: =AG_SCH11!F96 -> 665111.09 | F66: =IF(G66=0,0,(E66*100/G66)) -> 100.26753 | G66: =AG_SCH11!I96 -> 663336.46 | H66: =G66/$G$26*100 -> 22.923458 | I66: Electricity Expense | J66: =AG_SCH11!L96 -> 2563936.7 | K66: =J66/$J$26*100 -> 3.08757 | L66: =AG_SCH11!N96 -> 2651208.2 | M66: =IF(S66=0,0,(L66*100/S66)) -> 0 | N66: =AG_SCH11!P96 -> 421914.08 | O66: =IF(J66=0,0,(N66*100/J66)) -> 16.455713
A67: =AG_SCH11!A86 -> 9977.2 | B67: =IF(G67=0,0,(A67*100/G67)) -> 66.514667 | C67: =AG_SCH11!C86 -> 14505 | D67: =IF(G67=0,0,(C67*100/G67)) -> 96.7 | E67: =AG_SCH11!F86 -> 15000 | F67: =IF(G67=0,0,(E67*100/G67)) -> 100 | G67: =AG_SCH11!I86 -> 15000 | H67: =G67/$G$26*100 -> 0.51836721 | I67: R&M - FO & HK | J67: =AG_SCH11!L86 -> 41622.27 | K67: =J67/$J$26*100 -> 0.050122794 | L67: =AG_SCH11!N86 -> 41622.27 | M67: =IF(S67=0,0,(L67*100/S67)) -> 0 | N67: =AG_SCH11!P86 -> -19211.99 | O67: =IF(J67=0,0,(N67*100/J67)) -> -46.157958
A68: =A65-A66-A67 -> 61781.876 | B68: =IF(G68=0,0,(A68*100/G68)) -> -156.64186 | C68: =C65-C66-C67 -> -938181.92 | D68: =IF(G68=0,0,(C68*100/G68)) -> 2378.6679 | E68: =E65-E66-E67 -> -41216.108 | F68: =IF(G68=0,0,(E68*100/G68)) -> 104.49938 | G68: =G65-G66-G67 -> -39441.484 | H68: =G68/$G$26*100 -> -1.3630115 | I68: NET DIVISION INCOME (LOSS) | J68: =J65-J66-J67 -> 64681061 | K68: =J68/$J$26*100 -> 77.890886 | L68: =L65-L66-L67 -> 64593789 | M68: =IF(S68=0,0,(L68*100/S68)) -> 0 | N68: =N65-N66-N67 -> 629840.55 | O68: =IF(J68=0,0,(N68*100/J68)) -> 0.97376349
I70: KPI'S
A71: =+G71-R71 -> 0 | C71: =+G71-Z71 -> -116 | E71: =+G71-Q71 -> 0 | G71: =+SCH00!A73 -> 3480 | I71: Available Rooms | J71: =+SCH00!L73 -> 28188 | L71: =+J71-S71 -> 7192 | N71: =+J71-T71 -> 7192 | Q71: =+SCH00!S73 -> 3480 | R71: =+SCH00!T73 -> 3480 | S71: =+SCH00!U73 -> 20996 | T71: =+SCH00!V73 -> 20996 | Z71: =SCH00!X73 -> 3596 | AA71: =+SCH00!L73 -> 28188
A72: =+G72-R72 -> 32 | C72: =+G72-Z72 -> -489 | E72: =+G72-Q72 -> -361 | G72: =+SCH00!A74 -> 1399 | I72: Occupied Rooms | J72: =+SCH00!L74 -> 19717 | L72: =+J72-S72 -> 3619 | N72: =+J72-T72 -> 6017 | Q72: =+SCH00!S74 -> 1760 | R72: =+SCH00!T74 -> 1367 | S72: =+SCH00!U74 -> 16098 | T72: =+SCH00!V74 -> 13700 | Z72: =SCH00!X74 -> 1888 | AA72: =+SCH00!L74 -> 19717
A73: =+G73-R73 -> -10 | C73: =+G73-Z73 -> -979 | E73: =+G73-Q73 -> -644 | G73: =SCH00!A76 -> 2876 | I73: Number of Guests | J73: =SCH00!L76 -> 41951 | L73: =+J73-S73 -> 9755 | N73: =+J73-T73 -> 14864 | Q73: =SCH00!S76 -> 3520 | R73: =SCH00!T76 -> 2886 | S73: =SCH00!U76 -> 32196 | T73: =SCH00!V76 -> 27087 | Z73: =SCH00!X76 -> 3855 | AA73: 2899
A74: =+G74-R74 -> 0.91954023 | C74: =+G74-Z74 -> -12.301631 | E74: =+G74-Q74 -> -10.373563 | G74: =+G72/G71*100 -> 40.201149 | I74: Occupancy % | J74: =+J72/J71*100 -> 69.948205 | L74: =+J74-S74 -> -6.7235421 | N74: =+J74-T74 -> 4.697681 | Q74: =+Q72/Q71*100 -> 50.574713 | R74: =+R72/R71*100 -> 39.281609 | S74: =+S72/S71*100 -> 76.671747 | T74: =+T72/T71*100 -> 65.250524 | Z74: =+Z72/Z71*100 -> 52.502781 | AA74: =+AA72/AA71*100 -> 69.948205
A75: =+G75-R75 -> 1132.3344 | C75: =+G75-Z75 -> 547.72358 | E75: =+G75-Q75 -> 2068.4071 | G75: =+G26/G72 -> 2068.4071 | I75: ARR | J75: =+J26/J72 -> 4211.6246 | L75: =+J75-S75 -> 4211.6246 | N75: =+J75-T75 -> -1463.8563 | Q75: =+Q26/Q72 -> 0 | R75: =+R26/R72 -> 936.07269 | S75: =+S26/S72 -> 0 | T75: =+T26/T72 -> 5675.4809 | Z75: =+Z26/Z72 -> 1520.6835 | AA75: =+AA26/AA72 -> 0
A76: =+G76-R76 -> -5.5438282 | C76: =+G76-Z76 -> 1.391089 | E76: =+G76-Q76 -> 5.575411 | G76: =+(G73/G72-1)*100 -> 105.57541 | I76: Double Occupancy % | J76: =+(J73/J72-1)*100 -> 112.76563 | L76: =+J76-S76 -> 12.765634 | N76: =+J76-T76 -> 15.050305 | Q76: =+(Q73/Q72-1)*100 -> 100 | R76: =+(R73/R72-1)*100 -> 111.11924 | S76: =+(S73/S72-1)*100 -> 100 | T76: =+(T73/T72-1)*100 -> 97.715328 | Z76: =+(Z73/Z72-1)*100 -> 104.18432 | AA76: =+(AA73/AA72-1)*100 -> -85.296952
A77: =+G77-R77 -> -0.46552493 | C77: =+G77-Z77 -> -0.098198198 | E77: =+G77-Q77 -> 6.3018018 | G77: =SCH00!A79 -> 6.3018018 | I77: Average Length Stay | J77: =SCH00!L79 -> 0.72251272 | L77: =+J77-S77 -> 0.72251272 | N77: =+J77-T77 -> -2.0078294 | Q77: =SCH00!S79 -> 0 | R77: =SCH00!T79 -> 6.7673267 | S77: =SCH00!U79 -> 0 | T77: =SCH00!V79 -> 2.7303421 | Z77: =SCH00!X79 -> 6.4 | AA77: 5
A78: =+G78-R78 -> 463.81902 | C78: =+G78-Z78 -> 33.122288 | E78: =+G78-Q78 -> 831.52344 | G78: =+G75*G74/100 -> 831.52344 | I78: RevPAR | J78: =+J75*J74/100 -> 2945.9558 | L78: =+J78-S78 -> 2945.9558 | N78: =+J78-T78 -> -757.32525 | Q78: =+Q75*Q74/100 -> 0 | R78: =+R75*R74/100 -> 367.70442 | S78: =+S75*S74/100 -> 0 | T78: =+T75*T74/100 -> 3703.2811 | Z78: =+Z75*Z74/100 -> 798.40115 | AA78: =+AA75*AA74/100 -> 0
A79: =+G79-R79 -> 231.90951 | C79: =+G79-Z79 -> 16.561144 | E79: =+G79-Q79 -> 415.76172 | G79: =G26/(G71*2) -> 415.76172 | I79: RevPAG | J79: =J26/(J71*2) -> 1472.9779 | L79: =+J79-S79 -> 1472.9779 | N79: =+J79-T79 -> -378.66262 | Q79: =Q26/(Q71*2) -> 0 | R79: =R26/(R71*2) -> 183.85221 | S79: =S26/(S71*2) -> 0 | T79: =T26/(T71*2) -> 1851.6405 | Z79: =Z26/(Z71*2) -> 399.20057 | AA79: =AA26/AA73 -> 0
A80: =+G80-R80 -> -3.8844675 | C80: =+G80-Z80 -> 16.209829 | E80: =+G80-Q80 -> #DIV/0! | G80: =+G33/G24*100 -> 55.45038 | I80: Payroll % Room Revenue | J80: =+J33/J24*100 -> 10.75491 | L80: =+J80-S80 -> #DIV/0! | N80: =+J80-T80 -> 3.6436593 | Q80: =+Q33/Q24*100 -> #DIV/0! | R80: =+R33/R24*100 -> 59.334847 | S80: =+S33/S24*100 -> #DIV/0! | T80: =+T33/T24*100 -> 7.1112509 | Z80: =+Z33/Z24*100 -> 39.24055 | AA80: =+AA33/AA24*100 -> #DIV/0!
A81: =+G81-R81 -> 204.7389 | C81: =+G81-Z81 -> 194.07945 | E81: =+G81-Q81 -> 464.78776 | G81: =+G63/G72 -> 464.78776 | I81: Other Expenses per Occ. Room | J81: =+J63/J72 -> 346.0486 | L81: =+J81-S81 -> 346.0486 | N81: =+J81-T81 -> -89.770632 | Q81: =+Q63/Q72 -> 0 | R81: =+R63/R72 -> 260.04886 | S81: =+S63/S72 -> 0 | T81: =+T63/T72 -> 435.81923 | Z81: =+Z63/Z72 -> 270.70831 | AA81: =+AA63/AA72 -> 0
A82: =+G82-R82 -> -5.3100336 | C82: =+G82-Z82 -> 4.6690547 | E82: =+G82-Q82 -> #DIV/0! | G82: =+G63/G26*100 -> 22.470807 | I82: Other Expenses % Room Revenue | J82: =+J63/J26*100 -> 8.216511 | L82: =+J82-S82 -> #DIV/0! | N82: =+J82-T82 -> 0.53752777 | Q82: =+Q63/Q26*100 -> #DIV/0! | R82: =+R63/R26*100 -> 27.78084 | S82: =+S63/S26*100 -> #DIV/0! | T82: =+T63/T26*100 -> 7.6789833 | Z82: =+Z63/Z26*100 -> 17.801752 | AA82: =+AA63/AA26*100 -> #DIV/0!
A83: =+G83-R83 -> 9.1945011 | C83: =+G83-Z83 -> -20.878884 | E83: =+G83-Q83 -> #DIV/0! | G83: =+G65/G26*100 -> 22.078814 | I83: Room Division Profit % | J83: =+J65/J26*100 -> 81.028579 | L83: =+J83-S83 -> #DIV/0! | N83: =+J83-T83 -> -4.1811871 | Q83: =+Q65/Q26*100 -> #DIV/0! | R83: =+R65/R26*100 -> 12.884313 | S83: =+S65/S26*100 -> #DIV/0! | T83: =+T65/T26*100 -> 85.209766 | Z83: =+Z65/Z26*100 -> 42.957698 | AA83: =+AA63/AA26*100 -> #DIV/0!
A84: =+G84-R84 -> 591.5223 | C84: =+G84-Z84 -> 550.21501 | E84: =+G84-Q84 -> 1146.9396 | G84: =+G33/G72 -> 1146.9396 | I84: Payroll per Occ Room | J84: =+J33/J72 -> 452.95645 | L84: =+J84-S84 -> 452.95645 | N84: =+J84-T84 -> 49.358756 | Q84: =+Q33/Q72 -> 0 | R84: =+R33/R72 -> 555.4173 | S84: =+S33/S72 -> 0 | T84: =+T33/T72 -> 403.59769 | Z84: =+Z33/Z72 -> 596.72459 | AA84: =+AA33/AA72 -> 0
A85: =+G85-R85 -> 336.07322 | C85: =+G85-Z85 -> -196.57088 | E85: =+G85-Q85 -> 456.67976 | G85: =+G65/G72 -> 456.67976 | I85: Rooms Division Profit per Occ Room | J85: =+J65/J72 -> 3412.6196 | L85: =+J85-S85 -> 3412.6196 | N85: =+J85-T85 -> -1423.4445 | Q85: =+Q65/Q72 -> 0 | R85: =+R65/R72 -> 120.60653 | S85: =+S65/S72 -> 0 | T85: =+T65/T72 -> 4836.064 | Z85: =+Z65/Z72 -> 653.25064 | AA85: =+AA65/AA72 -> 0
A86: =+G86-R86 -> -2.5638332 | C86: =+G86-Z86 -> 0 | E86: =+G86-Q86 -> 0 | G86: =+G43/G72 -> 0 | I86: Newspapers/Mags per Occ. Room | J86: =+J43/J72 -> 0.7110103 | L86: =+J86-S86 -> 0.7110103 | N86: =+J86-T86 -> -0.89679919 | Q86: =+Q43/Q72 -> 0 | R86: =+R43/R72 -> 2.5638332 | S86: =+S43/S72 -> 0 | T86: =+T43/T72 -> 1.6078095 | Z86: =+Z43/Z72 -> 0 | AA86: =+AA43/AA72 -> 0
A87: =+G87-R87 -> 7.1642269 | C87: =+G87-Z87 -> 3.9956751 | E87: =+G87-Q87 -> 13.257555 | G87: =+G45/G72 -> 13.257555 | I87: Reservation Exp per Occ. Room | J87: =+J45/J72 -> 25.795843 | L87: =+J87-S87 -> 25.795843 | N87: =+J87-T87 -> 7.4167249 | Q87: =+Q45/Q72 -> 0 | R87: =+R45/R72 -> 6.0933285 | S87: =+S45/S72 -> 0 | T87: =+T45/T72 -> 18.379118 | Z87: =+Z45/Z72 -> 9.2618803 | AA87: =+AA45/AA72 -> 0
A88: =+G88-R88 -> 45.34196 | C88: =+G88-Z88 -> -25.264443 | E88: =+G88-Q88 -> 102.40598 | G88: =+G54/G72 -> 102.40598 | I88: T/A Commissions per Occ. Room | J88: =+J54/J72 -> 205.37517 | L88: =+J88-S88 -> 205.37517 | N88: =+J88-T88 -> -60.597093 | Q88: =+Q54/Q72 -> 0 | R88: =+R54/R72 -> 57.064016 | S88: =+S54/S72 -> 0 | T88: =+T54/T72 -> 265.97226 | Z88: =+Z54/Z72 -> 127.67042 | AA88: =+AA54/AA72 -> 0
A89: =+G89-R89 -> 69.813505 | C89: =+G89-Z89 -> 86.841265 | E89: =+G89-Q89 -> 120.63963 | G89: =+(G36+G37+G38+G39+G40+G41)/G72 -> 120.63963 | I89: Operating Supplies per Occ. Room | J89: =+(J36+J37+J38+J39+J40+J41)/J72 -> 32.789489 | L89: =+J89-S89 -> 32.789489 | N89: =+J89-T89 -> -5.424283 | Q89: =+(Q36+Q37+Q38+Q39+Q40+Q41)/Q72 -> 0 | R89: =+(R36+R37+R38+R39+R40+R41)/R72 -> 50.826123 | S89: =+(S36+S37+S38+S39+S40+S41)/S72 -> 0 | T89: =+(T36+T37+T38+T39+T40+T41)/T72 -> 38.213772 | Z89: =+(Z36+Z37+Z38+Z39+Z40+Z41)/Z72 -> 33.798363 | AA89: =+(AA36+AA37+AA38+AA39+AA40+AA41)/AA72 -> 0
A90: =+G90-R90 -> 0.067918871 | C90: =+G90-Z90 -> 0.088172302 | E90: =+G90-Q90 -> 0.17952823 | G90: =G49/G72 -> 0.17952823 | I90: Promotion & Entertain per Occ. Room | J90: =J49/J72 -> 0.06481412 | L90: =+J90-S90 -> 0.06481412 | N90: =+J90-T90 -> -0.18067566 | Q90: =Q49/Q72 -> 0 | R90: =R49/R72 -> 0.11160936 | S90: =S49/S72 -> 0 | T90: =T49/T72 -> 0.24548978 | Z90: =Z49/Z72 -> 0.091355932 | AA90: =AA49/AA72 -> 0
A91: =+G91-R91 -> 76.428651 | C91: =+G91-Z91 -> 90.138762 | E91: =+G91-Q91 -> 159.7198 | G91: =G52/G72 -> 159.7198 | I91: Laundry Expenses per Occ. Room | J91: =J52/J72 -> 51.86499 | L91: =+J91-S91 -> 51.86499 | N91: =+J91-T91 -> -19.344134 | Q91: =Q52/Q72 -> 0 | R91: =R52/R72 -> 83.291149 | S91: =S52/S72 -> 0 | T91: =T52/T72 -> 71.209124 | Z91: =Z52/Z72 -> 69.581038 | AA91: =AA52/AA72 -> 0
A92: =+G92-R92 -> 18.928901 | C92: =+G92-Z92 -> 21.655643 | E92: =+G92-Q92 -> 41.271623 | G92: =G53/G72 -> 41.271623 | I92: Complimentary Services per Occ. Room | J92: =J53/J72 -> 21.285226 | L92: =+J92-S92 -> 21.285226 | N92: =+J92-T92 -> -6.033004 | Q92: =Q53/Q72 -> 0 | R92: =R53/R72 -> 22.342721 | S92: =S53/S72 -> 0 | T92: =T53/T72 -> 27.31823 | Z92: =Z53/Z72 -> 19.61598 | AA92: =AA53/AA72 -> 0
A93: =G93-AD10 -> 43.851476 | C93: =G93-AE10 -> 43.851476 | E93: =G93-AC10 -> #DIV/0! | G93: =G10/$G$21*100 -> 43.851476 | I93: % Segment Rooms - Incentive | J93: =J10/$J$21*100 -> 1.6406136 | L93: =J93-AG10 -> #DIV/0! | N93: =J93-AH10 -> 1.6406136
A94: =G94-AD11 -> -45.274636 | C94: =G94-AE11 -> -39.790888 | E94: =G94-AC11 -> #DIV/0! | G94: =G11/$G$21*100 -> 25.027275 | I94: % Segment Rooms - Travel Agent | J94: =J11/$J$21*100 -> 70.231609 | L94: =J94-AG11 -> #DIV/0! | N94: =J94-AH11 -> -8.2626053
A95: =G95-AD12 -> -2.8675936 | C95: =G95-AE12 -> -11.381748 | E95: =G95-AC12 -> #DIV/0! | G95: =G12/$G$21*100 -> 20.388263 | I95: % Segment Rooms - OTA | J95: =J12/$J$21*100 -> 26.45182 | L95: =J95-AG12 -> #DIV/0! | N95: =J95-AH12 -> 7.2602393
A96: =G96-AD13 -> 0 | C96: =G96-AE13 -> 0 | E96: =G96-AC13 -> #DIV/0! | G96: =G13/$G$21*100 -> 0 | I96: % Segment Rooms - Airline/Hotelier | J96: =J13/$J$21*100 -> 0 | L96: =J96-AG13 -> #DIV/0! | N96: =J96-AH13 -> 0
A97: =G97-AD14 -> 0 | C97: =G97-AE14 -> 0 | E97: =G97-AC14 -> #DIV/0! | G97: =G14/$G$21*100 -> 0 | I97: % Segment Rooms - Direct Booking | J97: =J14/$J$21*100 -> 0 | L97: =J97-AG14 -> #DIV/0! | N97: =J97-AH14 -> 0
A98: =G98-AD15 -> 0 | C98: =G98-AE15 -> 0 | E98: =G98-AC15 -> #DIV/0! | G98: =G15/$G$21*100 -> 0 | I98: % Segment Rooms - Walk In | J98: =J15/$J$21*100 -> 0 | L98: =J98-AG15 -> #DIV/0! | N98: =J98-AH15 -> 0
A99: =G99-AD16 -> 0 | C99: =G99-AE16 -> 0 | E99: =G99-AC16 -> #DIV/0! | G99: =G16/$G$21*100 -> 0 | I99: % Segment Rooms - Website RKL | J99: =J16/$J$21*100 -> 0 | L99: =J99-AG16 -> #DIV/0! | N99: =J99-AH16 -> 0
A100: =G100-AD17 -> 0 | C100: =G100-AE17 -> 0 | E100: =G100-AC17 -> #DIV/0! | G100: =G17/$G$21*100 -> 0 | I100: % Segment Rooms - Special Package | J100: =J17/$J$21*100 -> 0 | L100: =J100-AG17 -> #DIV/0! | N100: =J100-AH17 -> 0
A101: =G101-AD20 -> 1.1210337 | C101: =G101-AE20 -> 2.9452556 | E101: =G101-AC20 -> #DIV/0! | G101: =G20/$G$21*100 -> 4.4694262 | I101: % Segment Rooms - Day Use/ Extra Bed | J101: =J20/$J$21*100 -> 0.62839876 | L101: =J101-AG20 -> #DIV/0! | N101: =J101-AH20 -> -0.51389127

Sheet FO
A1: =Cover!B2 -> Ramada Resort Khao Lak, Phang Nga | R1: =+BS!J1 -> 6
A2: Front Office
A3: Income Statement | Q3: Schedule 01 | BA3: Mapping Area
A4: =SCH00!J3 -> For the PRD of June 2026 | Q4: Local Currency : Thai Baht | BA4: *Department Code | BG4: *Account Code | CB4: Dimension
BA5: Dept 1 | BB5: Dept 2 | BC5: Dept 3 | BD5: Dept 4 | BE5: Dept 5 | BG5: 1st Range | BI5: 2nd Range | BK5: 3rd Range | BM5: 4rd Range | BO5: 5rd Range | BQ5: 6rd Range | BS5: 7rd Range | BU5: 8rd Range | BW5: 9rd Range | BY5: 10th Range
A6: Current Month | K6: Description | L6: Year To Date | S6: THIS MONTH | U6: Y-T-D | X6: LAST Y-T-D | BG6: From | BH6: To | BI6: From | BJ6: To | BK6: From | BL6: To | BM6: From | BN6: To | BO6: From | BP6: To | BQ6: From | BR6: To | BS6: From | BT6: To | BU6: From | BV6: To | BW6: From | BX6: To | BY6: From | BZ6: To | CB6: A/O | CC6: Field Name | CD6: Operator | CE6: Value
A7: vs Last Year | B7: % | C7: vs Last Month | D7: % | E7: Actual Last Month | F7: vh Plan | G7: % | H7: Plan | I7: Actual | J7: % | L7: Actual | M7: % | N7: vs Plan | O7: % | P7: vs Last Year | Q7: % | S7: Plan | T7: Last Year | U7: Plan | V7: Last Year | X7: Actual | Y7: Plan | Z7: Last Year
A8: Better/(worse) | N8: Better/(worse)
K9: REVENUE
A10: =+I10-T10 -> 683737.29 | B10: =IF(I10=0,0,(A10*100/I10)) -> 100 | C10: =I10-E10 -> 683737.29 | D10: =IF(I10=0,0,(C10*100/I10)) -> 100 | E10: =IFERROR(_xll.AC_BU(_xll.ArrayBU(DB),_xll.ArrayDPT($BA10:$BE10),_xll.ArrayCOA($BG10:$BZ10),YR,PRD-1,_xll.ArrayDIM($CB10:$CE10)),0) -> 0 | F10: =+I10-H10 -> 683737.29 | G10: =IF(I10=0,0,(F10*100/I10)) -> 100 | I10: =IFERROR(_xll.AC_BU(_xll.ArrayBU(DB),_xll.ArrayDPT($BA10:$BE10),_xll.ArrayCOA($BG10:$BZ10),YR,PRD,_xll.ArrayDIM($CB10:$CE10)),0) -> 683737.29 | J10: =I10/I$21*100 -> 43.851476 | K10: Rooms Revenue - Incentive | L10: =IFERROR(_xll.ACC_BU(_xll.ArrayBU(DB),_xll.ArrayDPT($BA10:$BE10),_xll.ArrayCOA($BG10:$BZ10),YR,PRD,_xll.ArrayDIM($CB10:$CE10)),0) -> 683737.29 | M10: =L10/L$21*100 -> 0.83594438 | N10: =+L10-U10 -> 683737.29 | O10: =IF(U10=0,0,(N10*100/U10)) -> 0 | P10: =+L10-V10 -> 683737.29 | Q10: =IF(L10=0,0,(P10*100/L10)) -> 100 | S10: =IFERROR(_xll.BC_BU(_xll.ArrayBU(DB),_xll.ArrayDPT($BA10:$BE10),_xll.ArrayCOA($BG10:$BZ10),YR,PRD,RV,_xll.ArrayDIM($CB10:$CE10)),0) -> 0 | T10: =IFERROR(_xll.AC_BU(_xll.ArrayBU(DB),_xll.ArrayDPT($BA10:$BE10),_xll.ArrayCOA($BG10:$BZ10),YR-1,PRD,_xll.ArrayDIM($CB10:$CE10)),0) -> 0 | U10: =IFERROR(_xll.BCC_BU(_xll.ArrayBU(DB),_xll.ArrayDPT($BA10:$BE10),_xll.ArrayCOA($BG10:$BZ10),YR,PRD,RV,_xll.ArrayDIM($CB10:$CE10)),0) -> 0 | V10: =IFERROR(_xll.ACC_BU(_xll.ArrayBU(DB),_xll.ArrayDPT($BA10:$BE10),_xll.ArrayCOA($BG10:$BZ10),YR-1,PRD,_xll.ArrayDIM($CB10:$CE10)),0) -> 0 | X10: =IFERROR(_xll.ACC_BU(_xll.ArrayBU(DB),_xll.ArrayDPT($BA10:$BE10),_xll.ArrayCOA($BG10:$BZ10),YR-1,PRD,_xll.ArrayDIM($CB10:$CE10)),0) -> 0 | Y10: =IFERROR(_xll.BCC_BU(_xll.ArrayBU(DB),_xll.ArrayDPT($BA10:$BE10),_xll.ArrayCOA($BG10:$BZ10),YR-1,PRD,RV,_xll.ArrayDIM($CB10:$CE10)),0) -> 0 | Z10: =IFERROR(_xll.ACC_BU(_xll.ArrayBU(DB),_xll.ArrayDPT($BA10:$BE10),_xll.ArrayCOA($BG10:$BZ10),YR-1-1,PRD,_xll.ArrayDIM($CB10:$CE10)),0) -> 0 | BG10: 414010 | DA10: 414010
A11: =+I11-T11 -> -511423.57 | B11: =IF(I11=0,0,(A11*100/I11)) -> -131.05757 | C11: =I11-E11 -> -1472235.7 | D11: =IF(I11=0,0,(C11*100/I11)) -> -377.27562 | E11: =IFERROR(_xll.AC_BU(_xll.ArrayBU(DB),_xll.ArrayDPT($BA11:$BE11),_xll.ArrayCOA($BG11:$BZ11),YR,PRD-1,_xll.ArrayDIM($CB11:$CE11)),0) -> 1862463.9 | F11: =+I11-H11 -> 390228.17 | G11: =IF(I11=0,0,(F11*100/I11)) -> 100 | I11: =IFERROR(_xll.AC_BU(_xll.ArrayBU(DB),_xll.ArrayDPT($BA11:$BE11),_xll.ArrayCOA($BG11:$BZ11),YR,PRD,_xll.ArrayDIM($CB11:$CE11)),0) -> 390228.17 | J11: =I11/I$21*100 -> 25.027275 | K11: Rooms Revenue - Travel Agent | L11: =IFERROR(_xll.ACC_BU(_xll.ArrayBU(DB),_xll.ArrayDPT($BA11:$BE11),_xll.ArrayCOA($BG11:$BZ11),YR,PRD,_xll.ArrayDIM($CB11:$CE11)),0) -> 58148808 | M11: =L11/L$21*100 -> 71.093343 | N11: =+L11-U11 -> 58148808 | O11: =IF(U11=0,0,(N11*100/U11)) -> 0 | P11: =+L11-V11 -> -2951469.1 | Q11: =IF(L11=0,0,(P11*100/L11)) -> -5.0757173 | S11: =IFERROR(_xll.BC_BU(_xll.ArrayBU(DB),_xll.ArrayDPT($BA11:$BE11),_xll.ArrayCOA($BG11:$BZ11),YR,PRD,RV,_xll.ArrayDIM($CB11:$CE11)),0) -> 0 | T11: =IFERROR(_xll.AC_BU(_xll.ArrayBU(DB),_xll.ArrayDPT($BA11:$BE11),_xll.ArrayCOA($BG11:$BZ11),YR-1,PRD,_xll.ArrayDIM($CB11:$CE11)),0) -> 901651.74 | U11: =IFERROR(_xll.BCC_BU(_xll.ArrayBU(DB),_xll.ArrayDPT($BA11:$BE11),_xll.ArrayCOA($BG11:$BZ11),YR,PRD,RV,_xll.ArrayDIM($CB11:$CE11)),0) -> 0 | V11: =IFERROR(_xll.ACC_BU(_xll.ArrayBU(DB),_xll.ArrayDPT($BA11:$BE11),_xll.ArrayCOA($BG11:$BZ11),YR-1,PRD,_xll.ArrayDIM($CB11:$CE11)),0) -> 61100278 | X11: =IFERROR(_xll.ACC_BU(_xll.ArrayBU(DB),_xll.ArrayDPT($BA11:$BE11),_xll.ArrayCOA($BG11:$BZ11),YR-1,PRD,_xll.ArrayDIM($CB11:$CE11)),0) -> 61100278 | Y11: =IFERROR(_xll.BCC_BU(_xll.ArrayBU(DB),_xll.ArrayDPT($BA11:$BE11),_xll.ArrayCOA($BG11:$BZ11),YR-1,PRD,RV,_xll.ArrayDIM($CB11:$CE11)),0) -> 0 | Z11: =IFERROR(_xll.ACC_BU(_xll.ArrayBU(DB),_xll.ArrayDPT($BA11:$BE11),_xll.ArrayCOA($BG11:$BZ11),YR-1-1,PRD,_xll.ArrayDIM($CB11:$CE11)),0) -> 65023901 | BG11: 414020 | DA11: 414020
A12: =+I12-T12 -> 19629.96 | B12: =IF(I12=0,0,(A12*100/I12)) -> 6.1749598 | C12: =I12-E12 -> -594972.94 | D12: =IF(I12=0,0,(C12*100/I12)) -> -187.15952 | E12: =IFERROR(_xll.AC_BU(_xll.ArrayBU(DB),_xll.ArrayDPT($BA12:$BE12),_xll.ArrayCOA($BG12:$BZ12),YR,PRD-1,_xll.ArrayDIM($CB12:$CE12)),0) -> 912869.1 | F12: =+I12-H12 -> 317896.16 | G12: =IF(I12=0,0,(F12*100/I12)) -> 100 | I12: =IFERROR(_xll.AC_BU(_xll.ArrayBU(DB),_xll.ArrayDPT($BA12:$BE12),_xll.ArrayCOA($BG12:$BZ12),YR,PRD,_xll.ArrayDIM($CB12:$CE12)),0) -> 317896.16 | J12: =I12/I$21*100 -> 20.388263 | K12: Rooms Revenue - Web Site (OTA) | L12: =IFERROR(_xll.ACC_BU(_xll.ArrayBU(DB),_xll.ArrayDPT($BA12:$BE12),_xll.ArrayCOA($BG12:$BZ12),YR,PRD,_xll.ArrayDIM($CB12:$CE12)),0) -> 21730069 | M12: =L12/L$21*100 -> 26.56741 | N12: =+L12-U12 -> 21730069 | O12: =IF(U12=0,0,(N12*100/U12)) -> 0 | P12: =+L12-V12 -> 6791249.3 | Q12: =IF(L12=0,0,(P12*100/L12)) -> 31.252774 | S12: =IFERROR(_xll.BC_BU(_xll.ArrayBU(DB),_xll.ArrayDPT($BA12:$BE12),_xll.ArrayCOA($BG12:$BZ12),YR,PRD,RV,_xll.ArrayDIM($CB12:$CE12)),0) -> 0 | T12: =IFERROR(_xll.AC_BU(_xll.ArrayBU(DB),_xll.ArrayDPT($BA12:$BE12),_xll.ArrayCOA($BG12:$BZ12),YR-1,PRD,_xll.ArrayDIM($CB12:$CE12)),0) -> 298266.2 | U12: =IFERROR(_xll.BCC_BU(_xll.ArrayBU(DB),_xll.ArrayDPT($BA12:$BE12),_xll.ArrayCOA($BG12:$BZ12),YR,PRD,RV,_xll.ArrayDIM($CB12:$CE12)),0) -> 0 | V12: =IFERROR(_xll.ACC_BU(_xll.ArrayBU(DB),_xll.ArrayDPT($BA12:$BE12),_xll.ArrayCOA($BG12:$BZ12),YR-1,PRD,_xll.ArrayDIM($CB12:$CE12)),0) -> 14938820 | X12: =IFERROR(_xll.ACC_BU(_xll.ArrayBU(DB),_xll.ArrayDPT($BA12:$BE12),_xll.ArrayCOA($BG12:$BZ12),YR-1,PRD,_xll.ArrayDIM($CB12:$CE12)),0) -> 14938820 | Y12: =IFERROR(_xll.BCC_BU(_xll.ArrayBU(DB),_xll.ArrayDPT($BA12:$BE12),_xll.ArrayCOA($BG12:$BZ12),YR-1,PRD,RV,_xll.ArrayDIM($CB12:$CE12)),0) -> 0 | Z12: =IFERROR(_xll.ACC_BU(_xll.ArrayBU(DB),_xll.ArrayDPT($BA12:$BE12),_xll.ArrayCOA($BG12:$BZ12),YR-1-1,PRD,_xll.ArrayDIM($CB12:$CE12)),0) -> 3956920.1 | BG12: 414030 | DA12: 414030
A13: =+I13-T13 -> 0 | B13: =IF(I13=0,0,(A13*100/I13)) -> 0 | C13: =I13-E13 -> 0 | D13: =IF(I13=0,0,(C13*100/I13)) -> 0 | E13: =IFERROR(_xll.AC_BU(_xll.ArrayBU(DB),_xll.ArrayDPT($BA13:$BE13),_xll.ArrayCOA($BG13:$BZ13),YR,PRD-1,_xll.ArrayDIM($CB13:$CE13)),0) -> 0 | F13: =+I13-H13 -> 0 | G13: =IF(I13=0,0,(F13*100/I13)) -> 0 | I13: =IFERROR(_xll.AC_BU(_xll.ArrayBU(DB),_xll.ArrayDPT($BA13:$BE13),_xll.ArrayCOA($BG13:$BZ13),YR,PRD,_xll.ArrayDIM($CB13:$CE13)),0) -> 0 | J13: =I13/I$21*100 -> 0 | K13: Rooms Revenue - Airline/Hotelier | L13: =IFERROR(_xll.ACC_BU(_xll.ArrayBU(DB),_xll.ArrayDPT($BA13:$BE13),_xll.ArrayCOA($BG13:$BZ13),YR,PRD,_xll.ArrayDIM($CB13:$CE13)),0) -> 0 | M13: =L13/L$21*100 -> 0 | N13: =+L13-U13 -> 0 | O13: =IF(U13=0,0,(N13*100/U13)) -> 0 | P13: =+L13-V13 -> 0 | Q13: =IF(L13=0,0,(P13*100/L13)) -> 0 | S13: =IFERROR(_xll.BC_BU(_xll.ArrayBU(DB),_xll.ArrayDPT($BA13:$BE13),_xll.ArrayCOA($BG13:$BZ13),YR,PRD,RV,_xll.ArrayDIM($CB13:$CE13)),0) -> 0 | T13: =IFERROR(_xll.AC_BU(_xll.ArrayBU(DB),_xll.ArrayDPT($BA13:$BE13),_xll.ArrayCOA($BG13:$BZ13),YR-1,PRD,_xll.ArrayDIM($CB13:$CE13)),0) -> 0 | U13: =IFERROR(_xll.BCC_BU(_xll.ArrayBU(DB),_xll.ArrayDPT($BA13:$BE13),_xll.ArrayCOA($BG13:$BZ13),YR,PRD,RV,_xll.ArrayDIM($CB13:$CE13)),0) -> 0 | V13: =IFERROR(_xll.ACC_BU(_xll.ArrayBU(DB),_xll.ArrayDPT($BA13:$BE13),_xll.ArrayCOA($BG13:$BZ13),YR-1,PRD,_xll.ArrayDIM($CB13:$CE13)),0) -> 0 | X13: =IFERROR(_xll.ACC_BU(_xll.ArrayBU(DB),_xll.ArrayDPT($BA13:$BE13),_xll.ArrayCOA($BG13:$BZ13),YR-1,PRD,_xll.ArrayDIM($CB13:$CE13)),0) -> 0 | Y13: =IFERROR(_xll.BCC_BU(_xll.ArrayBU(DB),_xll.ArrayDPT($BA13:$BE13),_xll.ArrayCOA($BG13:$BZ13),YR-1,PRD,RV,_xll.ArrayDIM($CB13:$CE13)),0) -> 0 | Z13: =IFERROR(_xll.ACC_BU(_xll.ArrayBU(DB),_xll.ArrayDPT($BA13:$BE13),_xll.ArrayCOA($BG13:$BZ13),YR-1-1,PRD,_xll.ArrayDIM($CB13:$CE13)),0) -> 0 | BG13: 414040 | DA13: 414040
A14: =+I14-T14 -> 0 | B14: =IF(I14=0,0,(A14*100/I14)) -> 0 | C14: =I14-E14 -> 0 | D14: =IF(I14=0,0,(C14*100/I14)) -> 0 | E14: =IFERROR(_xll.AC_BU(_xll.ArrayBU(DB),_xll.ArrayDPT($BA14:$BE14),_xll.ArrayCOA($BG14:$BZ14),YR,PRD-1,_xll.ArrayDIM($CB14:$CE14)),0) -> 0 | F14: =+I14-H14 -> 0 | G14: =IF(I14=0,0,(F14*100/I14)) -> 0 | I14: =IFERROR(_xll.AC_BU(_xll.ArrayBU(DB),_xll.ArrayDPT($BA14:$BE14),_xll.ArrayCOA($BG14:$BZ14),YR,PRD,_xll.ArrayDIM($CB14:$CE14)),0) -> 0 | J14: =I14/I$21*100 -> 0 | K14: Rooms Revenue - Direct Booking | L14: =IFERROR(_xll.ACC_BU(_xll.ArrayBU(DB),_xll.ArrayDPT($BA14:$BE14),_xll.ArrayCOA($BG14:$BZ14),YR,PRD,_xll.ArrayDIM($CB14:$CE14)),0) -> 0 | M14: =L14/L$21*100 -> 0 | N14: =+L14-U14 -> 0 | O14: =IF(U14=0,0,(N14*100/U14)) -> 0 | P14: =+L14-V14 -> 0 | Q14: =IF(L14=0,0,(P14*100/L14)) -> 0 | S14: =IFERROR(_xll.BC_BU(_xll.ArrayBU(DB),_xll.ArrayDPT($BA14:$BE14),_xll.ArrayCOA($BG14:$BZ14),YR,PRD,RV,_xll.ArrayDIM($CB14:$CE14)),0) -> 0 | T14: =IFERROR(_xll.AC_BU(_xll.ArrayBU(DB),_xll.ArrayDPT($BA14:$BE14),_xll.ArrayCOA($BG14:$BZ14),YR-1,PRD,_xll.ArrayDIM($CB14:$CE14)),0) -> 0 | U14: =IFERROR(_xll.BCC_BU(_xll.ArrayBU(DB),_xll.ArrayDPT($BA14:$BE14),_xll.ArrayCOA($BG14:$BZ14),YR,PRD,RV,_xll.ArrayDIM($CB14:$CE14)),0) -> 0 | V14: =IFERROR(_xll.ACC_BU(_xll.ArrayBU(DB),_xll.ArrayDPT($BA14:$BE14),_xll.ArrayCOA($BG14:$BZ14),YR-1,PRD,_xll.ArrayDIM($CB14:$CE14)),0) -> 0 | X14: =IFERROR(_xll.ACC_BU(_xll.ArrayBU(DB),_xll.ArrayDPT($BA14:$BE14),_xll.ArrayCOA($BG14:$BZ14),YR-1,PRD,_xll.ArrayDIM($CB14:$CE14)),0) -> 0 | Y14: =IFERROR(_xll.BCC_BU(_xll.ArrayBU(DB),_xll.ArrayDPT($BA14:$BE14),_xll.ArrayCOA($BG14:$BZ14),YR-1,PRD,RV,_xll.ArrayDIM($CB14:$CE14)),0) -> 0 | Z14: =IFERROR(_xll.ACC_BU(_xll.ArrayBU(DB),_xll.ArrayDPT($BA14:$BE14),_xll.ArrayCOA($BG14:$BZ14),YR-1-1,PRD,_xll.ArrayDIM($CB14:$CE14)),0) -> 359360.96 | BG14: 414050 | DA14: 414050
A15: =+I15-T15 -> 0 | B15: =IF(I15=0,0,(A15*100/I15)) -> 0 | C15: =I15-E15 -> 0 | D15: =IF(I15=0,0,(C15*100/I15)) -> 0 | E15: =IFERROR(_xll.AC_BU(_xll.ArrayBU(DB),_xll.ArrayDPT($BA15:$BE15),_xll.ArrayCOA($BG15:$BZ15),YR,PRD-1,_xll.ArrayDIM($CB15:$CE15)),0) -> 0 | F15: =+I15-H15 -> 0 | G15: =IF(I15=0,0,(F15*100/I15)) -> 0 | I15: =IFERROR(_xll.AC_BU(_xll.ArrayBU(DB),_xll.ArrayDPT($BA15:$BE15),_xll.ArrayCOA($BG15:$BZ15),YR,PRD,_xll.ArrayDIM($CB15:$CE15)),0) -> 0 | J15: =I15/I$21*100 -> 0 | K15: Rooms Revenue - Walk In | L15: =IFERROR(_xll.ACC_BU(_xll.ArrayBU(DB),_xll.ArrayDPT($BA15:$BE15),_xll.ArrayCOA($BG15:$BZ15),YR,PRD,_xll.ArrayDIM($CB15:$CE15)),0) -> 0 | M15: =L15/L$21*100 -> 0 | N15: =+L15-U15 -> 0 | O15: =IF(U15=0,0,(N15*100/U15)) -> 0 | P15: =+L15-V15 -> 0 | Q15: =IF(L15=0,0,(P15*100/L15)) -> 0 | S15: =IFERROR(_xll.BC_BU(_xll.ArrayBU(DB),_xll.ArrayDPT($BA15:$BE15),_xll.ArrayCOA($BG15:$BZ15),YR,PRD,RV,_xll.ArrayDIM($CB15:$CE15)),0) -> 0 | T15: =IFERROR(_xll.AC_BU(_xll.ArrayBU(DB),_xll.ArrayDPT($BA15:$BE15),_xll.ArrayCOA($BG15:$BZ15),YR-1,PRD,_xll.ArrayDIM($CB15:$CE15)),0) -> 0 | U15: =IFERROR(_xll.BCC_BU(_xll.ArrayBU(DB),_xll.ArrayDPT($BA15:$BE15),_xll.ArrayCOA($BG15:$BZ15),YR,PRD,RV,_xll.ArrayDIM($CB15:$CE15)),0) -> 0 | V15: =IFERROR(_xll.ACC_BU(_xll.ArrayBU(DB),_xll.ArrayDPT($BA15:$BE15),_xll.ArrayCOA($BG15:$BZ15),YR-1,PRD,_xll.ArrayDIM($CB15:$CE15)),0) -> 0 | X15: =IFERROR(_xll.ACC_BU(_xll.ArrayBU(DB),_xll.ArrayDPT($BA15:$BE15),_xll.ArrayCOA($BG15:$BZ15),YR-1,PRD,_xll.ArrayDIM($CB15:$CE15)),0) -> 0 | Y15: =IFERROR(_xll.BCC_BU(_xll.ArrayBU(DB),_xll.ArrayDPT($BA15:$BE15),_xll.ArrayCOA($BG15:$BZ15),YR-1,PRD,RV,_xll.ArrayDIM($CB15:$CE15)),0) -> 0 | Z15: =IFERROR(_xll.ACC_BU(_xll.ArrayBU(DB),_xll.ArrayDPT($BA15:$BE15),_xll.ArrayCOA($BG15:$BZ15),YR-1-1,PRD,_xll.ArrayDIM($CB15:$CE15)),0) -> 0 | BG15: 414060 | DA15: 414060
A16: =+I16-T16 -> 0 | B16: =IF(I16=0,0,(A16*100/I16)) -> 0 | C16: =I16-E16 -> 0 | D16: =IF(I16=0,0,(C16*100/I16)) -> 0 | E16: =IFERROR(_xll.AC_BU(_xll.ArrayBU(DB),_xll.ArrayDPT($BA16:$BE16),_xll.ArrayCOA($BG16:$BZ16),YR,PRD-1,_xll.ArrayDIM($CB16:$CE16)),0) -> 0 | F16: =+I16-H16 -> 0 | G16: =IF(I16=0,0,(F16*100/I16)) -> 0 | I16: =IFERROR(_xll.AC_BU(_xll.ArrayBU(DB),_xll.ArrayDPT($BA16:$BE16),_xll.ArrayCOA($BG16:$BZ16),YR,PRD,_xll.ArrayDIM($CB16:$CE16)),0) -> 0 | J16: =I16/I$21*100 -> 0 | K16: Rooms Revenue - Website RKL | L16: =IFERROR(_xll.ACC_BU(_xll.ArrayBU(DB),_xll.ArrayDPT($BA16:$BE16),_xll.ArrayCOA($BG16:$BZ16),YR,PRD,_xll.ArrayDIM($CB16:$CE16)),0) -> 0 | M16: =L16/L$21*100 -> 0 | N16: =+L16-U16 -> 0 | O16: =IF(U16=0,0,(N16*100/U16)) -> 0 | P16: =+L16-V16 -> 0 | Q16: =IF(L16=0,0,(P16*100/L16)) -> 0 | S16: =IFERROR(_xll.BC_BU(_xll.ArrayBU(DB),_xll.ArrayDPT($BA16:$BE16),_xll.ArrayCOA($BG16:$BZ16),YR,PRD,RV,_xll.ArrayDIM($CB16:$CE16)),0) -> 0 | T16: =IFERROR(_xll.AC_BU(_xll.ArrayBU(DB),_xll.ArrayDPT($BA16:$BE16),_xll.ArrayCOA($BG16:$BZ16),YR-1,PRD,_xll.ArrayDIM($CB16:$CE16)),0) -> 0 | U16: =IFERROR(_xll.BCC_BU(_xll.ArrayBU(DB),_xll.ArrayDPT($BA16:$BE16),_xll.ArrayCOA($BG16:$BZ16),YR,PRD,RV,_xll.ArrayDIM($CB16:$CE16)),0) -> 0 | V16: =IFERROR(_xll.ACC_BU(_xll.ArrayBU(DB),_xll.ArrayDPT($BA16:$BE16),_xll.ArrayCOA($BG16:$BZ16),YR-1,PRD,_xll.ArrayDIM($CB16:$CE16)),0) -> 0 | X16: =IFERROR(_xll.ACC_BU(_xll.ArrayBU(DB),_xll.ArrayDPT($BA16:$BE16),_xll.ArrayCOA($BG16:$BZ16),YR-1,PRD,_xll.ArrayDIM($CB16:$CE16)),0) -> 0 | Y16: =IFERROR(_xll.BCC_BU(_xll.ArrayBU(DB),_xll.ArrayDPT($BA16:$BE16),_xll.ArrayCOA($BG16:$BZ16),YR-1,PRD,RV,_xll.ArrayDIM($CB16:$CE16)),0) -> 0 | Z16: =IFERROR(_xll.ACC_BU(_xll.ArrayBU(DB),_xll.ArrayDPT($BA16:$BE16),_xll.ArrayCOA($BG16:$BZ16),YR-1-1,PRD,_xll.ArrayDIM($CB16:$CE16)),0) -> 212003.28 | BG16: 414070 | DA16: 414070
A17: =+I17-T17 -> 0 | B17: =IF(I17=0,0,(A17*100/I17)) -> 0 | C17: =I17-E17 -> 0 | D17: =IF(I17=0,0,(C17*100/I17)) -> 0 | E17: =IFERROR(_xll.AC_BU(_xll.ArrayBU(DB),_xll.ArrayDPT($BA17:$BE17),_xll.ArrayCOA($BG17:$BZ17),YR,PRD-1,_xll.ArrayDIM($CB17:$CE17)),0) -> 0 | F17: =+I17-H17 -> 0 | G17: =IF(I17=0,0,(F17*100/I17)) -> 0 | I17: =IFERROR(_xll.AC_BU(_xll.ArrayBU(DB),_xll.ArrayDPT($BA17:$BE17),_xll.ArrayCOA($BG17:$BZ17),YR,PRD,_xll.ArrayDIM($CB17:$CE17)),0) -> 0 | J17: =I17/I$21*100 -> 0 | K17: Rooms Revenue - Special Package | L17: =IFERROR(_xll.ACC_BU(_xll.ArrayBU(DB),_xll.ArrayDPT($BA17:$BE17),_xll.ArrayCOA($BG17:$BZ17),YR,PRD,_xll.ArrayDIM($CB17:$CE17)),0) -> 0 | M17: =L17/L$21*100 -> 0 | N17: =+L17-U17 -> 0 | O17: =IF(U17=0,0,(N17*100/U17)) -> 0 | P17: =+L17-V17 -> 0 | Q17: =IF(L17=0,0,(P17*100/L17)) -> 0 | S17: =IFERROR(_xll.BC_BU(_xll.ArrayBU(DB),_xll.ArrayDPT($BA17:$BE17),_xll.ArrayCOA($BG17:$BZ17),YR,PRD,RV,_xll.ArrayDIM($CB17:$CE17)),0) -> 0 | T17: =IFERROR(_xll.AC_BU(_xll.ArrayBU(DB),_xll.ArrayDPT($BA17:$BE17),_xll.ArrayCOA($BG17:$BZ17),YR-1,PRD,_xll.ArrayDIM($CB17:$CE17)),0) -> 0 | U17: =IFERROR(_xll.BCC_BU(_xll.ArrayBU(DB),_xll.ArrayDPT($BA17:$BE17),_xll.ArrayCOA($BG17:$BZ17),YR,PRD,RV,_xll.ArrayDIM($CB17:$CE17)),0) -> 0 | V17: =IFERROR(_xll.ACC_BU(_xll.ArrayBU(DB),_xll.ArrayDPT($BA17:$BE17),_xll.ArrayCOA($BG17:$BZ17),YR-1,PRD,_xll.ArrayDIM($CB17:$CE17)),0) -> 0 | X17: =IFERROR(_xll.ACC_BU(_xll.ArrayBU(DB),_xll.ArrayDPT($BA17:$BE17),_xll.ArrayCOA($BG17:$BZ17),YR-1,PRD,_xll.ArrayDIM($CB17:$CE17)),0) -> 0 | Y17: =IFERROR(_xll.BCC_BU(_xll.ArrayBU(DB),_xll.ArrayDPT($BA17:$BE17),_xll.ArrayCOA($BG17:$BZ17),YR-1,PRD,RV,_xll.ArrayDIM($CB17:$CE17)),0) -> 0 | Z17: =IFERROR(_xll.ACC_BU(_xll.ArrayBU(DB),_xll.ArrayDPT($BA17:$BE17),_xll.ArrayCOA($BG17:$BZ17),YR-1-1,PRD,_xll.ArrayDIM($CB17:$CE17)),0) -> 0 | BG17: 414080 | DA17: 414080
A18: =+I18-T18 -> 39595.65 | B18: =IF(I18=0,0,(A18*100/I18)) -> 64.827678 | C18: =I18-E18 -> 46630.12 | D18: =IF(I18=0,0,(C18*100/I18)) -> 76.34481 | E18: =IFERROR(_xll.AC_BU(_xll.ArrayBU(DB),_xll.ArrayDPT($BA18:$BE18),_xll.ArrayCOA($BG18:$BZ18),YR,PRD-1,_xll.ArrayDIM($CB18:$CE18)),0) -> 14448.19 | F18: =+I18-H18 -> 61078.31 | G18: =IF(I18=0,0,(F18*100/I18)) -> 100 | I18: =IFERROR(_xll.AC_BU(_xll.ArrayBU(DB),_xll.ArrayDPT($BA18:$BE18),_xll.ArrayCOA($BG18:$BZ18),YR,PRD,_xll.ArrayDIM($CB18:$CE18)),0) -> 61078.31 | J18: =I18/I$21*100 -> 3.9172561 | K18: Rooms Revenue - Room Upselling | L18: =IFERROR(_xll.ACC_BU(_xll.ArrayBU(DB),_xll.ArrayDPT($BA18:$BE18),_xll.ArrayCOA($BG18:$BZ18),YR,PRD,_xll.ArrayDIM($CB18:$CE18)),0) -> 318912.95 | M18: =L18/L$21*100 -> 0.38990632 | N18: =+L18-U18 -> 318912.95 | O18: =IF(U18=0,0,(N18*100/U18)) -> 0 | P18: =+L18-V18 -> 75666.48 | Q18: =IF(L18=0,0,(P18*100/L18)) -> 23.726374 | S18: =IFERROR(_xll.BC_BU(_xll.ArrayBU(DB),_xll.ArrayDPT($BA18:$BE18),_xll.ArrayCOA($BG18:$BZ18),YR,PRD,RV,_xll.ArrayDIM($CB18:$CE18)),0) -> 0 | T18: =IFERROR(_xll.AC_BU(_xll.ArrayBU(DB),_xll.ArrayDPT($BA18:$BE18),_xll.ArrayCOA($BG18:$BZ18),YR-1,PRD,_xll.ArrayDIM($CB18:$CE18)),0) -> 21482.66 | U18: =IFERROR(_xll.BCC_BU(_xll.ArrayBU(DB),_xll.ArrayDPT($BA18:$BE18),_xll.ArrayCOA($BG18:$BZ18),YR,PRD,RV,_xll.ArrayDIM($CB18:$CE18)),0) -> 0 | V18: =IFERROR(_xll.ACC_BU(_xll.ArrayBU(DB),_xll.ArrayDPT($BA18:$BE18),_xll.ArrayCOA($BG18:$BZ18),YR-1,PRD,_xll.ArrayDIM($CB18:$CE18)),0) -> 243246.47 | X18: =IFERROR(_xll.ACC_BU(_xll.ArrayBU(DB),_xll.ArrayDPT($BA18:$BE18),_xll.ArrayCOA($BG18:$BZ18),YR-1,PRD,_xll.ArrayDIM($CB18:$CE18)),0) -> 243246.47 | Y18: =IFERROR(_xll.BCC_BU(_xll.ArrayBU(DB),_xll.ArrayDPT($BA18:$BE18),_xll.ArrayCOA($BG18:$BZ18),YR-1,PRD,RV,_xll.ArrayDIM($CB18:$CE18)),0) -> 0 | Z18: =IFERROR(_xll.ACC_BU(_xll.ArrayBU(DB),_xll.ArrayDPT($BA18:$BE18),_xll.ArrayCOA($BG18:$BZ18),YR-1-1,PRD,_xll.ArrayDIM($CB18:$CE18)),0) -> 221794.31 | BG18: 414091 | BH18: 414091 | DA18: 414080 | DB18: 414091
A19: =+I19-T19 -> 18386.69 | B19: =IF(I19=0,0,(A19*100/I19)) -> 50.259063 | C19: =I19-E19 -> -3207.24 | D19: =IF(I19=0,0,(C19*100/I19)) -> -8.766824 | E19: =IFERROR(_xll.AC_BU(_xll.ArrayBU(DB),_xll.ArrayDPT($BA19:$BE19),_xll.ArrayCOA($BG19:$BZ19),YR,PRD-1,_xll.ArrayDIM($CB19:$CE19)),0) -> 39791.07 | F19: =+I19-H19 -> 36583.83 | G19: =IF(I19=0,0,(F19*100/I19)) -> 100 | I19: =IFERROR(_xll.AC_BU(_xll.ArrayBU(DB),_xll.ArrayDPT($BA19:$BE19),_xll.ArrayCOA($BG19:$BZ19),YR,PRD,_xll.ArrayDIM($CB19:$CE19)),0) -> 36583.83 | J19: =I19/I$21*100 -> 2.3463031 | K19: Rooms Revenue - Other Room Revenue | L19: =IFERROR(_xll.ACC_BU(_xll.ArrayBU(DB),_xll.ArrayDPT($BA19:$BE19),_xll.ArrayCOA($BG19:$BZ19),YR,PRD,_xll.ArrayDIM($CB19:$CE19)),0) -> 456580.12 | M19: =L19/L$21*100 -> 0.55821964 | N19: =+L19-U19 -> 456580.12 | O19: =IF(U19=0,0,(N19*100/U19)) -> 0 | P19: =+L19-V19 -> -212398.03 | Q19: =IF(L19=0,0,(P19*100/L19)) -> -46.519334 | S19: =IFERROR(_xll.BC_BU(_xll.ArrayBU(DB),_xll.ArrayDPT($BA19:$BE19),_xll.ArrayCOA($BG19:$BZ19),YR,PRD,RV,_xll.ArrayDIM($CB19:$CE19)),0) -> 0 | T19: =IFERROR(_xll.AC_BU(_xll.ArrayBU(DB),_xll.ArrayDPT($BA19:$BE19),_xll.ArrayCOA($BG19:$BZ19),YR-1,PRD,_xll.ArrayDIM($CB19:$CE19)),0) -> 18197.14 | U19: =IFERROR(_xll.BCC_BU(_xll.ArrayBU(DB),_xll.ArrayDPT($BA19:$BE19),_xll.ArrayCOA($BG19:$BZ19),YR,PRD,RV,_xll.ArrayDIM($CB19:$CE19)),0) -> 0 | V19: =IFERROR(_xll.ACC_BU(_xll.ArrayBU(DB),_xll.ArrayDPT($BA19:$BE19),_xll.ArrayCOA($BG19:$BZ19),YR-1,PRD,_xll.ArrayDIM($CB19:$CE19)),0) -> 668978.15 | X19: =IFERROR(_xll.ACC_BU(_xll.ArrayBU(DB),_xll.ArrayDPT($BA19:$BE19),_xll.ArrayCOA($BG19:$BZ19),YR-1,PRD,_xll.ArrayDIM($CB19:$CE19)),0) -> 668978.15 | Y19: =IFERROR(_xll.BCC_BU(_xll.ArrayBU(DB),_xll.ArrayDPT($BA19:$BE19),_xll.ArrayCOA($BG19:$BZ19),YR-1,PRD,RV,_xll.ArrayDIM($CB19:$CE19)),0) -> 0 | Z19: =IFERROR(_xll.ACC_BU(_xll.ArrayBU(DB),_xll.ArrayDPT($BA19:$BE19),_xll.ArrayCOA($BG19:$BZ19),YR-1-1,PRD,_xll.ArrayDIM($CB19:$CE19)),0) -> 160674.05 | BG19: 414099 | DA19: 414099
A20: =+I20-T20 -> 26743.26 | B20: =IF(I20=0,0,(A20*100/I20)) -> 38.375808 | C20: =I20-E20 -> 25892.79 | D20: =IF(I20=0,0,(C20*100/I20)) -> 37.155408 | E20: =IFERROR(_xll.AC_BU(_xll.ArrayBU(DB),_xll.ArrayDPT($BA20:$BE20),_xll.ArrayCOA($BG20:$BZ20),YR,PRD-1,_xll.ArrayDIM($CB20:$CE20)),0) -> 43795.02 | F20: =+I20-H20 -> 69687.81 | G20: =IF(I20=0,0,(F20*100/I20)) -> 100 | I20: =IFERROR(_xll.AC_BU(_xll.ArrayBU(DB),_xll.ArrayDPT($BA20:$BE20),_xll.ArrayCOA($BG20:$BZ20),YR,PRD,_xll.ArrayDIM($CB20:$CE20)),0) -> 69687.81 | J20: =I20/I$21*100 -> 4.4694262 | K20: Room Day Use/Extra Bed/late Check out | L20: =IFERROR(_xll.ACC_BU(_xll.ArrayBU(DB),_xll.ArrayDPT($BA20:$BE20),_xll.ArrayCOA($BG20:$BZ20),YR,PRD,_xll.ArrayDIM($CB20:$CE20)),0) -> 454091.42 | M20: =L20/L$21*100 -> 0.55517693 | N20: =+L20-U20 -> 454091.42 | O20: =IF(U20=0,0,(N20*100/U20)) -> 0 | P20: =+L20-V20 -> -435072.69 | Q20: =IF(L20=0,0,(P20*100/L20)) -> -95.811696 | S20: =IFERROR(_xll.BC_BU(_xll.ArrayBU(DB),_xll.ArrayDPT($BA20:$BE20),_xll.ArrayCOA($BG20:$BZ20),YR,PRD,RV,_xll.ArrayDIM($CB20:$CE20)),0) -> 0 | T20: =IFERROR(_xll.AC_BU(_xll.ArrayBU(DB),_xll.ArrayDPT($BA20:$BE20),_xll.ArrayCOA($BG20:$BZ20),YR-1,PRD,_xll.ArrayDIM($CB20:$CE20)),0) -> 42944.55 | U20: =IFERROR(_xll.BCC_BU(_xll.ArrayBU(DB),_xll.ArrayDPT($BA20:$BE20),_xll.ArrayCOA($BG20:$BZ20),YR,PRD,RV,_xll.ArrayDIM($CB20:$CE20)),0) -> 0 | V20: =IFERROR(_xll.ACC_BU(_xll.ArrayBU(DB),_xll.ArrayDPT($BA20:$BE20),_xll.ArrayCOA($BG20:$BZ20),YR-1,PRD,_xll.ArrayDIM($CB20:$CE20)),0) -> 889164.11 | X20: =IFERROR(_xll.ACC_BU(_xll.ArrayBU(DB),_xll.ArrayDPT($BA20:$BE20),_xll.ArrayCOA($BG20:$BZ20),YR-1,PRD,_xll.ArrayDIM($CB20:$CE20)),0) -> 889164.11 | Y20: =IFERROR(_xll.BCC_BU(_xll.ArrayBU(DB),_xll.ArrayDPT($BA20:$BE20),_xll.ArrayCOA($BG20:$BZ20),YR-1,PRD,RV,_xll.ArrayDIM($CB20:$CE20)),0) -> 0 | Z20: =IFERROR(_xll.ACC_BU(_xll.ArrayBU(DB),_xll.ArrayDPT($BA20:$BE20),_xll.ArrayCOA($BG20:$BZ20),YR-1-1,PRD,_xll.ArrayDIM($CB20:$CE20)),0) -> 654314.64 | BG20: 414090 | DA20: 414090
A21: =SUM(A10:A20) -> 276669.28 | B21: =IF(I21=0,0,(A21*100/I21)) -> 17.744178 | C21: =I21-E21 -> -1314155.7 | D21: =IF(I21=0,0,(C21*100/I21)) -> -84.283348 | E21: =SUM(E10:E20) -> 2873367.3 | F21: =SUM(F10:F20) -> 1559211.6 | G21: =IF(I21=0,0,(F21*100/I21)) -> 100 | H21: =SUM(H10:H20) -> 0 | I21: =SUM(I10:I20) -> 1559211.6 | J21: =I21/I$21*100 -> 100 | K21: Rooms Revenue | L21: =SUM(L10:L20) -> 81792199 | M21: =L21/L$21*100 -> 100 | N21: =SUM(N10:N20) -> 81792199 | O21: =IF(U21=0,0,(N21*100/U21)) -> 0 | P21: =SUM(P10:P20) -> 3951713.3 | Q21: =IF(L21=0,0,(P21*100/L21)) -> 4.831406 | S21: =SUM(S10:S20) -> 0 | T21: =SUM(T10:T20) -> 1282542.3 | U21: =SUM(U10:U20) -> 0 | V21: =SUM(V10:V20) -> 77840486 | X21: =SUM(X10:X20) -> 77840486 | Y21: =SUM(Y10:Y20) -> 0 | Z21: =SUM(Z10:Z20) -> 70588969
A22: =+I22-T22 -> 0 | B22: =IF(I22=0,0,(A22*100/I22)) -> 0 | C22: =I22-E22 -> 0 | D22: =IF(I22=0,0,(C22*100/I22)) -> 0 | E22: =IFERROR(_xll.AC_BU(_xll.ArrayBU(DB),_xll.ArrayDPT($BA22:$BE22),_xll.ArrayCOA($BG22:$BZ22),YR,PRD-1,_xll.ArrayDIM($CB22:$CE22)),0) -> 0 | F22: =+I22-H22 -> 0 | G22: =IF(I22=0,0,(F22*100/I22)) -> 0 | I22: =IFERROR(_xll.AC_BU(_xll.ArrayBU(DB),_xll.ArrayDPT($BA22:$BE22),_xll.ArrayCOA($BG22:$BZ22),YR,PRD,_xll.ArrayDIM($CB22:$CE22)),0) -> 0 | J22: =I22/$I$26*100 -> 0 | K22: Overbooking Expenses | L22: =IFERROR(_xll.ACC_BU(_xll.ArrayBU(DB),_xll.ArrayDPT($BA22:$BE22),_xll.ArrayCOA($BG22:$BZ22),YR,PRD,_xll.ArrayDIM($CB22:$CE22)),0) -> 0 | M22: =L22/$L$26*100 -> 0 | N22: =+L22-U22 -> 0 | O22: =IF(U22=0,0,(N22*100/U22)) -> 0 | P22: =+L22-V22 -> 0 | Q22: =IF(L22=0,0,(P22*100/L22)) -> 0 | S22: =IFERROR(_xll.BC_BU(_xll.ArrayBU(DB),_xll.ArrayDPT($BA22:$BE22),_xll.ArrayCOA($BG22:$BZ22),YR,PRD,RV,_xll.ArrayDIM($CB22:$CE22)),0) -> 0 | T22: =IFERROR(_xll.AC_BU(_xll.ArrayBU(DB),_xll.ArrayDPT($BA22:$BE22),_xll.ArrayCOA($BG22:$BZ22),YR-1,PRD,_xll.ArrayDIM($CB22:$CE22)),0) -> 0 | U22: =IFERROR(_xll.BCC_BU(_xll.ArrayBU(DB),_xll.ArrayDPT($BA22:$BE22),_xll.ArrayCOA($BG22:$BZ22),YR,PRD,RV,_xll.ArrayDIM($CB22:$CE22)),0) -> 0 | V22: =IFERROR(_xll.ACC_BU(_xll.ArrayBU(DB),_xll.ArrayDPT($BA22:$BE22),_xll.ArrayCOA($BG22:$BZ22),YR-1,PRD,_xll.ArrayDIM($CB22:$CE22)),0) -> 0 | X22: =IFERROR(_xll.ACC_BU(_xll.ArrayBU(DB),_xll.ArrayDPT($BA22:$BE22),_xll.ArrayCOA($BG22:$BZ22),YR-1,PRD,_xll.ArrayDIM($CB22:$CE22)),0) -> 0 | Y22: =IFERROR(_xll.BCC_BU(_xll.ArrayBU(DB),_xll.ArrayDPT($BA22:$BE22),_xll.ArrayCOA($BG22:$BZ22),YR-1,PRD,RV,_xll.ArrayDIM($CB22:$CE22)),0) -> 0 | Z22: =IFERROR(_xll.ACC_BU(_xll.ArrayBU(DB),_xll.ArrayDPT($BA22:$BE22),_xll.ArrayCOA($BG22:$BZ22),YR-1-1,PRD,_xll.ArrayDIM($CB22:$CE22)),0) -> 0 | BG22: 415772 | DA22: 415772
