Workbook
Name _Fill: #REF!
Name _Fill: #REF!
Name _Key1: '[1]Land (2)'!#REF!
Name _Key1: '[1]Land (2)'!#REF!
Name _Key2: #REF!
Name _Key2: #REF!
Name _Key3: #REF!
Name _Key3: #REF!
Name _Order1: 255
Name _Order2: 255
Name _Sort: '[1]Land (2)'!#REF!
Name _Sort: '[1]Land (2)'!#REF!
Name APR: '[2]Carmen Parameter'!$J$5
Name APR: 'Carmen Parameter'!$J$5
Name AS2DocOpenMode: "AS2DocumentEdit"
Name AS2NamedRange: 4
Name AUG: 'Carmen Parameter'!$J$9
Name DB: Intro!$H$21
Name DD: Intro!$H$18
Name DEC: 'Carmen Parameter'!$J$13
Name DME_BeforeCloseCompleted: "False"
Name DME_Dirty: "False"
Name DME_LocalFile: "True"
Name FEB: '[2]Carmen Parameter'!$J$3
Name FEB: 'Carmen Parameter'!$J$3
Name fr: {"Summary_Green",#N/A,FALSE,"YTD Owned";"Summary_White",#N/A,FALSE,"YTD Owned"}
Name fr: {"Summary_Green",#N/A,FALSE,"YTD Owned";"Summary_White",#N/A,FALSE,"YTD Owned"}
Name HName: Intro!$B$16
Name JAN: '[2]Carmen Parameter'!$J$2
Name JAN: 'Carmen Parameter'!$J$2
Name JUL: 'Carmen Parameter'!$J$8
Name JUN: '[2]Carmen Parameter'!$J$7
Name JUN: 'Carmen Parameter'!$J$7
Name MAR: '[2]Carmen Parameter'!$J$4
Name MAR: 'Carmen Parameter'!$J$4
Name MAY: '[2]Carmen Parameter'!$J$6
Name MAY: 'Carmen Parameter'!$J$6
Name NOV: 'Carmen Parameter'!$J$12
Name OCT: 'Carmen Parameter'!$J$11
Name PRD: Intro!$H$19
Name RV: Intro!$H$22
Name SEP: 'Carmen Parameter'!$J$10
Name ss: {"CF SUMMARY",#N/A,FALSE,"Cash Flow"}
Name ss: {"CF SUMMARY",#N/A,FALSE,"Cash Flow"}
Name TextRefCopyRangeCount: 14
Name wrn.BSDA_Report.: {"Summary_Green",#N/A,FALSE,"YTD Owned";"Summary_White",#N/A,FALSE,"YTD Owned"}
Name wrn.BSDA_Report.: {"Summary_Green",#N/A,FALSE,"YTD Owned";"Summary_White",#N/A,FALSE,"YTD Owned"}
Name wrn.Summary.: {"CF SUMMARY",#N/A,FALSE,"Cash Flow"}
Name wrn.Summary.: {"CF SUMMARY",#N/A,FALSE,"Cash Flow"}
Name YR: Intro!$H$20

Sheet MyConnect
A8: WebService : | B8: http://localhost/carmenservice/FinanceService.svc

Sheet Intro
B7: CONFIDENTAL
B9: Distribution | D9: [ ] | J9: [ ]
D10: [ ] | J10: [ ]
D11: [ ] | J11: [ ]
D12: [ ] | J12: [ ]
B15: =DB -> homm
B16: Example
B17: Profit & ( Loss ) Statement | N17: 2025
G18: Day | N18: 03
G19: Period | H19: 1 | N19: =DD -> 0
G20: Year | H20: 2026 | N20: =DB -> homm
G21: Database | H21: homm | N21: =RV -> 0
G22: Budget | H22: 0 | N22: =HName -> Example
B24: Conductions
C26: Balance Sheet
C27: Balance Sheet - Supporting
C28: Profit & ( Loss ) Statement
D29: Profit & Loss Summary
D30: Room Department
D31: Food & Beverage Summary
D32: Other Operated Department
D33: Administrative & General
D34: Sales & Marketing
D35: Summary Of Payroll And Employee Relations
D36: Property Operation, Main, Energy Cost

Sheet BS
A2: HOMM SUKHUMVIT34 BANGKOK | J2: Period | K2: =PRD -> 1
A3: BALANCE SHEET
H4: EXHIBIT - A | AA4: Mapping Area
AA5: *Department Code | AG5: *Account Code | BB5: Dimension
A6: REPORT DESCRIPTION | C6: AT THE END OF | E6: AT THE BEGINNING | G6: INCREASE | I6: % | AA6: Dept 1 | AB6: Dept 2 | AC6: Dept 3 | AD6: Dept 4 | AE6: Dept 5 | AG6: 1st Range | AI6: 2nd Range | AK6: 3rd Range | AM6: 4rd Range | AO6: 5rd Range | AQ6: 6rd Range | AS6: 7rd Range | AU6: 8rd Range | AW6: 9rd Range | AY6: 10th Range
C7: THIS MONTH | E7: OF FISCAL PERIOD | G7: (DECREASE) | AG7: From | AH7: To | AI7: From | AJ7: To | AK7: From | AL7: To | AM7: From | AN7: To | AO7: From | AP7: To | AQ7: From | AR7: To | AS7: From | AT7: To | AU7: From | AV7: To | AW7: From | AX7: To | AY7: From | AZ7: To | BB7: A/O | BC7: Field Name | BD7: Operator | BE7: Value
A8: ASSETS
A9: CURRENT ASSETS
A10: CASH ON HAND-HOUSE FUND
B11: Cash House Fund ( SCHEDULE A-1A ) | C11: ='BS-Support'!C18 -> -50351.07 | E11: ='BS-Support'!E18 -> -50351.07 | G11: =C11-E11 -> 0 | I11: =IF(G11=0,0,(G11*100/$G$13)) -> 0
B12: Cash At Bank ( SCHEDULE A-1B ) | C12: ='BS-Support'!C30 -> -3.09147e+08 | E12: ='BS-Support'!E30 -> -3.0293885e+08 | G12: =C12-E12 -> -6208145.9 | I12: =IF(G12=0,0,(G12*100/$G$13)) -> 100
B13: TOTAL CASH | C13: =SUM(C10:C12) -> -3.0919735e+08 | E13: =SUM(E10:E12) -> -3.029892e+08 | G13: =C13-E13 -> -6208145.9 | I13: =IF(G13=0,0,(G13*100/$G$13)) -> 100
A14: RECEIVABLES
B15: Acct. Receivable - Trade ( SCHEDULE A-2A ) | C15: ='BS-Support'!C40 -> -17038581 | E15: ='BS-Support'!E40 -> -19824339 | G15: =C15-E15 -> 2785758.2 | I15: =IF(G15=0,0,(G15*100/$G$20)) -> 24.428933
B16: Less:Allowance for Doubtful Accounts | C16: ='BS-Support'!C42 -> 0 | E16: ='BS-Support'!E42 -> 0 | G16: =C16-E16 -> 0 | I16: =IF(G16=0,0,(G16*100/$G$20)) -> 0
B17: Net Acct. Receivable - Trade | C17: =SUM(C15:C16) -> -17038581 | E17: =SUM(E15:E16) -> -19824339 | G17: =C17-E17 -> 2785758.2 | I17: =IF(G17=0,0,(G17*100/$G$20)) -> 24.428933
B18: Loans To Subsidiaries And Associated | C18: ='BS-Support'!C43 -> 0 | E18: ='BS-Support'!E43 -> 0 | G18: =C18-E18 -> 0 | I18: =IF(G18=0,0,(G18*100/$G$20)) -> 0
B19: Other Receivable ( SCHEDULE A-2B ) | C19: ='BS-Support'!C62 -> 3.6635173e+08 | E19: ='BS-Support'!E62 -> 3.5773397e+08 | G19: =C19-E19 -> 8617761.4 | I19: =IF(G19=0,0,(G19*100/$G$20)) -> 75.571067
B20: TOTAL RECEIVABLES | C20: =SUM(C17:C19) -> 3.4931315e+08 | E20: =SUM(E17:E19) -> 3.3790963e+08 | G20: =C20-E20 -> 11403520 | I20: =IF(G20=0,0,(G20*100/$G$20)) -> 100
A21: INVENTORIES
B22: Saleable Merchandise ( SCHEDULE A-3A ) | C22: ='BS-Support'!C84 -> 0 | E22: ='BS-Support'!E84 -> 0 | G22: =C22-E22 -> 0 | I22: =IF(G22=0,0,(G22*100/$G$25)) -> 0
B23: Operating Supplies ( SCHEDULE A-3B ) | C23: ='BS-Support'!C96 -> 5787.85 | E23: ='BS-Support'!E96 -> 5787.85 | G23: =C23-E23 -> 0 | I23: =IF(G23=0,0,(G23*100/$G$25)) -> 0
B24: Operating Equipment Operation ( SCHEDULE A-3C ) | C24: ='BS-Support'!C112 -> 795054.33 | E24: ='BS-Support'!E112 -> 694006.33 | G24: =C24-E24 -> 101048 | I24: =IF(G24=0,0,(G24*100/$G$25)) -> 100
B25: TOTAL INVENTORIES | C25: =SUM(C22:C24) -> 800842.18 | E25: =SUM(E22:E24) -> 699794.18 | G25: =C25-E25 -> 101048 | I25: =IF(G25=0,0,(G25*100/$G$25)) -> 100
A26: OTHER CURRENT ASSETS
B27: Other Prepaid Expenses (SCHEDULE A-4A ) | C27: ='BS-Support'!C127 -> 1967594 | E27: ='BS-Support'!E127 -> 1934000 | G27: =C27-E27 -> 33594 | I27: =IF(G27=0,0,(G27*100/$G$29)) -> -123.16322
B28: Other current Assets (SCHEDULE A-4B ) | C28: ='BS-Support'!C137 -> 82086 | E28: ='BS-Support'!E137 -> 142956 | G28: =C28-E28 -> -60870 | I28: =IF(G28=0,0,(G28*100/$G$29)) -> 223.16322
B29: TOTAL OTHER CURRENT ASSETS | C29: =SUM(C27:C28) -> 2049680 | E29: =SUM(E27:E28) -> 2076956 | G29: =C29-E29 -> -27276 | I29: =IF(G29=0,0,(G29*100/$G$29)) -> 100
B31: TOTAL CURRENT ASSETS | C31: =+C13+C20+C25+C29 -> 42966322 | E31: =+E13+E20+E25+E29 -> 37697177 | G31: =C31-E31 -> 5269145.6 | I31: =IF(G31=0,0,(G31*100/$G$31)) -> 100
A32: FIXED ASSETS
B33: PROPERTY, PLANT AND EQUIPMENT (SCHEDULE A-5A) | C33: ='BS-Support'!C202 -> 3041574.7 | E33: ='BS-Support'!E202 -> 2911351.8 | G33: =C33-E33 -> 130222.99 | I33: =IF(G33=0,0,(G33*100/$G$29)) -> -477.42701
B34: Less : Accumulated Depreciation | C34: ='BS-Support'!C203 -> 0 | E34: ='BS-Support'!E203 -> 0 | G34: =C34-E34 -> 0 | I34: =IF(G34=0,0,(G34*100/#REF!)) -> 0
B35: TOTAL PROPERTY, PLANT AND EQUIPMENT | C35: =C33-C34 -> 3041574.7 | E35: =E33-E34 -> 2911351.8 | G35: =C35-E35 -> 130222.99 | I35: =IF(G35=0,0,(G35*100/$G$35)) -> 100
B37: TOTAL ASSETS | C37: =C31+C35 -> 46007897 | E37: =E31+E35 -> 40608528 | G37: =C37-E37 -> 5399368.6 | I37: =IF(G37=0,0,(G37*100/$G$37)) -> 100
A40: LIABILITIES & SHAREHOLDERS' EQUPTY
A41: CURRENT LIABILITIES
B42: Accounts Payable ( SCHEDULE A-7A ) | C42: ='BS-Support'!C215 -> -2985829.8 | E42: ='BS-Support'!E215 -> -2914867.5 | G42: =C42-E42 -> -70962.28 | I42: =IF(G42=0,0,(G42*100/$G$48)) -> -5.7633723
B43: Guest Deposit | C43: ='BS-Support'!C217 -> 0 | E43: ='BS-Support'!E217 -> 0 | G43: =C43-E43 -> 0 | I43: =IF(G43=0,0,(G43*100/$G$48)) -> 0
B44: Other Current Liab. ( SCHEDULE A-7B ) | C44: ='BS-Support'!C226 -> 568.06 | E44: ='BS-Support'!E226 -> 568.06 | G44: =C44-E44 -> 0 | I44: =IF(G44=0,0,(G44*100/$G$48)) -> 0
B45: Accrued Taxes ( SCHEDULE A-7C ) | C45: ='BS-Support'!C242 -> 12217800 | E45: ='BS-Support'!E242 -> 11684956 | G45: =C45-E45 -> 532843.83 | I45: =IF(G45=0,0,(G45*100/$G$48)) -> 43.276193
B46: Accrued Expenses ( SCHEDULE A-7D ) | C46: ='BS-Support'!C265 -> 16804960 | E46: ='BS-Support'!E265 -> 16035579 | G46: =C46-E46 -> 769381.62 | I46: =IF(G46=0,0,(G46*100/$G$48)) -> 62.487179
B47: Reserve For Replacement ( SCHEDULE A-7E ) | C47: ='BS-Support'!C278 -> 0 | E47: ='BS-Support'!E278 -> 0 | G47: =C47-E47 -> 0 | I47: =IF(G47=0,0,(G47*100/$G$48)) -> 0
B48: TOTAL CURRENT LIABILITIES | C48: =SUM(C42:C47) -> 26037499 | E48: =SUM(E42:E47) -> 24806236 | G48: =C48-E48 -> 1231263.2 | I48: =IF(G48=0,0,(G48*100/$G$48)) -> 100
A49: LONG TERM LIABILITIES
B50: Loans from Director | C50: ='BS-Support'!C282 -> -761000 | E50: ='BS-Support'!E282 -> -761000 | G50: =C50-E50 -> 0 | I50: =IF(G50=0,0,(G50*100/$G$53)) -> 0
B51: Loans from Subsidiaries And Associated | C51: ='BS-Support'!C283 -> 0 | E51: ='BS-Support'!E283 -> 0 | G51: =C51-E51 -> 0 | I51: =IF(G51=0,0,(G51*100/$G$53)) -> 0
B52: Long Term Debt | C52: ='BS-Support'!C284 -> 0 | E52: ='BS-Support'!E284 -> 0 | G52: =C52-E52 -> 0 | I52: =IF(G52=0,0,(G52*100/$G$53)) -> 0
B53: TOTAL LONG TERM LIABILITIES | C53: =SUM(C50:C52) -> -761000 | E53: =SUM(E50:E52) -> -761000 | G53: =C53-E53 -> 0 | I53: =IF(G53=0,0,(G53*100/$G$53)) -> 0
A54: TOTAL LIABILITIES | C54: =SUM(C53,C48) -> 25276499 | E54: =SUM(E53,E48) -> 24045236 | G54: =C54-E54 -> 1231263.2 | I54: =IF(G54=0,0,(G54*100/$G$54)) -> 100
A55: SHAREHOLDERS' EQUITY
B56: Owning Co. Current Account | C56: ='BS-Support'!C289 -> -49054440 | E56: ='BS-Support'!E289 -> -49054440 | G56: =C56-E56 -> 0 | I56: =IF(G56=0,0,(G56*100/$G$62)) -> 0
B57: Ordinary Share | C57: ='BS-Support'!C290 -> 0 | E57: ='BS-Support'!E290 -> 0 | G57: =C57-E57 -> 0 | I57: =IF(G57=0,0,(G57*100/$G$62)) -> 0
A58: Retained Earnings
B59: Brought Forward | C59: ='BS-Support'!C293 -> 0 | E59: ='BS-Support'!E293 -> 0 | G59: =C59-E59 -> 0 | I59: =IF(G59=0,0,(G59*100/$G$62)) -> 0 | AG59: 90045 | AH59: 90045
B60: Current Year | C60: =_xll.REP(DB,YR,1,PRD) -> 4184916.5 | E60: {=IF(PRD =1,_xll.REP(DB,YR-1,1,12),_xll.REP(DB,YR,1,PRD-1))} -> 24664100 | G60: =C60-E60 -> -20479184 | I60: =IF(G60=0,0,(G60*100/$G$62)) -> 100
B61: Total Retained Earning | C61: =SUM(C59:C60) -> 4184916.5 | E61: =SUM(E59:E60) -> 24664100 | G61: =C61-E61 -> -20479184 | I61: =IF(G61=0,0,(G61*100/$G$62)) -> 100
B62: TOTAL SHAREHOLDERS' EQUITY | C62: =+C56+C57+C61 -> -44869523 | E62: =+E56+E57+E61 -> -24390340 | G62: =C62-E62 -> -20479184 | I62: =IF(G62=0,0,(G62*100/$G$62)) -> 100
B63: TOTAL LIAB. & SHAREHOLDERS' EQUITY | C63: =+C54+C62 -> -19593025 | E63: =+E54+E62 -> -345104.33 | G63: =C63-E63 -> -19247920 | I63: =IF(G63=0,0,(G63*100/$G$63)) -> 100
C65: =+C37-C63 -> 65600922 | E65: =+E37-E63 -> 40953633 | G65: =C65-E65 -> 24647289
C66: =C65-'BS-Support'!C300 -> 0 | E66: =E65-'BS-Support'!E300 -> 0 | G66: =G65-'BS-Support'!G300 -> 0

Sheet BS-Support
A2: HOMM SUKHUMVIT34 BANGKOK | J2: Period | K2: =PRD -> 1
A3: BALANCE SHEET SUPPORTING
G4: EXHIBIT - B1 - B4 | BA4: Mapping Area
BA5: *Department Code | BL5: *Account Code | CG5: Dimension
A6: REPORT DESCRIPTION | C6: AT THE END OF | E6: AT THE BEGINNING | G6: INCREASE | I6: % | BA6: Dept 1 | BC6: Dept 2 | BE6: Dept 3 | BG6: Dept 4 | BI6: Dept 5 | BL6: 1st Range | BN6: 2nd Range | BP6: 3rd Range | BR6: 4rd Range | BT6: 5rd Range | BV6: 6rd Range | BX6: 7rd Range | BZ6: 8rd Range | CB6: 9rd Range | CD6: 10th Range
C7: THIS MONTH | E7: OF FISCAL PERIOD | G7: (DECREASE) | BA7: From | BB7: to | BC7: From | BD7: to | BE7: From | BF7: to | BG7: From | BH7: to | BI7: From | BJ7: to | BL7: From | BM7: To | BN7: From | BO7: To | BP7: From | BQ7: To | BR7: From | BS7: To | BT7: From | BU7: To | BV7: From | BW7: To | BX7: From | BY7: To | BZ7: From | CA7: To | CB7: From | CC7: To | CD7: From | CE7: To | CG7: A/O | CH7: Field Name | CI7: Operator | CJ7: Value
A8: ASSET
A9: CURRENT ASSET
B10: CASH ON HAND-HOUSE FUND ( Schedule A-1A )
B11: - CASH ON HAND | C11: =_xll.ACC(DB,_xll.ArrayDPT($BA11:$BJ11),_xll.ArrayCOA($BL11:$CE11),YR,PRD,_xll.ArrayDIM($CG11:$CJ11)) -> 0 | E11: =_xll.ACC(DB,_xll.ArrayDPT($BA11:$BJ11),_xll.ArrayCOA($BL11:$CE11),YR,PRD-1,_xll.ArrayDIM($CG11:$CJ11)) -> 0 | G11: =C11-E11 -> 0 | I11: =IF(G11=0,0,(G11*100/$G$18)) -> 0 | BL11: 71110 | BM11: 71110
B12: - PETTY CASH - FRONT OFFICE | C12: =_xll.ACC(DB,_xll.ArrayDPT($BA12:$BJ12),_xll.ArrayCOA($BL12:$CE12),YR,PRD,_xll.ArrayDIM($CG12:$CJ12)) -> 0 | E12: =_xll.ACC(DB,_xll.ArrayDPT($BA12:$BJ12),_xll.ArrayCOA($BL12:$CE12),YR,PRD-1,_xll.ArrayDIM($CG12:$CJ12)) -> 0 | G12: =C12-E12 -> 0 | I12: =IF(G12=0,0,(G12*100/$G$18)) -> 0
B13: - PETTY CASH - GENERAL CASHIER | C13: =_xll.ACC(DB,_xll.ArrayDPT($BA13:$BJ13),_xll.ArrayCOA($BL13:$CE13),YR,PRD,_xll.ArrayDIM($CG13:$CJ13)) -> -85808.57 | E13: =_xll.ACC(DB,_xll.ArrayDPT($BA13:$BJ13),_xll.ArrayCOA($BL13:$CE13),YR,PRD-1,_xll.ArrayDIM($CG13:$CJ13)) -> -85808.57 | G13: =C13-E13 -> 0 | I13: =IF(G13=0,0,(G13*100/$G$18)) -> 0 | BL13: 71120 | BM13: 71120
B14: - CASH FLOATS -FRONT CASHIER | C14: =_xll.ACC(DB,_xll.ArrayDPT($BA14:$BJ14),_xll.ArrayCOA($BL14:$CE14),YR,PRD,_xll.ArrayDIM($CG14:$CJ14)) -> 35657.5 | E14: =_xll.ACC(DB,_xll.ArrayDPT($BA14:$BJ14),_xll.ArrayCOA($BL14:$CE14),YR,PRD-1,_xll.ArrayDIM($CG14:$CJ14)) -> 35657.5 | G14: =C14-E14 -> 0 | I14: =IF(G14=0,0,(G14*100/$G$18)) -> 0 | BL14: 71130 | BM14: 71130
B15: - CASH FLOATS - FOOD & BEVERAGE | C15: =_xll.ACC(DB,_xll.ArrayDPT($BA15:$BJ15),_xll.ArrayCOA($BL15:$CE15),YR,PRD,_xll.ArrayDIM($CG15:$CJ15)) -> 0 | E15: =_xll.ACC(DB,_xll.ArrayDPT($BA15:$BJ15),_xll.ArrayCOA($BL15:$CE15),YR,PRD-1,_xll.ArrayDIM($CG15:$CJ15)) -> 0 | G15: =C15-E15 -> 0 | I15: =IF(G15=0,0,(G15*100/$G$18)) -> 0
B16: - HOUSE FUNDS - GENERAL CASHIER | C16: =_xll.ACC(DB,_xll.ArrayDPT($BA16:$BJ16),_xll.ArrayCOA($BL16:$CE16),YR,PRD,_xll.ArrayDIM($CG16:$CJ16)) -> -200 | E16: =_xll.ACC(DB,_xll.ArrayDPT($BA16:$BJ16),_xll.ArrayCOA($BL16:$CE16),YR,PRD-1,_xll.ArrayDIM($CG16:$CJ16)) -> -200 | G16: =C16-E16 -> 0 | I16: =IF(G16=0,0,(G16*100/$G$18)) -> 0 | BL16: 71125 | BM16: 71125
B17: - HOUSE FUNDS - FRONT OFFICE | C17: =_xll.ACC(DB,_xll.ArrayDPT($BA17:$BJ17),_xll.ArrayCOA($BL17:$CE17),YR,PRD,_xll.ArrayDIM($CG17:$CJ17)) -> 0 | E17: =_xll.ACC(DB,_xll.ArrayDPT($BA17:$BJ17),_xll.ArrayCOA($BL17:$CE17),YR,PRD-1,_xll.ArrayDIM($CG17:$CJ17)) -> 0 | G17: =C17-E17 -> 0 | I17: =IF(G17=0,0,(G17*100/$G$18)) -> 0
B18: TOTAL CASH ON HAND-HOUSE FUND | C18: =SUM(C11:C17) -> -50351.07 | E18: =SUM(E11:E17) -> -50351.07 | G18: =C18-E18 -> 0 | I18: =IF(G18=0,0,(G18*100/$G$18)) -> 0
B20: CASH IN BANK ( Schedule A-1B )
B21: - BANK - BBL SA # 175-4-23258-3 | C21: =_xll.ACC(DB,_xll.ArrayDPT($BA21:$BJ21),_xll.ArrayCOA($BL21:$CE21),YR,PRD,_xll.ArrayDIM($CG21:$CJ21)) -> -31923562 | E21: =_xll.ACC(DB,_xll.ArrayDPT($BA21:$BJ21),_xll.ArrayCOA($BL21:$CE21),YR,PRD-1,_xll.ArrayDIM($CG21:$CJ21)) -> -31923562 | G21: =C21-E21 -> 0 | I21: =IF(G21=0,0,(G21*100/$G$30)) -> 0 | BL21: 71140 | BM21: 71140
B22: - BANK - SCB SA # 096-2-47077-3 | C22: =_xll.ACC(DB,_xll.ArrayDPT($BA22:$BJ22),_xll.ArrayCOA($BL22:$CE22),YR,PRD,_xll.ArrayDIM($CG22:$CJ22)) -> -92019685 | E22: =_xll.ACC(DB,_xll.ArrayDPT($BA22:$BJ22),_xll.ArrayCOA($BL22:$CE22),YR,PRD-1,_xll.ArrayDIM($CG22:$CJ22)) -> -90307956 | G22: =C22-E22 -> -1711728.6 | I22: =IF(G22=0,0,(G22*100/$G$30)) -> 27.572299 | BL22: 71155 | BM22: 71155
B23: - BANK - SCB CA # 096-3-02678-9 | C23: =_xll.ACC(DB,_xll.ArrayDPT($BA23:$BJ23),_xll.ArrayCOA($BL23:$CE23),YR,PRD,_xll.ArrayDIM($CG23:$CJ23)) -> -50590106 | E23: =_xll.ACC(DB,_xll.ArrayDPT($BA23:$BJ23),_xll.ArrayCOA($BL23:$CE23),YR,PRD-1,_xll.ArrayDIM($CG23:$CJ23)) -> -54538739 | G23: =C23-E23 -> 3948632.6 | I23: =IF(G23=0,0,(G23*100/$G$30)) -> -63.604056 | BL23: 71160 | BM23: 71160
B24: - BANK - BBL SA # 175-4-23258-3 | C24: =_xll.ACC(DB,_xll.ArrayDPT($BA24:$BJ24),_xll.ArrayCOA($BL24:$CE24),YR,PRD,_xll.ArrayDIM($CG24:$CJ24)) -> -42042211 | E24: =_xll.ACC(DB,_xll.ArrayDPT($BA24:$BJ24),_xll.ArrayCOA($BL24:$CE24),YR,PRD-1,_xll.ArrayDIM($CG24:$CJ24)) -> -32837161 | G24: =C24-E24 -> -9205050 | I24: =IF(G24=0,0,(G24*100/$G$30)) -> 148.27374 | BL24: 71165 | BM24: 71165
B25: - BANK - TTB CA # 917-1-00149-9 | C25: =_xll.ACC(DB,_xll.ArrayDPT($BA25:$BJ25),_xll.ArrayCOA($BL25:$CE25),YR,PRD,_xll.ArrayDIM($CG25:$CJ25)) -> -92571935 | E25: =_xll.ACC(DB,_xll.ArrayDPT($BA25:$BJ25),_xll.ArrayCOA($BL25:$CE25),YR,PRD-1,_xll.ArrayDIM($CG25:$CJ25)) -> -93331935 | G25: =C25-E25 -> 760000 | I25: =IF(G25=0,0,(G25*100/$G$30)) -> -12.24198 | BL25: 71145 | BM25: 71145
B26: - BANK - KTB SA # 660-0-44804-4 | C26: =_xll.ACC(DB,_xll.ArrayDPT($BA26:$BJ26),_xll.ArrayCOA($BL26:$CE26),YR,PRD,_xll.ArrayDIM($CG26:$CJ26)) -> 500 | E26: =_xll.ACC(DB,_xll.ArrayDPT($BA26:$BJ26),_xll.ArrayCOA($BL26:$CE26),YR,PRD-1,_xll.ArrayDIM($CG26:$CJ26)) -> 500 | G26: =C26-E26 -> 0 | I26: =IF(G26=0,0,(G26*100/$G$30)) -> 0 | BL26: 71175 | BM26: 71175
B27: - BANK - UOB SA # | C27: =_xll.ACC(DB,_xll.ArrayDPT($BA27:$BJ27),_xll.ArrayCOA($BL27:$CE27),YR,PRD,_xll.ArrayDIM($CG27:$CJ27)) -> 0 | E27: =_xll.ACC(DB,_xll.ArrayDPT($BA27:$BJ27),_xll.ArrayCOA($BL27:$CE27),YR,PRD-1,_xll.ArrayDIM($CG27:$CJ27)) -> 0 | G27: =C27-E27 -> 0 | I27: =IF(G27=0,0,(G27*100/$G$30)) -> 0
B28: - BANK - KBAND SA # | C28: =_xll.ACC(DB,_xll.ArrayDPT($BA28:$BJ28),_xll.ArrayCOA($BL28:$CE28),YR,PRD,_xll.ArrayDIM($CG28:$CJ28)) -> 0 | E28: =_xll.ACC(DB,_xll.ArrayDPT($BA28:$BJ28),_xll.ArrayCOA($BL28:$CE28),YR,PRD-1,_xll.ArrayDIM($CG28:$CJ28)) -> 0 | G28: =C28-E28 -> 0 | I28: =IF(G28=0,0,(G28*100/$G$30)) -> 0
B29: - BANK - FIXED # | C29: =_xll.ACC(DB,_xll.ArrayDPT($BA29:$BJ29),_xll.ArrayCOA($BL29:$CE29),YR,PRD,_xll.ArrayDIM($CG29:$CJ29)) -> 0 | E29: =_xll.ACC(DB,_xll.ArrayDPT($BA29:$BJ29),_xll.ArrayCOA($BL29:$CE29),YR,PRD-1,_xll.ArrayDIM($CG29:$CJ29)) -> 0 | G29: =C29-E29 -> 0 | I29: =IF(G29=0,0,(G29*100/$G$30)) -> 0
B30: TOTAL CASH IN BANK | C30: =SUM(C21:C29) -> -3.09147e+08 | E30: =SUM(E21:E29) -> -3.0293885e+08 | G30: =C30-E30 -> -6208145.9 | I30: =IF(G30=0,0,(G30*100/$G$30)) -> 100
A31: TOTAL CURRENT ASSET | C31: =+C30+C18 -> -3.0919735e+08 | E31: =+E30+E18 -> -3.029892e+08 | G31: =C31-E31 -> -6208145.9 | I31: =IF(G31=0,0,(G31*100/$G$31)) -> 100
A33: ACCOUNT RECEIVABLE - TRADE ( SCHEDULE A - 2A )
B34: - A/R TRADE - GUEST LEDGER | C34: =_xll.ACC(DB,_xll.ArrayDPT($BA34:$BJ34),_xll.ArrayCOA($BL34:$CE34),YR,PRD,_xll.ArrayDIM($CG34:$CJ34)) -> -17038581 | E34: =_xll.ACC(DB,_xll.ArrayDPT($BA34:$BJ34),_xll.ArrayCOA($BL34:$CE34),YR,PRD-1,_xll.ArrayDIM($CG34:$CJ34)) -> -19824339 | G34: =C34-E34 -> 2785758.2 | I34: =IF(G34=0,0,(G34*100/$G$44)) -> 100 | BL34: 71185 | BM34: 71185
B35: - A/R TRADE - CITY LEDGER | C35: =_xll.ACC(DB,_xll.ArrayDPT($BA35:$BJ35),_xll.ArrayCOA($BL35:$CE35),YR,PRD,_xll.ArrayDIM($CG35:$CJ35)) -> 0 | E35: =_xll.ACC(DB,_xll.ArrayDPT($BA35:$BJ35),_xll.ArrayCOA($BL35:$CE35),YR,PRD-1,_xll.ArrayDIM($CG35:$CJ35)) -> 0 | G35: =C35-E35 -> 0 | I35: =IF(G35=0,0,(G35*100/$G$44)) -> 0 | BL35: 71190 | BM35: 71190
B36: - A/R CREDIT CARD | C36: =_xll.ACC(DB,_xll.ArrayDPT($BA36:$BJ36),_xll.ArrayCOA($BL36:$CE36),YR,PRD,_xll.ArrayDIM($CG36:$CJ36)) -> 0 | E36: =_xll.ACC(DB,_xll.ArrayDPT($BA36:$BJ36),_xll.ArrayCOA($BL36:$CE36),YR,PRD-1,_xll.ArrayDIM($CG36:$CJ36)) -> 0 | G36: =C36-E36 -> 0 | I36: =IF(G36=0,0,(G36*100/$G$44)) -> 0 | BL36: 71195 | BM36: 71195 | BN36: 71200 | BO36: 71200 | BP36: 71205 | BQ36: 71205 | BR36: 71210 | BS36: 71210 | BT36: 71215 | BU36: 71215
B37: - ADVANCE CHEQUES | C37: =_xll.ACC(DB,_xll.ArrayDPT($BA37:$BJ37),_xll.ArrayCOA($BL37:$CE37),YR,PRD,_xll.ArrayDIM($CG37:$CJ37)) -> 0 | E37: =_xll.ACC(DB,_xll.ArrayDPT($BA37:$BJ37),_xll.ArrayCOA($BL37:$CE37),YR,PRD-1,_xll.ArrayDIM($CG37:$CJ37)) -> 0 | G37: =C37-E37 -> 0 | I37: =IF(G37=0,0,(G37*100/$G$44)) -> 0
B38: - A/R TRADE BARTER AGREEMENT | C38: =_xll.ACC(DB,_xll.ArrayDPT($BA38:$BJ38),_xll.ArrayCOA($BL38:$CE38),YR,PRD,_xll.ArrayDIM($CG38:$CJ38)) -> 0 | E38: =_xll.ACC(DB,_xll.ArrayDPT($BA38:$BJ38),_xll.ArrayCOA($BL38:$CE38),YR,PRD-1,_xll.ArrayDIM($CG38:$CJ38)) -> 0 | G38: =C38-E38 -> 0 | I38: =IF(G38=0,0,(G38*100/$G$44)) -> 0
B39: - A/R OTHER | C39: =_xll.ACC(DB,_xll.ArrayDPT($BA39:$BJ39),_xll.ArrayCOA($BL39:$CE39),YR,PRD,_xll.ArrayDIM($CG39:$CJ39)) -> 0 | E39: =_xll.ACC(DB,_xll.ArrayDPT($BA39:$BJ39),_xll.ArrayCOA($BL39:$CE39),YR,PRD-1,_xll.ArrayDIM($CG39:$CJ39)) -> 0 | G39: =C39-E39 -> 0 | I39: =IF(G39=0,0,(G39*100/$G$44)) -> 0 | BL39: 71220 | BM39: 71220 | BN39: 71225 | BO39: 71225 | BP39: 71230 | BQ39: 71230 | BR39: 71235 | BS39: 71235
B40: TOTAL ACCOUNT RECEIVABLE - TRADE | C40: =SUM(C34:C39) -> -17038581 | E40: =SUM(E34:E39) -> -19824339 | G40: =C40-E40 -> 2785758.2 | I40: =IF(G40=0,0,(G40*100/$G$44)) -> 100
B42: LESS : Allowance For Doubtful Account | C42: =_xll.ACC(DB,_xll.ArrayDPT($BA42:$BJ42),_xll.ArrayCOA($BL42:$CE42),YR,PRD,_xll.ArrayDIM($CG42:$CJ42)) -> 0 | E42: =_xll.ACC(DB,_xll.ArrayDPT($BA42:$BJ42),_xll.ArrayCOA($BL42:$CE42),YR-1,PRD,_xll.ArrayDIM($CG42:$CJ42)) -> 0 | G42: =C42-E42 -> 0 | I42: =IF(G42=0,0,(G42*100/$G$44)) -> 0
B43: Loans To Subsidiaries And Associated | C43: =_xll.ACC(DB,_xll.ArrayDPT($BA43:$BJ43),_xll.ArrayCOA($BL43:$CE43),YR,PRD,_xll.ArrayDIM($CG43:$CJ43)) -> 0 | E43: =_xll.ACC(DB,_xll.ArrayDPT($BA43:$BJ43),_xll.ArrayCOA($BL43:$CE43),YR-1,PRD,_xll.ArrayDIM($CG43:$CJ43)) -> 0 | G43: =C43-E43 -> 0 | I43: =IF(G43=0,0,(G43*100/$G$44)) -> 0
A44: NET - ACCOUNT RECEIVABLE - TRADE | C44: =C40+C42+C43 -> -17038581 | E44: =E40+E42+E43 -> -19824339 | G44: =C44-E44 -> 2785758.2 | I44: =IF(G44=0,0,(G44*100/$G$44)) -> 100 | J44: =C44-BS!C17 -> 0 | L44: =E44-BS!E17 -> 0
A47: OTHER RECEIVABLE ( SCHEDULE A - 2B ) | E47: =_xll.ACC(DB,_xll.ArrayDPT($BA47:$BJ47),_xll.ArrayCOA($BL47:$CE47),YR,PRD-1,_xll.ArrayDIM($CG47:$CJ47)) -> 0
B48: - ADVANCE TO SUPPLIER | C48: =_xll.ACC(DB,_xll.ArrayDPT($BA48:$BJ48),_xll.ArrayCOA($BL48:$CE48),YR,PRD,_xll.ArrayDIM($CG48:$CJ48)) -> 0 | E48: =_xll.ACC(DB,_xll.ArrayDPT($BA48:$BJ48),_xll.ArrayCOA($BL48:$CE48),YR,PRD-1,_xll.ArrayDIM($CG48:$CJ48)) -> 0 | G48: =C48-E48 -> 0 | I48: =IF(G48=0,0,(G48*100/$G$62)) -> 0
B49: - ADVANCE TO EMPLOYEES | C49: =_xll.ACC(DB,_xll.ArrayDPT($BA49:$BJ49),_xll.ArrayCOA($BL49:$CE49),YR,PRD,_xll.ArrayDIM($CG49:$CJ49)) -> 126076.59 | E49: =_xll.ACC(DB,_xll.ArrayDPT($BA49:$BJ49),_xll.ArrayCOA($BL49:$CE49),YR,PRD-1,_xll.ArrayDIM($CG49:$CJ49)) -> 126076.59 | G49: =C49-E49 -> 0 | I49: =IF(G49=0,0,(G49*100/$G$62)) -> 0 | BL49: 71260 | BM49: 71260
B50: - LOANS TO EMPLOYEES | C50: =_xll.ACC(DB,_xll.ArrayDPT($BA50:$BJ50),_xll.ArrayCOA($BL50:$CE50),YR,PRD,_xll.ArrayDIM($CG50:$CJ50)) -> 1.0061264e+08 | E50: =_xll.ACC(DB,_xll.ArrayDPT($BA50:$BJ50),_xll.ArrayCOA($BL50:$CE50),YR,PRD-1,_xll.ArrayDIM($CG50:$CJ50)) -> 1.0019764e+08 | G50: =C50-E50 -> 415000 | I50: =IF(G50=0,0,(G50*100/$G$62)) -> 4.8156358 | BL50: 71270 | BM50: 71270
B51: - CLAIMS - PROPERTIES | C51: =_xll.ACC(DB,_xll.ArrayDPT($BA51:$BJ51),_xll.ArrayCOA($BL51:$CE51),YR,PRD,_xll.ArrayDIM($CG51:$CJ51)) -> 6212.06 | E51: =_xll.ACC(DB,_xll.ArrayDPT($BA51:$BJ51),_xll.ArrayCOA($BL51:$CE51),YR,PRD-1,_xll.ArrayDIM($CG51:$CJ51)) -> 6212.06 | G51: =C51-E51 -> 0 | I51: =IF(G51=0,0,(G51*100/$G$62)) -> 0 | BL51: 71280 | BM51: 71280
B52: - UNDUE VAT - PURCHASE | C52: =_xll.ACC(DB,_xll.ArrayDPT($BA52:$BJ52),_xll.ArrayCOA($BL52:$CE52),YR,PRD,_xll.ArrayDIM($CG52:$CJ52)) -> 0 | E52: =_xll.ACC(DB,_xll.ArrayDPT($BA52:$BJ52),_xll.ArrayCOA($BL52:$CE52),YR,PRD-1,_xll.ArrayDIM($CG52:$CJ52)) -> 0 | G52: =C52-E52 -> 0 | I52: =IF(G52=0,0,(G52*100/$G$62)) -> 0
B53: - WITHHOLDNG TAX RECEIVABLE | C53: =_xll.ACC(DB,_xll.ArrayDPT($BA53:$BJ53),_xll.ArrayCOA($BL53:$CE53),YR,PRD,_xll.ArrayDIM($CG53:$CJ53)) -> 0 | E53: =_xll.ACC(DB,_xll.ArrayDPT($BA53:$BJ53),_xll.ArrayCOA($BL53:$CE53),YR,PRD-1,_xll.ArrayDIM($CG53:$CJ53)) -> 0 | G53: =C53-E53 -> 0 | I53: =IF(G53=0,0,(G53*100/$G$62)) -> 0
B54: - RECEIVABLE - REVENUE DEPARTMENY | C54: =_xll.ACC(DB,_xll.ArrayDPT($BA54:$BJ54),_xll.ArrayCOA($BL54:$CE54),YR,PRD,_xll.ArrayDIM($CG54:$CJ54)) -> 0 | E54: =_xll.ACC(DB,_xll.ArrayDPT($BA54:$BJ54),_xll.ArrayCOA($BL54:$CE54),YR,PRD-1,_xll.ArrayDIM($CG54:$CJ54)) -> 0 | G54: =C54-E54 -> 0 | I54: =IF(G54=0,0,(G54*100/$G$62)) -> 0
B55: - ADVANCE COPERATION TAX | C55: =_xll.ACC(DB,_xll.ArrayDPT($BA55:$BJ55),_xll.ArrayCOA($BL55:$CE55),YR,PRD,_xll.ArrayDIM($CG55:$CJ55)) -> 0 | E55: =_xll.ACC(DB,_xll.ArrayDPT($BA55:$BJ55),_xll.ArrayCOA($BL55:$CE55),YR,PRD-1,_xll.ArrayDIM($CG55:$CJ55)) -> 0 | G55: =C55-E55 -> 0 | I55: =IF(G55=0,0,(G55*100/$G$62)) -> 0
B56: - RECEIVABLE OTHER | C56: =_xll.ACC(DB,_xll.ArrayDPT($BA56:$BJ56),_xll.ArrayCOA($BL56:$CE56),YR,PRD,_xll.ArrayDIM($CG56:$CJ56)) -> -164600 | E56: =_xll.ACC(DB,_xll.ArrayDPT($BA56:$BJ56),_xll.ArrayCOA($BL56:$CE56),YR,PRD-1,_xll.ArrayDIM($CG56:$CJ56)) -> -164600 | G56: =C56-E56 -> 0 | I56: =IF(G56=0,0,(G56*100/$G$62)) -> 0 | BL56: 71295 | BM56: 71295
B57: - CLEARING ACCOUNT - CASH SALES | C57: =_xll.ACC(DB,_xll.ArrayDPT($BA57:$BJ57),_xll.ArrayCOA($BL57:$CE57),YR,PRD,_xll.ArrayDIM($CG57:$CJ57)) -> 1.6768246e+08 | E57: =_xll.ACC(DB,_xll.ArrayDPT($BA57:$BJ57),_xll.ArrayCOA($BL57:$CE57),YR,PRD-1,_xll.ArrayDIM($CG57:$CJ57)) -> 1.6708153e+08 | G57: =C57-E57 -> 600926.48 | I57: =IF(G57=0,0,(G57*100/$G$62)) -> 6.9731158 | BL57: 71410 | BM57: 71410
B58: - CLEARING ACCOUNT - ALLOWANCES | C58: =_xll.ACC(DB,_xll.ArrayDPT($BA58:$BJ58),_xll.ArrayCOA($BL58:$CE58),YR,PRD,_xll.ArrayDIM($CG58:$CJ58)) -> 4350.52 | E58: =_xll.ACC(DB,_xll.ArrayDPT($BA58:$BJ58),_xll.ArrayCOA($BL58:$CE58),YR,PRD-1,_xll.ArrayDIM($CG58:$CJ58)) -> 4350.52 | G58: =C58-E58 -> 0 | I58: =IF(G58=0,0,(G58*100/$G$62)) -> 0 | BL58: 71405 | BM58: 71405
B59: - CLEARING ACCOUNT - CL PAYMENT | C59: =_xll.ACC(DB,_xll.ArrayDPT($BA59:$BJ59),_xll.ArrayCOA($BL59:$CE59),YR,PRD,_xll.ArrayDIM($CG59:$CJ59)) -> 99976760 | E59: =_xll.ACC(DB,_xll.ArrayDPT($BA59:$BJ59),_xll.ArrayCOA($BL59:$CE59),YR,PRD-1,_xll.ArrayDIM($CG59:$CJ59)) -> 92374925 | G59: =C59-E59 -> 7601834.9 | I59: =IF(G59=0,0,(G59*100/$G$62)) -> 88.211248 | BL59: 71415 | BM59: 71415
B60: - CLEARING ACCOUNT - PAID OUT | C60: =_xll.ACC(DB,_xll.ArrayDPT($BA60:$BJ60),_xll.ArrayCOA($BL60:$CE60),YR,PRD,_xll.ArrayDIM($CG60:$CJ60)) -> -9224 | E60: =_xll.ACC(DB,_xll.ArrayDPT($BA60:$BJ60),_xll.ArrayCOA($BL60:$CE60),YR,PRD-1,_xll.ArrayDIM($CG60:$CJ60)) -> -9224 | G60: =C60-E60 -> 0 | I60: =IF(G60=0,0,(G60*100/$G$62)) -> 0 | BL60: 71430 | BM60: 71430
B61: - CLEARING ACCOUNT - CASH REFUND | C61: =_xll.ACC(DB,_xll.ArrayDPT($BA61:$BJ61),_xll.ArrayCOA($BL61:$CE61),YR,PRD,_xll.ArrayDIM($CG61:$CJ61)) -> -1882941 | E61: =_xll.ACC(DB,_xll.ArrayDPT($BA61:$BJ61),_xll.ArrayCOA($BL61:$CE61),YR,PRD-1,_xll.ArrayDIM($CG61:$CJ61)) -> -1882941 | G61: =C61-E61 -> 0 | I61: =IF(G61=0,0,(G61*100/$G$62)) -> 0 | BL61: 71450 | BM61: 71450
A62: TOTAL OTHER RECEIVABLE | C62: =SUM(C48:C61) -> 3.6635173e+08 | E62: =SUM(E48:E61) -> 3.5773397e+08 | G62: =C62-E62 -> 8617761.4 | I62: =IF(G62=0,0,(G62*100/$G$62)) -> 100 | J62: =C62-BS!C19 -> 0 | L62: =E62-BS!E19 -> 0
A64: SALEABLE MERCANDISE ( SCHEDULE A - 3A )
B65: INV. FOOD
B66: - INV. FOOD - KITCHEN | C66: =_xll.ACC(DB,_xll.ArrayDPT($BA66:$BJ66),_xll.ArrayCOA($BL66:$CE66),YR,PRD,_xll.ArrayDIM($CG66:$CJ66)) -> 0 | E66: =_xll.ACC(DB,_xll.ArrayDPT($BA66:$BJ66),_xll.ArrayCOA($BL66:$CE66),YR,PRD-1,_xll.ArrayDIM($CG66:$CJ66)) -> 0 | G66: =C66-E66 -> 0 | I66: =IF(G66=0,0,(G66*100/$G$84)) -> 0 | BL66: 71505 | BM66: 71505
B67: - INV. FOOD - DRY STORE | C67: =_xll.ACC(DB,_xll.ArrayDPT($BA67:$BJ67),_xll.ArrayCOA($BL67:$CE67),YR,PRD,_xll.ArrayDIM($CG67:$CJ67)) -> 0 | E67: =_xll.ACC(DB,_xll.ArrayDPT($BA67:$BJ67),_xll.ArrayCOA($BL67:$CE67),YR,PRD-1,_xll.ArrayDIM($CG67:$CJ67)) -> 0 | G67: =C67-E67 -> 0 | I67: =IF(G67=0,0,(G67*100/$G$84)) -> 0 | BL67: 71505 | BM67: 71505
B68: - INV. FOOD - FREEZER STORE | C68: =_xll.ACC(DB,_xll.ArrayDPT($BA68:$BJ68),_xll.ArrayCOA($BL68:$CE68),YR,PRD,_xll.ArrayDIM($CG68:$CJ68)) -> 0 | E68: =_xll.ACC(DB,_xll.ArrayDPT($BA68:$BJ68),_xll.ArrayCOA($BL68:$CE68),YR,PRD-1,_xll.ArrayDIM($CG68:$CJ68)) -> 0 | G68: =C68-E68 -> 0 | I68: =IF(G68=0,0,(G68*100/$G$84)) -> 0 | BL68: 71505 | BM68: 71505
B69: - INV. FOOD - MINI BAR | C69: =_xll.ACC(DB,_xll.ArrayDPT($BA69:$BJ69),_xll.ArrayCOA($BL69:$CE69),YR,PRD,_xll.ArrayDIM($CG69:$CJ69)) -> 0 | E69: =_xll.ACC(DB,_xll.ArrayDPT($BA69:$BJ69),_xll.ArrayCOA($BL69:$CE69),YR,PRD-1,_xll.ArrayDIM($CG69:$CJ69)) -> 0 | G69: =C69-E69 -> 0 | I69: =IF(G69=0,0,(G69*100/$G$84)) -> 0
B70: - INV. FOOD - OTHER | C70: =_xll.ACC(DB,_xll.ArrayDPT($BA70:$BJ70),_xll.ArrayCOA($BL70:$CE70),YR,PRD,_xll.ArrayDIM($CG70:$CJ70)) -> 0 | E70: =_xll.ACC(DB,_xll.ArrayDPT($BA70:$BJ70),_xll.ArrayCOA($BL70:$CE70),YR,PRD-1,_xll.ArrayDIM($CG70:$CJ70)) -> 0 | G70: =C70-E70 -> 0 | I70: =IF(G70=0,0,(G70*100/$G$84)) -> 0
C71: =SUM(C66:C70) -> 0 | E71: =SUM(E66:E70) -> 0 | G71: =C71-E71 -> 0 | I71: =IF(G71=0,0,(G71*100/$G$84)) -> 0
B72: INV.BEVERAGE
B73: - INV.BEVERAGE - BAR | C73: =_xll.ACC(DB,_xll.ArrayDPT($BA73:$BJ73),_xll.ArrayCOA($BL73:$CE73),YR,PRD,_xll.ArrayDIM($CG73:$CJ73)) -> 0 | E73: =_xll.ACC(DB,_xll.ArrayDPT($BA73:$BJ73),_xll.ArrayCOA($BL73:$CE73),YR,PRD-1,_xll.ArrayDIM($CG73:$CJ73)) -> 0 | G73: =C73-E73 -> 0 | I73: =IF(G73=0,0,(G73*100/$G$84)) -> 0 | BL73: 71510 | BM73: 71510
B74: - INV.BEVERAGE - STORE | C74: =_xll.ACC(DB,_xll.ArrayDPT($BA74:$BJ74),_xll.ArrayCOA($BL74:$CE74),YR,PRD,_xll.ArrayDIM($CG74:$CJ74)) -> 0 | E74: =_xll.ACC(DB,_xll.ArrayDPT($BA74:$BJ74),_xll.ArrayCOA($BL74:$CE74),YR,PRD-1,_xll.ArrayDIM($CG74:$CJ74)) -> 0 | G74: =C74-E74 -> 0 | I74: =IF(G74=0,0,(G74*100/$G$84)) -> 0 | BL74: 71510 | BM74: 71510
B75: - INV.BEVERAGE - LONG TERM CREDIT (CONSIGNMEN | C75: =_xll.ACC(DB,_xll.ArrayDPT($BA75:$BJ75),_xll.ArrayCOA($BL75:$CE75),YR,PRD,_xll.ArrayDIM($CG75:$CJ75)) -> 0 | E75: =_xll.ACC(DB,_xll.ArrayDPT($BA75:$BJ75),_xll.ArrayCOA($BL75:$CE75),YR,PRD-1,_xll.ArrayDIM($CG75:$CJ75)) -> 0 | G75: =C75-E75 -> 0 | I75: =IF(G75=0,0,(G75*100/$G$84)) -> 0 | BL75: 71615 | BM75: 71615
B76: - INV.BEVERAGE - MINI BAR | C76: =_xll.ACC(DB,_xll.ArrayDPT($BA76:$BJ76),_xll.ArrayCOA($BL76:$CE76),YR,PRD,_xll.ArrayDIM($CG76:$CJ76)) -> 0 | E76: =_xll.ACC(DB,_xll.ArrayDPT($BA76:$BJ76),_xll.ArrayCOA($BL76:$CE76),YR,PRD-1,_xll.ArrayDIM($CG76:$CJ76)) -> 0 | G76: =C76-E76 -> 0 | I76: =IF(G76=0,0,(G76*100/$G$84)) -> 0 | BL76: 71510 | BM76: 71510
B77: - INV.BEVERAGE - OTHER | C77: =_xll.ACC(DB,_xll.ArrayDPT($BA77:$BJ77),_xll.ArrayCOA($BL77:$CE77),YR,PRD,_xll.ArrayDIM($CG77:$CJ77)) -> 0 | E77: =_xll.ACC(DB,_xll.ArrayDPT($BA77:$BJ77),_xll.ArrayCOA($BL77:$CE77),YR,PRD-1,_xll.ArrayDIM($CG77:$CJ77)) -> 0 | G77: =C77-E77 -> 0 | I77: =IF(G77=0,0,(G77*100/$G$84)) -> 0
C78: =SUM(C73:C77) -> 0 | E78: =SUM(E73:E77) -> 0 | G78: =C78-E78 -> 0 | I78: =IF(G78=0,0,(G78*100/$G$84)) -> 0
B79: OTHERS SALEABLE MERCHANDISE
B80: - TOBACCO - STORE | C80: =_xll.ACC(DB,_xll.ArrayDPT($BA80:$BJ80),_xll.ArrayCOA($BL80:$CE80),YR,PRD,_xll.ArrayDIM($CG80:$CJ80)) -> 0 | E80: =_xll.ACC(DB,_xll.ArrayDPT($BA80:$BJ80),_xll.ArrayCOA($BL80:$CE80),YR,PRD-1,_xll.ArrayDIM($CG80:$CJ80)) -> 0 | G80: =C80-E80 -> 0 | I80: =IF(G80=0,0,(G80*100/$G$84)) -> 0 | BL80: 71520 | BM80: 71520
B81: - TOBACCO - OUTLET | C81: =_xll.ACC(DB,_xll.ArrayDPT($BA81:$BJ81),_xll.ArrayCOA($BL81:$CE81),YR,PRD,_xll.ArrayDIM($CG81:$CJ81)) -> 0 | E81: =_xll.ACC(DB,_xll.ArrayDPT($BA81:$BJ81),_xll.ArrayCOA($BL81:$CE81),YR,PRD-1,_xll.ArrayDIM($CG81:$CJ81)) -> 0 | G81: =C81-E81 -> 0 | I81: =IF(G81=0,0,(G81*100/$G$84)) -> 0 | BL81: 71520 | BM81: 71520
B82: - GIFT & SOUVENIR | C82: =_xll.ACC(DB,_xll.ArrayDPT($BA82:$BJ82),_xll.ArrayCOA($BL82:$CE82),YR,PRD,_xll.ArrayDIM($CG82:$CJ82)) -> 0 | E82: =_xll.ACC(DB,_xll.ArrayDPT($BA82:$BJ82),_xll.ArrayCOA($BL82:$CE82),YR,PRD-1,_xll.ArrayDIM($CG82:$CJ82)) -> 0 | G82: =C82-E82 -> 0 | I82: =IF(G82=0,0,(G82*100/$G$84)) -> 0
C83: =SUM(C80:C82) -> 0 | E83: =SUM(E80:E82) -> 0 | G83: =C83-E83 -> 0 | I83: =IF(G83=0,0,(G83*100/$G$84)) -> 0
A84: TOTAL SALESBLE MERCHANDISE INVENTORY | C84: =SUM(C71,C78,C83) -> 0 | E84: =SUM(E71,E78,E83) -> 0 | G84: =C84-E84 -> 0 | I84: =IF(G84=0,0,(G84*100/$G$84)) -> 0 | J84: =C84-BS!C22 -> 0
A86: INVENTORY - SUPPLY ( SCHEDULE A - 3B )
B87: - INV. CLEANING SUPPLY | C87: =_xll.ACC(DB,_xll.ArrayDPT($BA87:$BJ87),_xll.ArrayCOA($BL87:$CE87),YR,PRD,_xll.ArrayDIM($CG87:$CJ87)) -> 0 | E87: =_xll.ACC(DB,_xll.ArrayDPT($BA87:$BJ87),_xll.ArrayCOA($BL87:$CE87),YR,PRD-1,_xll.ArrayDIM($CG87:$CJ87)) -> 0 | G87: =C87-E87 -> 0 | I87: =IF(G87=0,0,(G87*100/$G$96)) -> 0 | BL87: 71525 | BM87: 71525
B88: - INV. PRINTING & STATIONERY | C88: =_xll.ACC(DB,_xll.ArrayDPT($BA88:$BJ88),_xll.ArrayCOA($BL88:$CE88),YR,PRD,_xll.ArrayDIM($CG88:$CJ88)) -> 0 | E88: =_xll.ACC(DB,_xll.ArrayDPT($BA88:$BJ88),_xll.ArrayCOA($BL88:$CE88),YR,PRD-1,_xll.ArrayDIM($CG88:$CJ88)) -> 0 | G88: =C88-E88 -> 0 | I88: =IF(G88=0,0,(G88*100/$G$96)) -> 0 | BL88: 71585 | BM88: 71585
B89: - INV. BAR & RESTURANT SUPPLIES | C89: =_xll.ACC(DB,_xll.ArrayDPT($BA89:$BJ89),_xll.ArrayCOA($BL89:$CE89),YR,PRD,_xll.ArrayDIM($CG89:$CJ89)) -> 0 | E89: =_xll.ACC(DB,_xll.ArrayDPT($BA89:$BJ89),_xll.ArrayCOA($BL89:$CE89),YR,PRD-1,_xll.ArrayDIM($CG89:$CJ89)) -> 0 | G89: =C89-E89 -> 0 | I89: =IF(G89=0,0,(G89*100/$G$96)) -> 0
B90: - INV. GUEST SUPPLY | C90: =_xll.ACC(DB,_xll.ArrayDPT($BA90:$BJ90),_xll.ArrayCOA($BL90:$CE90),YR,PRD,_xll.ArrayDIM($CG90:$CJ90)) -> 1682.24 | E90: =_xll.ACC(DB,_xll.ArrayDPT($BA90:$BJ90),_xll.ArrayCOA($BL90:$CE90),YR,PRD-1,_xll.ArrayDIM($CG90:$CJ90)) -> 1682.24 | G90: =C90-E90 -> 0 | I90: =IF(G90=0,0,(G90*100/$G$96)) -> 0 | BL90: 71560 | BM90: 71560
B91: - INV. LAUNDY SUPPLY | C91: =_xll.ACC(DB,_xll.ArrayDPT($BA91:$BJ91),_xll.ArrayCOA($BL91:$CE91),YR,PRD,_xll.ArrayDIM($CG91:$CJ91)) -> 0 | E91: =_xll.ACC(DB,_xll.ArrayDPT($BA91:$BJ91),_xll.ArrayCOA($BL91:$CE91),YR,PRD-1,_xll.ArrayDIM($CG91:$CJ91)) -> 0 | G91: =C91-E91 -> 0 | I91: =IF(G91=0,0,(G91*100/$G$96)) -> 0 | BL91: 71570 | BM91: 71570
B92: - INV. S&M SUPPLY | C92: =_xll.ACC(DB,_xll.ArrayDPT($BA92:$BJ92),_xll.ArrayCOA($BL92:$CE92),YR,PRD,_xll.ArrayDIM($CG92:$CJ92)) -> 4105.61 | E92: =_xll.ACC(DB,_xll.ArrayDPT($BA92:$BJ92),_xll.ArrayCOA($BL92:$CE92),YR,PRD-1,_xll.ArrayDIM($CG92:$CJ92)) -> 4105.61 | G92: =C92-E92 -> 0 | I92: =IF(G92=0,0,(G92*100/$G$96)) -> 0 | BL92: 71595 | BM92: 71595
B93: - INV. SPA SUPPLY | C93: =_xll.ACC(DB,_xll.ArrayDPT($BA93:$BJ93),_xll.ArrayCOA($BL93:$CE93),YR,PRD,_xll.ArrayDIM($CG93:$CJ93)) -> 0 | E93: =_xll.ACC(DB,_xll.ArrayDPT($BA93:$BJ93),_xll.ArrayCOA($BL93:$CE93),YR,PRD-1,_xll.ArrayDIM($CG93:$CJ93)) -> 0 | G93: =C93-E93 -> 0 | I93: =IF(G93=0,0,(G93*100/$G$96)) -> 0 | BL93: 71600 | BM93: 71600
B94: - INV. ENGINEERING SUPPLY | C94: =_xll.ACC(DB,_xll.ArrayDPT($BA94:$BJ94),_xll.ArrayCOA($BL94:$CE94),YR,PRD,_xll.ArrayDIM($CG94:$CJ94)) -> 0 | E94: =_xll.ACC(DB,_xll.ArrayDPT($BA94:$BJ94),_xll.ArrayCOA($BL94:$CE94),YR,PRD-1,_xll.ArrayDIM($CG94:$CJ94)) -> 0 | G94: =C94-E94 -> 0 | I94: =IF(G94=0,0,(G94*100/$G$96)) -> 0
B95: - INV. GENERAL SUPPLY | C95: =_xll.ACC(DB,_xll.ArrayDPT($BA95:$BJ95),_xll.ArrayCOA($BL95:$CE95),YR,PRD,_xll.ArrayDIM($CG95:$CJ95)) -> 0 | E95: =_xll.ACC(DB,_xll.ArrayDPT($BA95:$BJ95),_xll.ArrayCOA($BL95:$CE95),YR,PRD-1,_xll.ArrayDIM($CG95:$CJ95)) -> 0 | G95: =C95-E95 -> 0 | I95: =IF(G95=0,0,(G95*100/$G$96)) -> 0
A96: TOTAL INVENTORY - SUPPLY | C96: =SUM(C90:C95) -> 5787.85 | E96: =SUM(E90:E95) -> 5787.85 | G96: =C96-E96 -> 0 | I96: =IF(G96=0,0,(G96*100/$G$96)) -> 0 | J96: =C96-BS!C23 -> 0
A98: OPERATING EQUIPMENT OPERATION ( SCHEDULE A - 3C )
B99: - CHINAWARE | C99: =_xll.ACC(DB,_xll.ArrayDPT($BA99:$BJ99),_xll.ArrayCOA($BL99:$CE99),YR,PRD,_xll.ArrayDIM($CG99:$CJ99)) -> 5626.17 | E99: =_xll.ACC(DB,_xll.ArrayDPT($BA99:$BJ99),_xll.ArrayCOA($BL99:$CE99),YR,PRD-1,_xll.ArrayDIM($CG99:$CJ99)) -> 5626.17 | G99: =C99-E99 -> 0 | I99: =IF(G99=0,0,(G99*100/$G$112)) -> 0 | BL99: 71655 | BM99: 71655
B100: - GLASSWARE | C100: =_xll.ACC(DB,_xll.ArrayDPT($BA100:$BJ100),_xll.ArrayCOA($BL100:$CE100),YR,PRD,_xll.ArrayDIM($CG100:$CJ100)) -> 0 | E100: =_xll.ACC(DB,_xll.ArrayDPT($BA100:$BJ100),_xll.ArrayCOA($BL100:$CE100),YR,PRD-1,_xll.ArrayDIM($CG100:$CJ100)) -> 0 | G100: =C100-E100 -> 0 | I100: =IF(G100=0,0,(G100*100/$G$112)) -> 0 | BL100: 71660 | BM100: 71660
B101: - SILVERWARE/STANLESS | C101: =_xll.ACC(DB,_xll.ArrayDPT($BA101:$BJ101),_xll.ArrayCOA($BL101:$CE101),YR,PRD,_xll.ArrayDIM($CG101:$CJ101)) -> 4018.69 | E101: =_xll.ACC(DB,_xll.ArrayDPT($BA101:$BJ101),_xll.ArrayCOA($BL101:$CE101),YR,PRD-1,_xll.ArrayDIM($CG101:$CJ101)) -> 4018.69 | G101: =C101-E101 -> 0 | I101: =IF(G101=0,0,(G101*100/$G$112)) -> 0 | BL101: 71665 | BM101: 71665
B102: - MELAMINE WARE / PLASTICWARE | C102: =_xll.ACC(DB,_xll.ArrayDPT($BA102:$BJ102),_xll.ArrayCOA($BL102:$CE102),YR,PRD,_xll.ArrayDIM($CG102:$CJ102)) -> 0 | E102: =_xll.ACC(DB,_xll.ArrayDPT($BA102:$BJ102),_xll.ArrayCOA($BL102:$CE102),YR,PRD-1,_xll.ArrayDIM($CG102:$CJ102)) -> 0 | G102: =C102-E102 -> 0 | I102: =IF(G102=0,0,(G102*100/$G$112)) -> 0
B103: - WOODENWARE | C103: =_xll.ACC(DB,_xll.ArrayDPT($BA103:$BJ103),_xll.ArrayCOA($BL103:$CE103),YR,PRD,_xll.ArrayDIM($CG103:$CJ103)) -> 0 | E103: =_xll.ACC(DB,_xll.ArrayDPT($BA103:$BJ103),_xll.ArrayCOA($BL103:$CE103),YR,PRD-1,_xll.ArrayDIM($CG103:$CJ103)) -> 0 | G103: =C103-E103 -> 0 | I103: =IF(G103=0,0,(G103*100/$G$112)) -> 0
B104: - CUTLERY | C104: =_xll.ACC(DB,_xll.ArrayDPT($BA104:$BJ104),_xll.ArrayCOA($BL104:$CE104),YR,PRD,_xll.ArrayDIM($CG104:$CJ104)) -> 0 | E104: =_xll.ACC(DB,_xll.ArrayDPT($BA104:$BJ104),_xll.ArrayCOA($BL104:$CE104),YR,PRD-1,_xll.ArrayDIM($CG104:$CJ104)) -> 0 | G104: =C104-E104 -> 0 | I104: =IF(G104=0,0,(G104*100/$G$112)) -> 0
B105: - KITCHEN UTENSIL | C105: =_xll.ACC(DB,_xll.ArrayDPT($BA105:$BJ105),_xll.ArrayCOA($BL105:$CE105),YR,PRD,_xll.ArrayDIM($CG105:$CJ105)) -> 82844.47 | E105: =_xll.ACC(DB,_xll.ArrayDPT($BA105:$BJ105),_xll.ArrayCOA($BL105:$CE105),YR,PRD-1,_xll.ArrayDIM($CG105:$CJ105)) -> 80696.47 | G105: =C105-E105 -> 2148 | I105: =IF(G105=0,0,(G105*100/$G$112)) -> 2.1257224 | BL105: 71670 | BM105: 71670
B106: - LINEN | C106: =_xll.ACC(DB,_xll.ArrayDPT($BA106:$BJ106),_xll.ArrayCOA($BL106:$CE106),YR,PRD,_xll.ArrayDIM($CG106:$CJ106)) -> 702565 | E106: =_xll.ACC(DB,_xll.ArrayDPT($BA106:$BJ106),_xll.ArrayCOA($BL106:$CE106),YR,PRD-1,_xll.ArrayDIM($CG106:$CJ106)) -> 603665 | G106: =C106-E106 -> 98900 | I106: =IF(G106=0,0,(G106*100/$G$112)) -> 97.874278 | BL106: 71675 | BM106: 71675
B107: - UNIFORMS | C107: =_xll.ACC(DB,_xll.ArrayDPT($BA107:$BJ107),_xll.ArrayCOA($BL107:$CE107),YR,PRD,_xll.ArrayDIM($CG107:$CJ107)) -> 0 | E107: =_xll.ACC(DB,_xll.ArrayDPT($BA107:$BJ107),_xll.ArrayCOA($BL107:$CE107),YR,PRD-1,_xll.ArrayDIM($CG107:$CJ107)) -> 0 | G107: =C107-E107 -> 0 | I107: =IF(G107=0,0,(G107*100/$G$112)) -> 0 | BL107: 71680 | BM107: 71680
B108: - O/E STAFF CANTEEN | C108: =_xll.ACC(DB,_xll.ArrayDPT($BA108:$BJ108),_xll.ArrayCOA($BL108:$CE108),YR,PRD,_xll.ArrayDIM($CG108:$CJ108)) -> 0 | E108: =_xll.ACC(DB,_xll.ArrayDPT($BA108:$BJ108),_xll.ArrayCOA($BL108:$CE108),YR,PRD-1,_xll.ArrayDIM($CG108:$CJ108)) -> 0 | G108: =C108-E108 -> 0 | I108: =IF(G108=0,0,(G108*100/$G$112)) -> 0
B109: - TOOL ENG | C109: =_xll.ACC(DB,_xll.ArrayDPT($BA109:$BJ109),_xll.ArrayCOA($BL109:$CE109),YR,PRD,_xll.ArrayDIM($CG109:$CJ109)) -> 0 | E109: =_xll.ACC(DB,_xll.ArrayDPT($BA109:$BJ109),_xll.ArrayCOA($BL109:$CE109),YR,PRD-1,_xll.ArrayDIM($CG109:$CJ109)) -> 0 | G109: =C109-E109 -> 0 | I109: =IF(G109=0,0,(G109*100/$G$112)) -> 0
...

Sheet PL-Sum
A2: HOMM SUKHUMVIT34 BANGKOK | T2: Period | U2: =PRD -> 1
J3: Profit & Loss Summary | Q3: SCHEDULE - A | AA3: Mapping Area
A4: CURRENT MONTH | L4: YEAR TO DATE | AA4: *Department Code | AG4: *Account Code | BT4: Dimension
A5: LAST YEAR | C5: VARIANCE | E5: BUDGET | G5: ACTUAL | J5: DESCRIPTION | L5: ACTUAL | N5: BUDGET | P5: VARIANCE | R5: LAST YEAR | AA5: Dept 1 | AB5: Dept 2 | AC5: Dept 3 | AD5: Dept 4 | AE5: Dept 5 | AG5: 1st Range | AI5: 2nd Range | AK5: 3rd Range | AM5: 4rd Range | AO5: 5rd Range | AQ5: 6rd Range | AS5: 7rd Range | AU5: 8rd Range | AW5: 9rd Range | AY5: 10rd Range | BA5: 11rd Range | BC5: 12rd Range | BE5: 13rd Range | BG5: 14rd Range | BI5: 15rd Range | BK5: 16rd Range | BM5: 17rd Range | BO5: 18th Range | BQ5: 19th Range
A6: BHT | B6: % | C6: BHT | D6: % | E6: BHT | F6: % | G6: BHT | H6: % | L6: BHT | M6: % | N6: BHT | O6: % | P6: BHT | Q6: % | R6: BHT | S6: % | AG6: From | AH6: To | AI6: From | AJ6: To | AK6: From | AL6: To | AM6: From | AN6: To | AO6: From | AP6: To | AQ6: From | AR6: To | AS6: From | AT6: To | AU6: From | AV6: To | AW6: From | AX6: To | AY6: From | AZ6: To | BA6: From | BB6: To | BC6: From | BD6: To | BE6: From | BF6: To | BG6: From | BH6: To | BI6: From | BJ6: To | BK6: From | BL6: To | BM6: From | BN6: To | BO6: From | BP6: To | BQ6: From | BR6: To | BT6: A/O | BU6: Field Name | BV6: Operator | BW6: Value
A7: ='Sum Room'!A78 -> 4588 | C7: =G7-E7 -> 4588 | E7: ='Sum Room'!E78 -> 0 | G7: ='Sum Room'!G78 -> 4588 | J7: Total Roon In Hotel | L7: ='Sum Room'!L78 -> 4588 | N7: ='Sum Room'!N78 -> 0 | P7: ='Sum Room'!P78 -> -4588 | R7: ='Sum Room'!R78 -> 4588
A8: ='Sum Room'!A80 -> 3209 | C8: =G8-E8 -> 3442 | E8: ='Sum Room'!E80 -> 0 | G8: ='Sum Room'!G80 -> 3442 | J8: Room Occupied | L8: =Front!L80 -> 3442 | N8: =Front!N80 -> 0 | P8: =Front!P80 -> -3442 | R8: =Front!R80 -> 3209
A9: =A8/A7 -> 0.6994333 | C9: =C8/C7 -> 0.75021796 | E9: =E8/E7 -> #DIV/0! | G9: =G8/G7 -> 0.75021796 | J9: % Of Occupancy | L9: =L8/L7 -> 0.75021796 | N9: =N8/N7 -> #DIV/0! | P9: =P8/P7 -> 0.75021796 | R9: =R8/R7 -> 0.6994333
A10: 0 | C10: 0 | E10: 0 | G10: 0 | J10: Double Occupancy | L10: 0 | N10: 0 | P10: 0 | R10: 0
A11: ='Sum Room'!A81 -> 2254.4789 | C11: =G11-E11 -> #DIV/0! | E11: ='Sum Room'!E81 -> #DIV/0! | G11: ='Sum Room'!G81 -> 2294.0267 | J11: Average Room Rate | L11: ='Sum Room'!L81 -> 2294.0267 | N11: ='Sum Room'!N81 -> #DIV/0! | P11: ='Sum Room'!P81 -> 2294.0267 | R11: ='Sum Room'!R81 -> 2254.4789
A12: ='Sum Room'!A82 -> 6310 | C12: =G12-E12 -> 6408 | E12: ='Sum Room'!E82 -> 0 | G12: ='Sum Room'!G82 -> 6408 | J12: Number Of Guest | L12: ='Sum Room'!L82 -> 6408 | N12: ='Sum Room'!N82 -> 0 | P12: ='Sum Room'!P82 -> -6408 | R12: ='Sum Room'!R82 -> 6310
J14: R E V E N U E
A15: =Front!A14 -> 7249519.3 | B15: =IF(A15=0,0,(A15*100/A$19)) -> 87.066434 | C15: =Front!C14 -> -7921831 | D15: =IF(C15=0,0,(C15*100/C$19)) -> 91.476967 | E15: =Front!E14 -> 0 | F15: =IF(E15=0,0,(E15*100/E$19)) -> 0 | G15: ='Sum Room'!G14 -> 7921831 | H15: =IF(G15=0,0,(G15*100/G$19)) -> 91.476967 | J15: Rooms | L15: ='Sum Room'!L14 -> 7921831 | M15: =IF(L15=0,0,(L15*100/L$19)) -> 77.459648 | N15: =Front!N14 -> 0 | O15: =IF(N15=0,0,(N15*100/N$19)) -> 0 | P15: =Front!P14 -> -7921831 | Q15: =IF(P15=0,0,(P15*100/P$19)) -> 77.459648 | R15: =Front!R14 -> 7249519.3 | S15: =IF(R15=0,0,(R15*100/R$19)) -> 73.654521
A16: ='F&B'!A14 -> 809758.45 | B16: =IF(A16=0,0,(A16*100/A$19)) -> 9.7251663 | C16: ='F&B'!C14 -> -513215.19 | D16: =IF(C16=0,0,(C16*100/C$19)) -> 5.926328 | E16: ='F&B'!E14 -> 0 | F16: =IF(E16=0,0,(E16*100/E$19)) -> 0 | G16: ='F&B'!G14 -> 513215.19 | H16: =IF(G16=0,0,(G16*100/G$19)) -> 5.926328 | J16: Food & Beverage | L16: ='F&B'!L14 -> 2080338.7 | M16: =IF(L16=0,0,(L16*100/L$19)) -> 20.341548 | N16: ='F&B'!N14 -> 0 | O16: =IF(N16=0,0,(N16*100/N$19)) -> 0 | P16: ='F&B'!P14 -> -2080338.7 | Q16: =IF(P16=0,0,(P16*100/P$19)) -> 20.341548 | R16: ='F&B'!R14 -> 2325935 | S16: =IF(R16=0,0,(R16*100/R$19)) -> 23.631309
A17: ='Spa & Fitness'!A17 -> 59532.76 | B17: =IF(A17=0,0,(A17*100/A$19)) -> 0.71498605 | C17: ='Spa & Fitness'!C17 -> -424.81 | D17: =IF(C17=0,0,(C17*100/C$19)) -> 0.0049054733 | E17: ='Spa & Fitness'!E17 -> 0 | F17: =IF(E17=0,0,(E17*100/E$19)) -> 0 | G17: ='Spa & Fitness'!G17 -> 424.81 | H17: =IF(G17=0,0,(G17*100/G$19)) -> 0.0049054733 | J17: Spa & Fitness Center | L17: ='Spa & Fitness'!L17 -> 424.81 | M17: =IF(L17=0,0,(L17*100/L$19)) -> 0.0041537914 | N17: ='Spa & Fitness'!N17 -> 0 | O17: =IF(N17=0,0,(N17*100/N$19)) -> 0 | P17: ='Spa & Fitness'!P17 -> -424.81 | Q17: =IF(P17=0,0,(P17*100/P$19)) -> 0.0041537914 | R17: ='Spa & Fitness'!R17 -> 59532.76 | S17: =IF(R17=0,0,(R17*100/R$19)) -> 0.60484796
A18: =OOD!A19 -> 207612.13 | B18: =IF(A18=0,0,(A18*100/A$19)) -> 2.4934133 | C18: =OOD!C19 -> -224447.74 | D18: =IF(C18=0,0,(C18*100/C$19)) -> 2.5917996 | E18: =OOD!E19 -> 0 | F18: =IF(E18=0,0,(E18*100/E$19)) -> 0 | G18: =OOD!G19 -> 224447.74 | H18: =IF(G18=0,0,(G18*100/G$19)) -> 2.5917996 | J18: Other Operated Departments | L18: =OOD!L19 -> 224447.74 | M18: =IF(L18=0,0,(L18*100/L$19)) -> 2.1946496 | N18: =OOD!N19 -> 0 | O18: =IF(N18=0,0,(N18*100/N$19)) -> 0 | P18: =OOD!P19 -> -224447.74 | Q18: =IF(P18=0,0,(P18*100/P$19)) -> 2.1946496 | R18: =OOD!R19 -> 207612.13 | S18: =IF(R18=0,0,(R18*100/R$19)) -> 2.1093222
A19: =SUM(A15:A18) -> 8326422.6 | B19: =IF(A19=0,0,(A19*100/A$19)) -> 100 | C19: =SUM(C15:C18) -> -8659918.7 | D19: =IF(C19=0,0,(C19*100/C$19)) -> 100 | E19: =SUM(E15:E18) -> 0 | F19: =IF(E19=0,0,(E19*100/E$19)) -> 0 | G19: =SUM(G15:G18) -> 8659918.7 | H19: =IF(G19=0,0,(G19*100/G$19)) -> 100 | J19: TOTAL REVENUE | L19: =SUM(L15:L18) -> 10227042 | M19: =IF(L19=0,0,(L19*100/L$19)) -> 100 | N19: =SUM(N15:N18) -> 0 | O19: =IF(N19=0,0,(N19*100/N$19)) -> 0 | P19: =SUM(P15:P18) -> -10227042 | Q19: =IF(P19=0,0,(P19*100/P$19)) -> 100 | R19: =SUM(R15:R18) -> 9842599.2 | S19: =IF(R19=0,0,(R19*100/R$19)) -> 100
J20: C O S T O F S A L E
A21: ='F&B'!A23 -> 263952.68 | B21: =IF(A21=0,0,(A21*100/A$19)) -> 3.170061 | C21: ='F&B'!C23 -> -153250.75 | D21: =IF(C21=0,0,(C21*100/C$19)) -> 1.7696558 | E21: ='F&B'!E23 -> 0 | F21: =IF(E21=0,0,(E21*100/E$19)) -> 0 | G21: ='F&B'!G23 -> 153250.75 | H21: =IF(G21=0,0,(G21*100/G$16)) -> 29.860915 | J21: Food & Beverage | L21: ='F&B'!L23 -> 153250.75 | M21: =IF(L21=0,0,(L21*100/L$16)) -> 7.3666248 | N21: ='F&B'!N23 -> 0 | O21: =IF(N21=0,0,(N21*100/N$19)) -> 0 | P21: ='F&B'!P23 -> -153250.75 | Q21: =IF(P21=0,0,(P21*100/P$19)) -> 1.4984855 | R21: ='F&B'!R23 -> 263952.68 | S21: =IF(R21=0,0,(R21*100/R$19)) -> 2.6817376
A22: ='Spa & Fitness'!A27 -> 27684.35 | B22: =IF(A22=0,0,(A22*100/A$19)) -> 0.33248793 | C22: ='Spa & Fitness'!C27 -> 0 | D22: =IF(C22=0,0,(C22*100/C$19)) -> 0 | E22: ='Spa & Fitness'!E27 -> 0 | F22: =IF(E22=0,0,(E22*100/E$19)) -> 0 | G22: ='Spa & Fitness'!G27 -> 0 | H22: =IF(G22=0,0,(G22*100/G$17)) -> 0 | J22: Spa & Fitness Center | L22: ='Spa & Fitness'!L27 -> 0 | M22: =IF(L22=0,0,(L22*100/L$17)) -> 0 | N22: ='Spa & Fitness'!N27 -> 0 | O22: =IF(N22=0,0,(N22*100/N$19)) -> 0 | P22: ='Spa & Fitness'!P27 -> 0 | Q22: =IF(P22=0,0,(P22*100/P$19)) -> 0 | R22: ='Spa & Fitness'!R27 -> 27684.35 | S22: =IF(R22=0,0,(R22*100/R$19)) -> 0.28127072
A23: =OOD!A31 -> 12536.48 | B23: =IF(A23=0,0,(A23*100/A$19)) -> 0.15056262 | C23: =OOD!C31 -> -52136.89 | D23: =IF(C23=0,0,(C23*100/C$19)) -> 0.60204826 | E23: =OOD!E31 -> 0 | F23: =IF(E23=0,0,(E23*100/E$19)) -> 0 | G23: =OOD!G31 -> 52136.89 | H23: =IF(G23=0,0,(G23*100/G$18)) -> 23.228966 | J23: Other Operated Departments | L23: =OOD!L31 -> 52136.89 | M23: =IF(L23=0,0,(L23*100/L$18)) -> 23.228966 | N23: =OOD!N31 -> 0 | O23: =IF(N23=0,0,(N23*100/N$19)) -> 0 | P23: =OOD!P31 -> -52136.89 | Q23: =IF(P23=0,0,(P23*100/P$19)) -> 0.50979441 | R23: =OOD!R31 -> 12536.48 | S23: =IF(R23=0,0,(R23*100/R$19)) -> 0.12736961
A24: =SUM(A20:A23) -> 304173.51 | B24: =IF(A24=0,0,(A24*100/A$19)) -> 3.6531116 | C24: =SUM(C20:C23) -> -205387.64 | D24: =IF(C24=0,0,(C24*100/C$19)) -> 2.371704 | E24: =SUM(E20:E23) -> 0 | F24: =IF(E24=0,0,(E24*100/E$19)) -> 0 | G24: =SUM(G20:G23) -> 205387.64 | H24: =IF(G24=0,0,(G24*100/G$19)) -> 2.371704 | J24: TOTAL COST OF SALES | L24: =SUM(L20:L23) -> 205387.64 | M24: =IF(L24=0,0,(L24*100/L$19)) -> 2.00828 | N24: =SUM(N20:N23) -> 0 | O24: =IF(N24=0,0,(N24*100/N$19)) -> 0 | P24: =SUM(P20:P23) -> -205387.64 | Q24: =IF(P24=0,0,(P24*100/P$19)) -> 2.00828 | R24: =SUM(R20:R23) -> 304173.51 | S24: =IF(R24=0,0,(R24*100/R$19)) -> 3.0903779
J25: PAYROLL & EMPLOYEE RELATION
A26: =Front!A26 -> 133133.34 | B26: =IF(A26=0,0,(A26*100/A$19)) -> 1.598926 | C26: =Front!C26 -> -137465.61 | D26: =IF(C26=0,0,(C26*100/C$19)) -> 1.5873776 | E26: =Front!E26 -> 0 | F26: =IF(E26=0,0,(E26*100/E$19)) -> 0 | G26: ='Sum Room'!G26 -> 289005.28 | H26: =IF(G26=0,0,(G26*100/G$19)) -> 3.3372747 | J26: Rooms | L26: =Front!L26 -> 137465.61 | M26: =IF(L26=0,0,(L26*100/L$19)) -> 1.3441385 | N26: =Front!N26 -> 0 | O26: =IF(N26=0,0,(N26*100/N$19)) -> 0 | P26: =Front!P26 -> -137465.61 | Q26: =IF(P26=0,0,(P26*100/P$19)) -> 1.3441385 | R26: =Front!R26 -> 133133.34 | S26: =IF(R26=0,0,(R26*100/R$19)) -> 1.3526238
A27: ='F&B'!A34 -> 104000 | B27: =IF(A27=0,0,(A27*100/A$19)) -> 1.2490358 | C27: ='F&B'!C34 -> -116934.33 | D27: =IF(C27=0,0,(C27*100/C$19)) -> 1.3502936 | E27: ='F&B'!E34 -> 0 | F27: =IF(E27=0,0,(E27*100/E$19)) -> 0 | G27: ='F&B'!G34 -> 116934.33 | H27: =IF(G27=0,0,(G27*100/G$19)) -> 1.3502936 | J27: Food & Beverage | L27: ='F&B'!L34 -> 116934.33 | M27: =IF(L27=0,0,(L27*100/L$19)) -> 1.1433837 | N27: ='F&B'!N34 -> 0 | O27: =IF(N27=0,0,(N27*100/N$19)) -> 0 | P27: ='F&B'!P34 -> -116934.33 | Q27: =IF(P27=0,0,(P27*100/P$19)) -> 1.1433837 | R27: ='F&B'!R34 -> 104000 | S27: =IF(R27=0,0,(R27*100/R$19)) -> 1.0566315
A28: ='Spa & Fitness'!A34 -> 0 | B28: =IF(A28=0,0,(A28*100/A$19)) -> 0 | C28: ='Spa & Fitness'!C34 -> 0 | D28: =IF(C28=0,0,(C28*100/C$19)) -> 0 | E28: ='Spa & Fitness'!E34 -> 0 | F28: =IF(E28=0,0,(E28*100/E$19)) -> 0 | G28: =+'Spa & Fitness'!G34 -> 0 | H28: =IF(G28=0,0,(G28*100/G$19)) -> 0 | J28: Spa & Fitness Center | L28: ='Spa & Fitness'!L34 -> 0 | M28: =IF(L28=0,0,(L28*100/L$19)) -> 0 | N28: ='Spa & Fitness'!N34 -> 0 | O28: =IF(N28=0,0,(N28*100/N$19)) -> 0 | P28: ='Spa & Fitness'!P34 -> 0 | Q28: =IF(P28=0,0,(P28*100/P$19)) -> 0 | R28: ='Spa & Fitness'!R34 -> 0 | S28: =IF(R28=0,0,(R28*100/R$19)) -> 0
A29: =OOD!A38 -> 0 | B29: =IF(A29=0,0,(A29*100/A$19)) -> 0 | C29: =OOD!C38 -> 0 | D29: =IF(C29=0,0,(C29*100/C$19)) -> 0 | E29: =OOD!E38 -> 0 | F29: =IF(E29=0,0,(E29*100/E$19)) -> 0 | G29: =OOD!G38 -> 0 | H29: =IF(G29=0,0,(G29*100/G$19)) -> 0 | J29: Other Operated Departments | L29: =OOD!L38 -> 0 | M29: =IF(L29=0,0,(L29*100/L$19)) -> 0 | N29: =OOD!N38 -> 0 | O29: =IF(N29=0,0,(N29*100/N$19)) -> 0 | P29: =OOD!P38 -> 0 | Q29: =IF(P29=0,0,(P29*100/P$19)) -> 0 | R29: =OOD!R38 -> 0 | S29: =IF(R29=0,0,(R29*100/R$19)) -> 0
A30: =SUM(A26:A29) -> 237133.34 | B30: =IF(A30=0,0,(A30*100/A$19)) -> 2.8479618 | C30: =SUM(C26:C29) -> -254399.94 | D30: =IF(C30=0,0,(C30*100/C$19)) -> 2.9376712 | E30: =SUM(E26:E29) -> 0 | F30: =IF(E30=0,0,(E30*100/E$19)) -> 0 | G30: =SUM(G26:G29) -> 405939.61 | H30: =IF(G30=0,0,(G30*100/G$19)) -> 4.6875684 | J30: TOTAL PAYROLL & EMP. REL. | L30: =SUM(L26:L29) -> 254399.94 | M30: =IF(L30=0,0,(L30*100/L$19)) -> 2.4875221 | N30: =SUM(N26:N29) -> 0 | O30: =IF(N30=0,0,(N30*100/N$19)) -> 0 | P30: =SUM(P26:P29) -> -254399.94 | Q30: =IF(P30=0,0,(P30*100/P$19)) -> 2.4875221 | R30: =SUM(R26:R29) -> 237133.34 | S30: =IF(R30=0,0,(R30*100/R$19)) -> 2.4092553
J31: O T H E R E X P E N S E S
A32: =Front!A72 -> 227068.56 | B32: =IF(A32=0,0,(A32*100/A$19)) -> 2.7270842 | C32: =Front!C72 -> -30605.31 | D32: =IF(C32=0,0,(C32*100/C$19)) -> 0.35341336 | E32: =Front!E72 -> 0 | F32: =IF(E32=0,0,(E32*100/E$19)) -> 0 | G32: ='Sum Room'!G72 -> 1005211.1 | H32: =IF(G32=0,0,(G32*100/G$19)) -> 11.607628 | J32: Rooms | L32: =Front!L72 -> 30605.31 | M32: =IF(L32=0,0,(L32*100/L$19)) -> 0.29925866 | N32: =Front!N72 -> 0 | O32: =IF(N32=0,0,(N32*100/N$19)) -> 0 | P32: =Front!P72 -> -30605.31 | Q32: =IF(P32=0,0,(P32*100/P$19)) -> 0.29925866 | R32: =Front!R72 -> 227068.56 | S32: =IF(R32=0,0,(R32*100/R$19)) -> 2.3069979
A33: ='F&B'!A77 -> 29066.17 | B33: =IF(A33=0,0,(A33*100/A$19)) -> 0.34908353 | C33: ='F&B'!C77 -> -73088.92 | D33: =IF(C33=0,0,(C33*100/C$19)) -> 0.84399083 | E33: ='F&B'!E77 -> 0 | F33: =IF(E33=0,0,(E33*100/E$19)) -> 0 | G33: ='F&B'!G77 -> 73088.92 | H33: =IF(G33=0,0,(G33*100/G$19)) -> 0.84399083 | J33: Food & Beverage | L33: ='F&B'!L77 -> 73088.92 | M33: =IF(L33=0,0,(L33*100/L$19)) -> 0.71466332 | N33: ='F&B'!N77 -> 0 | O33: =IF(N33=0,0,(N33*100/N$19)) -> 0 | P33: ='F&B'!P77 -> -73088.92 | Q33: =IF(P33=0,0,(P33*100/P$19)) -> 0.71466332 | R33: ='F&B'!R77 -> 29066.17 | S33: =IF(R33=0,0,(R33*100/R$19)) -> 0.2953099
A34: ='Spa & Fitness'!A60 -> 0 | B34: =IF(A34=0,0,(A34*100/A$19)) -> 0 | C34: ='Spa & Fitness'!C60 -> 0 | D34: =IF(C34=0,0,(C34*100/C$19)) -> 0 | E34: ='Spa & Fitness'!E60 -> 0 | F34: =IF(E34=0,0,(E34*100/E$19)) -> 0 | G34: ='Spa & Fitness'!G60 -> 0 | H34: =IF(G34=0,0,(G34*100/G$19)) -> 0 | J34: Spa & Fitness Center | L34: ='Spa & Fitness'!L60 -> 0 | M34: =IF(L34=0,0,(L34*100/L$19)) -> 0 | N34: ='Spa & Fitness'!N60 -> 0 | O34: =IF(N34=0,0,(N34*100/N$19)) -> 0 | P34: ='Spa & Fitness'!P60 -> 0 | Q34: =IF(P34=0,0,(P34*100/P$19)) -> 0 | R34: ='Spa & Fitness'!R60 -> 0 | S34: =IF(R34=0,0,(R34*100/R$19)) -> 0
A35: =OOD!A58 -> 0 | B35: =IF(A35=0,0,(A35*100/A$19)) -> 0 | C35: =OOD!C58 -> 0 | D35: =IF(C35=0,0,(C35*100/C$19)) -> 0 | E35: =OOD!E58 -> 0 | F35: =IF(E35=0,0,(E35*100/E$19)) -> 0 | G35: =OOD!G58 -> 0 | H35: =IF(G35=0,0,(G35*100/G$19)) -> 0 | J35: Other Operated Departments | L35: =OOD!L58 -> 0 | M35: =IF(L35=0,0,(L35*100/L$19)) -> 0 | N35: =OOD!N58 -> 0 | O35: =IF(N35=0,0,(N35*100/N$19)) -> 0 | P35: =OOD!P58 -> 0 | Q35: =IF(P35=0,0,(P35*100/P$19)) -> 0 | R35: =OOD!R58 -> 0 | S35: =IF(R35=0,0,(R35*100/R$19)) -> 0
A36: =SUM(A32:A35) -> 256134.73 | B36: =IF(A36=0,0,(A36*100/A$19)) -> 3.0761678 | C36: =SUM(C32:C35) -> -103694.23 | D36: =IF(C36=0,0,(C36*100/C$19)) -> 1.1974042 | E36: =SUM(E32:E35) -> 0 | F36: =IF(E36=0,0,(E36*100/E$19)) -> 0 | G36: =SUM(G32:G35) -> 1078300 | H36: =IF(G36=0,0,(G36*100/G$19)) -> 12.451618 | J36: TOTALOTHER EXPENSES | L36: =SUM(L32:L35) -> 103694.23 | M36: =IF(L36=0,0,(L36*100/L$19)) -> 1.013922 | N36: =SUM(N32:N35) -> 0 | O36: =IF(N36=0,0,(N36*100/N$19)) -> 0 | P36: =SUM(P32:P35) -> -103694.23 | Q36: =IF(P36=0,0,(P36*100/P$19)) -> 1.013922 | R36: =SUM(R32:R35) -> 256134.73 | S36: =IF(R36=0,0,(R36*100/R$19)) -> 2.6023078
A37: =+A24+A30+A36 -> 797441.58 | B37: =IF(A37=0,0,(A37*100/A$19)) -> 9.5772412 | C37: =+C24+C30+C36 -> -563481.81 | D37: =IF(C37=0,0,(C37*100/C$19)) -> 6.5067794 | E37: =+E24+E30+E36 -> 0 | F37: =IF(E37=0,0,(E37*100/E$19)) -> 0 | G37: =+G24+G30+G36 -> 1689627.3 | H37: =IF(G37=0,0,(G37*100/G$19)) -> 19.510891 | J37: TOTAL DEPARTMENT EXPENSES | L37: =+L24+L30+L36 -> 563481.81 | M37: =IF(L37=0,0,(L37*100/L$19)) -> 5.5097241 | N37: =+N24+N30+N36 -> 0 | O37: =IF(N37=0,0,(N37*100/N$19)) -> 0 | P37: =+P24+P30+P36 -> -563481.81 | Q37: =IF(P37=0,0,(P37*100/P$19)) -> 5.5097241 | R37: =+L37-P37 -> 1126963.6 | S37: =IF(R37=0,0,(R37*100/R$19)) -> 11.449858
J38: DEPARTMENT PROFIT (LOSS)
A39: =+A15-A26-A32 -> 6889317.4 | B39: =IF(A39=0,0,(A39*100/A$19)) -> 82.740424 | C39: =+C15-C26-C32 -> -7753760.1 | D39: =IF(C39=0,0,(C39*100/C$19)) -> 89.536176 | E39: =+E15-E26-E32 -> 0 | F39: =IF(E39=0,0,(E39*100/E$19)) -> 0 | G39: =+G15-G26-G32 -> 6627614.6 | H39: =IF(G39=0,0,(G39*100/G$19)) -> 76.532065 | J39: Rooms | L39: =+L15-L26-L32 -> 7753760.1 | M39: =IF(L39=0,0,(L39*100/L$19)) -> 75.816251 | N39: =+N15-N26-N32 -> 0 | O39: =IF(N39=0,0,(N39*100/N$19)) -> 0 | P39: =+P15-P26-P32 -> -7753760.1 | Q39: =IF(P39=0,0,(P39*100/P$19)) -> 75.816251 | R39: =+R15-R26-R32 -> 6889317.4 | S39: =IF(R39=0,0,(R39*100/R$19)) -> 69.9949
A40: =+A16-A21-A27-A33 -> 412739.6 | B40: =IF(A40=0,0,(A40*100/A$19)) -> 4.9569859 | C40: =+C16-C21-C27-C33 -> -169941.19 | D40: =IF(C40=0,0,(C40*100/C$19)) -> 1.9623878 | E40: =+E16-E21-E27-E33 -> 0 | F40: =IF(E40=0,0,(E40*100/E$19)) -> 0 | G40: =+G16-G21-G27-G33 -> 169941.19 | H40: =IF(G40=0,0,(G40*100/G$19)) -> 1.9623878 | J40: Food & Beverage | L40: =+L16-L21-L27-L33 -> 1737064.7 | M40: =IF(L40=0,0,(L40*100/L$19)) -> 16.985016 | N40: =+N16-N21-N27-N33 -> 0 | O40: =IF(N40=0,0,(N40*100/N$19)) -> 0 | P40: =+P16-P21-P27-P33 -> -1737064.7 | Q40: =IF(P40=0,0,(P40*100/P$19)) -> 16.985016 | R40: =+R16-R21-R27-R33 -> 1928916.1 | S40: =IF(R40=0,0,(R40*100/R$19)) -> 19.59763
A41: =+A17-A22-A28-A34 -> 31848.41 | B41: =IF(A41=0,0,(A41*100/A$19)) -> 0.38249812 | C41: =+C17-C22-C28-C34 -> -424.81 | D41: =IF(C41=0,0,(C41*100/C$19)) -> 0.0049054733 | E41: =+E17-E22-E28-E34 -> 0 | F41: =IF(E41=0,0,(E41*100/E$19)) -> 0 | G41: =+G17-G22-G28-G34 -> 424.81 | H41: =IF(G41=0,0,(G41*100/G$19)) -> 0.0049054733 | J41: Spa & Fitness Center | L41: =+L17-L22-L28-L34 -> 424.81 | M41: =IF(L41=0,0,(L41*100/L$19)) -> 0.0041537914 | N41: =+N17-N22-N28-N34 -> 0 | O41: =IF(N41=0,0,(N41*100/N$19)) -> 0 | P41: =+P17-P22-P28-P34 -> -424.81 | Q41: =IF(P41=0,0,(P41*100/P$19)) -> 0.0041537914 | R41: =+R17-R22-R28-R34 -> 31848.41 | S41: =IF(R41=0,0,(R41*100/R$19)) -> 0.32357723
A42: =+A18-A23-A29-A35 -> 195075.65 | B42: =IF(A42=0,0,(A42*100/A$19)) -> 2.3428507 | C42: =+C18-C23-C29-C35 -> -172310.85 | D42: =IF(C42=0,0,(C42*100/C$19)) -> 1.9897513 | E42: =+E18-E23-E29-E35 -> 0 | F42: =IF(E42=0,0,(E42*100/E$19)) -> 0 | G42: =+G18-G23-G29-G35 -> 172310.85 | H42: =IF(G42=0,0,(G42*100/G$19)) -> 1.9897513 | J42: Other Operated Departments | L42: =+L18-L23-L29-L35 -> 172310.85 | M42: =IF(L42=0,0,(L42*100/L$19)) -> 1.6848552 | N42: =+N18-N23-N29-N35 -> 0 | O42: =IF(N42=0,0,(N42*100/N$19)) -> 0 | P42: =+P18-P23-P29-P35 -> -172310.85 | Q42: =IF(P42=0,0,(P42*100/P$19)) -> 1.6848552 | R42: =+R18-R23-R29-R35 -> 195075.65 | S42: =IF(R42=0,0,(R42*100/R$19)) -> 1.9819526
A43: =SUM(A39:A42) -> 7528981.1 | B43: =IF(A43=0,0,(A43*100/A$19)) -> 90.422759 | C43: =SUM(C39:C42) -> -8096436.9 | D43: =IF(C43=0,0,(C43*100/C$19)) -> 93.493221 | E43: =SUM(E39:E42) -> 0 | F43: =IF(E43=0,0,(E43*100/E$19)) -> 0 | G43: =SUM(G39:G42) -> 6970291.5 | H43: =IF(G43=0,0,(G43*100/G$19)) -> 80.489109 | J43: TOTAL DEPT. PROFIT (LOSS) | L43: =SUM(L39:L42) -> 9663560.5 | M43: =IF(L43=0,0,(L43*100/L$19)) -> 94.490276 | N43: =SUM(N39:N42) -> 0 | O43: =IF(N43=0,0,(N43*100/N$19)) -> 0 | P43: =SUM(P39:P42) -> -9663560.5 | Q43: =IF(P43=0,0,(P43*100/P$19)) -> 94.490276 | R43: =SUM(R39:R42) -> 9045157.6 | S43: =IF(R43=0,0,(R43*100/R$19)) -> 91.898059
J45: OVERHEAD DEPARTMENTS
J46: PAYROLL & EMPLOYEE RELATION
A47: =Admin!A21 -> 820126.48 | B47: =IF(A47=0,0,(A47*100/A$19)) -> 9.8496859 | C47: =Admin!C21 -> -434550.97 | D47: =IF(C47=0,0,(C47*100/C$19)) -> 5.0179567 | E47: =Admin!E21 -> 0 | F47: =IF(E47=0,0,(E47*100/E$19)) -> 0 | G47: =Admin!G21 -> 434550.97 | H47: =IF(G47=0,0,(G47*100/G$19)) -> 5.0179567 | J47: Administrative And General | L47: =Admin!L21 -> 434550.97 | M47: =IF(L47=0,0,(L47*100/L$19)) -> 4.2490386 | N47: =Admin!N21 -> 0 | O47: =IF(N47=0,0,(N47*100/N$19)) -> 0 | P47: =Admin!P21 -> -434550.97 | Q47: =IF(P47=0,0,(P47*100/P$19)) -> 4.2490386 | R47: =Admin!R21 -> 820126.48 | S47: =IF(R47=0,0,(R47*100/R$19)) -> 8.3324177
A48: =Marketing!A16 -> 115000 | B48: =IF(A48=0,0,(A48*100/A$19)) -> 1.3811454 | C48: =Marketing!C16 -> -99750 | D48: =IF(C48=0,0,(C48*100/C$19)) -> 1.1518584 | E48: =Marketing!E16 -> 0 | F48: =IF(E48=0,0,(E48*100/E$19)) -> 0 | G48: =Marketing!G16 -> 99750 | H48: =IF(G48=0,0,(G48*100/G$19)) -> 1.1518584 | J48: Sales & Marketing | L48: =Marketing!L16 -> 99750 | M48: =IF(L48=0,0,(L48*100/L$19)) -> 0.97535531 | N48: =Marketing!N16 -> 0 | O48: =IF(N48=0,0,(N48*100/N$19)) -> 0 | P48: =Marketing!P16 -> -99750 | Q48: =IF(P48=0,0,(P48*100/P$19)) -> 0.97535531 | R48: =Marketing!R16 -> 115000 | S48: =IF(R48=0,0,(R48*100/R$19)) -> 1.1683906
A49: =POMEC!A16 -> 71550 | B49: =IF(A49=0,0,(A49*100/A$19)) -> 0.85931261 | C49: =POMEC!C16 -> -48775 | D49: =IF(C49=0,0,(C49*100/C$19)) -> 0.56322699 | E49: =POMEC!E16 -> 0 | F49: =IF(E49=0,0,(E49*100/E$19)) -> 0 | G49: =POMEC!G16 -> 48775 | H49: =IF(G49=0,0,(G49*100/G$19)) -> 0.56322699 | J49: Property Operation, Maintenance | L49: =POMEC!L16 -> 48775 | M49: =IF(L49=0,0,(L49*100/L$19)) -> 0.47692186 | N49: =POMEC!N16 -> 0 | O49: =IF(N49=0,0,(N49*100/N$19)) -> 0 | P49: =POMEC!P16 -> -48775 | Q49: =IF(P49=0,0,(P49*100/P$19)) -> 0.47692186 | R49: =POMEC!R16 -> 71550 | S49: =IF(R49=0,0,(R49*100/R$19)) -> 0.72694213
A50: =SUM(A47:A49) -> 1006676.5 | B50: =IF(A50=0,0,(A50*100/A$19)) -> 12.090144 | C50: =SUM(C47:C49) -> -583075.97 | D50: =IF(C50=0,0,(C50*100/C$19)) -> 6.733042 | E50: =SUM(E47:E49) -> 0 | F50: =IF(E50=0,0,(E50*100/E$19)) -> 0 | G50: =SUM(G47:G49) -> 583075.97 | H50: =IF(G50=0,0,(G50*100/G$19)) -> 6.733042 | J50: TOTAL PAYROLL & EMP. REL. | L50: =SUM(L47:L49) -> 583075.97 | M50: =IF(L50=0,0,(L50*100/L$19)) -> 5.7013157 | N50: =SUM(N47:N49) -> 0 | O50: =IF(N50=0,0,(N50*100/N$19)) -> 0 | P50: =SUM(P47:P49) -> -583075.97 | Q50: =IF(P50=0,0,(P50*100/P$19)) -> 5.7013157 | R50: =SUM(R47:R49) -> 1006676.5 | S50: =IF(R50=0,0,(R50*100/R$19)) -> 10.22775
J51: O T H E R E X P E N S E S
A52: =Admin!A65 -> 894352.15 | B52: =IF(A52=0,0,(A52*100/A$19)) -> 10.741133 | C52: =Admin!C65 -> -1121799 | D52: =IF(C52=0,0,(C52*100/C$19)) -> 12.95392 | E52: =Admin!E65 -> 0 | F52: =IF(E52=0,0,(E52*100/E$19)) -> 0 | G52: =Admin!G65 -> 1121799 | H52: =IF(G52=0,0,(G52*100/G$19)) -> 12.95392 | J52: Administrative And General | L52: =Admin!L65 -> 1121799 | M52: =IF(L52=0,0,(L52*100/L$19)) -> 10.968948 | N52: =Admin!N65 -> 0 | O52: =IF(N52=0,0,(N52*100/N$19)) -> 0 | P52: =Admin!P65 -> -1121799 | Q52: =IF(P52=0,0,(P52*100/P$19)) -> 10.968948 | R52: =Admin!R65 -> 894352.15 | S52: =IF(R52=0,0,(R52*100/R$19)) -> 9.0865445
A53: =Marketing!A43 -> 63622.43 | B53: =IF(A53=0,0,(A53*100/A$19)) -> 0.76410282 | C53: =Marketing!C43 -> 0 | D53: =IF(C53=0,0,(C53*100/C$19)) -> 0 | E53: =Marketing!E43 -> 0 | F53: =IF(E53=0,0,(E53*100/E$19)) -> 0 | G53: =Marketing!G43 -> 0 | H53: =IF(G53=0,0,(G53*100/G$19)) -> 0 | J53: Sales & Marketing | L53: =Marketing!L43 -> 0 | M53: =IF(L53=0,0,(L53*100/L$19)) -> 0 | N53: =Marketing!N43 -> 0 | O53: =IF(N53=0,0,(N53*100/N$19)) -> 0 | P53: =Marketing!P43 -> 0 | Q53: =IF(P53=0,0,(P53*100/P$19)) -> 0 | R53: =Marketing!R43 -> 63622.43 | S53: =IF(R53=0,0,(R53*100/R$19)) -> 0.64639867
A54: =POMEC!A59 -> 34304.64 | B54: =IF(A54=0,0,(A54*100/A$19)) -> 0.41199734 | C54: =POMEC!C59 -> -23013.31 | D54: =IF(C54=0,0,(C54*100/C$19)) -> 0.2657451 | E54: =POMEC!E59 -> 0 | F54: =IF(E54=0,0,(E54*100/E$19)) -> 0 | G54: =POMEC!G59 -> 23013.31 | H54: =IF(G54=0,0,(G54*100/G$19)) -> 0.2657451 | J54: Property Operation, Maintenance | L54: =POMEC!L59 -> 23013.31 | M54: =IF(L54=0,0,(L54*100/L$19)) -> 0.2250241 | N54: =POMEC!N59 -> 0 | O54: =IF(N54=0,0,(N54*100/N$19)) -> 0 | P54: =POMEC!P59 -> -23013.31 | Q54: =IF(P54=0,0,(P54*100/P$19)) -> 0.2250241 | R54: =POMEC!R59 -> 34304.64 | S54: =IF(R54=0,0,(R54*100/R$19)) -> 0.34853233
A55: =POMEC!A68 -> 360406.4 | B55: =IF(A55=0,0,(A55*100/A$19)) -> 4.3284663 | C55: =POMEC!C68 -> -379370.11 | D55: =IF(C55=0,0,(C55*100/C$19)) -> 4.3807583 | E55: =POMEC!E68 -> 0 | F55: =IF(E55=0,0,(E55*100/E$19)) -> 0 | G55: =POMEC!G68 -> 379370.11 | H55: =IF(G55=0,0,(G55*100/G$19)) -> 4.3807583 | J55: Energy Cost | L55: =POMEC!L68 -> 379370.11 | M55: =IF(L55=0,0,(L55*100/L$19)) -> 3.7094802 | N55: =POMEC!N68 -> 0 | O55: =IF(N55=0,0,(N55*100/N$19)) -> 0 | P55: =POMEC!P68 -> -379370.11 | Q55: =IF(P55=0,0,(P55*100/P$19)) -> 3.7094802 | R55: =POMEC!R68 -> 360406.4 | S55: =IF(R55=0,0,(R55*100/R$19)) -> 3.6616994
A56: =SUM(A52:A55) -> 1352685.6 | B56: =IF(A56=0,0,(A56*100/A$19)) -> 16.2457 | C56: =SUM(C52:C55) -> -1524182.4 | D56: =IF(C56=0,0,(C56*100/C$19)) -> 17.600424 | E56: =SUM(E52:E55) -> 0 | F56: =IF(E56=0,0,(E56*100/E$19)) -> 0 | G56: =SUM(G52:G55) -> 1524182.4 | H56: =IF(G56=0,0,(G56*100/G$19)) -> 17.600424 | J56: TOTAL OTHER EXPENSES | L56: =SUM(L52:L55) -> 1524182.4 | M56: =IF(L56=0,0,(L56*100/L$19)) -> 14.903453 | N56: =SUM(N52:N55) -> 0 | O56: =IF(N56=0,0,(N56*100/N$19)) -> 0 | P56: =SUM(P52:P55) -> -1524182.4 | Q56: =IF(P56=0,0,(P56*100/P$19)) -> 14.903453 | R56: =SUM(R52:R55) -> 1352685.6 | S56: =IF(R56=0,0,(R56*100/R$19)) -> 13.743175
A57: =+A50+A56 -> 2359362.1 | B57: =IF(A57=0,0,(A57*100/A$19)) -> 28.335844 | C57: =+C50+C56 -> -2107258.4 | D57: =IF(C57=0,0,(C57*100/C$19)) -> 24.333466 | E57: =+E50+E56 -> 0 | F57: =IF(E57=0,0,(E57*100/E$19)) -> 0 | G57: =+G50+G56 -> 2107258.4 | H57: =IF(G57=0,0,(G57*100/G$19)) -> 24.333466 | J57: TOTAL OVERHEAD DEPT. | L57: =+L50+L56 -> 2107258.4 | M57: =IF(L57=0,0,(L57*100/L$19)) -> 20.604768 | N57: =+N50+N56 -> 0 | O57: =IF(N57=0,0,(N57*100/N$19)) -> 0 | P57: =+P50+P56 -> -2107258.4 | Q57: =IF(P57=0,0,(P57*100/P$19)) -> 20.604768 | R57: =+R50+R56 -> 2359362.1 | S57: =IF(R57=0,0,(R57*100/R$19)) -> 23.970925
A58: =+A43-A57 -> 5169619 | B58: =IF(A58=0,0,(A58*100/A$19)) -> 62.086915 | C58: =+C43-C57 -> -5989178.6 | D58: =IF(C58=0,0,(C58*100/C$19)) -> 69.159755 | E58: =+E43-E57 -> 0 | F58: =IF(E58=0,0,(E58*100/E$19)) -> 0 | G58: =+G43-G57 -> 4863033.1 | H58: =IF(G58=0,0,(G58*100/G$19)) -> 56.155643 | J58: HOUSE PROFIT | L58: =+L43-L57 -> 7556302.1 | M58: =IF(L58=0,0,(L58*100/L$19)) -> 73.885508 | N58: =+N43-N57 -> 0 | O58: =IF(N58=0,0,(N58*100/N$19)) -> 0 | P58: =+P43-P57 -> -7556302.1 | Q58: =IF(P58=0,0,(P58*100/P$19)) -> 73.885508 | R58: =+R43-R57 -> 6685795.5 | S58: =IF(R58=0,0,(R58*100/R$19)) -> 67.927134
A59: {=_xll.AC(DB,_xll.ArrayDPT($AA59:$AE59),_xll.ArrayCOA($AG59:$BR59),YR-1,PRD,_xll.ArrayDIM($BT59:$BW59))} -> 0 | B59: =IF(A59=0,0,(A59*100/A$19)) -> 0 | C59: =+E59-G59 -> 0 | D59: =IF(C59=0,0,(C59*100/C$19)) -> 0 | E59: {=_xll.BC(DB,_xll.ArrayDPT($AA59:$AE59),_xll.ArrayCOA($AG59:$BR59),YR,PRD,RV,_xll.ArrayDIM($BT59:$BW59))} -> 0 | F59: =IF(E59=0,0,(E59*100/E$19)) -> 0 | G59: {=_xll.AC(DB,_xll.ArrayDPT($AA59:$AE59),_xll.ArrayCOA($AG59:$BR59),YR,PRD,_xll.ArrayDIM($BT59:$BW59))} -> 0 | H59: =IF(G59=0,0,(G59*100/G$19)) -> 0 | J59: Basic Management Fee | L59: {=_xll.ACC(DB,_xll.ArrayDPT($AA59:$AE59),_xll.ArrayCOA($AG59:$BR59),YR,PRD,_xll.ArrayDIM($BT59:$BW59))} -> 0 | M59: =IF(L59=0,0,(L59*100/L$19)) -> 0 | N59: {=_xll.BCC(DB,_xll.ArrayDPT($AA59:$AE59),_xll.ArrayCOA($AG59:$BR59),YR,PRD,RV,_xll.ArrayDIM($BT59:$BW59))} -> 0 | O59: =IF(N59=0,0,(N59*100/N$19)) -> 0 | P59: =+N59-L59 -> 0 | Q59: =IF(P59=0,0,(P59*100/P$19)) -> 0 | R59: {=_xll.ACC(DB,_xll.ArrayDPT($AA59:$AE59),_xll.ArrayCOA($AG59:$BR59),YR-1,PRD,_xll.ArrayDIM($BT59:$BW59))} -> 0 | S59: =IF(R59=0,0,(R59*100/R$19)) -> 0 | AA59: 600 | AG59: 60000 | AH59: 60000
A60: {=_xll.AC(DB,_xll.ArrayDPT($AA60:$AE60),_xll.ArrayCOA($AG60:$BR60),YR-1,PRD,_xll.ArrayDIM($BT60:$BW60))} -> 0 | B60: =IF(A60=0,0,(A60*100/A$19)) -> 0 | C60: =+E60-G60 -> -384990.31 | D60: =IF(C60=0,0,(C60*100/C$19)) -> 4.4456573 | E60: {=_xll.BC(DB,_xll.ArrayDPT($AA60:$AE60),_xll.ArrayCOA($AG60:$BR60),YR,PRD,RV,_xll.ArrayDIM($BT60:$BW60))} -> 0 | F60: =IF(E60=0,0,(E60*100/E$19)) -> 0 | G60: {=_xll.AC(DB,_xll.ArrayDPT($AA60:$AE60),_xll.ArrayCOA($AG60:$BR60),YR,PRD,_xll.ArrayDIM($BT60:$BW60))} -> 384990.31 | H60: =IF(G60=0,0,(G60*100/G$19)) -> 4.4456573 | J60: Basic Fee / Royalty | L60: {=_xll.ACC(DB,_xll.ArrayDPT($AA60:$AE60),_xll.ArrayCOA($AG60:$BR60),YR,PRD,_xll.ArrayDIM($BT60:$BW60))} -> 384990.31 | M60: =IF(L60=0,0,(L60*100/L$19)) -> 3.7644345 | N60: {=_xll.BCC(DB,_xll.ArrayDPT($AA60:$AE60),_xll.ArrayCOA($AG60:$BR60),YR,PRD,RV,_xll.ArrayDIM($BT60:$BW60))} -> 0 | O60: =IF(N60=0,0,(N60*100/N$19)) -> 0 | P60: =+N60-L60 -> -384990.31 | Q60: =IF(P60=0,0,(P60*100/P$19)) -> 3.7644345 | R60: {=_xll.ACC(DB,_xll.ArrayDPT($AA60:$AE60),_xll.ArrayCOA($AG60:$BR60),YR-1,PRD,_xll.ArrayDIM($BT60:$BW60))} -> 0 | S60: =IF(R60=0,0,(R60*100/R$19)) -> 0 | AA60: 600 | AB60: 800 | AG60: 60005 | AH60: 60005
A61: {=_xll.AC(DB,_xll.ArrayDPT($AA61:$AE61),_xll.ArrayCOA($AG61:$BR61),YR-1,PRD,_xll.ArrayDIM($BT61:$BW61))} -> 0 | B61: =IF(A61=0,0,(A61*100/A$19)) -> 0 | C61: =+E61-G61 -> 0 | D61: =IF(C61=0,0,(C61*100/C$19)) -> 0 | E61: {=_xll.BC(DB,_xll.ArrayDPT($AA61:$AE61),_xll.ArrayCOA($AG61:$BR61),YR,PRD,RV,_xll.ArrayDIM($BT61:$BW61))} -> 0 | F61: =IF(E61=0,0,(E61*100/E$19)) -> 0 | G61: {=_xll.AC(DB,_xll.ArrayDPT($AA61:$AE61),_xll.ArrayCOA($AG61:$BR61),YR,PRD,_xll.ArrayDIM($BT61:$BW61))} -> 0 | H61: =IF(G61=0,0,(G61*100/G$19)) -> 0 | J61: Incentive Fee | L61: {=_xll.ACC(DB,_xll.ArrayDPT($AA61:$AE61),_xll.ArrayCOA($AG61:$BR61),YR,PRD,_xll.ArrayDIM($BT61:$BW61))} -> 0 | M61: =IF(L61=0,0,(L61*100/L$19)) -> 0 | N61: {=_xll.BCC(DB,_xll.ArrayDPT($AA61:$AE61),_xll.ArrayCOA($AG61:$BR61),YR,PRD,RV,_xll.ArrayDIM($BT61:$BW61))} -> 0 | O61: =IF(N61=0,0,(N61*100/N$19)) -> 0 | P61: =+N61-L61 -> 0 | Q61: =IF(P61=0,0,(P61*100/P$19)) -> 0 | R61: {=_xll.ACC(DB,_xll.ArrayDPT($AA61:$AE61),_xll.ArrayCOA($AG61:$BR61),YR-1,PRD,_xll.ArrayDIM($BT61:$BW61))} -> 0 | S61: =IF(R61=0,0,(R61*100/R$19)) -> 0 | AA61: 600 | AG61: 60010 | AH61: 60010
A62: =+A58-A59-A60-A61 -> 5169619 | B62: =IF(A62=0,0,(A62*100/A$19)) -> 62.086915 | C62: =+C58-C59-C60-C61 -> -5604188.3 | D62: =IF(C62=0,0,(C62*100/C$19)) -> 64.714097 | E62: =+E58-E59-E60-E61 -> 0 | F62: =IF(E62=0,0,(E62*100/E$19)) -> 0 | G62: =+G58-G59-G60-G61 -> 4478042.8 | H62: =IF(G62=0,0,(G62*100/G$19)) -> 51.709986 | J62: GROSS OPERATING PROFIT | L62: =+L58-L59-L60-L61 -> 7171311.8 | M62: =IF(L62=0,0,(L62*100/L$19)) -> 70.121073 | N62: =+N58-N59-N60-N61 -> 0 | O62: =IF(N62=0,0,(N62*100/N$19)) -> 0 | P62: =+P58-P59-P60-P61 -> -7171311.8 | Q62: =IF(P62=0,0,(P62*100/P$19)) -> 70.121073 | R62: =+R58-R59-R60-R61 -> 6685795.5 | S62: =IF(R62=0,0,(R62*100/R$19)) -> 67.927134
A63: {=_xll.AC(DB,_xll.ArrayDPT($AA63:$AE63),_xll.ArrayCOA($AG63:$BR63),YR-1,PRD,_xll.ArrayDIM($BT63:$BW63))} -> 0 | B63: =IF(A63=0,0,(A63*100/A$19)) -> 0 | C63: =+E63-G63 -> 0 | D63: =IF(C63=0,0,(C63*100/C$19)) -> 0 | E63: {=_xll.BC(DB,_xll.ArrayDPT($AA63:$AE63),_xll.ArrayCOA($AG63:$BR63),YR,PRD,RV,_xll.ArrayDIM($BT63:$BW63))} -> 0 | F63: =IF(E63=0,0,(E63*100/E$19)) -> 0 | G63: {=_xll.AC(DB,_xll.ArrayDPT($AA63:$AE63),_xll.ArrayCOA($AG63:$BR63),YR,PRD,_xll.ArrayDIM($BT63:$BW63))} -> 0 | H63: =IF(G63=0,0,(G63*100/G$19)) -> 0 | J63: Other Non Operating Exp. | L63: {=_xll.ACC(DB,_xll.ArrayDPT($AA63:$AE63),_xll.ArrayCOA($AG63:$BR63),YR,PRD,_xll.ArrayDIM($BT63:$BW63))} -> 0 | M63: =IF(L63=0,0,(L63*100/L$19)) -> 0 | N63: {=_xll.BCC(DB,_xll.ArrayDPT($AA63:$AE63),_xll.ArrayCOA($AG63:$BR63),YR,PRD,RV,_xll.ArrayDIM($BT63:$BW63))} -> 0 | O63: =IF(N63=0,0,(N63*100/N$19)) -> 0 | P63: =+N63-L63 -> 0 | Q63: =IF(P63=0,0,(P63*100/P$19)) -> 0 | R63: {=_xll.ACC(DB,_xll.ArrayDPT($AA63:$AE63),_xll.ArrayCOA($AG63:$BR63),YR-1,PRD,_xll.ArrayDIM($BT63:$BW63))} -> 0 | S63: =IF(R63=0,0,(R63*100/R$19)) -> 0
A64: {=_xll.AC(DB,_xll.ArrayDPT($AA64:$AE64),_xll.ArrayCOA($AG64:$BR64),YR-1,PRD,_xll.ArrayDIM($BT64:$BW64))} -> 0 | B64: =IF(A64=0,0,(A64*100/A$19)) -> 0 | C64: =+E64-G64 -> 0 | D64: =IF(C64=0,0,(C64*100/C$19)) -> 0 | E64: {=_xll.BC(DB,_xll.ArrayDPT($AA64:$AE64),_xll.ArrayCOA($AG64:$BR64),YR,PRD,RV,_xll.ArrayDIM($BT64:$BW64))} -> 0 | F64: =IF(E64=0,0,(E64*100/E$19)) -> 0 | G64: {=_xll.AC(DB,_xll.ArrayDPT($AA64:$AE64),_xll.ArrayCOA($AG64:$BR64),YR,PRD,_xll.ArrayDIM($BT64:$BW64))} -> 0 | H64: =IF(G64=0,0,(G64*100/G$19)) -> 0 | J64: Property Taxes | L64: {=_xll.ACC(DB,_xll.ArrayDPT($AA64:$AE64),_xll.ArrayCOA($AG64:$BR64),YR,PRD,_xll.ArrayDIM($BT64:$BW64))} -> 0 | M64: =IF(L64=0,0,(L64*100/L$19)) -> 0 | N64: {=_xll.BCC(DB,_xll.ArrayDPT($AA64:$AE64),_xll.ArrayCOA($AG64:$BR64),YR,PRD,RV,_xll.ArrayDIM($BT64:$BW64))} -> 0 | O64: =IF(N64=0,0,(N64*100/N$19)) -> 0 | P64: =+N64-L64 -> 0 | Q64: =IF(P64=0,0,(P64*100/P$19)) -> 0 | R64: {=_xll.ACC(DB,_xll.ArrayDPT($AA64:$AE64),_xll.ArrayCOA($AG64:$BR64),YR-1,PRD,_xll.ArrayDIM($BT64:$BW64))} -> 0 | S64: =IF(R64=0,0,(R64*100/R$19)) -> 0 | AA64: 800 | AG64: 61110 | AH64: 61110
A65: {=_xll.AC(DB,_xll.ArrayDPT($AA65:$AE65),_xll.ArrayCOA($AG65:$BR65),YR-1,PRD,_xll.ArrayDIM($BT65:$BW65))} -> 0 | B65: =IF(A65=0,0,(A65*100/A$19)) -> 0 | C65: =+E65-G65 -> 0 | D65: =IF(C65=0,0,(C65*100/C$19)) -> 0 | E65: {=_xll.BC(DB,_xll.ArrayDPT($AA65:$AE65),_xll.ArrayCOA($AG65:$BR65),YR,PRD,RV,_xll.ArrayDIM($BT65:$BW65))} -> 0 | F65: =IF(E65=0,0,(E65*100/E$19)) -> 0 | G65: {=_xll.AC(DB,_xll.ArrayDPT($AA65:$AE65),_xll.ArrayCOA($AG65:$BR65),YR,PRD,_xll.ArrayDIM($BT65:$BW65))} -> 0 | H65: =IF(G65=0,0,(G65*100/G$19)) -> 0 | J65: Land Taxes & Sign Taxes | L65: {=_xll.ACC(DB,_xll.ArrayDPT($AA65:$AE65),_xll.ArrayCOA($AG65:$BR65),YR,PRD,_xll.ArrayDIM($BT65:$BW65))} -> 0 | M65: =IF(L65=0,0,(L65*100/L$19)) -> 0 | N65: {=_xll.BCC(DB,_xll.ArrayDPT($AA65:$AE65),_xll.ArrayCOA($AG65:$BR65),YR,PRD,RV,_xll.ArrayDIM($BT65:$BW65))} -> 0 | O65: =IF(N65=0,0,(N65*100/N$19)) -> 0 | P65: =+N65-L65 -> 0 | Q65: =IF(P65=0,0,(P65*100/P$19)) -> 0 | R65: {=_xll.ACC(DB,_xll.ArrayDPT($AA65:$AE65),_xll.ArrayCOA($AG65:$BR65),YR-1,PRD,_xll.ArrayDIM($BT65:$BW65))} -> 0 | S65: =IF(R65=0,0,(R65*100/R$19)) -> 0 | AA65: 800 | AG65: 61115 | AH65: 61115
A66: {=_xll.AC(DB,_xll.ArrayDPT($AA66:$AE66),_xll.ArrayCOA($AG66:$BR66),YR-1,PRD,_xll.ArrayDIM($BT66:$BW66))} -> 0 | B66: =IF(A66=0,0,(A66*100/A$19)) -> 0 | C66: =+E66-G66 -> 0 | D66: =IF(C66=0,0,(C66*100/C$19)) -> 0 | E66: {=_xll.BC(DB,_xll.ArrayDPT($AA66:$AE66),_xll.ArrayCOA($AG66:$BR66),YR,PRD,RV,_xll.ArrayDIM($BT66:$BW66))} -> 0 | F66: =IF(E66=0,0,(E66*100/E$19)) -> 0 | G66: {=_xll.AC(DB,_xll.ArrayDPT($AA66:$AE66),_xll.ArrayCOA($AG66:$BR66),YR,PRD,_xll.ArrayDIM($BT66:$BW66))} -> 0 | H66: =IF(G66=0,0,(G66*100/G$19)) -> 0 | J66: Special Business Tax | L66: {=_xll.ACC(DB,_xll.ArrayDPT($AA66:$AE66),_xll.ArrayCOA($AG66:$BR66),YR,PRD,_xll.ArrayDIM($BT66:$BW66))} -> 0 | M66: =IF(L66=0,0,(L66*100/L$19)) -> 0 | N66: {=_xll.BCC(DB,_xll.ArrayDPT($AA66:$AE66),_xll.ArrayCOA($AG66:$BR66),YR,PRD,RV,_xll.ArrayDIM($BT66:$BW66))} -> 0 | O66: =IF(N66=0,0,(N66*100/N$19)) -> 0 | P66: =+N66-L66 -> 0 | Q66: =IF(P66=0,0,(P66*100/P$19)) -> 0 | R66: {=_xll.ACC(DB,_xll.ArrayDPT($AA66:$AE66),_xll.ArrayCOA($AG66:$BR66),YR-1,PRD,_xll.ArrayDIM($BT66:$BW66))} -> 0 | S66: =IF(R66=0,0,(R66*100/R$19)) -> 0
A67: {=_xll.AC(DB,_xll.ArrayDPT($AA67:$AE67),_xll.ArrayCOA($AG67:$BR67),YR-1,PRD,_xll.ArrayDIM($BT67:$BW67))} -> 0 | B67: =IF(A67=0,0,(A67*100/A$19)) -> 0 | C67: =+E67-G67 -> 0 | D67: =IF(C67=0,0,(C67*100/C$19)) -> 0 | E67: {=_xll.BC(DB,_xll.ArrayDPT($AA67:$AE67),_xll.ArrayCOA($AG67:$BR67),YR,PRD,RV,_xll.ArrayDIM($BT67:$BW67))} -> 0 | F67: =IF(E67=0,0,(E67*100/E$19)) -> 0 | G67: {=_xll.AC(DB,_xll.ArrayDPT($AA67:$AE67),_xll.ArrayCOA($AG67:$BR67),YR,PRD,_xll.ArrayDIM($BT67:$BW67))} -> 0 | H67: =IF(G67=0,0,(G67*100/G$19)) -> 0 | J67: Other Taxs | L67: {=_xll.ACC(DB,_xll.ArrayDPT($AA67:$AE67),_xll.ArrayCOA($AG67:$BR67),YR,PRD,_xll.ArrayDIM($BT67:$BW67))} -> 0 | M67: =IF(L67=0,0,(L67*100/L$19)) -> 0 | N67: {=_xll.BCC(DB,_xll.ArrayDPT($AA67:$AE67),_xll.ArrayCOA($AG67:$BR67),YR,PRD,RV,_xll.ArrayDIM($BT67:$BW67))} -> 0 | O67: =IF(N67=0,0,(N67*100/N$19)) -> 0 | P67: =+N67-L67 -> 0 | Q67: =IF(P67=0,0,(P67*100/P$19)) -> 0 | R67: {=_xll.ACC(DB,_xll.ArrayDPT($AA67:$AE67),_xll.ArrayCOA($AG67:$BR67),YR-1,PRD,_xll.ArrayDIM($BT67:$BW67))} -> 0 | S67: =IF(R67=0,0,(R67*100/R$19)) -> 0 | AA67: 800 | AG67: 61130 | AH67: 61130
A68: {=_xll.AC(DB,_xll.ArrayDPT($AA68:$AE68),_xll.ArrayCOA($AG68:$BR68),YR-1,PRD,_xll.ArrayDIM($BT68:$BW68))} -> 0 | B68: =IF(A68=0,0,(A68*100/A$19)) -> 0 | C68: =+E68-G68 -> 0 | D68: =IF(C68=0,0,(C68*100/C$19)) -> 0 | E68: {=_xll.BC(DB,_xll.ArrayDPT($AA68:$AE68),_xll.ArrayCOA($AG68:$BR68),YR,PRD,RV,_xll.ArrayDIM($BT68:$BW68))} -> 0 | F68: =IF(E68=0,0,(E68*100/E$19)) -> 0 | G68: {=_xll.AC(DB,_xll.ArrayDPT($AA68:$AE68),_xll.ArrayCOA($AG68:$BR68),YR,PRD,_xll.ArrayDIM($BT68:$BW68))} -> 0 | H68: =IF(G68=0,0,(G68*100/G$19)) -> 0 | J68: Insurance Building Liabilty | L68: {=_xll.ACC(DB,_xll.ArrayDPT($AA68:$AE68),_xll.ArrayCOA($AG68:$BR68),YR,PRD,_xll.ArrayDIM($BT68:$BW68))} -> 0 | M68: =IF(L68=0,0,(L68*100/L$19)) -> 0 | N68: {=_xll.BCC(DB,_xll.ArrayDPT($AA68:$AE68),_xll.ArrayCOA($AG68:$BR68),YR,PRD,RV,_xll.ArrayDIM($BT68:$BW68))} -> 0 | O68: =IF(N68=0,0,(N68*100/N$19)) -> 0 | P68: =+N68-L68 -> 0 | Q68: =IF(P68=0,0,(P68*100/P$19)) -> 0 | R68: {=_xll.ACC(DB,_xll.ArrayDPT($AA68:$AE68),_xll.ArrayCOA($AG68:$BR68),YR-1,PRD,_xll.ArrayDIM($BT68:$BW68))} -> 0 | S68: =IF(R68=0,0,(R68*100/R$19)) -> 0 | AA68: 800
A69: {=_xll.AC(DB,_xll.ArrayDPT($AA69:$AE69),_xll.ArrayCOA($AG69:$BR69),YR-1,PRD,_xll.ArrayDIM($BT69:$BW69))} -> 0 | B69: =IF(A69=0,0,(A69*100/A$19)) -> 0 | C69: =+E69-G69 -> 0 | D69: =IF(C69=0,0,(C69*100/C$19)) -> 0 | E69: {=_xll.BC(DB,_xll.ArrayDPT($AA69:$AE69),_xll.ArrayCOA($AG69:$BR69),YR,PRD,RV,_xll.ArrayDIM($BT69:$BW69))} -> 0 | F69: =IF(E69=0,0,(E69*100/E$19)) -> 0 | G69: {=_xll.AC(DB,_xll.ArrayDPT($AA69:$AE69),_xll.ArrayCOA($AG69:$BR69),YR,PRD,_xll.ArrayDIM($BT69:$BW69))} -> 0 | H69: =IF(G69=0,0,(G69*100/G$19)) -> 0 | J69: Insurance Vehicle | L69: {=_xll.ACC(DB,_xll.ArrayDPT($AA69:$AE69),_xll.ArrayCOA($AG69:$BR69),YR,PRD,_xll.ArrayDIM($BT69:$BW69))} -> 0 | M69: =IF(L69=0,0,(L69*100/L$19)) -> 0 | N69: {=_xll.BCC(DB,_xll.ArrayDPT($AA69:$AE69),_xll.ArrayCOA($AG69:$BR69),YR,PRD,RV,_xll.ArrayDIM($BT69:$BW69))} -> 0 | O69: =IF(N69=0,0,(N69*100/N$19)) -> 0 | P69: =+N69-L69 -> 0 | Q69: =IF(P69=0,0,(P69*100/P$19)) -> 0 | R69: {=_xll.ACC(DB,_xll.ArrayDPT($AA69:$AE69),_xll.ArrayCOA($AG69:$BR69),YR-1,PRD,_xll.ArrayDIM($BT69:$BW69))} -> 0 | S69: =IF(R69=0,0,(R69*100/R$19)) -> 0
A70: {=_xll.AC(DB,_xll.ArrayDPT($AA70:$AE70),_xll.ArrayCOA($AG70:$BR70),YR-1,PRD,_xll.ArrayDIM($BT70:$BW70))} -> 0 | B70: =IF(A70=0,0,(A70*100/A$19)) -> 0 | C70: =+E70-G70 -> 0 | D70: =IF(C70=0,0,(C70*100/C$19)) -> 0 | E70: {=_xll.BC(DB,_xll.ArrayDPT($AA70:$AE70),_xll.ArrayCOA($AG70:$BR70),YR,PRD,RV,_xll.ArrayDIM($BT70:$BW70))} -> 0 | F70: =IF(E70=0,0,(E70*100/E$19)) -> 0 | G70: {=_xll.AC(DB,_xll.ArrayDPT($AA70:$AE70),_xll.ArrayCOA($AG70:$BR70),YR,PRD,_xll.ArrayDIM($BT70:$BW70))} -> 0 | H70: =IF(G70=0,0,(G70*100/G$19)) -> 0 | J70: Owner Expenses | L70: {=_xll.ACC(DB,_xll.ArrayDPT($AA70:$AE70),_xll.ArrayCOA($AG70:$BR70),YR,PRD,_xll.ArrayDIM($BT70:$BW70))} -> 0 | M70: =IF(L70=0,0,(L70*100/L$19)) -> 0 | N70: {=_xll.BCC(DB,_xll.ArrayDPT($AA70:$AE70),_xll.ArrayCOA($AG70:$BR70),YR,PRD,RV,_xll.ArrayDIM($BT70:$BW70))} -> 0 | O70: =IF(N70=0,0,(N70*100/N$19)) -> 0 | P70: =+N70-L70 -> 0 | Q70: =IF(P70=0,0,(P70*100/P$19)) -> 0 | R70: {=_xll.ACC(DB,_xll.ArrayDPT($AA70:$AE70),_xll.ArrayCOA($AG70:$BR70),YR-1,PRD,_xll.ArrayDIM($BT70:$BW70))} -> 0 | S70: =IF(R70=0,0,(R70*100/R$19)) -> 0 | AA70: 800 | AG70: 61230 | AH70: 61230 | AI70: 50032 | AJ70: 50032 | AK70: 46070 | AL70: 46070 | AM70: 50015 | AN70: 50015
A71: {=_xll.AC(DB,_xll.ArrayDPT($AA71:$AE71),_xll.ArrayCOA($AG71:$BR71),YR-1,PRD,_xll.ArrayDIM($BT71:$BW71))} -> 0 | B71: =IF(A71=0,0,(A71*100/A$19)) -> 0 | C71: =+E71-G71 -> 0 | D71: =IF(C71=0,0,(C71*100/C$19)) -> 0 | E71: {=_xll.BC(DB,_xll.ArrayDPT($AA71:$AE71),_xll.ArrayCOA($AG71:$BR71),YR,PRD,RV,_xll.ArrayDIM($BT71:$BW71))} -> 0 | F71: =IF(E71=0,0,(E71*100/E$19)) -> 0 | G71: {=_xll.AC(DB,_xll.ArrayDPT($AA71:$AE71),_xll.ArrayCOA($AG71:$BR71),YR,PRD,_xll.ArrayDIM($BT71:$BW71))} -> 0 | H71: =IF(G71=0,0,(G71*100/G$19)) -> 0 | J71: Gain (Loss) on Sales of Fixed Assets | L71: {=_xll.ACC(DB,_xll.ArrayDPT($AA71:$AE71),_xll.ArrayCOA($AG71:$BR71),YR,PRD,_xll.ArrayDIM($BT71:$BW71))} -> 0 | M71: =IF(L71=0,0,(L71*100/L$19)) -> 0 | N71: {=_xll.BCC(DB,_xll.ArrayDPT($AA71:$AE71),_xll.ArrayCOA($AG71:$BR71),YR,PRD,RV,_xll.ArrayDIM($BT71:$BW71))} -> 0 | O71: =IF(N71=0,0,(N71*100/N$19)) -> 0 | P71: =+N71-L71 -> 0 | Q71: =IF(P71=0,0,(P71*100/P$19)) -> 0 | R71: {=_xll.ACC(DB,_xll.ArrayDPT($AA71:$AE71),_xll.ArrayCOA($AG71:$BR71),YR-1,PRD,_xll.ArrayDIM($BT71:$BW71))} -> 0 | S71: =IF(R71=0,0,(R71*100/R$19)) -> 0 | AA71: 800 | AG71: 61225 | AH71: 61225
A72: {=_xll.AC(DB,_xll.ArrayDPT($AA72:$AE72),_xll.ArrayCOA($AG72:$BR72),YR-1,PRD,_xll.ArrayDIM($BT72:$BW72))} -> 0 | B72: =IF(A72=0,0,(A72*100/A$19)) -> 0 | C72: =+E72-G72 -> 0 | D72: =IF(C72=0,0,(C72*100/C$19)) -> 0 | E72: {=_xll.BC(DB,_xll.ArrayDPT($AA72:$AE72),_xll.ArrayCOA($AG72:$BR72),YR,PRD,RV,_xll.ArrayDIM($BT72:$BW72))} -> 0 | F72: =IF(E72=0,0,(E72*100/E$19)) -> 0 | G72: {=_xll.AC(DB,_xll.ArrayDPT($AA72:$AE72),_xll.ArrayCOA($AG72:$BR72),YR,PRD,_xll.ArrayDIM($BT72:$BW72))} -> 0 | H72: =IF(G72=0,0,(G72*100/G$19)) -> 0 | J72: Gain (Loss) on Foreign Exchange | L72: {=_xll.ACC(DB,_xll.ArrayDPT($AA72:$AE72),_xll.ArrayCOA($AG72:$BR72),YR,PRD,_xll.ArrayDIM($BT72:$BW72))} -> 0 | M72: =IF(L72=0,0,(L72*100/L$19)) -> 0 | N72: {=_xll.BCC(DB,_xll.ArrayDPT($AA72:$AE72),_xll.ArrayCOA($AG72:$BR72),YR,PRD,RV,_xll.ArrayDIM($BT72:$BW72))} -> 0 | O72: =IF(N72=0,0,(N72*100/N$19)) -> 0 | P72: =+N72-L72 -> 0 | Q72: =IF(P72=0,0,(P72*100/P$19)) -> 0 | R72: {=_xll.ACC(DB,_xll.ArrayDPT($AA72:$AE72),_xll.ArrayCOA($AG72:$BR72),YR-1,PRD,_xll.ArrayDIM($BT72:$BW72))} -> 0 | S72: =IF(R72=0,0,(R72*100/R$19)) -> 0
A73: =+A62-A63-A64-A65-A68-A71-A72-A66-A67-A69-A70 -> 5169619 | B73: =IF(A73=0,0,(A73*100/A$19)) -> 62.086915 | C73: =+C62-C63-C64-C65-C68-C71-C72-C66-C67-C69-C70 -> -5604188.3 | D73: =IF(C73=0,0,(C73*100/C$19)) -> 64.714097 | E73: =+E62-E63-E64-E65-E68-E71-E72-E66-E67-E69-E70 -> 0 | F73: =IF(E73=0,0,(E73*100/E$19)) -> 0 | G73: =+G62-G63-G64-G65-G68-G71-G72-G66-G67-G69-G70 -> 4478042.8 | H73: =IF(G73=0,0,(G73*100/G$19)) -> 51.709986 | J73: PROFIT BEFORE INTEREST | L73: =+L62-L63-L64-L65-L68-L71-L72-L66-L67-L69-L70 -> 7171311.8 | M73: =IF(L73=0,0,(L73*100/L$19)) -> 70.121073 | N73: =+N62-N63-N64-N65-N68-N71-N72-N66-N67-N69-N70 -> 0 | O73: =IF(N73=0,0,(N73*100/N$19)) -> 0 | P73: =+P62-P63-P64-P65-P68-P71-P72-P66-P67-P69-P70 -> -7171311.8 | Q73: =IF(P73=0,0,(P73*100/P$19)) -> 70.121073 | R73: =+R62-R63-R64-R65-R68-R71-R72-R66-R67-R69-R70 -> 6685795.5 | S73: =IF(R73=0,0,(R73*100/R$19)) -> 67.927134
A74: {=_xll.AC(DB,_xll.ArrayDPT($AA74:$AE74),_xll.ArrayCOA($AG74:$BR74),YR-1,PRD,_xll.ArrayDIM($BT74:$BW74))} -> 0 | B74: =IF(A74=0,0,(A74*100/A$19)) -> 0 | C74: =+E74-G74 -> 0 | D74: =IF(C74=0,0,(C74*100/C$19)) -> 0 | E74: {=_xll.BC(DB,_xll.ArrayDPT($AA74:$AE74),_xll.ArrayCOA($AG74:$BR74),YR,PRD,RV,_xll.ArrayDIM($BT74:$BW74))} -> 0 | F74: =IF(E74=0,0,(E74*100/E$19)) -> 0 | G74: {=_xll.AC(DB,_xll.ArrayDPT($AA74:$AE74),_xll.ArrayCOA($AG74:$BR74),YR,PRD,_xll.ArrayDIM($BT74:$BW74))} -> 0 | H74: =IF(G74=0,0,(G74*100/G$19)) -> 0 | J74: Interest Income | L74: {=_xll.ACC(DB,_xll.ArrayDPT($AA74:$AE74),_xll.ArrayCOA($AG74:$BR74),YR,PRD,_xll.ArrayDIM($BT74:$BW74))} -> 0 | M74: =IF(L74=0,0,(L74*100/L$19)) -> 0 | N74: {=_xll.BCC(DB,_xll.ArrayDPT($AA74:$AE74),_xll.ArrayCOA($AG74:$BR74),YR,PRD,RV,_xll.ArrayDIM($BT74:$BW74))} -> 0 | O74: =IF(N74=0,0,(N74*100/N$19)) -> 0 | P74: =+N74-L74 -> 0 | Q74: =IF(P74=0,0,(P74*100/P$19)) -> 0 | R74: {=_xll.ACC(DB,_xll.ArrayDPT($AA74:$AE74),_xll.ArrayCOA($AG74:$BR74),YR-1,PRD,_xll.ArrayDIM($BT74:$BW74))} -> 0 | S74: =IF(R74=0,0,(R74*100/R$19)) -> 0
A75: {=_xll.AC(DB,_xll.ArrayDPT($AA75:$AE75),_xll.ArrayCOA($AG75:$BR75),YR-1,PRD,_xll.ArrayDIM($BT75:$BW75))} -> 0 | B75: =IF(A75=0,0,(A75*100/A$19)) -> 0 | C75: =+E75-G75 -> 0 | D75: =IF(C75=0,0,(C75*100/C$19)) -> 0 | E75: {=_xll.BC(DB,_xll.ArrayDPT($AA75:$AE75),_xll.ArrayCOA($AG75:$BR75),YR,PRD,RV,_xll.ArrayDIM($BT75:$BW75))} -> 0 | F75: =IF(E75=0,0,(E75*100/E$19)) -> 0 | G75: {=_xll.AC(DB,_xll.ArrayDPT($AA75:$AE75),_xll.ArrayCOA($AG75:$BR75),YR,PRD,_xll.ArrayDIM($BT75:$BW75))} -> 0 | H75: =IF(G75=0,0,(G75*100/G$19)) -> 0 | J75: Interest Expenses | L75: {=_xll.ACC(DB,_xll.ArrayDPT($AA75:$AE75),_xll.ArrayCOA($AG75:$BR75),YR,PRD,_xll.ArrayDIM($BT75:$BW75))} -> 0 | M75: =IF(L75=0,0,(L75*100/L$19)) -> 0 | N75: {=_xll.BCC(DB,_xll.ArrayDPT($AA75:$AE75),_xll.ArrayCOA($AG75:$BR75),YR,PRD,RV,_xll.ArrayDIM($BT75:$BW75))} -> 0 | O75: =IF(N75=0,0,(N75*100/N$19)) -> 0 | P75: =+N75-L75 -> 0 | Q75: =IF(P75=0,0,(P75*100/P$19)) -> 0 | R75: {=_xll.ACC(DB,_xll.ArrayDPT($AA75:$AE75),_xll.ArrayCOA($AG75:$BR75),YR-1,PRD,_xll.ArrayDIM($BT75:$BW75))} -> 0 | S75: =IF(R75=0,0,(R75*100/R$19)) -> 0
A76: {=_xll.AC(DB,_xll.ArrayDPT($AA76:$AE76),_xll.ArrayCOA($AG76:$BR76),YR-1,PRD,_xll.ArrayDIM($BT76:$BW76))} -> 0 | B76: =IF(A76=0,0,(A76*100/A$19)) -> 0 | C76: =+E76-G76 -> 0 | D76: =IF(C76=0,0,(C76*100/C$19)) -> 0 | E76: {=_xll.BC(DB,_xll.ArrayDPT($AA76:$AE76),_xll.ArrayCOA($AG76:$BR76),YR,PRD,RV,_xll.ArrayDIM($BT76:$BW76))} -> 0 | F76: =IF(E76=0,0,(E76*100/E$19)) -> 0 | G76: {=_xll.AC(DB,_xll.ArrayDPT($AA76:$AE76),_xll.ArrayCOA($AG76:$BR76),YR,PRD,_xll.ArrayDIM($BT76:$BW76))} -> 0 | H76: =IF(G76=0,0,(G76*100/G$19)) -> 0 | J76: Loan Interest | L76: {=_xll.ACC(DB,_xll.ArrayDPT($AA76:$AE76),_xll.ArrayCOA($AG76:$BR76),YR,PRD,_xll.ArrayDIM($BT76:$BW76))} -> 0 | M76: =IF(L76=0,0,(L76*100/L$19)) -> 0 | N76: {=_xll.BCC(DB,_xll.ArrayDPT($AA76:$AE76),_xll.ArrayCOA($AG76:$BR76),YR,PRD,RV,_xll.ArrayDIM($BT76:$BW76))} -> 0 | O76: =IF(N76=0,0,(N76*100/N$19)) -> 0 | P76: =+N76-L76 -> 0 | Q76: =IF(P76=0,0,(P76*100/P$19)) -> 0 | R76: {=_xll.ACC(DB,_xll.ArrayDPT($AA76:$AE76),_xll.ArrayCOA($AG76:$BR76),YR-1,PRD,_xll.ArrayDIM($BT76:$BW76))} -> 0 | S76: =IF(R76=0,0,(R76*100/R$19)) -> 0
A77: =+A73-A74-A75-A76 -> 5169619 | B77: =IF(A77=0,0,(A77*100/A$19)) -> 62.086915 | C77: =+C73-C74-C75-C76 -> -5604188.3 | D77: =IF(C77=0,0,(C77*100/C$19)) -> 64.714097 | E77: =+E73-E74-E75-E76 -> 0 | F77: =IF(E77=0,0,(E77*100/E$19)) -> 0 | G77: =+G73-G74-G75-G76 -> 4478042.8 | H77: =IF(G77=0,0,(G77*100/G$19)) -> 51.709986 | J77: PROFIT BEFORE DPRE. & AMRT. | L77: =+L73-L74-L75-L76 -> 7171311.8 | M77: =IF(L77=0,0,(L77*100/L$19)) -> 70.121073 | N77: =+N73-N74-N75-N76 -> 0 | O77: =IF(N77=0,0,(N77*100/N$19)) -> 0 | P77: =+P73-P74-P75-P76 -> -7171311.8 | Q77: =IF(P77=0,0,(P77*100/P$19)) -> 70.121073 | R77: =+R73-R74-R75-R76 -> 6685795.5 | S77: =IF(R77=0,0,(R77*100/R$19)) -> 67.927134
A78: {=_xll.AC(DB,_xll.ArrayDPT($AA78:$AE78),_xll.ArrayCOA($AG78:$BR78),YR-1,PRD,_xll.ArrayDIM($BT78:$BW78))} -> 0 | B78: =IF(A78=0,0,(A78*100/A$19)) -> 0 | C78: =+E78-G78 -> 0 | D78: =IF(C78=0,0,(C78*100/C$19)) -> 0 | E78: {=_xll.BC(DB,_xll.ArrayDPT($AA78:$AE78),_xll.ArrayCOA($AG78:$BR78),YR,PRD,RV,_xll.ArrayDIM($BT78:$BW78))} -> 0 | F78: =IF(E78=0,0,(E78*100/E$19)) -> 0 | G78: {=_xll.AC(DB,_xll.ArrayDPT($AA78:$AE78),_xll.ArrayCOA($AG78:$BR78),YR,PRD,_xll.ArrayDIM($BT78:$BW78))} -> 0 | H78: =IF(G78=0,0,(G78*100/G$19)) -> 0 | J78: Depreciation | L78: {=_xll.ACC(DB,_xll.ArrayDPT($AA78:$AE78),_xll.ArrayCOA($AG78:$BR78),YR,PRD,_xll.ArrayDIM($BT78:$BW78))} -> 0 | M78: =IF(L78=0,0,(L78*100/L$19)) -> 0 | N78: {=_xll.BCC(DB,_xll.ArrayDPT($AA78:$AE78),_xll.ArrayCOA($AG78:$BR78),YR,PRD,RV,_xll.ArrayDIM($BT78:$BW78))} -> 0 | O78: =IF(N78=0,0,(N78*100/N$19)) -> 0 | P78: =+N78-L78 -> 0 | Q78: =IF(P78=0,0,(P78*100/P$19)) -> 0 | R78: {=_xll.ACC(DB,_xll.ArrayDPT($AA78:$AE78),_xll.ArrayCOA($AG78:$BR78),YR-1,PRD,_xll.ArrayDIM($BT78:$BW78))} -> 0 | S78: =IF(R78=0,0,(R78*100/R$19)) -> 0 | AA78: 800 | AG78: 63020 | AH78: 63020 | AI78: 63025 | AJ78: 63025 | AK78: 63026 | AL78: 63026 | AM78: 63030 | AN78: 63030 | AO78: 63035 | AP78: 63035 | AQ78: 63040 | AR78: 63040 | AS78: 63045 | AT78: 63045 | AU78: 63050 | AV78: 63050 | AW78: 63065 | AX78: 63065 | AY78: 63085 | AZ78: 63085 | BA78: 63090 | BB78: 63090 | BC78: 63095 | BD78: 63095 | BE78: 63105 | BF78: 63105 | BG78: 63130 | BH78: 63130 | BI78: 63140 | BJ78: 63140 | BK78: 63145 | BL78: 63145 | BM78: 63155 | BN78: 63155 | BO78: 63160 | BP78: 63160 | BQ78: 63175 | BR78: 63175
A79: {=_xll.AC(DB,_xll.ArrayDPT($AA79:$AE79),_xll.ArrayCOA($AG79:$BR79),YR-1,PRD,_xll.ArrayDIM($BT79:$BW79))} -> 0 | B79: =IF(A79=0,0,(A79*100/A$19)) -> 0 | C79: =+E79-G79 -> 0 | D79: =IF(C79=0,0,(C79*100/C$19)) -> 0 | E79: {=_xll.BC(DB,_xll.ArrayDPT($AA79:$AE79),_xll.ArrayCOA($AG79:$BR79),YR,PRD,RV,_xll.ArrayDIM($BT79:$BW79))} -> 0 | F79: =IF(E79=0,0,(E79*100/E$19)) -> 0 | G79: {=_xll.AC(DB,_xll.ArrayDPT($AA79:$AE79),_xll.ArrayCOA($AG79:$BR79),YR,PRD,_xll.ArrayDIM($BT79:$BW79))} -> 0 | H79: =IF(G79=0,0,(G79*100/G$19)) -> 0 | J79: Amortization | L79: {=_xll.ACC(DB,_xll.ArrayDPT($AA79:$AE79),_xll.ArrayCOA($AG79:$BR79),YR,PRD,_xll.ArrayDIM($BT79:$BW79))} -> 0 | M79: =IF(L79=0,0,(L79*100/L$19)) -> 0 | N79: {=_xll.BCC(DB,_xll.ArrayDPT($AA79:$AE79),_xll.ArrayCOA($AG79:$BR79),YR,PRD,RV,_xll.ArrayDIM($BT79:$BW79))} -> 0 | O79: =IF(N79=0,0,(N79*100/N$19)) -> 0 | P79: =+N79-L79 -> 0 | Q79: =IF(P79=0,0,(P79*100/P$19)) -> 0 | R79: {=_xll.ACC(DB,_xll.ArrayDPT($AA79:$AE79),_xll.ArrayCOA($AG79:$BR79),YR-1,PRD,_xll.ArrayDIM($BT79:$BW79))} -> 0 | S79: =IF(R79=0,0,(R79*100/R$19)) -> 0
A80: =+A77-A78-A79 -> 5169619 | B80: =IF(A80=0,0,(A80*100/A$19)) -> 62.086915 | C80: =+C77-C78-C79 -> -5604188.3 | D80: =IF(C80=0,0,(C80*100/C$19)) -> 64.714097 | E80: =+E77-E78-E79 -> 0 | F80: =IF(E80=0,0,(E80*100/E$19)) -> 0 | G80: =+G77-G78-G79 -> 4478042.8 | H80: =IF(G80=0,0,(G80*100/G$19)) -> 51.709986 | J80: PROFIT BEFORE CORPORATE INCOME TAXES | L80: =+L77-L78-L79 -> 7171311.8 | M80: =IF(L80=0,0,(L80*100/L$19)) -> 70.121073 | N80: =+N77-N78-N79 -> 0 | O80: =IF(N80=0,0,(N80*100/N$19)) -> 0 | P80: =+P77-P78-P79 -> -7171311.8 | Q80: =IF(P80=0,0,(P80*100/P$19)) -> 70.121073 | R80: =+R77-R78-R79 -> 6685795.5 | S80: =IF(R80=0,0,(R80*100/R$19)) -> 67.927134
A81: {=_xll.AC(DB,_xll.ArrayDPT($AA81:$AE81),_xll.ArrayCOA($AG81:$BR81),YR-1,PRD,_xll.ArrayDIM($BT81:$BW81))} -> 0 | B81: =IF(A81=0,0,(A81*100/A$19)) -> 0 | C81: =+E81-G81 -> 0 | D81: =IF(C81=0,0,(C81*100/C$19)) -> 0 | E81: {=_xll.BC(DB,_xll.ArrayDPT($AA81:$AE81),_xll.ArrayCOA($AG81:$BR81),YR,PRD,RV,_xll.ArrayDIM($BT81:$BW81))} -> 0 | F81: =IF(E81=0,0,(E81*100/E$19)) -> 0 | G81: {=_xll.AC(DB,_xll.ArrayDPT($AA81:$AE81),_xll.ArrayCOA($AG81:$BR81),YR,PRD,_xll.ArrayDIM($BT81:$BW81))} -> 0 | H81: =IF(G81=0,0,(G81*100/G$19)) -> 0 | J81: Corporate Income Taxes | L81: {=_xll.ACC(DB,_xll.ArrayDPT($AA81:$AE81),_xll.ArrayCOA($AG81:$BR81),YR,PRD,_xll.ArrayDIM($BT81:$BW81))} -> 0 | M81: =IF(L81=0,0,(L81*100/L$19)) -> 0 | N81: {=_xll.BCC(DB,_xll.ArrayDPT($AA81:$AE81),_xll.ArrayCOA($AG81:$BR81),YR,PRD,RV,_xll.ArrayDIM($BT81:$BW81))} -> 0 | O81: =IF(N81=0,0,(N81*100/N$19)) -> 0 | P81: =+N81-L81 -> 0 | Q81: =IF(P81=0,0,(P81*100/P$19)) -> 0 | R81: {=_xll.ACC(DB,_xll.ArrayDPT($AA81:$AE81),_xll.ArrayCOA($AG81:$BR81),YR-1,PRD,_xll.ArrayDIM($BT81:$BW81))} -> 0 | S81: =IF(R81=0,0,(R81*100/R$19)) -> 0
A82: =+A80-A81 -> 5169619 | B82: =IF(A82=0,0,(A82*100/A$19)) -> 62.086915 | C82: =+C80-C81 -> -5604188.3 | D82: =IF(C82=0,0,(C82*100/C$19)) -> 64.714097 | E82: =+E80-E81 -> 0 | F82: =IF(E82=0,0,(E82*100/E$19)) -> 0 | G82: =+G80-G81 -> 4478042.8 | H82: =IF(G82=0,0,(G82*100/G$19)) -> 51.709986 | J82: NET PROFIT ( LOSS ) | L82: =+L80-L81 -> 7171311.8 | M82: =IF(L82=0,0,(L82*100/L$19)) -> 70.121073 | N82: =+N80-N81 -> 0 | O82: =IF(N82=0,0,(N82*100/N$19)) -> 0 | P82: =+P80-P81 -> -7171311.8 | Q82: =IF(P82=0,0,(P82*100/P$19)) -> 70.121073 | R82: =+R80-R81 -> 6685795.5 | S82: =IF(R82=0,0,(R82*100/R$19)) -> 67.927134
G84: =+G82-G86 -> 4478042.8
A85: =+A84-A82 -> -5169619 | G85: =+A85-L85 -> -5169619 | L85: =+G78-L78 -> 0

Sheet Sum Room
A2: HOMM SUKHUMVIT34 BANGKOK | T2: Period | U2: =PRD -> 1
J3: Room Department | Q3: SCHEDULE - B | AA3: Mapping Area
A4: CURRENT MONTH | L4: YEAR TO DATE | AA4: *Department Code | AG4: *Account Code | BB4: Dimension | BF4: Dimension
A5: LAST YEAR | C5: VARIANCE | E5: BUDGET | G5: ACTUAL | J5: DESCRIPTION | L5: ACTUAL | N5: BUDGET | P5: VARIANCE | R5: LAST YEAR | AA5: Dept 1 | AB5: Dept 2 | AC5: Dept 3 | AD5: Dept 4 | AE5: Dept 5 | AG5: 1st Range | AI5: 2nd Range | AK5: 3rd Range | AM5: 4rd Range | AO5: 5rd Range | AQ5: 6rd Range | AS5: 7rd Range | AU5: 8rd Range | AW5: 9rd Range | AY5: 10th Range
A6: BHT | B6: % | C6: BHT | D6: % | E6: BHT | F6: % | G6: BHT | H6: % | L6: BHT | M6: % | N6: BHT | O6: % | P6: BHT | Q6: % | R6: BHT | S6: % | AG6: From | AH6: To | AI6: From | AJ6: To | AK6: From | AL6: To | AM6: From | AN6: To | AO6: From | AP6: To | AQ6: From | AR6: To | AS6: From | AT6: To | AU6: From | AV6: To | AW6: From | AX6: To | AY6: From | AZ6: To | BB6: A/O | BC6: Field Name | BD6: Operator | BE6: Value | BF6: A/O | BG6: Field Name | BH6: Operator | BI6: Value
J7: REVENUE | BB7: A | BC7: Matket1 | BD7: in | BE7: OTA,FIT | BF7: A | BG7: Matket2 | BH7: in | BI7: OTA1,FIT1
A8: {=_xll.AC(DB,_xll.ArrayDPT($AA8:$AE8),_xll.ArrayCOA($AG8:$AZ8),YR-1,PRD,_xll.ArrayDIM($BB8:$BE8))} -> 7234622.9 | B8: =IF(A8=0,0,(A8*100/A$14)) -> 99.794519 | C8: =+E8-G8 -> -7896040 | D8: =IF(C8=0,0,(C8*100/C$14)) -> 99.674431 | E8: {=_xll.BC(DB,_xll.ArrayDPT($AA8:$AE8),_xll.ArrayCOA($AG8:$AZ8),YR,PRD,RV,_xll.ArrayDIM($BB8:$BE8))} -> 0 | F8: =IF(E8=0,0,(E8*100/E$14)) -> 0 | G8: =_xll.AC(DB,_xll.ArrayDPT($AA8:$AE8),_xll.ArrayCOA($AG8:$AZ8),YR,PRD,_xll.ArrayDIM($BB8:$BE8)) -> 7896040 | H8: =IF(G8=0,0,(G8*100/G$14)) -> 99.674431 | J8: ROOM REVENUE | L8: =_xll.ACC(DB,_xll.ArrayDPT($AA8:$AE8),_xll.ArrayCOA($AG8:$AZ8),YR,PRD,_xll.ArrayDIM($BB8:$BE8)) -> 7896040 | M8: =IF(L8=0,0,(L8*100/L$14)) -> 99.674431 | N8: {=_xll.BCC(DB,_xll.ArrayDPT($AA8:$AE8),_xll.ArrayCOA($AG8:$AZ8),YR,PRD,RV,_xll.ArrayDIM($BB8:$BE8))} -> 0 | O8: =IF(N8=0,0,(N8*100/N$14)) -> 0 | P8: =+N8-L8 -> -7896040 | Q8: =IF(P8=0,0,(P8*100/P$14)) -> 99.674431 | R8: {=_xll.ACC(DB,_xll.ArrayDPT($AA8:$AE8),_xll.ArrayCOA($AG8:$AZ8),YR-1,PRD,_xll.ArrayDIM($BB8:$BE8))} -> 7234622.9 | S8: =IF(R8=0,0,(R8*100/R$14)) -> 99.794519 | AA8: 101 | AG8: 11100 | AH8: 11100
A9: {=_xll.AC(DB,_xll.ArrayDPT($AA9:$AE9),_xll.ArrayCOA($AG9:$AZ9),YR-1,PRD,_xll.ArrayDIM($BB9:$BE9))} -> 0 | B9: =IF(A9=0,0,(A9*100/A$14)) -> 0 | C9: =+E9-G9 -> 0 | D9: =IF(C9=0,0,(C9*100/C$14)) -> 0 | E9: {=_xll.BC(DB,_xll.ArrayDPT($AA9:$AE9),_xll.ArrayCOA($AG9:$AZ9),YR,PRD,RV,_xll.ArrayDIM($BB9:$BE9))} -> 0 | F9: =IF(E9=0,0,(E9*100/E$14)) -> 0 | G9: {=_xll.AC(DB,_xll.ArrayDPT($AA9:$AE9),_xll.ArrayCOA($AG9:$AZ9),YR,PRD,_xll.ArrayDIM($BB9:$BE9))} -> 0 | H9: =IF(G9=0,0,(G9*100/G$14)) -> 0 | J9: SERVICECHARGE - ROOM REVENUE | L9: {=_xll.ACC(DB,_xll.ArrayDPT($AA9:$AE9),_xll.ArrayCOA($AG9:$AZ9),YR,PRD,_xll.ArrayDIM($BB9:$BE9))} -> 0 | M9: =IF(L9=0,0,(L9*100/L$14)) -> 0 | N9: {=_xll.BCC(DB,_xll.ArrayDPT($AA9:$AE9),_xll.ArrayCOA($AG9:$AZ9),YR,PRD,RV,_xll.ArrayDIM($BB9:$BE9))} -> 0 | O9: =IF(N9=0,0,(N9*100/N$14)) -> 0 | P9: =+N9-L9 -> 0 | Q9: =IF(P9=0,0,(P9*100/P$14)) -> 0 | R9: {=_xll.ACC(DB,_xll.ArrayDPT($AA9:$AE9),_xll.ArrayCOA($AG9:$AZ9),YR-1,PRD,_xll.ArrayDIM($BB9:$BE9))} -> 0 | S9: =IF(R9=0,0,(R9*100/R$14)) -> 0
A10: {=_xll.AC(DB,_xll.ArrayDPT($AA10:$AE10),_xll.ArrayCOA($AG10:$AZ10),YR-1,PRD,_xll.ArrayDIM($BB10:$BE10))} -> 36402.76 | B10: =IF(A10=0,0,(A10*100/A$14)) -> 0.50214033 | C10: =+E10-G10 -> -38913.08 | D10: =IF(C10=0,0,(C10*100/C$14)) -> 0.49121321 | E10: {=_xll.BC(DB,_xll.ArrayDPT($AA10:$AE10),_xll.ArrayCOA($AG10:$AZ10),YR,PRD,RV,_xll.ArrayDIM($BB10:$BE10))} -> 0 | F10: =IF(E10=0,0,(E10*100/E$14)) -> 0 | G10: {=_xll.AC(DB,_xll.ArrayDPT($AA10:$AE10),_xll.ArrayCOA($AG10:$AZ10),YR,PRD,_xll.ArrayDIM($BB10:$BE10))} -> 38913.08 | H10: =IF(G10=0,0,(G10*100/G$14)) -> 0.49121321 | J10: ROOM REVENUE - OTHER | L10: {=_xll.ACC(DB,_xll.ArrayDPT($AA10:$AE10),_xll.ArrayCOA($AG10:$AZ10),YR,PRD,_xll.ArrayDIM($BB10:$BE10))} -> 38913.08 | M10: =IF(L10=0,0,(L10*100/L$14)) -> 0.49121321 | N10: {=_xll.BCC(DB,_xll.ArrayDPT($AA10:$AE10),_xll.ArrayCOA($AG10:$AZ10),YR,PRD,RV,_xll.ArrayDIM($BB10:$BE10))} -> 0 | O10: =IF(N10=0,0,(N10*100/N$14)) -> 0 | P10: =+N10-L10 -> -38913.08 | Q10: =IF(P10=0,0,(P10*100/P$14)) -> 0.49121321 | R10: {=_xll.ACC(DB,_xll.ArrayDPT($AA10:$AE10),_xll.ArrayCOA($AG10:$AZ10),YR-1,PRD,_xll.ArrayDIM($BB10:$BE10))} -> 36402.76 | S10: =IF(R10=0,0,(R10*100/R$14)) -> 0.50214033 | AA10: 101 | AG10: 11101 | AH10: 11101
A11: {=_xll.AC(DB,_xll.ArrayDPT($AA11:$AE11),_xll.ArrayCOA($AG11:$AZ11),YR-1,PRD,_xll.ArrayDIM($BB11:$BE11))} -> -21506.38 | B11: =IF(A11=0,0,(A11*100/A$14)) -> -0.29665939 | C11: =+E11-G11 -> 13122.06 | D11: =IF(C11=0,0,(C11*100/C$14)) -> -0.16564428 | E11: {=_xll.BC(DB,_xll.ArrayDPT($AA11:$AE11),_xll.ArrayCOA($AG11:$AZ11),YR,PRD,RV,_xll.ArrayDIM($BB11:$BE11))} -> 0 | F11: =IF(E11=0,0,(E11*100/E$14)) -> 0 | G11: {=_xll.AC(DB,_xll.ArrayDPT($AA11:$AE11),_xll.ArrayCOA($AG11:$AZ11),YR,PRD,_xll.ArrayDIM($BB11:$BE11))} -> -13122.06 | H11: =IF(G11=0,0,(G11*100/G$14)) -> -0.16564428 | J11: ALLOWANCES | L11: {=_xll.ACC(DB,_xll.ArrayDPT($AA11:$AE11),_xll.ArrayCOA($AG11:$AZ11),YR,PRD,_xll.ArrayDIM($BB11:$BE11))} -> -13122.06 | M11: =IF(L11=0,0,(L11*100/L$14)) -> -0.16564428 | N11: {=_xll.BCC(DB,_xll.ArrayDPT($AA11:$AE11),_xll.ArrayCOA($AG11:$AZ11),YR,PRD,RV,_xll.ArrayDIM($BB11:$BE11))} -> 0 | O11: =IF(N11=0,0,(N11*100/N$14)) -> 0 | P11: =+N11-L11 -> 13122.06 | Q11: =IF(P11=0,0,(P11*100/P$14)) -> -0.16564428 | R11: {=_xll.ACC(DB,_xll.ArrayDPT($AA11:$AE11),_xll.ArrayCOA($AG11:$AZ11),YR-1,PRD,_xll.ArrayDIM($BB11:$BE11))} -> -21506.38 | S11: =IF(R11=0,0,(R11*100/R$14)) -> -0.29665939 | AA11: 101 | AG11: 20005 | AH11: 20005
A12: {=_xll.AC(DB,_xll.ArrayDPT($AA12:$AE12),_xll.ArrayCOA($AG12:$AZ12),YR-1,PRD,_xll.ArrayDIM($BB12:$BE12))} -> 0 | B12: =IF(A12=0,0,(A12*100/A$14)) -> 0 | C12: =+E12-G12 -> 0 | D12: =IF(C12=0,0,(C12*100/C$14)) -> 0 | E12: {=_xll.BC(DB,_xll.ArrayDPT($AA12:$AE12),_xll.ArrayCOA($AG12:$AZ12),YR,PRD,RV,_xll.ArrayDIM($BB12:$BE12))} -> 0 | F12: =IF(E12=0,0,(E12*100/E$14)) -> 0 | G12: {=_xll.AC(DB,_xll.ArrayDPT($AA12:$AE12),_xll.ArrayCOA($AG12:$AZ12),YR,PRD,_xll.ArrayDIM($BB12:$BE12))} -> 0 | H12: =IF(G12=0,0,(G12*100/G$14)) -> 0 | J12: EXTRA ROOM REVENUE | L12: {=_xll.ACC(DB,_xll.ArrayDPT($AA12:$AE12),_xll.ArrayCOA($AG12:$AZ12),YR,PRD,_xll.ArrayDIM($BB12:$BE12))} -> 0 | M12: =IF(L12=0,0,(L12*100/L$14)) -> 0 | N12: {=_xll.BCC(DB,_xll.ArrayDPT($AA12:$AE12),_xll.ArrayCOA($AG12:$AZ12),YR,PRD,RV,_xll.ArrayDIM($BB12:$BE12))} -> 0 | O12: =IF(N12=0,0,(N12*100/N$14)) -> 0 | P12: =+N12-L12 -> 0 | Q12: =IF(P12=0,0,(P12*100/P$14)) -> 0 | R12: {=_xll.ACC(DB,_xll.ArrayDPT($AA12:$AE12),_xll.ArrayCOA($AG12:$AZ12),YR-1,PRD,_xll.ArrayDIM($BB12:$BE12))} -> 0 | S12: =IF(R12=0,0,(R12*100/R$14)) -> 0 | AA12: 101
A14: =SUM(A8:A13) -> 7249519.3 | B14: =IF(A14=0,0,(A14*100/A$14)) -> 100 | C14: =SUM(C8:C13) -> -7921831 | D14: =IF(C14=0,0,(C14*100/C$14)) -> 100 | E14: =SUM(E8:E13) -> 0 | F14: =IF(E14=0,0,(E14*100/E$14)) -> 0 | G14: =SUM(G8:G13) -> 7921831 | H14: =IF(G14=0,0,(G14*100/G$14)) -> 100 | J14: NET REVENUE | L14: =SUM(L8:L13) -> 7921831 | M14: =IF(L14=0,0,(L14*100/L$14)) -> 100 | N14: =SUM(N8:N13) -> 0 | O14: =IF(N14=0,0,(N14*100/N$14)) -> 0 | P14: =SUM(P8:P13) -> -7921831 | Q14: =IF(P14=0,0,(P14*100/P$14)) -> 100 | R14: =SUM(R8:R13) -> 7249519.3 | S14: =IF(R14=0,0,(R14*100/R$14)) -> 100
J15: PAYROLL & EMP. RELATION
A16: {=_xll.AC(DB,_xll.ArrayDPT($AA16:$AE16),_xll.ArrayCOA($AG16:$AZ16),YR-1,PRD,_xll.ArrayDIM($BB16:$BE16))} -> 0 | B16: =IF(A16=0,0,(A16*100/A$14)) -> 0 | C16: =+E16-G16 -> 0 | D16: =IF(C16=0,0,(C16*100/C$14)) -> 0 | E16: {=_xll.BC(DB,_xll.ArrayDPT($AA16:$AE16),_xll.ArrayCOA($AG16:$AZ16),YR,PRD,RV,_xll.ArrayDIM($BB16:$BE16))} -> 0 | F16: =IF(E16=0,0,(E16*100/E$14)) -> 0 | G16: =_xll.AC(DB,_xll.ArrayDPT($AA16:$AE16),_xll.ArrayCOA($AG16:$AZ16),YR,PRD,_xll.ArrayDIM($BB16:$BE16)) -> 0 | H16: =IF(G16=0,0,(G16*100/G$14)) -> 0 | J16: SALARIES & WAGES - FRONT OFFICE | L16: {=_xll.ACC(DB,_xll.ArrayDPT($AA16:$AE16),_xll.ArrayCOA($AG16:$AZ16),YR,PRD,_xll.ArrayDIM($BB16:$BE16))} -> 0 | M16: =IF(L16=0,0,(L16*100/L$14)) -> 0 | N16: {=_xll.BCC(DB,_xll.ArrayDPT($AA16:$AE16),_xll.ArrayCOA($AG16:$AZ16),YR,PRD,RV,_xll.ArrayDIM($BB16:$BE16))} -> 0 | O16: =IF(N16=0,0,(N16*100/N$14)) -> 0 | P16: =+N16-L16 -> 0 | Q16: =IF(P16=0,0,(P16*100/P$14)) -> 0 | R16: {=_xll.ACC(DB,_xll.ArrayDPT($AA16:$AE16),_xll.ArrayCOA($AG16:$AZ16),YR-1,PRD,_xll.ArrayDIM($BB16:$BE16))} -> 0 | S16: =IF(R16=0,0,(R16*100/R$14)) -> 0 | AA16: 103 | AG16: 42104 | AH16: 42104
A17: {=_xll.AC(DB,_xll.ArrayDPT($AA17:$AE17),_xll.ArrayCOA($AG17:$AZ17),YR-1,PRD,_xll.ArrayDIM($BB17:$BE17))} -> 0 | B17: =IF(A17=0,0,(A17*100/A$14)) -> 0 | C17: =+E17-G17 -> -53066.67 | D17: =IF(C17=0,0,(C17*100/C$14)) -> 0.66987884 | E17: {=_xll.BC(DB,_xll.ArrayDPT($AA17:$AE17),_xll.ArrayCOA($AG17:$AZ17),YR,PRD,RV,_xll.ArrayDIM($BB17:$BE17))} -> 0 | F17: =IF(E17=0,0,(E17*100/E$14)) -> 0 | G17: {=_xll.AC(DB,_xll.ArrayDPT($AA17:$AE17),_xll.ArrayCOA($AG17:$AZ17),YR,PRD,_xll.ArrayDIM($BB17:$BE17))} -> 53066.67 | H17: =IF(G17=0,0,(G17*100/G$14)) -> 0.66987884 | J17: SALARIES & WAGES - MANAGEMENT | L17: {=_xll.ACC(DB,_xll.ArrayDPT($AA17:$AE17),_xll.ArrayCOA($AG17:$AZ17),YR,PRD,_xll.ArrayDIM($BB17:$BE17))} -> 53066.67 | M17: =IF(L17=0,0,(L17*100/L$14)) -> 0.66987884 | N17: {=_xll.BCC(DB,_xll.ArrayDPT($AA17:$AE17),_xll.ArrayCOA($AG17:$AZ17),YR,PRD,RV,_xll.ArrayDIM($BB17:$BE17))} -> 0 | O17: =IF(N17=0,0,(N17*100/N$14)) -> 0 | P17: =+N17-L17 -> -53066.67 | Q17: =IF(P17=0,0,(P17*100/P$14)) -> 0.66987884 | R17: {=_xll.ACC(DB,_xll.ArrayDPT($AA17:$AE17),_xll.ArrayCOA($AG17:$AZ17),YR-1,PRD,_xll.ArrayDIM($BB17:$BE17))} -> 0 | S17: =IF(R17=0,0,(R17*100/R$14)) -> 0 | AA17: 103 | AB17: 104 | AG17: 42006 | AH17: 42006
A18: {=_xll.AC(DB,_xll.ArrayDPT($AA18:$AE18),_xll.ArrayCOA($AG18:$AZ18),YR-1,PRD,_xll.ArrayDIM($BB18:$BE18))} -> 273833.34 | B18: =IF(A18=0,0,(A18*100/A$14)) -> 3.777262 | C18: =+E18-G18 -> -219666.67 | D18: =IF(C18=0,0,(C18*100/C$14)) -> 2.772928 | E18: {=_xll.BC(DB,_xll.ArrayDPT($AA18:$AE18),_xll.ArrayCOA($AG18:$AZ18),YR,PRD,RV,_xll.ArrayDIM($BB18:$BE18))} -> 0 | F18: =IF(E18=0,0,(E18*100/E$14)) -> 0 | G18: {=_xll.AC(DB,_xll.ArrayDPT($AA18:$AE18),_xll.ArrayCOA($AG18:$AZ18),YR,PRD,_xll.ArrayDIM($BB18:$BE18))} -> 219666.67 | H18: =IF(G18=0,0,(G18*100/G$14)) -> 2.772928 | J18: SALARIES & WAGES_NON MANAGEMENT | L18: {=_xll.ACC(DB,_xll.ArrayDPT($AA18:$AE18),_xll.ArrayCOA($AG18:$AZ18),YR,PRD,_xll.ArrayDIM($BB18:$BE18))} -> 219666.67 | M18: =IF(L18=0,0,(L18*100/L$14)) -> 2.772928 | N18: {=_xll.BCC(DB,_xll.ArrayDPT($AA18:$AE18),_xll.ArrayCOA($AG18:$AZ18),YR,PRD,RV,_xll.ArrayDIM($BB18:$BE18))} -> 0 | O18: =IF(N18=0,0,(N18*100/N$14)) -> 0 | P18: =+N18-L18 -> -219666.67 | Q18: =IF(P18=0,0,(P18*100/P$14)) -> 2.772928 | R18: {=_xll.ACC(DB,_xll.ArrayDPT($AA18:$AE18),_xll.ArrayCOA($AG18:$AZ18),YR-1,PRD,_xll.ArrayDIM($BB18:$BE18))} -> 273833.34 | S18: =IF(R18=0,0,(R18*100/R$14)) -> 3.777262 | AA18: 103 | AB18: 104 | AC18: 107 | AG18: 42005 | AH18: 42005
A19: {=_xll.AC(DB,_xll.ArrayDPT($AA19:$AE19),_xll.ArrayCOA($AG19:$AZ19),YR-1,PRD,_xll.ArrayDIM($BB19:$BE19))} -> 0 | B19: =IF(A19=0,0,(A19*100/A$14)) -> 0 | C19: =+E19-G19 -> 0 | D19: =IF(C19=0,0,(C19*100/C$14)) -> 0 | E19: {=_xll.BC(DB,_xll.ArrayDPT($AA19:$AE19),_xll.ArrayCOA($AG19:$AZ19),YR,PRD,RV,_xll.ArrayDIM($BB19:$BE19))} -> 0 | F19: =IF(E19=0,0,(E19*100/E$14)) -> 0 | G19: =_xll.AC(DB,_xll.ArrayDPT($AA19:$AE19),_xll.ArrayCOA($AG19:$AZ19),YR,PRD,_xll.ArrayDIM($BB19:$BE19)) -> 0 | H19: =IF(G19=0,0,(G19*100/G$14)) -> 0 | J19: SALARIES & WAGES - RESERVATION | L19: {=_xll.ACC(DB,_xll.ArrayDPT($AA19:$AE19),_xll.ArrayCOA($AG19:$AZ19),YR,PRD,_xll.ArrayDIM($BB19:$BE19))} -> 0 | M19: =IF(L19=0,0,(L19*100/L$14)) -> 0 | N19: {=_xll.BCC(DB,_xll.ArrayDPT($AA19:$AE19),_xll.ArrayCOA($AG19:$AZ19),YR,PRD,RV,_xll.ArrayDIM($BB19:$BE19))} -> 0 | O19: =IF(N19=0,0,(N19*100/N$14)) -> 0 | P19: =+N19-L19 -> 0 | Q19: =IF(P19=0,0,(P19*100/P$14)) -> 0 | R19: {=_xll.ACC(DB,_xll.ArrayDPT($AA19:$AE19),_xll.ArrayCOA($AG19:$AZ19),YR-1,PRD,_xll.ArrayDIM($BB19:$BE19))} -> 0 | S19: =IF(R19=0,0,(R19*100/R$14)) -> 0 | AA19: 107 | AG19: 42105 | AH19: 42105
A20: {=_xll.AC(DB,_xll.ArrayDPT($AA20:$AE20),_xll.ArrayCOA($AG20:$AZ20),YR-1,PRD,_xll.ArrayDIM($BB20:$BE20))} -> 0 | B20: =IF(A20=0,0,(A20*100/A$14)) -> 0 | C20: =+E20-G20 -> 0 | D20: =IF(C20=0,0,(C20*100/C$14)) -> 0 | E20: {=_xll.BC(DB,_xll.ArrayDPT($AA20:$AE20),_xll.ArrayCOA($AG20:$AZ20),YR,PRD,RV,_xll.ArrayDIM($BB20:$BE20))} -> 0 | F20: =IF(E20=0,0,(E20*100/E$14)) -> 0 | G20: {=_xll.AC(DB,_xll.ArrayDPT($AA20:$AE20),_xll.ArrayCOA($AG20:$AZ20),YR,PRD,_xll.ArrayDIM($BB20:$BE20))} -> 0 | H20: =IF(G20=0,0,(G20*100/G$14)) -> 0 | J20: SALARIES & WAGES - HOUSEKEEPING | L20: {=_xll.ACC(DB,_xll.ArrayDPT($AA20:$AE20),_xll.ArrayCOA($AG20:$AZ20),YR,PRD,_xll.ArrayDIM($BB20:$BE20))} -> 0 | M20: =IF(L20=0,0,(L20*100/L$14)) -> 0 | N20: {=_xll.BCC(DB,_xll.ArrayDPT($AA20:$AE20),_xll.ArrayCOA($AG20:$AZ20),YR,PRD,RV,_xll.ArrayDIM($BB20:$BE20))} -> 0 | O20: =IF(N20=0,0,(N20*100/N$14)) -> 0 | P20: =+N20-L20 -> 0 | Q20: =IF(P20=0,0,(P20*100/P$14)) -> 0 | R20: {=_xll.ACC(DB,_xll.ArrayDPT($AA20:$AE20),_xll.ArrayCOA($AG20:$AZ20),YR-1,PRD,_xll.ArrayDIM($BB20:$BE20))} -> 0 | S20: =IF(R20=0,0,(R20*100/R$14)) -> 0 | AA20: 104 | AG20: 42101 | AH20: 42101
A21: {=_xll.AC(DB,_xll.ArrayDPT($AA21:$AE21),_xll.ArrayCOA($AG21:$AZ21),YR-1,PRD,_xll.ArrayDIM($BB21:$BE21))} -> 0 | B21: =IF(A21=0,0,(A21*100/A$14)) -> 0 | C21: =+E21-G21 -> -10436 | D21: =IF(C21=0,0,(C21*100/C$14)) -> 0.13173722 | E21: {=_xll.BC(DB,_xll.ArrayDPT($AA21:$AE21),_xll.ArrayCOA($AG21:$AZ21),YR,PRD,RV,_xll.ArrayDIM($BB21:$BE21))} -> 0 | F21: =IF(E21=0,0,(E21*100/E$14)) -> 0 | G21: {=_xll.AC(DB,_xll.ArrayDPT($AA21:$AE21),_xll.ArrayCOA($AG21:$AZ21),YR,PRD,_xll.ArrayDIM($BB21:$BE21))} -> 10436 | H21: =IF(G21=0,0,(G21*100/G$14)) -> 0.13173722 | J21: PAYROLL TAXES ON SOCIAL SECURITY CONTRIBUTION | L21: {=_xll.ACC(DB,_xll.ArrayDPT($AA21:$AE21),_xll.ArrayCOA($AG21:$AZ21),YR,PRD,_xll.ArrayDIM($BB21:$BE21))} -> 10436 | M21: =IF(L21=0,0,(L21*100/L$14)) -> 0.13173722 | N21: {=_xll.BCC(DB,_xll.ArrayDPT($AA21:$AE21),_xll.ArrayCOA($AG21:$AZ21),YR,PRD,RV,_xll.ArrayDIM($BB21:$BE21))} -> 0 | O21: =IF(N21=0,0,(N21*100/N$14)) -> 0 | P21: =+N21-L21 -> -10436 | Q21: =IF(P21=0,0,(P21*100/P$14)) -> 0.13173722 | R21: {=_xll.ACC(DB,_xll.ArrayDPT($AA21:$AE21),_xll.ArrayCOA($AG21:$AZ21),YR-1,PRD,_xll.ArrayDIM($BB21:$BE21))} -> 0 | S21: =IF(R21=0,0,(R21*100/R$14)) -> 0 | AA21: 103 | AB21: 104 | AC21: 107 | AG21: 45005 | AH21: 45005
A22: {=_xll.AC(DB,_xll.ArrayDPT($AA22:$AE22),_xll.ArrayCOA($AG22:$AZ22),YR-1,PRD,_xll.ArrayDIM($BB22:$BE22))} -> 0 | B22: =IF(A22=0,0,(A22*100/A$14)) -> 0 | C22: =+E22-G22 -> 0 | D22: =IF(C22=0,0,(C22*100/C$14)) -> 0 | E22: {=_xll.BC(DB,_xll.ArrayDPT($AA22:$AE22),_xll.ArrayCOA($AG22:$AZ22),YR,PRD,RV,_xll.ArrayDIM($BB22:$BE22))} -> 0 | F22: =IF(E22=0,0,(E22*100/E$14)) -> 0 | G22: {=_xll.AC(DB,_xll.ArrayDPT($AA22:$AE22),_xll.ArrayCOA($AG22:$AZ22),YR,PRD,_xll.ArrayDIM($BB22:$BE22))} -> 0 | H22: =IF(G22=0,0,(G22*100/G$14)) -> 0 | J22: CASUAL & DAILY HIRE | L22: {=_xll.ACC(DB,_xll.ArrayDPT($AA22:$AE22),_xll.ArrayCOA($AG22:$AZ22),YR,PRD,_xll.ArrayDIM($BB22:$BE22))} -> 0 | M22: =IF(L22=0,0,(L22*100/L$14)) -> 0 | N22: {=_xll.BCC(DB,_xll.ArrayDPT($AA22:$AE22),_xll.ArrayCOA($AG22:$AZ22),YR,PRD,RV,_xll.ArrayDIM($BB22:$BE22))} -> 0 | O22: =IF(N22=0,0,(N22*100/N$14)) -> 0 | P22: =+N22-L22 -> 0 | Q22: =IF(P22=0,0,(P22*100/P$14)) -> 0 | R22: {=_xll.ACC(DB,_xll.ArrayDPT($AA22:$AE22),_xll.ArrayCOA($AG22:$AZ22),YR-1,PRD,_xll.ArrayDIM($BB22:$BE22))} -> 0 | S22: =IF(R22=0,0,(R22*100/R$14)) -> 0 | AA22: 104 | AG22: 42015 | AH22: 42015
A23: {=_xll.AC(DB,_xll.ArrayDPT($AA23:$AE23),_xll.ArrayCOA($AG23:$AZ23),YR-1,PRD,_xll.ArrayDIM($BB23:$BE23))} -> 0 | B23: =IF(A23=0,0,(A23*100/A$14)) -> 0 | C23: =+E23-G23 -> -5835.94 | D23: =IF(C23=0,0,(C23*100/C$14)) -> 0.07366908 | E23: {=_xll.BC(DB,_xll.ArrayDPT($AA23:$AE23),_xll.ArrayCOA($AG23:$AZ23),YR,PRD,RV,_xll.ArrayDIM($BB23:$BE23))} -> 0 | F23: =IF(E23=0,0,(E23*100/E$14)) -> 0 | G23: {=_xll.AC(DB,_xll.ArrayDPT($AA23:$AE23),_xll.ArrayCOA($AG23:$AZ23),YR,PRD,_xll.ArrayDIM($BB23:$BE23))} -> 5835.94 | H23: =IF(G23=0,0,(G23*100/G$14)) -> 0.07366908 | J23: EXTRA & OVERTIME | L23: {=_xll.ACC(DB,_xll.ArrayDPT($AA23:$AE23),_xll.ArrayCOA($AG23:$AZ23),YR,PRD,_xll.ArrayDIM($BB23:$BE23))} -> 5835.94 | M23: =IF(L23=0,0,(L23*100/L$14)) -> 0.07366908 | N23: {=_xll.BCC(DB,_xll.ArrayDPT($AA23:$AE23),_xll.ArrayCOA($AG23:$AZ23),YR,PRD,RV,_xll.ArrayDIM($BB23:$BE23))} -> 0 | O23: =IF(N23=0,0,(N23*100/N$14)) -> 0 | P23: =+N23-L23 -> -5835.94 | Q23: =IF(P23=0,0,(P23*100/P$14)) -> 0.07366908 | R23: {=_xll.ACC(DB,_xll.ArrayDPT($AA23:$AE23),_xll.ArrayCOA($AG23:$AZ23),YR-1,PRD,_xll.ArrayDIM($BB23:$BE23))} -> 0 | S23: =IF(R23=0,0,(R23*100/R$14)) -> 0 | AA23: 103 | AB23: 104 | AG23: 42011 | AH23: 42011
A24: {=_xll.AC(DB,_xll.ArrayDPT($AA24:$AE24),_xll.ArrayCOA($AG24:$AZ24),YR-1,PRD,_xll.ArrayDIM($BB24:$BE24))} -> 3800 | B24: =IF(A24=0,0,(A24*100/A$14)) -> 0.052417268 | C24: =+E24-G24 -> 0 | D24: =IF(C24=0,0,(C24*100/C$14)) -> 0 | E24: {=_xll.BC(DB,_xll.ArrayDPT($AA24:$AE24),_xll.ArrayCOA($AG24:$AZ24),YR,PRD,RV,_xll.ArrayDIM($BB24:$BE24))} -> 0 | F24: =IF(E24=0,0,(E24*100/E$14)) -> 0 | G24: {=_xll.AC(DB,_xll.ArrayDPT($AA24:$AE24),_xll.ArrayCOA($AG24:$AZ24),YR,PRD,_xll.ArrayDIM($BB24:$BE24))} -> 0 | H24: =IF(G24=0,0,(G24*100/G$14)) -> 0 | J24: OTHER EMPLOYEE BENEFITS | L24: {=_xll.ACC(DB,_xll.ArrayDPT($AA24:$AE24),_xll.ArrayCOA($AG24:$AZ24),YR,PRD,_xll.ArrayDIM($BB24:$BE24))} -> 0 | M24: =IF(L24=0,0,(L24*100/L$14)) -> 0 | N24: {=_xll.BCC(DB,_xll.ArrayDPT($AA24:$AE24),_xll.ArrayCOA($AG24:$AZ24),YR,PRD,RV,_xll.ArrayDIM($BB24:$BE24))} -> 0 | O24: =IF(N24=0,0,(N24*100/N$14)) -> 0 | P24: =+N24-L24 -> 0 | Q24: =IF(P24=0,0,(P24*100/P$14)) -> 0 | R24: {=_xll.ACC(DB,_xll.ArrayDPT($AA24:$AE24),_xll.ArrayCOA($AG24:$AZ24),YR-1,PRD,_xll.ArrayDIM($BB24:$BE24))} -> 3800 | S24: =IF(R24=0,0,(R24*100/R$14)) -> 0.052417268 | AA24: 103 | AB24: 104 | AC24: 107 | AG24: 46070 | AH24: 46070
A26: =SUM(A16:A25) -> 277633.34 | B26: =IF(A26=0,0,(A26*100/A$14)) -> 3.8296793 | C26: =SUM(C16:C25) -> -289005.28 | D26: =IF(C26=0,0,(C26*100/C$14)) -> 3.6482131 | E26: =SUM(E16:E25) -> 0 | F26: =IF(E26=0,0,(E26*100/E$14)) -> 0 | G26: =SUM(G16:G25) -> 289005.28 | H26: =IF(G26=0,0,(G26*100/G$14)) -> 3.6482131 | J26: TOTAL PAYROLL & EMP. REL. | L26: =SUM(L16:L25) -> 289005.28 | M26: =IF(L26=0,0,(L26*100/L$14)) -> 3.6482131 | N26: =SUM(N16:N25) -> 0 | O26: =IF(N26=0,0,(N26*100/N$14)) -> 0 | P26: =SUM(P16:P25) -> -289005.28 | Q26: =IF(P26=0,0,(P26*100/P$14)) -> 3.6482131 | R26: =SUM(R16:R25) -> 277633.34 | S26: =IF(R26=0,0,(R26*100/R$14)) -> 3.8296793
J27: OTHER EXPENSES
A28: {=_xll.AC(DB,_xll.ArrayDPT($AA28:$AE28),_xll.ArrayCOA($AG28:$AZ28),YR-1,PRD,_xll.ArrayDIM($BB28:$BE28))} -> 254484.17 | B28: =IF(A28=0,0,(A28*100/A$14)) -> 3.5103592 | C28: =+E28-G28 -> -608078.65 | D28: =IF(C28=0,0,(C28*100/C$14)) -> 7.6759861 | E28: {=_xll.BC(DB,_xll.ArrayDPT($AA28:$AE28),_xll.ArrayCOA($AG28:$AZ28),YR,PRD,RV,_xll.ArrayDIM($BB28:$BE28))} -> 0 | F28: =IF(E28=0,0,(E28*100/E$14)) -> 0 | G28: {=_xll.AC(DB,_xll.ArrayDPT($AA28:$AE28),_xll.ArrayCOA($AG28:$AZ28),YR,PRD,_xll.ArrayDIM($BB28:$BE28))} -> 608078.65 | H28: =IF(G28=0,0,(G28*100/G$14)) -> 7.6759861 | J28: TRAVEL AGENCY COMMISSION | L28: {=_xll.ACC(DB,_xll.ArrayDPT($AA28:$AE28),_xll.ArrayCOA($AG28:$AZ28),YR,PRD,_xll.ArrayDIM($BB28:$BE28))} -> 608078.65 | M28: =IF(L28=0,0,(L28*100/L$14)) -> 7.6759861 | N28: {=_xll.BCC(DB,_xll.ArrayDPT($AA28:$AE28),_xll.ArrayCOA($AG28:$AZ28),YR,PRD,RV,_xll.ArrayDIM($BB28:$BE28))} -> 0 | O28: =IF(N28=0,0,(N28*100/N$14)) -> 0 | P28: =+N28-L28 -> -608078.65 | Q28: =IF(P28=0,0,(P28*100/P$14)) -> 7.6759861 | R28: {=_xll.ACC(DB,_xll.ArrayDPT($AA28:$AE28),_xll.ArrayCOA($AG28:$AZ28),YR-1,PRD,_xll.ArrayDIM($BB28:$BE28))} -> 254484.17 | S28: =IF(R28=0,0,(R28*100/R$14)) -> 3.5103592 | AA28: 103 | AB28: 107 | AG28: 50005 | AH28: 50005
A29: {=_xll.AC(DB,_xll.ArrayDPT($AA29:$AE29),_xll.ArrayCOA($AG29:$AZ29),YR-1,PRD,_xll.ArrayDIM($BB29:$BE29))} -> 24772.01 | B29: =IF(A29=0,0,(A29*100/A$14)) -> 0.34170555 | C29: =+E29-G29 -> -9435.8 | D29: =IF(C29=0,0,(C29*100/C$14)) -> 0.11911135 | E29: {=_xll.BC(DB,_xll.ArrayDPT($AA29:$AE29),_xll.ArrayCOA($AG29:$AZ29),YR,PRD,RV,_xll.ArrayDIM($BB29:$BE29))} -> 0 | F29: =IF(E29=0,0,(E29*100/E$14)) -> 0 | G29: {=_xll.AC(DB,_xll.ArrayDPT($AA29:$AE29),_xll.ArrayCOA($AG29:$AZ29),YR,PRD,_xll.ArrayDIM($BB29:$BE29))} -> 9435.8 | H29: =IF(G29=0,0,(G29*100/G$14)) -> 0.11911135 | J29: INCENTIVES INCENTIVES | L29: {=_xll.ACC(DB,_xll.ArrayDPT($AA29:$AE29),_xll.ArrayCOA($AG29:$AZ29),YR,PRD,_xll.ArrayDIM($BB29:$BE29))} -> 9435.8 | M29: =IF(L29=0,0,(L29*100/L$14)) -> 0.11911135 | N29: {=_xll.BCC(DB,_xll.ArrayDPT($AA29:$AE29),_xll.ArrayCOA($AG29:$AZ29),YR,PRD,RV,_xll.ArrayDIM($BB29:$BE29))} -> 0 | O29: =IF(N29=0,0,(N29*100/N$14)) -> 0 | P29: =+N29-L29 -> -9435.8 | Q29: =IF(P29=0,0,(P29*100/P$14)) -> 0.11911135 | R29: {=_xll.ACC(DB,_xll.ArrayDPT($AA29:$AE29),_xll.ArrayCOA($AG29:$AZ29),YR-1,PRD,_xll.ArrayDIM($BB29:$BE29))} -> 24772.01 | S29: =IF(R29=0,0,(R29*100/R$14)) -> 0.34170555 | AA29: 103 | AG29: 42025 | AH29: 42025
A30: {=_xll.AC(DB,_xll.ArrayDPT($AA30:$AE30),_xll.ArrayCOA($AG30:$AZ30),YR-1,PRD,_xll.ArrayDIM($BB30:$BE30))} -> 269564.86 | B30: =IF(A30=0,0,(A30*100/A$14)) -> 3.7183825 | C30: =+E30-G30 -> -165220.05 | D30: =IF(C30=0,0,(C30*100/C$14)) -> 2.0856296 | E30: {=_xll.BC(DB,_xll.ArrayDPT($AA30:$AE30),_xll.ArrayCOA($AG30:$AZ30),YR,PRD,RV,_xll.ArrayDIM($BB30:$BE30))} -> 0 | F30: =IF(E30=0,0,(E30*100/E$14)) -> 0 | G30: {=_xll.AC(DB,_xll.ArrayDPT($AA30:$AE30),_xll.ArrayCOA($AG30:$AZ30),YR,PRD,_xll.ArrayDIM($BB30:$BE30))} -> 165220.05 | H30: =IF(G30=0,0,(G30*100/G$14)) -> 2.0856296 | J30: RESERVATIONS | L30: {=_xll.ACC(DB,_xll.ArrayDPT($AA30:$AE30),_xll.ArrayCOA($AG30:$AZ30),YR,PRD,_xll.ArrayDIM($BB30:$BE30))} -> 165220.05 | M30: =IF(L30=0,0,(L30*100/L$14)) -> 2.0856296 | N30: {=_xll.BCC(DB,_xll.ArrayDPT($AA30:$AE30),_xll.ArrayCOA($AG30:$AZ30),YR,PRD,RV,_xll.ArrayDIM($BB30:$BE30))} -> 0 | O30: =IF(N30=0,0,(N30*100/N$14)) -> 0 | P30: =+N30-L30 -> -165220.05 | Q30: =IF(P30=0,0,(P30*100/P$14)) -> 2.0856296 | R30: {=_xll.ACC(DB,_xll.ArrayDPT($AA30:$AE30),_xll.ArrayCOA($AG30:$AZ30),YR-1,PRD,_xll.ArrayDIM($BB30:$BE30))} -> 269564.86 | S30: =IF(R30=0,0,(R30*100/R$14)) -> 3.7183825 | AA30: 107 | AG30: 51025 | AH30: 51025
A31: {=_xll.AC(DB,_xll.ArrayDPT($AA31:$AE31),_xll.ArrayCOA($AG31:$AZ31),YR-1,PRD,_xll.ArrayDIM($BB31:$BE31))} -> 0 | B31: =IF(A31=0,0,(A31*100/A$14)) -> 0 | C31: =+E31-G31 -> -42217.74 | D31: =IF(C31=0,0,(C31*100/C$14)) -> 0.53292907 | E31: {=_xll.BC(DB,_xll.ArrayDPT($AA31:$AE31),_xll.ArrayCOA($AG31:$AZ31),YR,PRD,RV,_xll.ArrayDIM($BB31:$BE31))} -> 0 | F31: =IF(E31=0,0,(E31*100/E$14)) -> 0 | G31: {=_xll.AC(DB,_xll.ArrayDPT($AA31:$AE31),_xll.ArrayCOA($AG31:$AZ31),YR,PRD,_xll.ArrayDIM($BB31:$BE31))} -> 42217.74 | H31: =IF(G31=0,0,(G31*100/G$14)) -> 0.53292907 | J31: CONTRACT SERVICE | L31: {=_xll.ACC(DB,_xll.ArrayDPT($AA31:$AE31),_xll.ArrayCOA($AG31:$AZ31),YR,PRD,_xll.ArrayDIM($BB31:$BE31))} -> 42217.74 | M31: =IF(L31=0,0,(L31*100/L$14)) -> 0.53292907 | N31: {=_xll.BCC(DB,_xll.ArrayDPT($AA31:$AE31),_xll.ArrayCOA($AG31:$AZ31),YR,PRD,RV,_xll.ArrayDIM($BB31:$BE31))} -> 0 | O31: =IF(N31=0,0,(N31*100/N$14)) -> 0 | P31: =+N31-L31 -> -42217.74 | Q31: =IF(P31=0,0,(P31*100/P$14)) -> 0.53292907 | R31: {=_xll.ACC(DB,_xll.ArrayDPT($AA31:$AE31),_xll.ArrayCOA($AG31:$AZ31),YR-1,PRD,_xll.ArrayDIM($BB31:$BE31))} -> 0 | S31: =IF(R31=0,0,(R31*100/R$14)) -> 0 | AA31: 103 | AB31: 104 | AG31: 50015 | AH31: 50015
A32: {=_xll.AC(DB,_xll.ArrayDPT($AA32:$AE32),_xll.ArrayCOA($AG32:$AZ32),YR-1,PRD,_xll.ArrayDIM($BB32:$BE32))} -> 0 | B32: =IF(A32=0,0,(A32*100/A$14)) -> 0 | C32: =+E32-G32 -> 0 | D32: =IF(C32=0,0,(C32*100/C$14)) -> 0 | E32: {=_xll.BC(DB,_xll.ArrayDPT($AA32:$AE32),_xll.ArrayCOA($AG32:$AZ32),YR,PRD,RV,_xll.ArrayDIM($BB32:$BE32))} -> 0 | F32: =IF(E32=0,0,(E32*100/E$14)) -> 0 | G32: {=_xll.AC(DB,_xll.ArrayDPT($AA32:$AE32),_xll.ArrayCOA($AG32:$AZ32),YR,PRD,_xll.ArrayDIM($BB32:$BE32))} -> 0 | H32: =IF(G32=0,0,(G32*100/G$14)) -> 0 | J32: LOYALTY PROGRAMMES | L32: {=_xll.ACC(DB,_xll.ArrayDPT($AA32:$AE32),_xll.ArrayCOA($AG32:$AZ32),YR,PRD,_xll.ArrayDIM($BB32:$BE32))} -> 0 | M32: =IF(L32=0,0,(L32*100/L$14)) -> 0 | N32: {=_xll.BCC(DB,_xll.ArrayDPT($AA32:$AE32),_xll.ArrayCOA($AG32:$AZ32),YR,PRD,RV,_xll.ArrayDIM($BB32:$BE32))} -> 0 | O32: =IF(N32=0,0,(N32*100/N$14)) -> 0 | P32: =+N32-L32 -> 0 | Q32: =IF(P32=0,0,(P32*100/P$14)) -> 0 | R32: {=_xll.ACC(DB,_xll.ArrayDPT($AA32:$AE32),_xll.ArrayCOA($AG32:$AZ32),YR-1,PRD,_xll.ArrayDIM($BB32:$BE32))} -> 0 | S32: =IF(R32=0,0,(R32*100/R$14)) -> 0 | AA32: 103 | AG32: 55135 | AH32: 55135
A33: {=_xll.AC(DB,_xll.ArrayDPT($AA33:$AE33),_xll.ArrayCOA($AG33:$AZ33),YR-1,PRD,_xll.ArrayDIM($BB33:$BE33))} -> 172926 | B33: =IF(A33=0,0,(A33*100/A$14)) -> 2.3853444 | C33: =+E33-G33 -> -105408.31 | D33: =IF(C33=0,0,(C33*100/C$14)) -> 1.3306054 | E33: {=_xll.BC(DB,_xll.ArrayDPT($AA33:$AE33),_xll.ArrayCOA($AG33:$AZ33),YR,PRD,RV,_xll.ArrayDIM($BB33:$BE33))} -> 0 | F33: =IF(E33=0,0,(E33*100/E$14)) -> 0 | G33: {=_xll.AC(DB,_xll.ArrayDPT($AA33:$AE33),_xll.ArrayCOA($AG33:$AZ33),YR,PRD,_xll.ArrayDIM($BB33:$BE33))} -> 105408.31 | H33: =IF(G33=0,0,(G33*100/G$14)) -> 1.3306054 | J33: LAUNDRY & DRY CLEANING | L33: {=_xll.ACC(DB,_xll.ArrayDPT($AA33:$AE33),_xll.ArrayCOA($AG33:$AZ33),YR,PRD,_xll.ArrayDIM($BB33:$BE33))} -> 105408.31 | M33: =IF(L33=0,0,(L33*100/L$14)) -> 1.3306054 | N33: {=_xll.BCC(DB,_xll.ArrayDPT($AA33:$AE33),_xll.ArrayCOA($AG33:$AZ33),YR,PRD,RV,_xll.ArrayDIM($BB33:$BE33))} -> 0 | O33: =IF(N33=0,0,(N33*100/N$14)) -> 0 | P33: =+N33-L33 -> -105408.31 | Q33: =IF(P33=0,0,(P33*100/P$14)) -> 1.3306054 | R33: {=_xll.ACC(DB,_xll.ArrayDPT($AA33:$AE33),_xll.ArrayCOA($AG33:$AZ33),YR-1,PRD,_xll.ArrayDIM($BB33:$BE33))} -> 172926 | S33: =IF(R33=0,0,(R33*100/R$14)) -> 2.3853444 | AA33: 104 | AG33: 50040 | AH33: 50040
A34: {=_xll.AC(DB,_xll.ArrayDPT($AA34:$AE34),_xll.ArrayCOA($AG34:$AZ34),YR-1,PRD,_xll.ArrayDIM($BB34:$BE34))} -> 0 | B34: =IF(A34=0,0,(A34*100/A$14)) -> 0 | C34: =+E34-G34 -> 0 | D34: =IF(C34=0,0,(C34*100/C$14)) -> 0 | E34: {=_xll.BC(DB,_xll.ArrayDPT($AA34:$AE34),_xll.ArrayCOA($AG34:$AZ34),YR,PRD,RV,_xll.ArrayDIM($BB34:$BE34))} -> 0 | F34: =IF(E34=0,0,(E34*100/E$14)) -> 0 | G34: {=_xll.AC(DB,_xll.ArrayDPT($AA34:$AE34),_xll.ArrayCOA($AG34:$AZ34),YR,PRD,_xll.ArrayDIM($BB34:$BE34))} -> 0 | H34: =IF(G34=0,0,(G34*100/G$14)) -> 0 | J34: SUPPLIES - LAUNDRY | L34: {=_xll.ACC(DB,_xll.ArrayDPT($AA34:$AE34),_xll.ArrayCOA($AG34:$AZ34),YR,PRD,_xll.ArrayDIM($BB34:$BE34))} -> 0 | M34: =IF(L34=0,0,(L34*100/L$14)) -> 0 | N34: {=_xll.BCC(DB,_xll.ArrayDPT($AA34:$AE34),_xll.ArrayCOA($AG34:$AZ34),YR,PRD,RV,_xll.ArrayDIM($BB34:$BE34))} -> 0 | O34: =IF(N34=0,0,(N34*100/N$14)) -> 0 | P34: =+N34-L34 -> 0 | Q34: =IF(P34=0,0,(P34*100/P$14)) -> 0 | R34: {=_xll.ACC(DB,_xll.ArrayDPT($AA34:$AE34),_xll.ArrayCOA($AG34:$AZ34),YR-1,PRD,_xll.ArrayDIM($BB34:$BE34))} -> 0 | S34: =IF(R34=0,0,(R34*100/R$14)) -> 0 | AA34: 104 | AG34: 50550 | AH34: 50550
A35: {=_xll.AC(DB,_xll.ArrayDPT($AA35:$AE35),_xll.ArrayCOA($AG35:$AZ35),YR-1,PRD,_xll.ArrayDIM($BB35:$BE35))} -> 0 | B35: =IF(A35=0,0,(A35*100/A$14)) -> 0 | C35: =+E35-G35 -> 0 | D35: =IF(C35=0,0,(C35*100/C$14)) -> 0 | E35: {=_xll.BC(DB,_xll.ArrayDPT($AA35:$AE35),_xll.ArrayCOA($AG35:$AZ35),YR,PRD,RV,_xll.ArrayDIM($BB35:$BE35))} -> 0 | F35: =IF(E35=0,0,(E35*100/E$14)) -> 0 | G35: {=_xll.AC(DB,_xll.ArrayDPT($AA35:$AE35),_xll.ArrayCOA($AG35:$AZ35),YR,PRD,_xll.ArrayDIM($BB35:$BE35))} -> 0 | H35: =IF(G35=0,0,(G35*100/G$14)) -> 0 | J35: EQUIPMENT RENTALS | L35: {=_xll.ACC(DB,_xll.ArrayDPT($AA35:$AE35),_xll.ArrayCOA($AG35:$AZ35),YR,PRD,_xll.ArrayDIM($BB35:$BE35))} -> 0 | M35: =IF(L35=0,0,(L35*100/L$14)) -> 0 | N35: {=_xll.BCC(DB,_xll.ArrayDPT($AA35:$AE35),_xll.ArrayCOA($AG35:$AZ35),YR,PRD,RV,_xll.ArrayDIM($BB35:$BE35))} -> 0 | O35: =IF(N35=0,0,(N35*100/N$14)) -> 0 | P35: =+N35-L35 -> 0 | Q35: =IF(P35=0,0,(P35*100/P$14)) -> 0 | R35: {=_xll.ACC(DB,_xll.ArrayDPT($AA35:$AE35),_xll.ArrayCOA($AG35:$AZ35),YR-1,PRD,_xll.ArrayDIM($BB35:$BE35))} -> 0 | S35: =IF(R35=0,0,(R35*100/R$14)) -> 0 | AA35: 104 | AG35: 50035 | AH35: 50035
A36: {=_xll.AC(DB,_xll.ArrayDPT($AA36:$AE36),_xll.ArrayCOA($AG36:$AZ36),YR-1,PRD,_xll.ArrayDIM($BB36:$BE36))} -> 0 | B36: =IF(A36=0,0,(A36*100/A$14)) -> 0 | C36: =+E36-G36 -> 0 | D36: =IF(C36=0,0,(C36*100/C$14)) -> 0 | E36: {=_xll.BC(DB,_xll.ArrayDPT($AA36:$AE36),_xll.ArrayCOA($AG36:$AZ36),YR,PRD,RV,_xll.ArrayDIM($BB36:$BE36))} -> 0 | F36: =IF(E36=0,0,(E36*100/E$14)) -> 0 | G36: {=_xll.AC(DB,_xll.ArrayDPT($AA36:$AE36),_xll.ArrayCOA($AG36:$AZ36),YR,PRD,_xll.ArrayDIM($BB36:$BE36))} -> 0 | H36: =IF(G36=0,0,(G36*100/G$14)) -> 0 | J36: OE EXPENSES | L36: {=_xll.ACC(DB,_xll.ArrayDPT($AA36:$AE36),_xll.ArrayCOA($AG36:$AZ36),YR,PRD,_xll.ArrayDIM($BB36:$BE36))} -> 0 | M36: =IF(L36=0,0,(L36*100/L$14)) -> 0 | N36: {=_xll.BCC(DB,_xll.ArrayDPT($AA36:$AE36),_xll.ArrayCOA($AG36:$AZ36),YR,PRD,RV,_xll.ArrayDIM($BB36:$BE36))} -> 0 | O36: =IF(N36=0,0,(N36*100/N$14)) -> 0 | P36: =+N36-L36 -> 0 | Q36: =IF(P36=0,0,(P36*100/P$14)) -> 0 | R36: {=_xll.ACC(DB,_xll.ArrayDPT($AA36:$AE36),_xll.ArrayCOA($AG36:$AZ36),YR-1,PRD,_xll.ArrayDIM($BB36:$BE36))} -> 0 | S36: =IF(R36=0,0,(R36*100/R$14)) -> 0
A37: {=_xll.AC(DB,_xll.ArrayDPT($AA37:$AE37),_xll.ArrayCOA($AG37:$AZ37),YR-1,PRD,_xll.ArrayDIM($BB37:$BE37))} -> 0 | B37: =IF(A37=0,0,(A37*100/A$14)) -> 0 | C37: =+E37-G37 -> 0 | D37: =IF(C37=0,0,(C37*100/C$14)) -> 0 | E37: {=_xll.BC(DB,_xll.ArrayDPT($AA37:$AE37),_xll.ArrayCOA($AG37:$AZ37),YR,PRD,RV,_xll.ArrayDIM($BB37:$BE37))} -> 0 | F37: =IF(E37=0,0,(E37*100/E$14)) -> 0 | G37: {=_xll.AC(DB,_xll.ArrayDPT($AA37:$AE37),_xll.ArrayCOA($AG37:$AZ37),YR,PRD,_xll.ArrayDIM($BB37:$BE37))} -> 0 | H37: =IF(G37=0,0,(G37*100/G$14)) -> 0 | J37: - OE EXPENSES - UNIFORMS | L37: {=_xll.ACC(DB,_xll.ArrayDPT($AA37:$AE37),_xll.ArrayCOA($AG37:$AZ37),YR,PRD,_xll.ArrayDIM($BB37:$BE37))} -> 0 | M37: =IF(L37=0,0,(L37*100/L$14)) -> 0 | N37: {=_xll.BCC(DB,_xll.ArrayDPT($AA37:$AE37),_xll.ArrayCOA($AG37:$AZ37),YR,PRD,RV,_xll.ArrayDIM($BB37:$BE37))} -> 0 | O37: =IF(N37=0,0,(N37*100/N$14)) -> 0 | P37: =+N37-L37 -> 0 | Q37: =IF(P37=0,0,(P37*100/P$14)) -> 0 | R37: {=_xll.ACC(DB,_xll.ArrayDPT($AA37:$AE37),_xll.ArrayCOA($AG37:$AZ37),YR-1,PRD,_xll.ArrayDIM($BB37:$BE37))} -> 0 | S37: =IF(R37=0,0,(R37*100/R$14)) -> 0
A38: {=_xll.AC(DB,_xll.ArrayDPT($AA38:$AE38),_xll.ArrayCOA($AG38:$AZ38),YR-1,PRD,_xll.ArrayDIM($BB38:$BE38))} -> 0 | B38: =IF(A38=0,0,(A38*100/A$14)) -> 0 | C38: =+E38-G38 -> 0 | D38: =IF(C38=0,0,(C38*100/C$14)) -> 0 | E38: {=_xll.BC(DB,_xll.ArrayDPT($AA38:$AE38),_xll.ArrayCOA($AG38:$AZ38),YR,PRD,RV,_xll.ArrayDIM($BB38:$BE38))} -> 0 | F38: =IF(E38=0,0,(E38*100/E$14)) -> 0 | G38: {=_xll.AC(DB,_xll.ArrayDPT($AA38:$AE38),_xll.ArrayCOA($AG38:$AZ38),YR,PRD,_xll.ArrayDIM($BB38:$BE38))} -> 0 | H38: =IF(G38=0,0,(G38*100/G$14)) -> 0 | J38: - OE EXPENSES - CHINAWARE | L38: {=_xll.ACC(DB,_xll.ArrayDPT($AA38:$AE38),_xll.ArrayCOA($AG38:$AZ38),YR,PRD,_xll.ArrayDIM($BB38:$BE38))} -> 0 | M38: =IF(L38=0,0,(L38*100/L$14)) -> 0 | N38: {=_xll.BCC(DB,_xll.ArrayDPT($AA38:$AE38),_xll.ArrayCOA($AG38:$AZ38),YR,PRD,RV,_xll.ArrayDIM($BB38:$BE38))} -> 0 | O38: =IF(N38=0,0,(N38*100/N$14)) -> 0 | P38: =+N38-L38 -> 0 | Q38: =IF(P38=0,0,(P38*100/P$14)) -> 0 | R38: {=_xll.ACC(DB,_xll.ArrayDPT($AA38:$AE38),_xll.ArrayCOA($AG38:$AZ38),YR-1,PRD,_xll.ArrayDIM($BB38:$BE38))} -> 0 | S38: =IF(R38=0,0,(R38*100/R$14)) -> 0
A39: {=_xll.AC(DB,_xll.ArrayDPT($AA39:$AE39),_xll.ArrayCOA($AG39:$AZ39),YR-1,PRD,_xll.ArrayDIM($BB39:$BE39))} -> 2808 | B39: =IF(A39=0,0,(A39*100/A$14)) -> 0.038733603 | C39: =+E39-G39 -> 0 | D39: =IF(C39=0,0,(C39*100/C$14)) -> 0 | E39: {=_xll.BC(DB,_xll.ArrayDPT($AA39:$AE39),_xll.ArrayCOA($AG39:$AZ39),YR,PRD,RV,_xll.ArrayDIM($BB39:$BE39))} -> 0 | F39: =IF(E39=0,0,(E39*100/E$14)) -> 0 | G39: {=_xll.AC(DB,_xll.ArrayDPT($AA39:$AE39),_xll.ArrayCOA($AG39:$AZ39),YR,PRD,_xll.ArrayDIM($BB39:$BE39))} -> 0 | H39: =IF(G39=0,0,(G39*100/G$14)) -> 0 | J39: - OE EXPENSES - GLASSWARE | L39: {=_xll.ACC(DB,_xll.ArrayDPT($AA39:$AE39),_xll.ArrayCOA($AG39:$AZ39),YR,PRD,_xll.ArrayDIM($BB39:$BE39))} -> 0 | M39: =IF(L39=0,0,(L39*100/L$14)) -> 0 | N39: {=_xll.BCC(DB,_xll.ArrayDPT($AA39:$AE39),_xll.ArrayCOA($AG39:$AZ39),YR,PRD,RV,_xll.ArrayDIM($BB39:$BE39))} -> 0 | O39: =IF(N39=0,0,(N39*100/N$14)) -> 0 | P39: =+N39-L39 -> 0 | Q39: =IF(P39=0,0,(P39*100/P$14)) -> 0 | R39: {=_xll.ACC(DB,_xll.ArrayDPT($AA39:$AE39),_xll.ArrayCOA($AG39:$AZ39),YR-1,PRD,_xll.ArrayDIM($BB39:$BE39))} -> 2808 | S39: =IF(R39=0,0,(R39*100/R$14)) -> 0.038733603 | AA39: 104 | AG39: 48010 | AH39: 48010
A40: {=_xll.AC(DB,_xll.ArrayDPT($AA40:$AE40),_xll.ArrayCOA($AG40:$AZ40),YR-1,PRD,_xll.ArrayDIM($BB40:$BE40))} -> 0 | B40: =IF(A40=0,0,(A40*100/A$14)) -> 0 | C40: =+E40-G40 -> 0 | D40: =IF(C40=0,0,(C40*100/C$14)) -> 0 | E40: {=_xll.BC(DB,_xll.ArrayDPT($AA40:$AE40),_xll.ArrayCOA($AG40:$AZ40),YR,PRD,RV,_xll.ArrayDIM($BB40:$BE40))} -> 0 | F40: =IF(E40=0,0,(E40*100/E$14)) -> 0 | G40: {=_xll.AC(DB,_xll.ArrayDPT($AA40:$AE40),_xll.ArrayCOA($AG40:$AZ40),YR,PRD,_xll.ArrayDIM($BB40:$BE40))} -> 0 | H40: =IF(G40=0,0,(G40*100/G$14)) -> 0 | J40: - OE EXPENSES - SILVERWARE | L40: {=_xll.ACC(DB,_xll.ArrayDPT($AA40:$AE40),_xll.ArrayCOA($AG40:$AZ40),YR,PRD,_xll.ArrayDIM($BB40:$BE40))} -> 0 | M40: =IF(L40=0,0,(L40*100/L$14)) -> 0 | N40: {=_xll.BCC(DB,_xll.ArrayDPT($AA40:$AE40),_xll.ArrayCOA($AG40:$AZ40),YR,PRD,RV,_xll.ArrayDIM($BB40:$BE40))} -> 0 | O40: =IF(N40=0,0,(N40*100/N$14)) -> 0 | P40: =+N40-L40 -> 0 | Q40: =IF(P40=0,0,(P40*100/P$14)) -> 0 | R40: {=_xll.ACC(DB,_xll.ArrayDPT($AA40:$AE40),_xll.ArrayCOA($AG40:$AZ40),YR-1,PRD,_xll.ArrayDIM($BB40:$BE40))} -> 0 | S40: =IF(R40=0,0,(R40*100/R$14)) -> 0
A41: {=_xll.AC(DB,_xll.ArrayDPT($AA41:$AE41),_xll.ArrayCOA($AG41:$AZ41),YR-1,PRD,_xll.ArrayDIM($BB41:$BE41))} -> 0 | B41: =IF(A41=0,0,(A41*100/A$14)) -> 0 | C41: =+E41-G41 -> 0 | D41: =IF(C41=0,0,(C41*100/C$14)) -> 0 | E41: {=_xll.BC(DB,_xll.ArrayDPT($AA41:$AE41),_xll.ArrayCOA($AG41:$AZ41),YR,PRD,RV,_xll.ArrayDIM($BB41:$BE41))} -> 0 | F41: =IF(E41=0,0,(E41*100/E$14)) -> 0 | G41: {=_xll.AC(DB,_xll.ArrayDPT($AA41:$AE41),_xll.ArrayCOA($AG41:$AZ41),YR,PRD,_xll.ArrayDIM($BB41:$BE41))} -> 0 | H41: =IF(G41=0,0,(G41*100/G$14)) -> 0 | J41: - OE EXPENSES - LINEN | L41: {=_xll.ACC(DB,_xll.ArrayDPT($AA41:$AE41),_xll.ArrayCOA($AG41:$AZ41),YR,PRD,_xll.ArrayDIM($BB41:$BE41))} -> 0 | M41: =IF(L41=0,0,(L41*100/L$14)) -> 0 | N41: {=_xll.BCC(DB,_xll.ArrayDPT($AA41:$AE41),_xll.ArrayCOA($AG41:$AZ41),YR,PRD,RV,_xll.ArrayDIM($BB41:$BE41))} -> 0 | O41: =IF(N41=0,0,(N41*100/N$14)) -> 0 | P41: =+N41-L41 -> 0 | Q41: =IF(P41=0,0,(P41*100/P$14)) -> 0 | R41: {=_xll.ACC(DB,_xll.ArrayDPT($AA41:$AE41),_xll.ArrayCOA($AG41:$AZ41),YR-1,PRD,_xll.ArrayDIM($BB41:$BE41))} -> 0 | S41: =IF(R41=0,0,(R41*100/R$14)) -> 0
A42: {=_xll.AC(DB,_xll.ArrayDPT($AA42:$AE42),_xll.ArrayCOA($AG42:$AZ42),YR-1,PRD,_xll.ArrayDIM($BB42:$BE42))} -> 0 | B42: =IF(A42=0,0,(A42*100/A$14)) -> 0 | C42: =+E42-G42 -> 0 | D42: =IF(C42=0,0,(C42*100/C$14)) -> 0 | E42: {=_xll.BC(DB,_xll.ArrayDPT($AA42:$AE42),_xll.ArrayCOA($AG42:$AZ42),YR,PRD,RV,_xll.ArrayDIM($BB42:$BE42))} -> 0 | F42: =IF(E42=0,0,(E42*100/E$14)) -> 0 | G42: {=_xll.AC(DB,_xll.ArrayDPT($AA42:$AE42),_xll.ArrayCOA($AG42:$AZ42),YR,PRD,_xll.ArrayDIM($BB42:$BE42))} -> 0 | H42: =IF(G42=0,0,(G42*100/G$14)) -> 0 | J42: - OE EXPENSES - OE OTHER | L42: {=_xll.ACC(DB,_xll.ArrayDPT($AA42:$AE42),_xll.ArrayCOA($AG42:$AZ42),YR,PRD,_xll.ArrayDIM($BB42:$BE42))} -> 0 | M42: =IF(L42=0,0,(L42*100/L$14)) -> 0 | N42: {=_xll.BCC(DB,_xll.ArrayDPT($AA42:$AE42),_xll.ArrayCOA($AG42:$AZ42),YR,PRD,RV,_xll.ArrayDIM($BB42:$BE42))} -> 0 | O42: =IF(N42=0,0,(N42*100/N$14)) -> 0 | P42: =+N42-L42 -> 0 | Q42: =IF(P42=0,0,(P42*100/P$14)) -> 0 | R42: {=_xll.ACC(DB,_xll.ArrayDPT($AA42:$AE42),_xll.ArrayCOA($AG42:$AZ42),YR-1,PRD,_xll.ArrayDIM($BB42:$BE42))} -> 0 | S42: =IF(R42=0,0,(R42*100/R$14)) -> 0
A43: {=_xll.AC(DB,_xll.ArrayDPT($AA43:$AE43),_xll.ArrayCOA($AG43:$AZ43),YR-1,PRD,_xll.ArrayDIM($BB43:$BE43))} -> 0 | B43: =IF(A43=0,0,(A43*100/A$14)) -> 0 | C43: =+E43-G43 -> 0 | D43: =IF(C43=0,0,(C43*100/C$14)) -> 0 | E43: {=_xll.BC(DB,_xll.ArrayDPT($AA43:$AE43),_xll.ArrayCOA($AG43:$AZ43),YR,PRD,RV,_xll.ArrayDIM($BB43:$BE43))} -> 0 | F43: =IF(E43=0,0,(E43*100/E$14)) -> 0 | G43: {=_xll.AC(DB,_xll.ArrayDPT($AA43:$AE43),_xll.ArrayCOA($AG43:$AZ43),YR,PRD,_xll.ArrayDIM($BB43:$BE43))} -> 0 | H43: =IF(G43=0,0,(G43*100/G$14)) -> 0 | J43: OPERATING SUPPLIES | L43: {=_xll.ACC(DB,_xll.ArrayDPT($AA43:$AE43),_xll.ArrayCOA($AG43:$AZ43),YR,PRD,_xll.ArrayDIM($BB43:$BE43))} -> 0 | M43: =IF(L43=0,0,(L43*100/L$14)) -> 0 | N43: {=_xll.BCC(DB,_xll.ArrayDPT($AA43:$AE43),_xll.ArrayCOA($AG43:$AZ43),YR,PRD,RV,_xll.ArrayDIM($BB43:$BE43))} -> 0 | O43: =IF(N43=0,0,(N43*100/N$14)) -> 0 | P43: =+N43-L43 -> 0 | Q43: =IF(P43=0,0,(P43*100/P$14)) -> 0 | R43: {=_xll.ACC(DB,_xll.ArrayDPT($AA43:$AE43),_xll.ArrayCOA($AG43:$AZ43),YR-1,PRD,_xll.ArrayDIM($BB43:$BE43))} -> 0 | S43: =IF(R43=0,0,(R43*100/R$14)) -> 0
A44: {=_xll.AC(DB,_xll.ArrayDPT($AA44:$AE44),_xll.ArrayCOA($AG44:$AZ44),YR-1,PRD,_xll.ArrayDIM($BB44:$BE44))} -> 72660.31 | B44: =IF(A44=0,0,(A44*100/A$14)) -> 1.0022776 | C44: =+E44-G44 -> -45440.25 | D44: =IF(C44=0,0,(C44*100/C$14)) -> 0.57360792 | E44: {=_xll.BC(DB,_xll.ArrayDPT($AA44:$AE44),_xll.ArrayCOA($AG44:$AZ44),YR,PRD,RV,_xll.ArrayDIM($BB44:$BE44))} -> 0 | F44: =IF(E44=0,0,(E44*100/E$14)) -> 0 | G44: {=_xll.AC(DB,_xll.ArrayDPT($AA44:$AE44),_xll.ArrayCOA($AG44:$AZ44),YR,PRD,_xll.ArrayDIM($BB44:$BE44))} -> 45440.25 | H44: =IF(G44=0,0,(G44*100/G$14)) -> 0.57360792 | J44: - GUEST SUPPLIES | L44: {=_xll.ACC(DB,_xll.ArrayDPT($AA44:$AE44),_xll.ArrayCOA($AG44:$AZ44),YR,PRD,_xll.ArrayDIM($BB44:$BE44))} -> 45440.25 | M44: =IF(L44=0,0,(L44*100/L$14)) -> 0.57360792 | N44: {=_xll.BCC(DB,_xll.ArrayDPT($AA44:$AE44),_xll.ArrayCOA($AG44:$AZ44),YR,PRD,RV,_xll.ArrayDIM($BB44:$BE44))} -> 0 | O44: =IF(N44=0,0,(N44*100/N$14)) -> 0 | P44: =+N44-L44 -> -45440.25 | Q44: =IF(P44=0,0,(P44*100/P$14)) -> 0.57360792 | R44: {=_xll.ACC(DB,_xll.ArrayDPT($AA44:$AE44),_xll.ArrayCOA($AG44:$AZ44),YR-1,PRD,_xll.ArrayDIM($BB44:$BE44))} -> 72660.31 | S44: =IF(R44=0,0,(R44*100/R$14)) -> 1.0022776 | AA44: 101 | AB44: 103 | AC44: 104 | AG44: 50540 | AH44: 50540
A45: {=_xll.AC(DB,_xll.ArrayDPT($AA45:$AE45),_xll.ArrayCOA($AG45:$AZ45),YR-1,PRD,_xll.ArrayDIM($BB45:$BE45))} -> 0 | B45: =IF(A45=0,0,(A45*100/A$14)) -> 0 | C45: =+E45-G45 -> -4680 | D45: =IF(C45=0,0,(C45*100/C$14)) -> 0.059077251 | E45: {=_xll.BC(DB,_xll.ArrayDPT($AA45:$AE45),_xll.ArrayCOA($AG45:$AZ45),YR,PRD,RV,_xll.ArrayDIM($BB45:$BE45))} -> 0 | F45: =IF(E45=0,0,(E45*100/E$14)) -> 0 | G45: {=_xll.AC(DB,_xll.ArrayDPT($AA45:$AE45),_xll.ArrayCOA($AG45:$AZ45),YR,PRD,_xll.ArrayDIM($BB45:$BE45))} -> 4680 | H45: =IF(G45=0,0,(G45*100/G$14)) -> 0.059077251 | J45: - OPERATION SUPPLIES | L45: {=_xll.ACC(DB,_xll.ArrayDPT($AA45:$AE45),_xll.ArrayCOA($AG45:$AZ45),YR,PRD,_xll.ArrayDIM($BB45:$BE45))} -> 4680 | M45: =IF(L45=0,0,(L45*100/L$14)) -> 0.059077251 | N45: {=_xll.BCC(DB,_xll.ArrayDPT($AA45:$AE45),_xll.ArrayCOA($AG45:$AZ45),YR,PRD,RV,_xll.ArrayDIM($BB45:$BE45))} -> 0 | O45: =IF(N45=0,0,(N45*100/N$14)) -> 0 | P45: =+N45-L45 -> -4680 | Q45: =IF(P45=0,0,(P45*100/P$14)) -> 0.059077251 | R45: {=_xll.ACC(DB,_xll.ArrayDPT($AA45:$AE45),_xll.ArrayCOA($AG45:$AZ45),YR-1,PRD,_xll.ArrayDIM($BB45:$BE45))} -> 0 | S45: =IF(R45=0,0,(R45*100/R$14)) -> 0 | AA45: 101 | AB45: 103 | AC45: 104 | AG45: 50555 | AH45: 50555
A46: {=_xll.AC(DB,_xll.ArrayDPT($AA46:$AE46),_xll.ArrayCOA($AG46:$AZ46),YR-1,PRD,_xll.ArrayDIM($BB46:$BE46))} -> 8907.48 | B46: =IF(A46=0,0,(A46*100/A$14)) -> 0.12286994 | C46: =+E46-G46 -> -6420.7 | D46: =IF(C46=0,0,(C46*100/C$14)) -> 0.081050707 | E46: {=_xll.BC(DB,_xll.ArrayDPT($AA46:$AE46),_xll.ArrayCOA($AG46:$AZ46),YR,PRD,RV,_xll.ArrayDIM($BB46:$BE46))} -> 0 | F46: =IF(E46=0,0,(E46*100/E$14)) -> 0 | G46: {=_xll.AC(DB,_xll.ArrayDPT($AA46:$AE46),_xll.ArrayCOA($AG46:$AZ46),YR,PRD,_xll.ArrayDIM($BB46:$BE46))} -> 6420.7 | H46: =IF(G46=0,0,(G46*100/G$14)) -> 0.081050707 | J46: - CLEANING SUPPLIES | L46: {=_xll.ACC(DB,_xll.ArrayDPT($AA46:$AE46),_xll.ArrayCOA($AG46:$AZ46),YR,PRD,_xll.ArrayDIM($BB46:$BE46))} -> 6420.7 | M46: =IF(L46=0,0,(L46*100/L$14)) -> 0.081050707 | N46: {=_xll.BCC(DB,_xll.ArrayDPT($AA46:$AE46),_xll.ArrayCOA($AG46:$AZ46),YR,PRD,RV,_xll.ArrayDIM($BB46:$BE46))} -> 0 | O46: =IF(N46=0,0,(N46*100/N$14)) -> 0 | P46: =+N46-L46 -> -6420.7 | Q46: =IF(P46=0,0,(P46*100/P$14)) -> 0.081050707 | R46: {=_xll.ACC(DB,_xll.ArrayDPT($AA46:$AE46),_xll.ArrayCOA($AG46:$AZ46),YR-1,PRD,_xll.ArrayDIM($BB46:$BE46))} -> 8907.48 | S46: =IF(R46=0,0,(R46*100/R$14)) -> 0.12286994 | AA46: 101 | AB46: 103 | AC46: 104 | AG46: 50505 | AH46: 50505
A47: {=_xll.AC(DB,_xll.ArrayDPT($AA47:$AE47),_xll.ArrayCOA($AG47:$AZ47),YR-1,PRD,_xll.ArrayDIM($BB47:$BE47))} -> 29392.99 | B47: =IF(A47=0,0,(A47*100/A$14)) -> 0.40544743 | C47: =+E47-G47 -> -11280.41 | D47: =IF(C47=0,0,(C47*100/C$14)) -> 0.1423965 | E47: {=_xll.BC(DB,_xll.ArrayDPT($AA47:$AE47),_xll.ArrayCOA($AG47:$AZ47),YR,PRD,RV,_xll.ArrayDIM($BB47:$BE47))} -> 0 | F47: =IF(E47=0,0,(E47*100/E$14)) -> 0 | G47: {=_xll.AC(DB,_xll.ArrayDPT($AA47:$AE47),_xll.ArrayCOA($AG47:$AZ47),YR,PRD,_xll.ArrayDIM($BB47:$BE47))} -> 11280.41 | H47: =IF(G47=0,0,(G47*100/G$14)) -> 0.1423965 | J47: - PRINTING & STATIONERY | L47: {=_xll.ACC(DB,_xll.ArrayDPT($AA47:$AE47),_xll.ArrayCOA($AG47:$AZ47),YR,PRD,_xll.ArrayDIM($BB47:$BE47))} -> 11280.41 | M47: =IF(L47=0,0,(L47*100/L$14)) -> 0.1423965 | N47: {=_xll.BCC(DB,_xll.ArrayDPT($AA47:$AE47),_xll.ArrayCOA($AG47:$AZ47),YR,PRD,RV,_xll.ArrayDIM($BB47:$BE47))} -> 0 | O47: =IF(N47=0,0,(N47*100/N$14)) -> 0 | P47: =+N47-L47 -> -11280.41 | Q47: =IF(P47=0,0,(P47*100/P$14)) -> 0.1423965 | R47: {=_xll.ACC(DB,_xll.ArrayDPT($AA47:$AE47),_xll.ArrayCOA($AG47:$AZ47),YR-1,PRD,_xll.ArrayDIM($BB47:$BE47))} -> 29392.99 | S47: =IF(R47=0,0,(R47*100/R$14)) -> 0.40544743 | AA47: 101 | AB47: 103 | AC47: 104 | AD47: 107 | AG47: 50065 | AH47: 50065
A48: {=_xll.AC(DB,_xll.ArrayDPT($AA48:$AE48),_xll.ArrayCOA($AG48:$AZ48),YR-1,PRD,_xll.ArrayDIM($BB48:$BE48))} -> 0 | B48: =IF(A48=0,0,(A48*100/A$14)) -> 0 | C48: =+E48-G48 -> 0 | D48: =IF(C48=0,0,(C48*100/C$14)) -> 0 | E48: {=_xll.BC(DB,_xll.ArrayDPT($AA48:$AE48),_xll.ArrayCOA($AG48:$AZ48),YR,PRD,RV,_xll.ArrayDIM($BB48:$BE48))} -> 0 | F48: =IF(E48=0,0,(E48*100/E$14)) -> 0 | G48: {=_xll.AC(DB,_xll.ArrayDPT($AA48:$AE48),_xll.ArrayCOA($AG48:$AZ48),YR,PRD,_xll.ArrayDIM($BB48:$BE48))} -> 0 | H48: =IF(G48=0,0,(G48*100/G$14)) -> 0 | J48: OTHER OPERATING EXPENSES | L48: {=_xll.ACC(DB,_xll.ArrayDPT($AA48:$AE48),_xll.ArrayCOA($AG48:$AZ48),YR,PRD,_xll.ArrayDIM($BB48:$BE48))} -> 0 | M48: =IF(L48=0,0,(L48*100/L$14)) -> 0 | N48: {=_xll.BCC(DB,_xll.ArrayDPT($AA48:$AE48),_xll.ArrayCOA($AG48:$AZ48),YR,PRD,RV,_xll.ArrayDIM($BB48:$BE48))} -> 0 | O48: =IF(N48=0,0,(N48*100/N$14)) -> 0 | P48: =+N48-L48 -> 0 | Q48: =IF(P48=0,0,(P48*100/P$14)) -> 0 | R48: {=_xll.ACC(DB,_xll.ArrayDPT($AA48:$AE48),_xll.ArrayCOA($AG48:$AZ48),YR-1,PRD,_xll.ArrayDIM($BB48:$BE48))} -> 0 | S48: =IF(R48=0,0,(R48*100/R$14)) -> 0
A49: {=_xll.AC(DB,_xll.ArrayDPT($AA49:$AE49),_xll.ArrayCOA($AG49:$AZ49),YR-1,PRD,_xll.ArrayDIM($BB49:$BE49))} -> 5337 | B49: =IF(A49=0,0,(A49*100/A$14)) -> 0.073618674 | C49: =+E49-G49 -> 0 | D49: =IF(C49=0,0,(C49*100/C$14)) -> 0 | E49: {=_xll.BC(DB,_xll.ArrayDPT($AA49:$AE49),_xll.ArrayCOA($AG49:$AZ49),YR,PRD,RV,_xll.ArrayDIM($BB49:$BE49))} -> 0 | F49: =IF(E49=0,0,(E49*100/E$14)) -> 0 | G49: {=_xll.AC(DB,_xll.ArrayDPT($AA49:$AE49),_xll.ArrayCOA($AG49:$AZ49),YR,PRD,_xll.ArrayDIM($BB49:$BE49))} -> 0 | H49: =IF(G49=0,0,(G49*100/G$14)) -> 0 | J49: - FLOWER & DECORATION | L49: {=_xll.ACC(DB,_xll.ArrayDPT($AA49:$AE49),_xll.ArrayCOA($AG49:$AZ49),YR,PRD,_xll.ArrayDIM($BB49:$BE49))} -> 0 | M49: =IF(L49=0,0,(L49*100/L$14)) -> 0 | N49: {=_xll.BCC(DB,_xll.ArrayDPT($AA49:$AE49),_xll.ArrayCOA($AG49:$AZ49),YR,PRD,RV,_xll.ArrayDIM($BB49:$BE49))} -> 0 | O49: =IF(N49=0,0,(N49*100/N$14)) -> 0 | P49: =+N49-L49 -> 0 | Q49: =IF(P49=0,0,(P49*100/P$14)) -> 0 | R49: {=_xll.ACC(DB,_xll.ArrayDPT($AA49:$AE49),_xll.ArrayCOA($AG49:$AZ49),YR-1,PRD,_xll.ArrayDIM($BB49:$BE49))} -> 5337 | S49: =IF(R49=0,0,(R49*100/R$14)) -> 0.073618674 | AA49: 101 | AB49: 103 | AC49: 104 | AD49: 107 | AG49: 50025 | AH49: 50025
A50: {=_xll.AC(DB,_xll.ArrayDPT($AA50:$AE50),_xll.ArrayCOA($AG50:$AZ50),YR-1,PRD,_xll.ArrayDIM($BB50:$BE50))} -> 11620.56 | B50: =IF(A50=0,0,(A50*100/A$14)) -> 0.16029421 | C50: =+E50-G50 -> 0 | D50: =IF(C50=0,0,(C50*100/C$14)) -> 0 | E50: {=_xll.BC(DB,_xll.ArrayDPT($AA50:$AE50),_xll.ArrayCOA($AG50:$AZ50),YR,PRD,RV,_xll.ArrayDIM($BB50:$BE50))} -> 0 | F50: =IF(E50=0,0,(E50*100/E$14)) -> 0 | G50: {=_xll.AC(DB,_xll.ArrayDPT($AA50:$AE50),_xll.ArrayCOA($AG50:$AZ50),YR,PRD,_xll.ArrayDIM($BB50:$BE50))} -> 0 | H50: =IF(G50=0,0,(G50*100/G$14)) -> 0 | J50: - GUEST TRANSPORTATION | L50: {=_xll.ACC(DB,_xll.ArrayDPT($AA50:$AE50),_xll.ArrayCOA($AG50:$AZ50),YR,PRD,_xll.ArrayDIM($BB50:$BE50))} -> 0 | M50: =IF(L50=0,0,(L50*100/L$14)) -> 0 | N50: {=_xll.BCC(DB,_xll.ArrayDPT($AA50:$AE50),_xll.ArrayCOA($AG50:$AZ50),YR,PRD,RV,_xll.ArrayDIM($BB50:$BE50))} -> 0 | O50: =IF(N50=0,0,(N50*100/N$14)) -> 0 | P50: =+N50-L50 -> 0 | Q50: =IF(P50=0,0,(P50*100/P$14)) -> 0 | R50: {=_xll.ACC(DB,_xll.ArrayDPT($AA50:$AE50),_xll.ArrayCOA($AG50:$AZ50),YR-1,PRD,_xll.ArrayDIM($BB50:$BE50))} -> 11620.56 | S50: =IF(R50=0,0,(R50*100/R$14)) -> 0.16029421 | AA50: 103 | AG50: 51030 | AH50: 51030
A51: {=_xll.AC(DB,_xll.ArrayDPT($AA51:$AE51),_xll.ArrayCOA($AG51:$AZ51),YR-1,PRD,_xll.ArrayDIM($BB51:$BE51))} -> 0 | B51: =IF(A51=0,0,(A51*100/A$14)) -> 0 | C51: =+E51-G51 -> 0 | D51: =IF(C51=0,0,(C51*100/C$14)) -> 0 | E51: {=_xll.BC(DB,_xll.ArrayDPT($AA51:$AE51),_xll.ArrayCOA($AG51:$AZ51),YR,PRD,RV,_xll.ArrayDIM($BB51:$BE51))} -> 0 | F51: =IF(E51=0,0,(E51*100/E$14)) -> 0 | G51: {=_xll.AC(DB,_xll.ArrayDPT($AA51:$AE51),_xll.ArrayCOA($AG51:$AZ51),YR,PRD,_xll.ArrayDIM($BB51:$BE51))} -> 0 | H51: =IF(G51=0,0,(G51*100/G$14)) -> 0 | J51: - LICENCE & TAXES | L51: {=_xll.ACC(DB,_xll.ArrayDPT($AA51:$AE51),_xll.ArrayCOA($AG51:$AZ51),YR,PRD,_xll.ArrayDIM($BB51:$BE51))} -> 0 | M51: =IF(L51=0,0,(L51*100/L$14)) -> 0 | N51: {=_xll.BCC(DB,_xll.ArrayDPT($AA51:$AE51),_xll.ArrayCOA($AG51:$AZ51),YR,PRD,RV,_xll.ArrayDIM($BB51:$BE51))} -> 0 | O51: =IF(N51=0,0,(N51*100/N$14)) -> 0 | P51: =+N51-L51 -> 0 | Q51: =IF(P51=0,0,(P51*100/P$14)) -> 0 | R51: {=_xll.ACC(DB,_xll.ArrayDPT($AA51:$AE51),_xll.ArrayCOA($AG51:$AZ51),YR-1,PRD,_xll.ArrayDIM($BB51:$BE51))} -> 0 | S51: =IF(R51=0,0,(R51*100/R$14)) -> 0 | AA51: 101 | AB51: 103 | AC51: 104 | AG51: 50045 | AH51: 50045
A52: {=_xll.AC(DB,_xll.ArrayDPT($AA52:$AE52),_xll.ArrayCOA($AG52:$AZ52),YR-1,PRD,_xll.ArrayDIM($BB52:$BE52))} -> 0 | B52: =IF(A52=0,0,(A52*100/A$14)) -> 0 | C52: =+E52-G52 -> 0 | D52: =IF(C52=0,0,(C52*100/C$14)) -> 0 | E52: {=_xll.BC(DB,_xll.ArrayDPT($AA52:$AE52),_xll.ArrayCOA($AG52:$AZ52),YR,PRD,RV,_xll.ArrayDIM($BB52:$BE52))} -> 0 | F52: =IF(E52=0,0,(E52*100/E$14)) -> 0 | G52: {=_xll.AC(DB,_xll.ArrayDPT($AA52:$AE52),_xll.ArrayCOA($AG52:$AZ52),YR,PRD,_xll.ArrayDIM($BB52:$BE52))} -> 0 | H52: =IF(G52=0,0,(G52*100/G$14)) -> 0 | J52: - GUEST RELOCATION | L52: {=_xll.ACC(DB,_xll.ArrayDPT($AA52:$AE52),_xll.ArrayCOA($AG52:$AZ52),YR,PRD,_xll.ArrayDIM($BB52:$BE52))} -> 0 | M52: =IF(L52=0,0,(L52*100/L$14)) -> 0 | N52: {=_xll.BCC(DB,_xll.ArrayDPT($AA52:$AE52),_xll.ArrayCOA($AG52:$AZ52),YR,PRD,RV,_xll.ArrayDIM($BB52:$BE52))} -> 0 | O52: =IF(N52=0,0,(N52*100/N$14)) -> 0 | P52: =+N52-L52 -> 0 | Q52: =IF(P52=0,0,(P52*100/P$14)) -> 0 | R52: {=_xll.ACC(DB,_xll.ArrayDPT($AA52:$AE52),_xll.ArrayCOA($AG52:$AZ52),YR-1,PRD,_xll.ArrayDIM($BB52:$BE52))} -> 0 | S52: =IF(R52=0,0,(R52*100/R$14)) -> 0 | AA52: 101 | AG52: 51015 | AH52: 51015
A53: {=_xll.AC(DB,_xll.ArrayDPT($AA53:$AE53),_xll.ArrayCOA($AG53:$AZ53),YR-1,PRD,_xll.ArrayDIM($BB53:$BE53))} -> 155000 | B53: =IF(A53=0,0,(A53*100/A$14)) -> 2.1380728 | C53: =+E53-G53 -> 0 | D53: =IF(C53=0,0,(C53*100/C$14)) -> 0 | E53: {=_xll.BC(DB,_xll.ArrayDPT($AA53:$AE53),_xll.ArrayCOA($AG53:$AZ53),YR,PRD,RV,_xll.ArrayDIM($BB53:$BE53))} -> 0 | F53: =IF(E53=0,0,(E53*100/E$14)) -> 0 | G53: {=_xll.AC(DB,_xll.ArrayDPT($AA53:$AE53),_xll.ArrayCOA($AG53:$AZ53),YR,PRD,_xll.ArrayDIM($BB53:$BE53))} -> 0 | H53: =IF(G53=0,0,(G53*100/G$14)) -> 0 | J53: - CABLE / SATELLITE TELEVISION | L53: {=_xll.ACC(DB,_xll.ArrayDPT($AA53:$AE53),_xll.ArrayCOA($AG53:$AZ53),YR,PRD,_xll.ArrayDIM($BB53:$BE53))} -> 0 | M53: =IF(L53=0,0,(L53*100/L$14)) -> 0 | N53: {=_xll.BCC(DB,_xll.ArrayDPT($AA53:$AE53),_xll.ArrayCOA($AG53:$AZ53),YR,PRD,RV,_xll.ArrayDIM($BB53:$BE53))} -> 0 | O53: =IF(N53=0,0,(N53*100/N$14)) -> 0 | P53: =+N53-L53 -> 0 | Q53: =IF(P53=0,0,(P53*100/P$14)) -> 0 | R53: {=_xll.ACC(DB,_xll.ArrayDPT($AA53:$AE53),_xll.ArrayCOA($AG53:$AZ53),YR-1,PRD,_xll.ArrayDIM($BB53:$BE53))} -> 155000 | S53: =IF(R53=0,0,(R53*100/R$14)) -> 2.1380728 | AA53: 103 | AG53: 51005 | AH53: 51005
A54: {=_xll.AC(DB,_xll.ArrayDPT($AA54:$AE54),_xll.ArrayCOA($AG54:$AZ54),YR-1,PRD,_xll.ArrayDIM($BB54:$BE54))} -> 0 | B54: =IF(A54=0,0,(A54*100/A$14)) -> 0 | C54: =+E54-G54 -> 0 | D54: =IF(C54=0,0,(C54*100/C$14)) -> 0 | E54: {=_xll.BC(DB,_xll.ArrayDPT($AA54:$AE54),_xll.ArrayCOA($AG54:$AZ54),YR,PRD,RV,_xll.ArrayDIM($BB54:$BE54))} -> 0 | F54: =IF(E54=0,0,(E54*100/E$14)) -> 0 | G54: {=_xll.AC(DB,_xll.ArrayDPT($AA54:$AE54),_xll.ArrayCOA($AG54:$AZ54),YR,PRD,_xll.ArrayDIM($BB54:$BE54))} -> 0 | H54: =IF(G54=0,0,(G54*100/G$14)) -> 0 | J54: - INTERNET / SERVIEC FOR GUEST | L54: {=_xll.ACC(DB,_xll.ArrayDPT($AA54:$AE54),_xll.ArrayCOA($AG54:$AZ54),YR,PRD,_xll.ArrayDIM($BB54:$BE54))} -> 0 | M54: =IF(L54=0,0,(L54*100/L$14)) -> 0 | N54: {=_xll.BCC(DB,_xll.ArrayDPT($AA54:$AE54),_xll.ArrayCOA($AG54:$AZ54),YR,PRD,RV,_xll.ArrayDIM($BB54:$BE54))} -> 0 | O54: =IF(N54=0,0,(N54*100/N$14)) -> 0 | P54: =+N54-L54 -> 0 | Q54: =IF(P54=0,0,(P54*100/P$14)) -> 0 | R54: {=_xll.ACC(DB,_xll.ArrayDPT($AA54:$AE54),_xll.ArrayCOA($AG54:$AZ54),YR-1,PRD,_xll.ArrayDIM($BB54:$BE54))} -> 0 | S54: =IF(R54=0,0,(R54*100/R$14)) -> 0 | AA54: 101 | AG54: 50072 | AH54: 50072
A55: {=_xll.AC(DB,_xll.ArrayDPT($AA55:$AE55),_xll.ArrayCOA($AG55:$AZ55),YR-1,PRD,_xll.ArrayDIM($BB55:$BE55))} -> 0 | B55: =IF(A55=0,0,(A55*100/A$14)) -> 0 | C55: =+E55-G55 -> 0 | D55: =IF(C55=0,0,(C55*100/C$14)) -> 0 | E55: {=_xll.BC(DB,_xll.ArrayDPT($AA55:$AE55),_xll.ArrayCOA($AG55:$AZ55),YR,PRD,RV,_xll.ArrayDIM($BB55:$BE55))} -> 0 | F55: =IF(E55=0,0,(E55*100/E$14)) -> 0 | G55: {=_xll.AC(DB,_xll.ArrayDPT($AA55:$AE55),_xll.ArrayCOA($AG55:$AZ55),YR,PRD,_xll.ArrayDIM($BB55:$BE55))} -> 0 | H55: =IF(G55=0,0,(G55*100/G$14)) -> 0 | J55: - ONLINE RESERVATION SERVICE | L55: {=_xll.ACC(DB,_xll.ArrayDPT($AA55:$AE55),_xll.ArrayCOA($AG55:$AZ55),YR,PRD,_xll.ArrayDIM($BB55:$BE55))} -> 0 | M55: =IF(L55=0,0,(L55*100/L$14)) -> 0 | N55: {=_xll.BCC(DB,_xll.ArrayDPT($AA55:$AE55),_xll.ArrayCOA($AG55:$AZ55),YR,PRD,RV,_xll.ArrayDIM($BB55:$BE55))} -> 0 | O55: =IF(N55=0,0,(N55*100/N$14)) -> 0 | P55: =+N55-L55 -> 0 | Q55: =IF(P55=0,0,(P55*100/P$14)) -> 0 | R55: {=_xll.ACC(DB,_xll.ArrayDPT($AA55:$AE55),_xll.ArrayCOA($AG55:$AZ55),YR-1,PRD,_xll.ArrayDIM($BB55:$BE55))} -> 0 | S55: =IF(R55=0,0,(R55*100/R$14)) -> 0
A56: {=_xll.AC(DB,_xll.ArrayDPT($AA56:$AE56),_xll.ArrayCOA($AG56:$AZ56),YR-1,PRD,_xll.ArrayDIM($BB56:$BE56))} -> 0 | B56: =IF(A56=0,0,(A56*100/A$14)) -> 0 | C56: =+E56-G56 -> 0 | D56: =IF(C56=0,0,(C56*100/C$14)) -> 0 | E56: {=_xll.BC(DB,_xll.ArrayDPT($AA56:$AE56),_xll.ArrayCOA($AG56:$AZ56),YR,PRD,RV,_xll.ArrayDIM($BB56:$BE56))} -> 0 | F56: =IF(E56=0,0,(E56*100/E$14)) -> 0 | G56: {=_xll.AC(DB,_xll.ArrayDPT($AA56:$AE56),_xll.ArrayCOA($AG56:$AZ56),YR,PRD,_xll.ArrayDIM($BB56:$BE56))} -> 0 | H56: =IF(G56=0,0,(G56*100/G$14)) -> 0 | J56: MEETING EXPENSES | L56: {=_xll.ACC(DB,_xll.ArrayDPT($AA56:$AE56),_xll.ArrayCOA($AG56:$AZ56),YR,PRD,_xll.ArrayDIM($BB56:$BE56))} -> 0 | M56: =IF(L56=0,0,(L56*100/L$14)) -> 0 | N56: {=_xll.BCC(DB,_xll.ArrayDPT($AA56:$AE56),_xll.ArrayCOA($AG56:$AZ56),YR,PRD,RV,_xll.ArrayDIM($BB56:$BE56))} -> 0 | O56: =IF(N56=0,0,(N56*100/N$14)) -> 0 | P56: =+N56-L56 -> 0 | Q56: =IF(P56=0,0,(P56*100/P$14)) -> 0 | R56: {=_xll.ACC(DB,_xll.ArrayDPT($AA56:$AE56),_xll.ArrayCOA($AG56:$AZ56),YR-1,PRD,_xll.ArrayDIM($BB56:$BE56))} -> 0 | S56: =IF(R56=0,0,(R56*100/R$14)) -> 0
A57: {=_xll.AC(DB,_xll.ArrayDPT($AA57:$AE57),_xll.ArrayCOA($AG57:$AZ57),YR-1,PRD,_xll.ArrayDIM($BB57:$BE57))} -> 0 | B57: =IF(A57=0,0,(A57*100/A$14)) -> 0 | C57: =+E57-G57 -> 0 | D57: =IF(C57=0,0,(C57*100/C$14)) -> 0 | E57: {=_xll.BC(DB,_xll.ArrayDPT($AA57:$AE57),_xll.ArrayCOA($AG57:$AZ57),YR,PRD,RV,_xll.ArrayDIM($BB57:$BE57))} -> 0 | F57: =IF(E57=0,0,(E57*100/E$14)) -> 0 | G57: {=_xll.AC(DB,_xll.ArrayDPT($AA57:$AE57),_xll.ArrayCOA($AG57:$AZ57),YR,PRD,_xll.ArrayDIM($BB57:$BE57))} -> 0 | H57: =IF(G57=0,0,(G57*100/G$14)) -> 0 | J57: DUES & SUBSCRIPTIONS | L57: {=_xll.ACC(DB,_xll.ArrayDPT($AA57:$AE57),_xll.ArrayCOA($AG57:$AZ57),YR,PRD,_xll.ArrayDIM($BB57:$BE57))} -> 0 | M57: =IF(L57=0,0,(L57*100/L$14)) -> 0 | N57: {=_xll.BCC(DB,_xll.ArrayDPT($AA57:$AE57),_xll.ArrayCOA($AG57:$AZ57),YR,PRD,RV,_xll.ArrayDIM($BB57:$BE57))} -> 0 | O57: =IF(N57=0,0,(N57*100/N$14)) -> 0 | P57: =+N57-L57 -> 0 | Q57: =IF(P57=0,0,(P57*100/P$14)) -> 0 | R57: {=_xll.ACC(DB,_xll.ArrayDPT($AA57:$AE57),_xll.ArrayCOA($AG57:$AZ57),YR-1,PRD,_xll.ArrayDIM($BB57:$BE57))} -> 0 | S57: =IF(R57=0,0,(R57*100/R$14)) -> 0 | AA57: 107 | AB57: 104 | AG57: 50030 | AH57: 50030
A58: {=_xll.AC(DB,_xll.ArrayDPT($AA58:$AE58),_xll.ArrayCOA($AG58:$AZ58),YR-1,PRD,_xll.ArrayDIM($BB58:$BE58))} -> 0 | B58: =IF(A58=0,0,(A58*100/A$14)) -> 0 | C58: =+E58-G58 -> 0 | D58: =IF(C58=0,0,(C58*100/C$14)) -> 0 | E58: {=_xll.BC(DB,_xll.ArrayDPT($AA58:$AE58),_xll.ArrayCOA($AG58:$AZ58),YR,PRD,RV,_xll.ArrayDIM($BB58:$BE58))} -> 0 | F58: =IF(E58=0,0,(E58*100/E$14)) -> 0 | G58: {=_xll.AC(DB,_xll.ArrayDPT($AA58:$AE58),_xll.ArrayCOA($AG58:$AZ58),YR,PRD,_xll.ArrayDIM($BB58:$BE58))} -> 0 | H58: =IF(G58=0,0,(G58*100/G$14)) -> 0 | J58: GUEST ENTERTAINMENT | L58: {=_xll.ACC(DB,_xll.ArrayDPT($AA58:$AE58),_xll.ArrayCOA($AG58:$AZ58),YR,PRD,_xll.ArrayDIM($BB58:$BE58))} -> 0 | M58: =IF(L58=0,0,(L58*100/L$14)) -> 0 | N58: {=_xll.BCC(DB,_xll.ArrayDPT($AA58:$AE58),_xll.ArrayCOA($AG58:$AZ58),YR,PRD,RV,_xll.ArrayDIM($BB58:$BE58))} -> 0 | O58: =IF(N58=0,0,(N58*100/N$14)) -> 0 | P58: =+N58-L58 -> 0 | Q58: =IF(P58=0,0,(P58*100/P$14)) -> 0 | R58: {=_xll.ACC(DB,_xll.ArrayDPT($AA58:$AE58),_xll.ArrayCOA($AG58:$AZ58),YR-1,PRD,_xll.ArrayDIM($BB58:$BE58))} -> 0 | S58: =IF(R58=0,0,(R58*100/R$14)) -> 0 | AA58: 101 | AB58: 103 | AC58: 107 | AG58: 50032 | AH58: 50032
A59: {=_xll.AC(DB,_xll.ArrayDPT($AA59:$AE59),_xll.ArrayCOA($AG59:$AZ59),YR-1,PRD,_xll.ArrayDIM($BB59:$BE59))} -> 0 | B59: =IF(A59=0,0,(A59*100/A$14)) -> 0 | C59: =+E59-G59 -> 0 | D59: =IF(C59=0,0,(C59*100/C$14)) -> 0 | E59: {=_xll.BC(DB,_xll.ArrayDPT($AA59:$AE59),_xll.ArrayCOA($AG59:$AZ59),YR,PRD,RV,_xll.ArrayDIM($BB59:$BE59))} -> 0 | F59: =IF(E59=0,0,(E59*100/E$14)) -> 0 | G59: {=_xll.AC(DB,_xll.ArrayDPT($AA59:$AE59),_xll.ArrayCOA($AG59:$AZ59),YR,PRD,_xll.ArrayDIM($BB59:$BE59))} -> 0 | H59: =IF(G59=0,0,(G59*100/G$14)) -> 0 | J59: TELEPHONE ,FAX ,INTERNET & POSTAGE | L59: {=_xll.ACC(DB,_xll.ArrayDPT($AA59:$AE59),_xll.ArrayCOA($AG59:$AZ59),YR,PRD,_xll.ArrayDIM($BB59:$BE59))} -> 0 | M59: =IF(L59=0,0,(L59*100/L$14)) -> 0 | N59: {=_xll.BCC(DB,_xll.ArrayDPT($AA59:$AE59),_xll.ArrayCOA($AG59:$AZ59),YR,PRD,RV,_xll.ArrayDIM($BB59:$BE59))} -> 0 | O59: =IF(N59=0,0,(N59*100/N$14)) -> 0 | P59: =+N59-L59 -> 0 | Q59: =IF(P59=0,0,(P59*100/P$14)) -> 0 | R59: {=_xll.ACC(DB,_xll.ArrayDPT($AA59:$AE59),_xll.ArrayCOA($AG59:$AZ59),YR-1,PRD,_xll.ArrayDIM($BB59:$BE59))} -> 0 | S59: =IF(R59=0,0,(R59*100/R$14)) -> 0
A60: {=_xll.AC(DB,_xll.ArrayDPT($AA60:$AE60),_xll.ArrayCOA($AG60:$AZ60),YR-1,PRD,_xll.ArrayDIM($BB60:$BE60))} -> 0 | B60: =IF(A60=0,0,(A60*100/A$14)) -> 0 | C60: =+E60-G60 -> 0 | D60: =IF(C60=0,0,(C60*100/C$14)) -> 0 | E60: {=_xll.BC(DB,_xll.ArrayDPT($AA60:$AE60),_xll.ArrayCOA($AG60:$AZ60),YR,PRD,RV,_xll.ArrayDIM($BB60:$BE60))} -> 0 | F60: =IF(E60=0,0,(E60*100/E$14)) -> 0 | G60: {=_xll.AC(DB,_xll.ArrayDPT($AA60:$AE60),_xll.ArrayCOA($AG60:$AZ60),YR,PRD,_xll.ArrayDIM($BB60:$BE60))} -> 0 | H60: =IF(G60=0,0,(G60*100/G$14)) -> 0 | J60: POSTAGE & COURIER / STAMP | L60: {=_xll.ACC(DB,_xll.ArrayDPT($AA60:$AE60),_xll.ArrayCOA($AG60:$AZ60),YR,PRD,_xll.ArrayDIM($BB60:$BE60))} -> 0 | M60: =IF(L60=0,0,(L60*100/L$14)) -> 0 | N60: {=_xll.BCC(DB,_xll.ArrayDPT($AA60:$AE60),_xll.ArrayCOA($AG60:$AZ60),YR,PRD,RV,_xll.ArrayDIM($BB60:$BE60))} -> 0 | O60: =IF(N60=0,0,(N60*100/N$14)) -> 0 | P60: =+N60-L60 -> 0 | Q60: =IF(P60=0,0,(P60*100/P$14)) -> 0 | R60: {=_xll.ACC(DB,_xll.ArrayDPT($AA60:$AE60),_xll.ArrayCOA($AG60:$AZ60),YR-1,PRD,_xll.ArrayDIM($BB60:$BE60))} -> 0 | S60: =IF(R60=0,0,(R60*100/R$14)) -> 0 | AA60: 101 | AB60: 103 | AC60: 104 | AD60: 107 | AG60: 50060 | AH60: 50060
A61: {=_xll.AC(DB,_xll.ArrayDPT($AA61:$AE61),_xll.ArrayCOA($AG61:$AZ61),YR-1,PRD,_xll.ArrayDIM($BB61:$BE61))} -> 0 | B61: =IF(A61=0,0,(A61*100/A$14)) -> 0 | C61: =+E61-G61 -> 0 | D61: =IF(C61=0,0,(C61*100/C$14)) -> 0 | E61: {=_xll.BC(DB,_xll.ArrayDPT($AA61:$AE61),_xll.ArrayCOA($AG61:$AZ61),YR,PRD,RV,_xll.ArrayDIM($BB61:$BE61))} -> 0 | F61: =IF(E61=0,0,(E61*100/E$14)) -> 0 | G61: {=_xll.AC(DB,_xll.ArrayDPT($AA61:$AE61),_xll.ArrayCOA($AG61:$AZ61),YR,PRD,_xll.ArrayDIM($BB61:$BE61))} -> 0 | H61: =IF(G61=0,0,(G61*100/G$14)) -> 0 | J61: MUSICIAN & ENTERTAINMENT | L61: {=_xll.ACC(DB,_xll.ArrayDPT($AA61:$AE61),_xll.ArrayCOA($AG61:$AZ61),YR,PRD,_xll.ArrayDIM($BB61:$BE61))} -> 0 | M61: =IF(L61=0,0,(L61*100/L$14)) -> 0 | N61: {=_xll.BCC(DB,_xll.ArrayDPT($AA61:$AE61),_xll.ArrayCOA($AG61:$AZ61),YR,PRD,RV,_xll.ArrayDIM($BB61:$BE61))} -> 0 | O61: =IF(N61=0,0,(N61*100/N$14)) -> 0 | P61: =+N61-L61 -> 0 | Q61: =IF(P61=0,0,(P61*100/P$14)) -> 0 | R61: {=_xll.ACC(DB,_xll.ArrayDPT($AA61:$AE61),_xll.ArrayCOA($AG61:$AZ61),YR-1,PRD,_xll.ArrayDIM($BB61:$BE61))} -> 0 | S61: =IF(R61=0,0,(R61*100/R$14)) -> 0 | AA61: 101 | AB61: 103 | AC61: 107 | AG61: 52025 | AH61: 52025
A62: {=_xll.AC(DB,_xll.ArrayDPT($AA62:$AE62),_xll.ArrayCOA($AG62:$AZ62),YR-1,PRD,_xll.ArrayDIM($BB62:$BE62))} -> 720 | B62: =IF(A62=0,0,(A62*100/A$14)) -> 0.009931693 | C62: =+E62-G62 -> 0 | D62: =IF(C62=0,0,(C62*100/C$14)) -> 0 | E62: {=_xll.BC(DB,_xll.ArrayDPT($AA62:$AE62),_xll.ArrayCOA($AG62:$AZ62),YR,PRD,RV,_xll.ArrayDIM($BB62:$BE62))} -> 0 | F62: =IF(E62=0,0,(E62*100/E$14)) -> 0 | G62: {=_xll.AC(DB,_xll.ArrayDPT($AA62:$AE62),_xll.ArrayCOA($AG62:$AZ62),YR,PRD,_xll.ArrayDIM($BB62:$BE62))} -> 0 | H62: =IF(G62=0,0,(G62*100/G$14)) -> 0 | J62: GUEST COMPLIMENTARY | L62: {=_xll.ACC(DB,_xll.ArrayDPT($AA62:$AE62),_xll.ArrayCOA($AG62:$AZ62),YR,PRD,_xll.ArrayDIM($BB62:$BE62))} -> 0 | M62: =IF(L62=0,0,(L62*100/L$14)) -> 0 | N62: {=_xll.BCC(DB,_xll.ArrayDPT($AA62:$AE62),_xll.ArrayCOA($AG62:$AZ62),YR,PRD,RV,_xll.ArrayDIM($BB62:$BE62))} -> 0 | O62: =IF(N62=0,0,(N62*100/N$14)) -> 0 | P62: =+N62-L62 -> 0 | Q62: =IF(P62=0,0,(P62*100/P$14)) -> 0 | R62: {=_xll.ACC(DB,_xll.ArrayDPT($AA62:$AE62),_xll.ArrayCOA($AG62:$AZ62),YR-1,PRD,_xll.ArrayDIM($BB62:$BE62))} -> 720 | S62: =IF(R62=0,0,(R62*100/R$14)) -> 0.009931693 | AA62: 101 | AB62: 103 | AC62: 104 | AD62: 107 | AG62: 50010 | AH62: 50010
A63: {=_xll.AC(DB,_xll.ArrayDPT($AA63:$AE63),_xll.ArrayCOA($AG63:$AZ63),YR-1,PRD,_xll.ArrayDIM($BB63:$BE63))} -> 0 | B63: =IF(A63=0,0,(A63*100/A$14)) -> 0 | C63: =+E63-G63 -> 0 | D63: =IF(C63=0,0,(C63*100/C$14)) -> 0 | E63: {=_xll.BC(DB,_xll.ArrayDPT($AA63:$AE63),_xll.ArrayCOA($AG63:$AZ63),YR,PRD,RV,_xll.ArrayDIM($BB63:$BE63))} -> 0 | F63: =IF(E63=0,0,(E63*100/E$14)) -> 0 | G63: {=_xll.AC(DB,_xll.ArrayDPT($AA63:$AE63),_xll.ArrayCOA($AG63:$AZ63),YR,PRD,_xll.ArrayDIM($BB63:$BE63))} -> 0 | H63: =IF(G63=0,0,(G63*100/G$14)) -> 0 | J63: TRAVELLING EXPENSES | L63: {=_xll.ACC(DB,_xll.ArrayDPT($AA63:$AE63),_xll.ArrayCOA($AG63:$AZ63),YR,PRD,_xll.ArrayDIM($BB63:$BE63))} -> 0 | M63: =IF(L63=0,0,(L63*100/L$14)) -> 0 | N63: {=_xll.BCC(DB,_xll.ArrayDPT($AA63:$AE63),_xll.ArrayCOA($AG63:$AZ63),YR,PRD,RV,_xll.ArrayDIM($BB63:$BE63))} -> 0 | O63: =IF(N63=0,0,(N63*100/N$14)) -> 0 | P63: =+N63-L63 -> 0 | Q63: =IF(P63=0,0,(P63*100/P$14)) -> 0 | R63: {=_xll.ACC(DB,_xll.ArrayDPT($AA63:$AE63),_xll.ArrayCOA($AG63:$AZ63),YR-1,PRD,_xll.ArrayDIM($BB63:$BE63))} -> 0 | S63: =IF(R63=0,0,(R63*100/R$14)) -> 0 | AA63: 103 | AB63: 104 | AC63: 107 | AG63: 50085 | AH63: 50085
A64: {=_xll.AC(DB,_xll.ArrayDPT($AA64:$AE64),_xll.ArrayCOA($AG64:$AZ64),YR-1,PRD,_xll.ArrayDIM($BB64:$BE64))} -> 0 | B64: =IF(A64=0,0,(A64*100/A$14)) -> 0 | C64: =+E64-G64 -> 0 | D64: =IF(C64=0,0,(C64*100/C$14)) -> 0 | E64: {=_xll.BC(DB,_xll.ArrayDPT($AA64:$AE64),_xll.ArrayCOA($AG64:$AZ64),YR,PRD,RV,_xll.ArrayDIM($BB64:$BE64))} -> 0 | F64: =IF(E64=0,0,(E64*100/E$14)) -> 0 | G64: {=_xll.AC(DB,_xll.ArrayDPT($AA64:$AE64),_xll.ArrayCOA($AG64:$AZ64),YR,PRD,_xll.ArrayDIM($BB64:$BE64))} -> 0 | H64: =IF(G64=0,0,(G64*100/G$14)) -> 0 | J64: GUEST NEWSPAPER | L64: {=_xll.ACC(DB,_xll.ArrayDPT($AA64:$AE64),_xll.ArrayCOA($AG64:$AZ64),YR,PRD,_xll.ArrayDIM($BB64:$BE64))} -> 0 | M64: =IF(L64=0,0,(L64*100/L$14)) -> 0 | N64: {=_xll.BCC(DB,_xll.ArrayDPT($AA64:$AE64),_xll.ArrayCOA($AG64:$AZ64),YR,PRD,RV,_xll.ArrayDIM($BB64:$BE64))} -> 0 | O64: =IF(N64=0,0,(N64*100/N$14)) -> 0 | P64: =+N64-L64 -> 0 | Q64: =IF(P64=0,0,(P64*100/P$14)) -> 0 | R64: {=_xll.ACC(DB,_xll.ArrayDPT($AA64:$AE64),_xll.ArrayCOA($AG64:$AZ64),YR-1,PRD,_xll.ArrayDIM($BB64:$BE64))} -> 0 | S64: =IF(R64=0,0,(R64*100/R$14)) -> 0
A65: {=_xll.AC(DB,_xll.ArrayDPT($AA65:$AE65),_xll.ArrayCOA($AG65:$AZ65),YR-1,PRD,_xll.ArrayDIM($BB65:$BE65))} -> 0 | B65: =IF(A65=0,0,(A65*100/A$14)) -> 0 | C65: =+E65-G65 -> 0 | D65: =IF(C65=0,0,(C65*100/C$14)) -> 0 | E65: {=_xll.BC(DB,_xll.ArrayDPT($AA65:$AE65),_xll.ArrayCOA($AG65:$AZ65),YR,PRD,RV,_xll.ArrayDIM($BB65:$BE65))} -> 0 | F65: =IF(E65=0,0,(E65*100/E$14)) -> 0 | G65: {=_xll.AC(DB,_xll.ArrayDPT($AA65:$AE65),_xll.ArrayCOA($AG65:$AZ65),YR,PRD,_xll.ArrayDIM($BB65:$BE65))} -> 0 | H65: =IF(G65=0,0,(G65*100/G$14)) -> 0 | J65: TRAINING EXPENSES | L65: {=_xll.ACC(DB,_xll.ArrayDPT($AA65:$AE65),_xll.ArrayCOA($AG65:$AZ65),YR,PRD,_xll.ArrayDIM($BB65:$BE65))} -> 0 | M65: =IF(L65=0,0,(L65*100/L$14)) -> 0 | N65: {=_xll.BCC(DB,_xll.ArrayDPT($AA65:$AE65),_xll.ArrayCOA($AG65:$AZ65),YR,PRD,RV,_xll.ArrayDIM($BB65:$BE65))} -> 0 | O65: =IF(N65=0,0,(N65*100/N$14)) -> 0 | P65: =+N65-L65 -> 0 | Q65: =IF(P65=0,0,(P65*100/P$14)) -> 0 | R65: {=_xll.ACC(DB,_xll.ArrayDPT($AA65:$AE65),_xll.ArrayCOA($AG65:$AZ65),YR-1,PRD,_xll.ArrayDIM($BB65:$BE65))} -> 0 | S65: =IF(R65=0,0,(R65*100/R$14)) -> 0 | AA65: 101 | AB65: 103 | AC65: 104 | AD65: 107 | AG65: 50080 | AH65: 50080 | AI65: 50081 | AJ65: 50081
A66: {=_xll.AC(DB,_xll.ArrayDPT($AA66:$AE66),_xll.ArrayCOA($AG66:$AZ66),YR-1,PRD,_xll.ArrayDIM($BB66:$BE66))} -> 0 | B66: =IF(A66=0,0,(A66*100/A$14)) -> 0 | C66: =+E66-G66 -> -3649.59 | D66: =IF(C66=0,0,(C66*100/C$14)) -> 0.046070031 | E66: {=_xll.BC(DB,_xll.ArrayDPT($AA66:$AE66),_xll.ArrayCOA($AG66:$AZ66),YR,PRD,RV,_xll.ArrayDIM($BB66:$BE66))} -> 0 | F66: =IF(E66=0,0,(E66*100/E$14)) -> 0 | G66: {=_xll.AC(DB,_xll.ArrayDPT($AA66:$AE66),_xll.ArrayCOA($AG66:$AZ66),YR,PRD,_xll.ArrayDIM($BB66:$BE66))} -> 3649.59 | H66: =IF(G66=0,0,(G66*100/G$14)) -> 0.046070031 | J66: TRANSPORTATION | L66: {=_xll.ACC(DB,_xll.ArrayDPT($AA66:$AE66),_xll.ArrayCOA($AG66:$AZ66),YR,PRD,_xll.ArrayDIM($BB66:$BE66))} -> 3649.59 | M66: =IF(L66=0,0,(L66*100/L$14)) -> 0.046070031 | N66: {=_xll.BCC(DB,_xll.ArrayDPT($AA66:$AE66),_xll.ArrayCOA($AG66:$AZ66),YR,PRD,RV,_xll.ArrayDIM($BB66:$BE66))} -> 0 | O66: =IF(N66=0,0,(N66*100/N$14)) -> 0 | P66: =+N66-L66 -> -3649.59 | Q66: =IF(P66=0,0,(P66*100/P$14)) -> 0.046070031 | R66: {=_xll.ACC(DB,_xll.ArrayDPT($AA66:$AE66),_xll.ArrayCOA($AG66:$AZ66),YR-1,PRD,_xll.ArrayDIM($BB66:$BE66))} -> 0 | S66: =IF(R66=0,0,(R66*100/R$14)) -> 0 | AA66: 101 | AB66: 103 | AC66: 104 | AD66: 107 | AG66: 54110 | AH66: 54110
A67: {=_xll.AC(DB,_xll.ArrayDPT($AA67:$AE67),_xll.ArrayCOA($AG67:$AZ67),YR-1,PRD,_xll.ArrayDIM($BB67:$BE67))} -> 1800 | B67: =IF(A67=0,0,(A67*100/A$14)) -> 0.024829232 | C67: =+E67-G67 -> 0 | D67: =IF(C67=0,0,(C67*100/C$14)) -> 0 | E67: {=_xll.BC(DB,_xll.ArrayDPT($AA67:$AE67),_xll.ArrayCOA($AG67:$AZ67),YR,PRD,RV,_xll.ArrayDIM($BB67:$BE67))} -> 0 | F67: =IF(E67=0,0,(E67*100/E$14)) -> 0 | G67: {=_xll.AC(DB,_xll.ArrayDPT($AA67:$AE67),_xll.ArrayCOA($AG67:$AZ67),YR,PRD,_xll.ArrayDIM($BB67:$BE67))} -> 0 | H67: =IF(G67=0,0,(G67*100/G$14)) -> 0 | J67: UNIFORM | L67: {=_xll.ACC(DB,_xll.ArrayDPT($AA67:$AE67),_xll.ArrayCOA($AG67:$AZ67),YR,PRD,_xll.ArrayDIM($BB67:$BE67))} -> 0 | M67: =IF(L67=0,0,(L67*100/L$14)) -> 0 | N67: {=_xll.BCC(DB,_xll.ArrayDPT($AA67:$AE67),_xll.ArrayCOA($AG67:$AZ67),YR,PRD,RV,_xll.ArrayDIM($BB67:$BE67))} -> 0 | O67: =IF(N67=0,0,(N67*100/N$14)) -> 0 | P67: =+N67-L67 -> 0 | Q67: =IF(P67=0,0,(P67*100/P$14)) -> 0 | R67: {=_xll.ACC(DB,_xll.ArrayDPT($AA67:$AE67),_xll.ArrayCOA($AG67:$AZ67),YR-1,PRD,_xll.ArrayDIM($BB67:$BE67))} -> 1800 | S67: =IF(R67=0,0,(R67*100/R$14)) -> 0.024829232 | AA67: 103 | AB67: 104 | AG67: 48030 | AH67: 48030
A68: {=_xll.AC(DB,_xll.ArrayDPT($AA68:$AE68),_xll.ArrayCOA($AG68:$AZ68),YR-1,PRD,_xll.ArrayDIM($BB68:$BE68))} -> 226 | B68: =IF(A68=0,0,(A68*100/A$14)) -> 0.0031174481 | C68: =+E68-G68 -> -1879.62 | D68: =IF(C68=0,0,(C68*100/C$14)) -> 0.02372709 | E68: {=_xll.BC(DB,_xll.ArrayDPT($AA68:$AE68),_xll.ArrayCOA($AG68:$AZ68),YR,PRD,RV,_xll.ArrayDIM($BB68:$BE68))} -> 0 | F68: =IF(E68=0,0,(E68*100/E$14)) -> 0 | G68: {=_xll.AC(DB,_xll.ArrayDPT($AA68:$AE68),_xll.ArrayCOA($AG68:$AZ68),YR,PRD,_xll.ArrayDIM($BB68:$BE68))} -> 1879.62 | H68: =IF(G68=0,0,(G68*100/G$14)) -> 0.02372709 | J68: MISCELLANEOUS | L68: {=_xll.ACC(DB,_xll.ArrayDPT($AA68:$AE68),_xll.ArrayCOA($AG68:$AZ68),YR,PRD,_xll.ArrayDIM($BB68:$BE68))} -> 1879.62 | M68: =IF(L68=0,0,(L68*100/L$14)) -> 0.02372709 | N68: {=_xll.BCC(DB,_xll.ArrayDPT($AA68:$AE68),_xll.ArrayCOA($AG68:$AZ68),YR,PRD,RV,_xll.ArrayDIM($BB68:$BE68))} -> 0 | O68: =IF(N68=0,0,(N68*100/N$14)) -> 0 | P68: =+N68-L68 -> -1879.62 | Q68: =IF(P68=0,0,(P68*100/P$14)) -> 0.02372709 | R68: {=_xll.ACC(DB,_xll.ArrayDPT($AA68:$AE68),_xll.ArrayCOA($AG68:$AZ68),YR-1,PRD,_xll.ArrayDIM($BB68:$BE68))} -> 226 | S68: =IF(R68=0,0,(R68*100/R$14)) -> 0.0031174481 | AA68: 101 | AB68: 103 | AC68: 104 | AD68: 107 | AG68: 50055 | AH68: 50055
A69: {=_xll.AC(DB,_xll.ArrayDPT($AA69:$AE69),_xll.ArrayCOA($AG69:$AZ69),YR-1,PRD,_xll.ArrayDIM($BB69:$BE69))} -> 1500 | B69: =IF(A69=0,0,(A69*100/A$14)) -> 0.020691027 | C69: =+E69-G69 -> -1500 | D69: =IF(C69=0,0,(C69*100/C$14)) -> 0.018935016 | E69: {=_xll.BC(DB,_xll.ArrayDPT($AA69:$AE69),_xll.ArrayCOA($AG69:$AZ69),YR,PRD,RV,_xll.ArrayDIM($BB69:$BE69))} -> 0 | F69: =IF(E69=0,0,(E69*100/E$14)) -> 0 | G69: {=_xll.AC(DB,_xll.ArrayDPT($AA69:$AE69),_xll.ArrayCOA($AG69:$AZ69),YR,PRD,_xll.ArrayDIM($BB69:$BE69))} -> 1500 | H69: =IF(G69=0,0,(G69*100/G$14)) -> 0.018935016 | J69: WATER & REMOVALS | L69: {=_xll.ACC(DB,_xll.ArrayDPT($AA69:$AE69),_xll.ArrayCOA($AG69:$AZ69),YR,PRD,_xll.ArrayDIM($BB69:$BE69))} -> 1500 | M69: =IF(L69=0,0,(L69*100/L$14)) -> 0.018935016 | N69: {=_xll.BCC(DB,_xll.ArrayDPT($AA69:$AE69),_xll.ArrayCOA($AG69:$AZ69),YR,PRD,RV,_xll.ArrayDIM($BB69:$BE69))} -> 0 | O69: =IF(N69=0,0,(N69*100/N$14)) -> 0 | P69: =+N69-L69 -> -1500 | Q69: =IF(P69=0,0,(P69*100/P$14)) -> 0.018935016 | R69: {=_xll.ACC(DB,_xll.ArrayDPT($AA69:$AE69),_xll.ArrayCOA($AG69:$AZ69),YR-1,PRD,_xll.ArrayDIM($BB69:$BE69))} -> 1500 | S69: =IF(R69=0,0,(R69*100/R$14)) -> 0.020691027 | AA69: 104 | AG69: 56075 | AH69: 56075
A70: {=_xll.AC(DB,_xll.ArrayDPT($AA70:$AE70),_xll.ArrayCOA($AG70:$AZ70),YR-1,PRD,_xll.ArrayDIM($BB70:$BE70))} -> 0 | B70: =IF(A70=0,0,(A70*100/A$14)) -> 0 | C70: =+E70-G70 -> 0 | D70: =IF(C70=0,0,(C70*100/C$14)) -> 0 | E70: {=_xll.BC(DB,_xll.ArrayDPT($AA70:$AE70),_xll.ArrayCOA($AG70:$AZ70),YR,PRD,RV,_xll.ArrayDIM($BB70:$BE70))} -> 0 | F70: =IF(E70=0,0,(E70*100/E$14)) -> 0 | G70: {=_xll.AC(DB,_xll.ArrayDPT($AA70:$AE70),_xll.ArrayCOA($AG70:$AZ70),YR,PRD,_xll.ArrayDIM($BB70:$BE70))} -> 0 | H70: =IF(G70=0,0,(G70*100/G$14)) -> 0 | J70: COS-Misc. OTHER REVENUE | L70: {=_xll.ACC(DB,_xll.ArrayDPT($AA70:$AE70),_xll.ArrayCOA($AG70:$AZ70),YR,PRD,_xll.ArrayDIM($BB70:$BE70))} -> 0 | M70: =IF(L70=0,0,(L70*100/L$14)) -> 0 | N70: {=_xll.BCC(DB,_xll.ArrayDPT($AA70:$AE70),_xll.ArrayCOA($AG70:$AZ70),YR,PRD,RV,_xll.ArrayDIM($BB70:$BE70))} -> 0 | O70: =IF(N70=0,0,(N70*100/N$14)) -> 0 | P70: =+N70-L70 -> 0 | Q70: =IF(P70=0,0,(P70*100/P$14)) -> 0 | R70: {=_xll.ACC(DB,_xll.ArrayDPT($AA70:$AE70),_xll.ArrayCOA($AG70:$AZ70),YR-1,PRD,_xll.ArrayDIM($BB70:$BE70))} -> 0 | S70: =IF(R70=0,0,(R70*100/R$14)) -> 0 | AA70: 103 | AG70: 31025 | AH70: 31025
A72: =SUM(A28:A71) -> 1011719.4 | B72: =IF(A72=0,0,(A72*100/A$14)) -> 13.955675 | C72: =SUM(C28:C71) -> -1005211.1 | D72: =IF(C72=0,0,(C72*100/C$14)) -> 12.689126 | E72: =SUM(E28:E71) -> 0 | F72: =IF(E72=0,0,(E72*100/E$14)) -> 0 | G72: =SUM(G28:G71) -> 1005211.1 | H72: =IF(G72=0,0,(G72*100/G$14)) -> 12.689126 | J72: TOTAL OTHER EXPENSES | L72: =SUM(L28:L71) -> 1005211.1 | M72: =IF(L72=0,0,(L72*100/L$14)) -> 12.689126 | N72: =SUM(N28:N71) -> 0 | O72: =IF(N72=0,0,(N72*100/N$14)) -> 0 | P72: =SUM(P28:P71) -> -1005211.1 | Q72: =IF(P72=0,0,(P72*100/P$14)) -> 12.689126 | R72: =SUM(R28:R71) -> 1011719.4 | S72: =IF(R72=0,0,(R72*100/R$14)) -> 13.955675
A73: =+A26+A72 -> 1289352.7 | B73: =IF(A73=0,0,(A73*100/A$14)) -> 17.785355 | C73: =+C26+C72 -> -1294216.4 | D73: =IF(C73=0,0,(C73*100/C$14)) -> 16.337339 | E73: =+E26+E72 -> 0 | F73: =IF(E73=0,0,(E73*100/E$14)) -> 0 | G73: =+G26+G72 -> 1294216.4 | H73: =IF(G73=0,0,(G73*100/G$14)) -> 16.337339 | J73: TOTAL DEPT. EXPENSES | L73: =+L26+L72 -> 1294216.4 | M73: =IF(L73=0,0,(L73*100/L$14)) -> 16.337339 | N73: =+N26+N72 -> 0 | O73: =IF(N73=0,0,(N73*100/N$14)) -> 0 | P73: =+P26+P72 -> -1294216.4 | Q73: =IF(P73=0,0,(P73*100/P$14)) -> 16.337339 | R73: =+R26+R72 -> 1289352.7 | S73: =IF(R73=0,0,(R73*100/R$14)) -> 17.785355
A74: =+A14-A73 -> 5960166.6 | B74: =IF(A74=0,0,(A74*100/A$14)) -> 82.214645 | C74: =+C14-C73 -> -6627614.6 | D74: =IF(C74=0,0,(C74*100/C$14)) -> 83.662661 | E74: =+E14-E73 -> 0 | F74: =IF(E74=0,0,(E74*100/E$14)) -> 0 | G74: =+G14-G73 -> 6627614.6 | H74: =IF(G74=0,0,(G74*100/G$14)) -> 83.662661 | J74: ROOMS DEPT. P&L | L74: =+L14-L73 -> 6627614.6 | M74: =IF(L74=0,0,(L74*100/L$14)) -> 83.662661 | N74: =+N14-N73 -> 0 | O74: =IF(N74=0,0,(N74*100/N$14)) -> 0 | P74: =+P14-P73 -> -6627614.6 | Q74: =IF(P74=0,0,(P74*100/P$14)) -> 83.662661 | R74: =+R14-R73 -> 5960166.6 | S74: =IF(R74=0,0,(R74*100/R$14)) -> 82.214645
J77: STATISTICS
A78: {=-_xll.AC(DB,_xll.ArrayDPT($AA78:$AE78),_xll.ArrayCOA($AG78:$AZ78),YR-1,PRD,_xll.ArrayDIM($BB78:$BE78))} -> 4588 | C78: =+G78-E78 -> 4588 | E78: {=_xll.BC(DB,_xll.ArrayDPT($AA78:$AE78),_xll.ArrayCOA($AG78:$AZ78),YR,PRD,RV,_xll.ArrayDIM($BB78:$BE78))} -> 0 | G78: =-_xll.AC(DB,_xll.ArrayDPT($AA78:$AE78),_xll.ArrayCOA($AG78:$AZ78),YR,PRD,_xll.ArrayDIM($BB78:$BE78)) -> 4588 | J78: TOTAL ROOM IN HOTEL | L78: {=-_xll.ACC(DB,_xll.ArrayDPT($AA78:$AE78),_xll.ArrayCOA($AG78:$AZ78),YR,PRD,_xll.ArrayDIM($BB78:$BE78))} -> 4588 | N78: {=_xll.BCC(DB,_xll.ArrayDPT($AA78:$AE78),_xll.ArrayCOA($AG78:$AZ78),YR,PRD,RV,_xll.ArrayDIM($BB78:$BE78))} -> 0 | P78: =+N78-L78 -> -4588 | R78: {=-_xll.ACC(DB,_xll.ArrayDPT($AA78:$AE78),_xll.ArrayCOA($AG78:$AZ78),YR-1,PRD,_xll.ArrayDIM($BB78:$BE78))} -> 4588 | AA78: 103 | AB78: 103 | AG78: Z91115 | AH78: Z91115
A79: =A80/A78 -> 0.6994333 | C79: =C80/C78 -> 0.75021796 | E79: =E80/E78 -> #DIV/0! | G79: =G80/G78 -> 0.75021796 | J79: % OF OCCUPANCY | L79: =L80/L78 -> 0.75021796 | N79: =N80/N78 -> #DIV/0! | P79: =P80/P78 -> 0.75021796 | R79: =R80/R78 -> 0.6994333
A80: {=-_xll.AC(DB,_xll.ArrayDPT($AA80:$AE80),_xll.ArrayCOA($AG80:$AZ80),YR-1,PRD,_xll.ArrayDIM($BB80:$BE80))} -> 3209 | C80: =+G80-E80 -> 3442 | E80: {=_xll.BC(DB,_xll.ArrayDPT($AA80:$AE80),_xll.ArrayCOA($AG80:$AZ80),YR,PRD,RV,_xll.ArrayDIM($BB80:$BE80))} -> 0 | G80: =-_xll.AC(DB,_xll.ArrayDPT($AA80:$AE80),_xll.ArrayCOA($AG80:$AZ80),YR,PRD,_xll.ArrayDIM($BB80:$BE80)) -> 3442 | J80: ROOM OCCUPIED | L80: {=-_xll.ACC(DB,_xll.ArrayDPT($AA80:$AE80),_xll.ArrayCOA($AG80:$AZ80),YR,PRD,_xll.ArrayDIM($BB80:$BE80))} -> 3442 | N80: {=_xll.BCC(DB,_xll.ArrayDPT($AA80:$AE80),_xll.ArrayCOA($AG80:$AZ80),YR,PRD,RV,_xll.ArrayDIM($BB80:$BE80))} -> 0 | P80: =+N80-L80 -> -3442 | R80: {=-_xll.ACC(DB,_xll.ArrayDPT($AA80:$AE80),_xll.ArrayCOA($AG80:$AZ80),YR-1,PRD,_xll.ArrayDIM($BB80:$BE80))} -> 3209 | AA80: 103 | AB80: 103 | AG80: Z91125 | AH80: Z91125
A81: =A8/A80 -> 2254.4789 | C81: =C8/C80 -> -2294.0267 | E81: =E8/E80 -> #DIV/0! | G81: =G8/G80 -> 2294.0267 | J81: AVERAGE ROOM RATE | L81: =L8/L80 -> 2294.0267 | N81: =N8/N80 -> #DIV/0! | P81: =P8/P80 -> 2294.0267 | R81: =R8/R80 -> 2254.4789
A82: {=-_xll.AC(DB,_xll.ArrayDPT($AA82:$AE82),_xll.ArrayCOA($AG82:$AZ82),YR-1,PRD,_xll.ArrayDIM($BB82:$BE82))} -> 6310 | C82: =+G82-E82 -> 6408 | E82: {=_xll.BC(DB,_xll.ArrayDPT($AA82:$AE82),_xll.ArrayCOA($AG82:$AZ82),YR,PRD,RV,_xll.ArrayDIM($BB82:$BE82))} -> 0 | G82: =-_xll.AC(DB,_xll.ArrayDPT($AA82:$AE82),_xll.ArrayCOA($AG82:$AZ82),YR,PRD,_xll.ArrayDIM($BB82:$BE82)) -> 6408 | J82: NUMBER OF GUEST | L82: {=-_xll.ACC(DB,_xll.ArrayDPT($AA82:$AE82),_xll.ArrayCOA($AG82:$AZ82),YR,PRD,_xll.ArrayDIM($BB82:$BE82))} -> 6408 | N82: {=_xll.BCC(DB,_xll.ArrayDPT($AA82:$AE82),_xll.ArrayCOA($AG82:$AZ82),YR,PRD,RV,_xll.ArrayDIM($BB82:$BE82))} -> 0 | P82: =+N82-L82 -> -6408 | R82: {=-_xll.ACC(DB,_xll.ArrayDPT($AA82:$AE82),_xll.ArrayCOA($AG82:$AZ82),YR-1,PRD,_xll.ArrayDIM($BB82:$BE82))} -> 6310 | AA82: 103 | AB82: 103 | AG82: Z91425 | AH82: Z91425
G84: =Front!G74-Housekeeping!G72-Reservation!G70 -> 6623448.5
G85: =G84-G74 -> -4166.07

Sheet Front
A2: HOMM SUKHUMVIT34 BANGKOK | T2: Period | U2: =PRD -> 1
J3: Front Department | Q3: SCHEDULE - B | AA3: Mapping Area
A4: CURRENT MONTH | L4: YEAR TO DATE | AA4: *Department Code | AG4: *Account Code | BB4: Dimension | BF4: Dimension
A5: LAST YEAR | C5: VARIANCE | E5: BUDGET | G5: ACTUAL | J5: DESCRIPTION | L5: ACTUAL | N5: BUDGET | P5: VARIANCE | R5: LAST YEAR | AA5: Dept 1 | AB5: Dept 2 | AC5: Dept 3 | AD5: Dept 4 | AE5: Dept 5 | AG5: 1st Range | AI5: 2nd Range | AK5: 3rd Range | AM5: 4rd Range | AO5: 5rd Range | AQ5: 6rd Range | AS5: 7rd Range | AU5: 8rd Range | AW5: 9rd Range | AY5: 10th Range
A6: BHT | B6: % | C6: BHT | D6: % | E6: BHT | F6: % | G6: BHT | H6: % | L6: BHT | M6: % | N6: BHT | O6: % | P6: BHT | Q6: % | R6: BHT | S6: % | AG6: From | AH6: To | AI6: From | AJ6: To | AK6: From | AL6: To | AM6: From | AN6: To | AO6: From | AP6: To | AQ6: From | AR6: To | AS6: From | AT6: To | AU6: From | AV6: To | AW6: From | AX6: To | AY6: From | AZ6: To | BB6: A/O | BC6: Field Name | BD6: Operator | BE6: Value | BF6: A/O | BG6: Field Name | BH6: Operator | BI6: Value
J7: REVENUE | BB7: A | BC7: Matket1 | BD7: in | BE7: OTA,FIT | BF7: A | BG7: Matket2 | BH7: in | BI7: OTA1,FIT1
A8: {=_xll.AC(DB,_xll.ArrayDPT($AA8:$AE8),_xll.ArrayCOA($AG8:$AZ8),YR-1,PRD,_xll.ArrayDIM($BB8:$BE8))} -> 7234622.9 | B8: =IF(A8=0,0,(A8*100/A$14)) -> 99.794519 | C8: =+E8-G8 -> -7896040 | D8: =IF(C8=0,0,(C8*100/C$14)) -> 99.674431 | E8: {=_xll.BC(DB,_xll.ArrayDPT($AA8:$AE8),_xll.ArrayCOA($AG8:$AZ8),YR,PRD,RV,_xll.ArrayDIM($BB8:$BE8))} -> 0 | F8: =IF(E8=0,0,(E8*100/E$14)) -> 0 | G8: {=_xll.AC(DB,_xll.ArrayDPT($AA8:$AE8),_xll.ArrayCOA($AG8:$AZ8),YR,PRD,_xll.ArrayDIM($BB8:$BE8))} -> 7896040 | H8: =IF(G8=0,0,(G8*100/G$14)) -> 99.674431 | J8: ROOM REVENUE | L8: =_xll.ACC(DB,_xll.ArrayDPT($AA8:$AE8),_xll.ArrayCOA($AG8:$AZ8),YR,PRD,_xll.ArrayDIM($BB8:$BE8)) -> 7896040 | M8: =IF(L8=0,0,(L8*100/L$14)) -> 99.674431 | N8: {=_xll.BCC(DB,_xll.ArrayDPT($AA8:$AE8),_xll.ArrayCOA($AG8:$AZ8),YR,PRD,RV,_xll.ArrayDIM($BB8:$BE8))} -> 0 | O8: =IF(N8=0,0,(N8*100/N$14)) -> 0 | P8: =+N8-L8 -> -7896040 | Q8: =IF(P8=0,0,(P8*100/P$14)) -> 99.674431 | R8: {=_xll.ACC(DB,_xll.ArrayDPT($AA8:$AE8),_xll.ArrayCOA($AG8:$AZ8),YR-1,PRD,_xll.ArrayDIM($BB8:$BE8))} -> 7234622.9 | S8: =IF(R8=0,0,(R8*100/R$14)) -> 99.794519 | AA8: 101 | AG8: 11100 | AH8: 11100
A9: {=_xll.AC(DB,_xll.ArrayDPT($AA9:$AE9),_xll.ArrayCOA($AG9:$AZ9),YR-1,PRD,_xll.ArrayDIM($BB9:$BE9))} -> 0 | B9: =IF(A9=0,0,(A9*100/A$14)) -> 0 | C9: =+E9-G9 -> 0 | D9: =IF(C9=0,0,(C9*100/C$14)) -> 0 | E9: {=_xll.BC(DB,_xll.ArrayDPT($AA9:$AE9),_xll.ArrayCOA($AG9:$AZ9),YR,PRD,RV,_xll.ArrayDIM($BB9:$BE9))} -> 0 | F9: =IF(E9=0,0,(E9*100/E$14)) -> 0 | G9: {=_xll.AC(DB,_xll.ArrayDPT($AA9:$AE9),_xll.ArrayCOA($AG9:$AZ9),YR,PRD,_xll.ArrayDIM($BB9:$BE9))} -> 0 | H9: =IF(G9=0,0,(G9*100/G$14)) -> 0 | J9: SERVICECHARGE - ROOM REVENUE | L9: {=_xll.ACC(DB,_xll.ArrayDPT($AA9:$AE9),_xll.ArrayCOA($AG9:$AZ9),YR,PRD,_xll.ArrayDIM($BB9:$BE9))} -> 0 | M9: =IF(L9=0,0,(L9*100/L$14)) -> 0 | N9: {=_xll.BCC(DB,_xll.ArrayDPT($AA9:$AE9),_xll.ArrayCOA($AG9:$AZ9),YR,PRD,RV,_xll.ArrayDIM($BB9:$BE9))} -> 0 | O9: =IF(N9=0,0,(N9*100/N$14)) -> 0 | P9: =+N9-L9 -> 0 | Q9: =IF(P9=0,0,(P9*100/P$14)) -> 0 | R9: {=_xll.ACC(DB,_xll.ArrayDPT($AA9:$AE9),_xll.ArrayCOA($AG9:$AZ9),YR-1,PRD,_xll.ArrayDIM($BB9:$BE9))} -> 0 | S9: =IF(R9=0,0,(R9*100/R$14)) -> 0
A10: {=_xll.AC(DB,_xll.ArrayDPT($AA10:$AE10),_xll.ArrayCOA($AG10:$AZ10),YR-1,PRD,_xll.ArrayDIM($BB10:$BE10))} -> 36402.76 | B10: =IF(A10=0,0,(A10*100/A$14)) -> 0.50214033 | C10: =+E10-G10 -> -38913.08 | D10: =IF(C10=0,0,(C10*100/C$14)) -> 0.49121321 | E10: {=_xll.BC(DB,_xll.ArrayDPT($AA10:$AE10),_xll.ArrayCOA($AG10:$AZ10),YR,PRD,RV,_xll.ArrayDIM($BB10:$BE10))} -> 0 | F10: =IF(E10=0,0,(E10*100/E$14)) -> 0 | G10: {=_xll.AC(DB,_xll.ArrayDPT($AA10:$AE10),_xll.ArrayCOA($AG10:$AZ10),YR,PRD,_xll.ArrayDIM($BB10:$BE10))} -> 38913.08 | H10: =IF(G10=0,0,(G10*100/G$14)) -> 0.49121321 | J10: ROOM REVENUE - OTHER | L10: {=_xll.ACC(DB,_xll.ArrayDPT($AA10:$AE10),_xll.ArrayCOA($AG10:$AZ10),YR,PRD,_xll.ArrayDIM($BB10:$BE10))} -> 38913.08 | M10: =IF(L10=0,0,(L10*100/L$14)) -> 0.49121321 | N10: {=_xll.BCC(DB,_xll.ArrayDPT($AA10:$AE10),_xll.ArrayCOA($AG10:$AZ10),YR,PRD,RV,_xll.ArrayDIM($BB10:$BE10))} -> 0 | O10: =IF(N10=0,0,(N10*100/N$14)) -> 0 | P10: =+N10-L10 -> -38913.08 | Q10: =IF(P10=0,0,(P10*100/P$14)) -> 0.49121321 | R10: {=_xll.ACC(DB,_xll.ArrayDPT($AA10:$AE10),_xll.ArrayCOA($AG10:$AZ10),YR-1,PRD,_xll.ArrayDIM($BB10:$BE10))} -> 36402.76 | S10: =IF(R10=0,0,(R10*100/R$14)) -> 0.50214033 | AA10: 101 | AG10: 11101 | AH10: 11101
A11: {=_xll.AC(DB,_xll.ArrayDPT($AA11:$AE11),_xll.ArrayCOA($AG11:$AZ11),YR-1,PRD,_xll.ArrayDIM($BB11:$BE11))} -> -21506.38 | B11: =IF(A11=0,0,(A11*100/A$14)) -> -0.29665939 | C11: =+E11-G11 -> 13122.06 | D11: =IF(C11=0,0,(C11*100/C$14)) -> -0.16564428 | E11: {=_xll.BC(DB,_xll.ArrayDPT($AA11:$AE11),_xll.ArrayCOA($AG11:$AZ11),YR,PRD,RV,_xll.ArrayDIM($BB11:$BE11))} -> 0 | F11: =IF(E11=0,0,(E11*100/E$14)) -> 0 | G11: {=_xll.AC(DB,_xll.ArrayDPT($AA11:$AE11),_xll.ArrayCOA($AG11:$AZ11),YR,PRD,_xll.ArrayDIM($BB11:$BE11))} -> -13122.06 | H11: =IF(G11=0,0,(G11*100/G$14)) -> -0.16564428 | J11: ALLOWANCES | L11: {=_xll.ACC(DB,_xll.ArrayDPT($AA11:$AE11),_xll.ArrayCOA($AG11:$AZ11),YR,PRD,_xll.ArrayDIM($BB11:$BE11))} -> -13122.06 | M11: =IF(L11=0,0,(L11*100/L$14)) -> -0.16564428 | N11: {=_xll.BCC(DB,_xll.ArrayDPT($AA11:$AE11),_xll.ArrayCOA($AG11:$AZ11),YR,PRD,RV,_xll.ArrayDIM($BB11:$BE11))} -> 0 | O11: =IF(N11=0,0,(N11*100/N$14)) -> 0 | P11: =+N11-L11 -> 13122.06 | Q11: =IF(P11=0,0,(P11*100/P$14)) -> -0.16564428 | R11: {=_xll.ACC(DB,_xll.ArrayDPT($AA11:$AE11),_xll.ArrayCOA($AG11:$AZ11),YR-1,PRD,_xll.ArrayDIM($BB11:$BE11))} -> -21506.38 | S11: =IF(R11=0,0,(R11*100/R$14)) -> -0.29665939 | AA11: 101 | AG11: 20005 | AH11: 20005
A12: {=_xll.AC(DB,_xll.ArrayDPT($AA12:$AE12),_xll.ArrayCOA($AG12:$AZ12),YR-1,PRD,_xll.ArrayDIM($BB12:$BE12))} -> 0 | B12: =IF(A12=0,0,(A12*100/A$14)) -> 0 | C12: =+E12-G12 -> 0 | D12: =IF(C12=0,0,(C12*100/C$14)) -> 0 | E12: {=_xll.BC(DB,_xll.ArrayDPT($AA12:$AE12),_xll.ArrayCOA($AG12:$AZ12),YR,PRD,RV,_xll.ArrayDIM($BB12:$BE12))} -> 0 | F12: =IF(E12=0,0,(E12*100/E$14)) -> 0 | G12: {=_xll.AC(DB,_xll.ArrayDPT($AA12:$AE12),_xll.ArrayCOA($AG12:$AZ12),YR,PRD,_xll.ArrayDIM($BB12:$BE12))} -> 0 | H12: =IF(G12=0,0,(G12*100/G$14)) -> 0 | J12: EXTRA ROOM REVENUE | L12: {=_xll.ACC(DB,_xll.ArrayDPT($AA12:$AE12),_xll.ArrayCOA($AG12:$AZ12),YR,PRD,_xll.ArrayDIM($BB12:$BE12))} -> 0 | M12: =IF(L12=0,0,(L12*100/L$14)) -> 0 | N12: {=_xll.BCC(DB,_xll.ArrayDPT($AA12:$AE12),_xll.ArrayCOA($AG12:$AZ12),YR,PRD,RV,_xll.ArrayDIM($BB12:$BE12))} -> 0 | O12: =IF(N12=0,0,(N12*100/N$14)) -> 0 | P12: =+N12-L12 -> 0 | Q12: =IF(P12=0,0,(P12*100/P$14)) -> 0 | R12: {=_xll.ACC(DB,_xll.ArrayDPT($AA12:$AE12),_xll.ArrayCOA($AG12:$AZ12),YR-1,PRD,_xll.ArrayDIM($BB12:$BE12))} -> 0 | S12: =IF(R12=0,0,(R12*100/R$14)) -> 0 | AA12: 101
A14: =SUM(A8:A13) -> 7249519.3 | B14: =IF(A14=0,0,(A14*100/A$14)) -> 100 | C14: =SUM(C8:C13) -> -7921831 | D14: =IF(C14=0,0,(C14*100/C$14)) -> 100 | E14: =SUM(E8:E13) -> 0 | F14: =IF(E14=0,0,(E14*100/E$14)) -> 0 | G14: =SUM(G8:G13) -> 7921831 | H14: =IF(G14=0,0,(G14*100/G$14)) -> 100 | J14: NET REVENUE | L14: =SUM(L8:L13) -> 7921831 | M14: =IF(L14=0,0,(L14*100/L$14)) -> 100 | N14: =SUM(N8:N13) -> 0 | O14: =IF(N14=0,0,(N14*100/N$14)) -> 0 | P14: =SUM(P8:P13) -> -7921831 | Q14: =IF(P14=0,0,(P14*100/P$14)) -> 100 | R14: =SUM(R8:R13) -> 7249519.3 | S14: =IF(R14=0,0,(R14*100/R$14)) -> 100
J15: PAYROLL & EMP. RELATION
A16: {=_xll.AC(DB,_xll.ArrayDPT($AA16:$AE16),_xll.ArrayCOA($AG16:$AZ16),YR-1,PRD,_xll.ArrayDIM($BB16:$BE16))} -> 0 | B16: =IF(A16=0,0,(A16*100/A$14)) -> 0 | C16: =+E16-G16 -> 0 | D16: =IF(C16=0,0,(C16*100/C$14)) -> 0 | E16: {=_xll.BC(DB,_xll.ArrayDPT($AA16:$AE16),_xll.ArrayCOA($AG16:$AZ16),YR,PRD,RV,_xll.ArrayDIM($BB16:$BE16))} -> 0 | F16: =IF(E16=0,0,(E16*100/E$14)) -> 0 | G16: =_xll.AC(DB,_xll.ArrayDPT($AA16:$AE16),_xll.ArrayCOA($AG16:$AZ16),YR,PRD,_xll.ArrayDIM($BB16:$BE16)) -> 0 | H16: =IF(G16=0,0,(G16*100/G$14)) -> 0 | J16: SALARIES & WAGES - FRONT OFFICE | L16: {=_xll.ACC(DB,_xll.ArrayDPT($AA16:$AE16),_xll.ArrayCOA($AG16:$AZ16),YR,PRD,_xll.ArrayDIM($BB16:$BE16))} -> 0 | M16: =IF(L16=0,0,(L16*100/L$14)) -> 0 | N16: {=_xll.BCC(DB,_xll.ArrayDPT($AA16:$AE16),_xll.ArrayCOA($AG16:$AZ16),YR,PRD,RV,_xll.ArrayDIM($BB16:$BE16))} -> 0 | O16: =IF(N16=0,0,(N16*100/N$14)) -> 0 | P16: =+N16-L16 -> 0 | Q16: =IF(P16=0,0,(P16*100/P$14)) -> 0 | R16: {=_xll.ACC(DB,_xll.ArrayDPT($AA16:$AE16),_xll.ArrayCOA($AG16:$AZ16),YR-1,PRD,_xll.ArrayDIM($BB16:$BE16))} -> 0 | S16: =IF(R16=0,0,(R16*100/R$14)) -> 0 | AA16: 103 | AB16: 101 | AG16: 42104 | AH16: 42104
A17: {=_xll.AC(DB,_xll.ArrayDPT($AA17:$AE17),_xll.ArrayCOA($AG17:$AZ17),YR-1,PRD,_xll.ArrayDIM($BB17:$BE17))} -> 0 | B17: =IF(A17=0,0,(A17*100/A$14)) -> 0 | C17: =+E17-G17 -> -37066.67 | D17: =IF(C17=0,0,(C17*100/C$14)) -> 0.46790534 | E17: {=_xll.BC(DB,_xll.ArrayDPT($AA17:$AE17),_xll.ArrayCOA($AG17:$AZ17),YR,PRD,RV,_xll.ArrayDIM($BB17:$BE17))} -> 0 | F17: =IF(E17=0,0,(E17*100/E$14)) -> 0 | G17: {=_xll.AC(DB,_xll.ArrayDPT($AA17:$AE17),_xll.ArrayCOA($AG17:$AZ17),YR,PRD,_xll.ArrayDIM($BB17:$BE17))} -> 37066.67 | H17: =IF(G17=0,0,(G17*100/G$14)) -> 0.46790534 | J17: SALARIES & WAGES - MANAGEMENT | L17: {=_xll.ACC(DB,_xll.ArrayDPT($AA17:$AE17),_xll.ArrayCOA($AG17:$AZ17),YR,PRD,_xll.ArrayDIM($BB17:$BE17))} -> 37066.67 | M17: =IF(L17=0,0,(L17*100/L$14)) -> 0.46790534 | N17: {=_xll.BCC(DB,_xll.ArrayDPT($AA17:$AE17),_xll.ArrayCOA($AG17:$AZ17),YR,PRD,RV,_xll.ArrayDIM($BB17:$BE17))} -> 0 | O17: =IF(N17=0,0,(N17*100/N$14)) -> 0 | P17: =+N17-L17 -> -37066.67 | Q17: =IF(P17=0,0,(P17*100/P$14)) -> 0.46790534 | R17: {=_xll.ACC(DB,_xll.ArrayDPT($AA17:$AE17),_xll.ArrayCOA($AG17:$AZ17),YR-1,PRD,_xll.ArrayDIM($BB17:$BE17))} -> 0 | S17: =IF(R17=0,0,(R17*100/R$14)) -> 0 | AA17: 103 | AB17: 101 | AG17: 42006 | AH17: 42006
A18: {=_xll.AC(DB,_xll.ArrayDPT($AA18:$AE18),_xll.ArrayCOA($AG18:$AZ18),YR-1,PRD,_xll.ArrayDIM($BB18:$BE18))} -> 129333.34 | B18: =IF(A18=0,0,(A18*100/A$14)) -> 1.7840264 | C18: =+E18-G18 -> -90200 | D18: =IF(C18=0,0,(C18*100/C$14)) -> 1.1386257 | E18: {=_xll.BC(DB,_xll.ArrayDPT($AA18:$AE18),_xll.ArrayCOA($AG18:$AZ18),YR,PRD,RV,_xll.ArrayDIM($BB18:$BE18))} -> 0 | F18: =IF(E18=0,0,(E18*100/E$14)) -> 0 | G18: {=_xll.AC(DB,_xll.ArrayDPT($AA18:$AE18),_xll.ArrayCOA($AG18:$AZ18),YR,PRD,_xll.ArrayDIM($BB18:$BE18))} -> 90200 | H18: =IF(G18=0,0,(G18*100/G$14)) -> 1.1386257 | J18: SALARIES & WAGES_NON MANAGEMENT | L18: {=_xll.ACC(DB,_xll.ArrayDPT($AA18:$AE18),_xll.ArrayCOA($AG18:$AZ18),YR,PRD,_xll.ArrayDIM($BB18:$BE18))} -> 90200 | M18: =IF(L18=0,0,(L18*100/L$14)) -> 1.1386257 | N18: {=_xll.BCC(DB,_xll.ArrayDPT($AA18:$AE18),_xll.ArrayCOA($AG18:$AZ18),YR,PRD,RV,_xll.ArrayDIM($BB18:$BE18))} -> 0 | O18: =IF(N18=0,0,(N18*100/N$14)) -> 0 | P18: =+N18-L18 -> -90200 | Q18: =IF(P18=0,0,(P18*100/P$14)) -> 1.1386257 | R18: {=_xll.ACC(DB,_xll.ArrayDPT($AA18:$AE18),_xll.ArrayCOA($AG18:$AZ18),YR-1,PRD,_xll.ArrayDIM($BB18:$BE18))} -> 129333.34 | S18: =IF(R18=0,0,(R18*100/R$14)) -> 1.7840264 | AA18: 103 | AB18: 101 | AG18: 42005 | AH18: 42005
A19: {=_xll.AC(DB,_xll.ArrayDPT($AA19:$AE19),_xll.ArrayCOA($AG19:$AZ19),YR-1,PRD,_xll.ArrayDIM($BB19:$BE19))} -> 0 | B19: =IF(A19=0,0,(A19*100/A$14)) -> 0 | C19: =+E19-G19 -> 0 | D19: =IF(C19=0,0,(C19*100/C$14)) -> 0 | E19: {=_xll.BC(DB,_xll.ArrayDPT($AA19:$AE19),_xll.ArrayCOA($AG19:$AZ19),YR,PRD,RV,_xll.ArrayDIM($BB19:$BE19))} -> 0 | F19: =IF(E19=0,0,(E19*100/E$14)) -> 0 | G19: {=_xll.AC(DB,_xll.ArrayDPT($AA19:$AE19),_xll.ArrayCOA($AG19:$AZ19),YR,PRD,_xll.ArrayDIM($BB19:$BE19))} -> 0 | H19: =IF(G19=0,0,(G19*100/G$14)) -> 0 | J19: SALARIES & WAGES - RESERVATION | L19: {=_xll.ACC(DB,_xll.ArrayDPT($AA19:$AE19),_xll.ArrayCOA($AG19:$AZ19),YR,PRD,_xll.ArrayDIM($BB19:$BE19))} -> 0 | M19: =IF(L19=0,0,(L19*100/L$14)) -> 0 | N19: {=_xll.BCC(DB,_xll.ArrayDPT($AA19:$AE19),_xll.ArrayCOA($AG19:$AZ19),YR,PRD,RV,_xll.ArrayDIM($BB19:$BE19))} -> 0 | O19: =IF(N19=0,0,(N19*100/N$14)) -> 0 | P19: =+N19-L19 -> 0 | Q19: =IF(P19=0,0,(P19*100/P$14)) -> 0 | R19: {=_xll.ACC(DB,_xll.ArrayDPT($AA19:$AE19),_xll.ArrayCOA($AG19:$AZ19),YR-1,PRD,_xll.ArrayDIM($BB19:$BE19))} -> 0 | S19: =IF(R19=0,0,(R19*100/R$14)) -> 0 | AA19: 103 | AB19: 101 | AG19: 42105 | AH19: 42105
A20: {=_xll.AC(DB,_xll.ArrayDPT($AA20:$AE20),_xll.ArrayCOA($AG20:$AZ20),YR-1,PRD,_xll.ArrayDIM($BB20:$BE20))} -> 0 | B20: =IF(A20=0,0,(A20*100/A$14)) -> 0 | C20: =+E20-G20 -> 0 | D20: =IF(C20=0,0,(C20*100/C$14)) -> 0 | E20: {=_xll.BC(DB,_xll.ArrayDPT($AA20:$AE20),_xll.ArrayCOA($AG20:$AZ20),YR,PRD,RV,_xll.ArrayDIM($BB20:$BE20))} -> 0 | F20: =IF(E20=0,0,(E20*100/E$14)) -> 0 | G20: {=_xll.AC(DB,_xll.ArrayDPT($AA20:$AE20),_xll.ArrayCOA($AG20:$AZ20),YR,PRD,_xll.ArrayDIM($BB20:$BE20))} -> 0 | H20: =IF(G20=0,0,(G20*100/G$14)) -> 0 | J20: SALARIES & WAGES - HOUSEKEEPING | L20: {=_xll.ACC(DB,_xll.ArrayDPT($AA20:$AE20),_xll.ArrayCOA($AG20:$AZ20),YR,PRD,_xll.ArrayDIM($BB20:$BE20))} -> 0 | M20: =IF(L20=0,0,(L20*100/L$14)) -> 0 | N20: {=_xll.BCC(DB,_xll.ArrayDPT($AA20:$AE20),_xll.ArrayCOA($AG20:$AZ20),YR,PRD,RV,_xll.ArrayDIM($BB20:$BE20))} -> 0 | O20: =IF(N20=0,0,(N20*100/N$14)) -> 0 | P20: =+N20-L20 -> 0 | Q20: =IF(P20=0,0,(P20*100/P$14)) -> 0 | R20: {=_xll.ACC(DB,_xll.ArrayDPT($AA20:$AE20),_xll.ArrayCOA($AG20:$AZ20),YR-1,PRD,_xll.ArrayDIM($BB20:$BE20))} -> 0 | S20: =IF(R20=0,0,(R20*100/R$14)) -> 0 | AA20: 103 | AB20: 101 | AG20: 42101 | AH20: 42101
A21: {=_xll.AC(DB,_xll.ArrayDPT($AA21:$AE21),_xll.ArrayCOA($AG21:$AZ21),YR-1,PRD,_xll.ArrayDIM($BB21:$BE21))} -> 0 | B21: =IF(A21=0,0,(A21*100/A$14)) -> 0 | C21: =+E21-G21 -> -5863 | D21: =IF(C21=0,0,(C21*100/C$14)) -> 0.074010667 | E21: {=_xll.BC(DB,_xll.ArrayDPT($AA21:$AE21),_xll.ArrayCOA($AG21:$AZ21),YR,PRD,RV,_xll.ArrayDIM($BB21:$BE21))} -> 0 | F21: =IF(E21=0,0,(E21*100/E$14)) -> 0 | G21: {=_xll.AC(DB,_xll.ArrayDPT($AA21:$AE21),_xll.ArrayCOA($AG21:$AZ21),YR,PRD,_xll.ArrayDIM($BB21:$BE21))} -> 5863 | H21: =IF(G21=0,0,(G21*100/G$14)) -> 0.074010667 | J21: PAYROLL TAXES ON SOCIAL SECURITY CONTRIBUTION | L21: {=_xll.ACC(DB,_xll.ArrayDPT($AA21:$AE21),_xll.ArrayCOA($AG21:$AZ21),YR,PRD,_xll.ArrayDIM($BB21:$BE21))} -> 5863 | M21: =IF(L21=0,0,(L21*100/L$14)) -> 0.074010667 | N21: {=_xll.BCC(DB,_xll.ArrayDPT($AA21:$AE21),_xll.ArrayCOA($AG21:$AZ21),YR,PRD,RV,_xll.ArrayDIM($BB21:$BE21))} -> 0 | O21: =IF(N21=0,0,(N21*100/N$14)) -> 0 | P21: =+N21-L21 -> -5863 | Q21: =IF(P21=0,0,(P21*100/P$14)) -> 0.074010667 | R21: {=_xll.ACC(DB,_xll.ArrayDPT($AA21:$AE21),_xll.ArrayCOA($AG21:$AZ21),YR-1,PRD,_xll.ArrayDIM($BB21:$BE21))} -> 0 | S21: =IF(R21=0,0,(R21*100/R$14)) -> 0 | AA21: 103 | AG21: 45005 | AH21: 45005
A22: {=_xll.AC(DB,_xll.ArrayDPT($AA22:$AE22),_xll.ArrayCOA($AG22:$AZ22),YR-1,PRD,_xll.ArrayDIM($BB22:$BE22))} -> 0 | B22: =IF(A22=0,0,(A22*100/A$14)) -> 0 | C22: =+E22-G22 -> 0 | D22: =IF(C22=0,0,(C22*100/C$14)) -> 0 | E22: {=_xll.BC(DB,_xll.ArrayDPT($AA22:$AE22),_xll.ArrayCOA($AG22:$AZ22),YR,PRD,RV,_xll.ArrayDIM($BB22:$BE22))} -> 0 | F22: =IF(E22=0,0,(E22*100/E$14)) -> 0 | G22: {=_xll.AC(DB,_xll.ArrayDPT($AA22:$AE22),_xll.ArrayCOA($AG22:$AZ22),YR,PRD,_xll.ArrayDIM($BB22:$BE22))} -> 0 | H22: =IF(G22=0,0,(G22*100/G$14)) -> 0 | J22: CASUAL & DAILY HIRE | L22: {=_xll.ACC(DB,_xll.ArrayDPT($AA22:$AE22),_xll.ArrayCOA($AG22:$AZ22),YR,PRD,_xll.ArrayDIM($BB22:$BE22))} -> 0 | M22: =IF(L22=0,0,(L22*100/L$14)) -> 0 | N22: {=_xll.BCC(DB,_xll.ArrayDPT($AA22:$AE22),_xll.ArrayCOA($AG22:$AZ22),YR,PRD,RV,_xll.ArrayDIM($BB22:$BE22))} -> 0 | O22: =IF(N22=0,0,(N22*100/N$14)) -> 0 | P22: =+N22-L22 -> 0 | Q22: =IF(P22=0,0,(P22*100/P$14)) -> 0 | R22: {=_xll.ACC(DB,_xll.ArrayDPT($AA22:$AE22),_xll.ArrayCOA($AG22:$AZ22),YR-1,PRD,_xll.ArrayDIM($BB22:$BE22))} -> 0 | S22: =IF(R22=0,0,(R22*100/R$14)) -> 0 | AA22: 103 | AB22: 101 | AG22: 42015 | AH22: 42015
A23: {=_xll.AC(DB,_xll.ArrayDPT($AA23:$AE23),_xll.ArrayCOA($AG23:$AZ23),YR-1,PRD,_xll.ArrayDIM($BB23:$BE23))} -> 0 | B23: =IF(A23=0,0,(A23*100/A$14)) -> 0 | C23: =+E23-G23 -> -4335.94 | D23: =IF(C23=0,0,(C23*100/C$14)) -> 0.054734063 | E23: {=_xll.BC(DB,_xll.ArrayDPT($AA23:$AE23),_xll.ArrayCOA($AG23:$AZ23),YR,PRD,RV,_xll.ArrayDIM($BB23:$BE23))} -> 0 | F23: =IF(E23=0,0,(E23*100/E$14)) -> 0 | G23: {=_xll.AC(DB,_xll.ArrayDPT($AA23:$AE23),_xll.ArrayCOA($AG23:$AZ23),YR,PRD,_xll.ArrayDIM($BB23:$BE23))} -> 4335.94 | H23: =IF(G23=0,0,(G23*100/G$14)) -> 0.054734063 | J23: EXTRA & OVERTIME | L23: {=_xll.ACC(DB,_xll.ArrayDPT($AA23:$AE23),_xll.ArrayCOA($AG23:$AZ23),YR,PRD,_xll.ArrayDIM($BB23:$BE23))} -> 4335.94 | M23: =IF(L23=0,0,(L23*100/L$14)) -> 0.054734063 | N23: {=_xll.BCC(DB,_xll.ArrayDPT($AA23:$AE23),_xll.ArrayCOA($AG23:$AZ23),YR,PRD,RV,_xll.ArrayDIM($BB23:$BE23))} -> 0 | O23: =IF(N23=0,0,(N23*100/N$14)) -> 0 | P23: =+N23-L23 -> -4335.94 | Q23: =IF(P23=0,0,(P23*100/P$14)) -> 0.054734063 | R23: {=_xll.ACC(DB,_xll.ArrayDPT($AA23:$AE23),_xll.ArrayCOA($AG23:$AZ23),YR-1,PRD,_xll.ArrayDIM($BB23:$BE23))} -> 0 | S23: =IF(R23=0,0,(R23*100/R$14)) -> 0 | AA23: 103 | AB23: 101 | AG23: 42011 | AH23: 42011
A24: {=_xll.AC(DB,_xll.ArrayDPT($AA24:$AE24),_xll.ArrayCOA($AG24:$AZ24),YR-1,PRD,_xll.ArrayDIM($BB24:$BE24))} -> 3800 | B24: =IF(A24=0,0,(A24*100/A$14)) -> 0.052417268 | C24: =+E24-G24 -> 0 | D24: =IF(C24=0,0,(C24*100/C$14)) -> 0 | E24: {=_xll.BC(DB,_xll.ArrayDPT($AA24:$AE24),_xll.ArrayCOA($AG24:$AZ24),YR,PRD,RV,_xll.ArrayDIM($BB24:$BE24))} -> 0 | F24: =IF(E24=0,0,(E24*100/E$14)) -> 0 | G24: {=_xll.AC(DB,_xll.ArrayDPT($AA24:$AE24),_xll.ArrayCOA($AG24:$AZ24),YR,PRD,_xll.ArrayDIM($BB24:$BE24))} -> 0 | H24: =IF(G24=0,0,(G24*100/G$14)) -> 0 | J24: OTHER EMPLOYEE BENEFITS | L24: {=_xll.ACC(DB,_xll.ArrayDPT($AA24:$AE24),_xll.ArrayCOA($AG24:$AZ24),YR,PRD,_xll.ArrayDIM($BB24:$BE24))} -> 0 | M24: =IF(L24=0,0,(L24*100/L$14)) -> 0 | N24: {=_xll.BCC(DB,_xll.ArrayDPT($AA24:$AE24),_xll.ArrayCOA($AG24:$AZ24),YR,PRD,RV,_xll.ArrayDIM($BB24:$BE24))} -> 0 | O24: =IF(N24=0,0,(N24*100/N$14)) -> 0 | P24: =+N24-L24 -> 0 | Q24: =IF(P24=0,0,(P24*100/P$14)) -> 0 | R24: {=_xll.ACC(DB,_xll.ArrayDPT($AA24:$AE24),_xll.ArrayCOA($AG24:$AZ24),YR-1,PRD,_xll.ArrayDIM($BB24:$BE24))} -> 3800 | S24: =IF(R24=0,0,(R24*100/R$14)) -> 0.052417268 | AA24: 103 | AB24: 101 | AG24: 46070 | AH24: 46070
A26: =SUM(A16:A25) -> 133133.34 | B26: =IF(A26=0,0,(A26*100/A$14)) -> 1.8364437 | C26: =SUM(C16:C25) -> -137465.61 | D26: =IF(C26=0,0,(C26*100/C$14)) -> 1.7352757 | E26: =SUM(E16:E25) -> 0 | F26: =IF(E26=0,0,(E26*100/E$14)) -> 0 | G26: =SUM(G16:G25) -> 137465.61 | H26: =IF(G26=0,0,(G26*100/G$14)) -> 1.7352757 | J26: TOTAL PAYROLL & EMP. REL. | L26: =SUM(L16:L25) -> 137465.61 | M26: =IF(L26=0,0,(L26*100/L$14)) -> 1.7352757 | N26: =SUM(N16:N25) -> 0 | O26: =IF(N26=0,0,(N26*100/N$14)) -> 0 | P26: =SUM(P16:P25) -> -137465.61 | Q26: =IF(P26=0,0,(P26*100/P$14)) -> 1.7352757 | R26: =SUM(R16:R25) -> 133133.34 | S26: =IF(R26=0,0,(R26*100/R$14)) -> 1.8364437
J27: OTHER EXPENSES
A28: {=_xll.AC(DB,_xll.ArrayDPT($AA28:$AE28),_xll.ArrayCOA($AG28:$AZ28),YR-1,PRD,_xll.ArrayDIM($BB28:$BE28))} -> 0 | B28: =IF(A28=0,0,(A28*100/A$14)) -> 0 | C28: =+E28-G28 -> 0 | D28: =IF(C28=0,0,(C28*100/C$14)) -> 0 | E28: {=_xll.BC(DB,_xll.ArrayDPT($AA28:$AE28),_xll.ArrayCOA($AG28:$AZ28),YR,PRD,RV,_xll.ArrayDIM($BB28:$BE28))} -> 0 | F28: =IF(E28=0,0,(E28*100/E$14)) -> 0 | G28: {=_xll.AC(DB,_xll.ArrayDPT($AA28:$AE28),_xll.ArrayCOA($AG28:$AZ28),YR,PRD,_xll.ArrayDIM($BB28:$BE28))} -> 0 | H28: =IF(G28=0,0,(G28*100/G$14)) -> 0 | J28: TRAVEL AGENCY COMMISSION | L28: {=_xll.ACC(DB,_xll.ArrayDPT($AA28:$AE28),_xll.ArrayCOA($AG28:$AZ28),YR,PRD,_xll.ArrayDIM($BB28:$BE28))} -> 0 | M28: =IF(L28=0,0,(L28*100/L$14)) -> 0 | N28: {=_xll.BCC(DB,_xll.ArrayDPT($AA28:$AE28),_xll.ArrayCOA($AG28:$AZ28),YR,PRD,RV,_xll.ArrayDIM($BB28:$BE28))} -> 0 | O28: =IF(N28=0,0,(N28*100/N$14)) -> 0 | P28: =+N28-L28 -> 0 | Q28: =IF(P28=0,0,(P28*100/P$14)) -> 0 | R28: {=_xll.ACC(DB,_xll.ArrayDPT($AA28:$AE28),_xll.ArrayCOA($AG28:$AZ28),YR-1,PRD,_xll.ArrayDIM($BB28:$BE28))} -> 0 | S28: =IF(R28=0,0,(R28*100/R$14)) -> 0 | AA28: 103 | AG28: 50005 | AH28: 50005
A29: {=_xll.AC(DB,_xll.ArrayDPT($AA29:$AE29),_xll.ArrayCOA($AG29:$AZ29),YR-1,PRD,_xll.ArrayDIM($BB29:$BE29))} -> 24772.01 | B29: =IF(A29=0,0,(A29*100/A$14)) -> 0.34170555 | C29: =+E29-G29 -> -9435.8 | D29: =IF(C29=0,0,(C29*100/C$14)) -> 0.11911135 | E29: {=_xll.BC(DB,_xll.ArrayDPT($AA29:$AE29),_xll.ArrayCOA($AG29:$AZ29),YR,PRD,RV,_xll.ArrayDIM($BB29:$BE29))} -> 0 | F29: =IF(E29=0,0,(E29*100/E$14)) -> 0 | G29: {=_xll.AC(DB,_xll.ArrayDPT($AA29:$AE29),_xll.ArrayCOA($AG29:$AZ29),YR,PRD,_xll.ArrayDIM($BB29:$BE29))} -> 9435.8 | H29: =IF(G29=0,0,(G29*100/G$14)) -> 0.11911135 | J29: INCENTIVES INCENTIVES | L29: {=_xll.ACC(DB,_xll.ArrayDPT($AA29:$AE29),_xll.ArrayCOA($AG29:$AZ29),YR,PRD,_xll.ArrayDIM($BB29:$BE29))} -> 9435.8 | M29: =IF(L29=0,0,(L29*100/L$14)) -> 0.11911135 | N29: {=_xll.BCC(DB,_xll.ArrayDPT($AA29:$AE29),_xll.ArrayCOA($AG29:$AZ29),YR,PRD,RV,_xll.ArrayDIM($BB29:$BE29))} -> 0 | O29: =IF(N29=0,0,(N29*100/N$14)) -> 0 | P29: =+N29-L29 -> -9435.8 | Q29: =IF(P29=0,0,(P29*100/P$14)) -> 0.11911135 | R29: {=_xll.ACC(DB,_xll.ArrayDPT($AA29:$AE29),_xll.ArrayCOA($AG29:$AZ29),YR-1,PRD,_xll.ArrayDIM($BB29:$BE29))} -> 24772.01 | S29: =IF(R29=0,0,(R29*100/R$14)) -> 0.34170555 | AA29: 103 | AG29: 42025 | AH29: 42025
A30: {=_xll.AC(DB,_xll.ArrayDPT($AA30:$AE30),_xll.ArrayCOA($AG30:$AZ30),YR-1,PRD,_xll.ArrayDIM($BB30:$BE30))} -> 0 | B30: =IF(A30=0,0,(A30*100/A$14)) -> 0 | C30: =+E30-G30 -> 0 | D30: =IF(C30=0,0,(C30*100/C$14)) -> 0 | E30: {=_xll.BC(DB,_xll.ArrayDPT($AA30:$AE30),_xll.ArrayCOA($AG30:$AZ30),YR,PRD,RV,_xll.ArrayDIM($BB30:$BE30))} -> 0 | F30: =IF(E30=0,0,(E30*100/E$14)) -> 0 | G30: {=_xll.AC(DB,_xll.ArrayDPT($AA30:$AE30),_xll.ArrayCOA($AG30:$AZ30),YR,PRD,_xll.ArrayDIM($BB30:$BE30))} -> 0 | H30: =IF(G30=0,0,(G30*100/G$14)) -> 0 | J30: RESERVATIONS | L30: {=_xll.ACC(DB,_xll.ArrayDPT($AA30:$AE30),_xll.ArrayCOA($AG30:$AZ30),YR,PRD,_xll.ArrayDIM($BB30:$BE30))} -> 0 | M30: =IF(L30=0,0,(L30*100/L$14)) -> 0 | N30: {=_xll.BCC(DB,_xll.ArrayDPT($AA30:$AE30),_xll.ArrayCOA($AG30:$AZ30),YR,PRD,RV,_xll.ArrayDIM($BB30:$BE30))} -> 0 | O30: =IF(N30=0,0,(N30*100/N$14)) -> 0 | P30: =+N30-L30 -> 0 | Q30: =IF(P30=0,0,(P30*100/P$14)) -> 0 | R30: {=_xll.ACC(DB,_xll.ArrayDPT($AA30:$AE30),_xll.ArrayCOA($AG30:$AZ30),YR-1,PRD,_xll.ArrayDIM($BB30:$BE30))} -> 0 | S30: =IF(R30=0,0,(R30*100/R$14)) -> 0 | AA30: 103 | AG30: 51025 | AH30: 51025
A31: {=_xll.AC(DB,_xll.ArrayDPT($AA31:$AE31),_xll.ArrayCOA($AG31:$AZ31),YR-1,PRD,_xll.ArrayDIM($BB31:$BE31))} -> 0 | B31: =IF(A31=0,0,(A31*100/A$14)) -> 0 | C31: =+E31-G31 -> 0 | D31: =IF(C31=0,0,(C31*100/C$14)) -> 0 | E31: {=_xll.BC(DB,_xll.ArrayDPT($AA31:$AE31),_xll.ArrayCOA($AG31:$AZ31),YR,PRD,RV,_xll.ArrayDIM($BB31:$BE31))} -> 0 | F31: =IF(E31=0,0,(E31*100/E$14)) -> 0 | G31: {=_xll.AC(DB,_xll.ArrayDPT($AA31:$AE31),_xll.ArrayCOA($AG31:$AZ31),YR,PRD,_xll.ArrayDIM($BB31:$BE31))} -> 0 | H31: =IF(G31=0,0,(G31*100/G$14)) -> 0 | J31: CONTRACT SERVICE | L31: {=_xll.ACC(DB,_xll.ArrayDPT($AA31:$AE31),_xll.ArrayCOA($AG31:$AZ31),YR,PRD,_xll.ArrayDIM($BB31:$BE31))} -> 0 | M31: =IF(L31=0,0,(L31*100/L$14)) -> 0 | N31: {=_xll.BCC(DB,_xll.ArrayDPT($AA31:$AE31),_xll.ArrayCOA($AG31:$AZ31),YR,PRD,RV,_xll.ArrayDIM($BB31:$BE31))} -> 0 | O31: =IF(N31=0,0,(N31*100/N$14)) -> 0 | P31: =+N31-L31 -> 0 | Q31: =IF(P31=0,0,(P31*100/P$14)) -> 0 | R31: {=_xll.ACC(DB,_xll.ArrayDPT($AA31:$AE31),_xll.ArrayCOA($AG31:$AZ31),YR-1,PRD,_xll.ArrayDIM($BB31:$BE31))} -> 0 | S31: =IF(R31=0,0,(R31*100/R$14)) -> 0 | AA31: 103 | AG31: 50015 | AH31: 50015
A32: {=_xll.AC(DB,_xll.ArrayDPT($AA32:$AE32),_xll.ArrayCOA($AG32:$AZ32),YR-1,PRD,_xll.ArrayDIM($BB32:$BE32))} -> 0 | B32: =IF(A32=0,0,(A32*100/A$14)) -> 0 | C32: =+E32-G32 -> 0 | D32: =IF(C32=0,0,(C32*100/C$14)) -> 0 | E32: {=_xll.BC(DB,_xll.ArrayDPT($AA32:$AE32),_xll.ArrayCOA($AG32:$AZ32),YR,PRD,RV,_xll.ArrayDIM($BB32:$BE32))} -> 0 | F32: =IF(E32=0,0,(E32*100/E$14)) -> 0 | G32: {=_xll.AC(DB,_xll.ArrayDPT($AA32:$AE32),_xll.ArrayCOA($AG32:$AZ32),YR,PRD,_xll.ArrayDIM($BB32:$BE32))} -> 0 | H32: =IF(G32=0,0,(G32*100/G$14)) -> 0 | J32: LOYALTY PROGRAMMES | L32: {=_xll.ACC(DB,_xll.ArrayDPT($AA32:$AE32),_xll.ArrayCOA($AG32:$AZ32),YR,PRD,_xll.ArrayDIM($BB32:$BE32))} -> 0 | M32: =IF(L32=0,0,(L32*100/L$14)) -> 0 | N32: {=_xll.BCC(DB,_xll.ArrayDPT($AA32:$AE32),_xll.ArrayCOA($AG32:$AZ32),YR,PRD,RV,_xll.ArrayDIM($BB32:$BE32))} -> 0 | O32: =IF(N32=0,0,(N32*100/N$14)) -> 0 | P32: =+N32-L32 -> 0 | Q32: =IF(P32=0,0,(P32*100/P$14)) -> 0 | R32: {=_xll.ACC(DB,_xll.ArrayDPT($AA32:$AE32),_xll.ArrayCOA($AG32:$AZ32),YR-1,PRD,_xll.ArrayDIM($BB32:$BE32))} -> 0 | S32: =IF(R32=0,0,(R32*100/R$14)) -> 0 | AA32: 103 | AG32: 55135 | AH32: 55135
A33: {=_xll.AC(DB,_xll.ArrayDPT($AA33:$AE33),_xll.ArrayCOA($AG33:$AZ33),YR-1,PRD,_xll.ArrayDIM($BB33:$BE33))} -> 0 | B33: =IF(A33=0,0,(A33*100/A$14)) -> 0 | C33: =+E33-G33 -> 0 | D33: =IF(C33=0,0,(C33*100/C$14)) -> 0 | E33: {=_xll.BC(DB,_xll.ArrayDPT($AA33:$AE33),_xll.ArrayCOA($AG33:$AZ33),YR,PRD,RV,_xll.ArrayDIM($BB33:$BE33))} -> 0 | F33: =IF(E33=0,0,(E33*100/E$14)) -> 0 | G33: {=_xll.AC(DB,_xll.ArrayDPT($AA33:$AE33),_xll.ArrayCOA($AG33:$AZ33),YR,PRD,_xll.ArrayDIM($BB33:$BE33))} -> 0 | H33: =IF(G33=0,0,(G33*100/G$14)) -> 0 | J33: LAUNDRY & DRY CLEANING | L33: {=_xll.ACC(DB,_xll.ArrayDPT($AA33:$AE33),_xll.ArrayCOA($AG33:$AZ33),YR,PRD,_xll.ArrayDIM($BB33:$BE33))} -> 0 | M33: =IF(L33=0,0,(L33*100/L$14)) -> 0 | N33: {=_xll.BCC(DB,_xll.ArrayDPT($AA33:$AE33),_xll.ArrayCOA($AG33:$AZ33),YR,PRD,RV,_xll.ArrayDIM($BB33:$BE33))} -> 0 | O33: =IF(N33=0,0,(N33*100/N$14)) -> 0 | P33: =+N33-L33 -> 0 | Q33: =IF(P33=0,0,(P33*100/P$14)) -> 0 | R33: {=_xll.ACC(DB,_xll.ArrayDPT($AA33:$AE33),_xll.ArrayCOA($AG33:$AZ33),YR-1,PRD,_xll.ArrayDIM($BB33:$BE33))} -> 0 | S33: =IF(R33=0,0,(R33*100/R$14)) -> 0 | AA33: 103 | AG33: 50040 | AH33: 50040
A34: {=_xll.AC(DB,_xll.ArrayDPT($AA34:$AE34),_xll.ArrayCOA($AG34:$AZ34),YR-1,PRD,_xll.ArrayDIM($BB34:$BE34))} -> 0 | B34: =IF(A34=0,0,(A34*100/A$14)) -> 0 | C34: =+E34-G34 -> 0 | D34: =IF(C34=0,0,(C34*100/C$14)) -> 0 | E34: {=_xll.BC(DB,_xll.ArrayDPT($AA34:$AE34),_xll.ArrayCOA($AG34:$AZ34),YR,PRD,RV,_xll.ArrayDIM($BB34:$BE34))} -> 0 | F34: =IF(E34=0,0,(E34*100/E$14)) -> 0 | G34: {=_xll.AC(DB,_xll.ArrayDPT($AA34:$AE34),_xll.ArrayCOA($AG34:$AZ34),YR,PRD,_xll.ArrayDIM($BB34:$BE34))} -> 0 | H34: =IF(G34=0,0,(G34*100/G$14)) -> 0 | J34: SUPPLIES - LAUNDRY | L34: {=_xll.ACC(DB,_xll.ArrayDPT($AA34:$AE34),_xll.ArrayCOA($AG34:$AZ34),YR,PRD,_xll.ArrayDIM($BB34:$BE34))} -> 0 | M34: =IF(L34=0,0,(L34*100/L$14)) -> 0 | N34: {=_xll.BCC(DB,_xll.ArrayDPT($AA34:$AE34),_xll.ArrayCOA($AG34:$AZ34),YR,PRD,RV,_xll.ArrayDIM($BB34:$BE34))} -> 0 | O34: =IF(N34=0,0,(N34*100/N$14)) -> 0 | P34: =+N34-L34 -> 0 | Q34: =IF(P34=0,0,(P34*100/P$14)) -> 0 | R34: {=_xll.ACC(DB,_xll.ArrayDPT($AA34:$AE34),_xll.ArrayCOA($AG34:$AZ34),YR-1,PRD,_xll.ArrayDIM($BB34:$BE34))} -> 0 | S34: =IF(R34=0,0,(R34*100/R$14)) -> 0 | AA34: 103 | AG34: 50550 | AH34: 50550
A35: {=_xll.AC(DB,_xll.ArrayDPT($AA35:$AE35),_xll.ArrayCOA($AG35:$AZ35),YR-1,PRD,_xll.ArrayDIM($BB35:$BE35))} -> 0 | B35: =IF(A35=0,0,(A35*100/A$14)) -> 0 | C35: =+E35-G35 -> 0 | D35: =IF(C35=0,0,(C35*100/C$14)) -> 0 | E35: {=_xll.BC(DB,_xll.ArrayDPT($AA35:$AE35),_xll.ArrayCOA($AG35:$AZ35),YR,PRD,RV,_xll.ArrayDIM($BB35:$BE35))} -> 0 | F35: =IF(E35=0,0,(E35*100/E$14)) -> 0 | G35: {=_xll.AC(DB,_xll.ArrayDPT($AA35:$AE35),_xll.ArrayCOA($AG35:$AZ35),YR,PRD,_xll.ArrayDIM($BB35:$BE35))} -> 0 | H35: =IF(G35=0,0,(G35*100/G$14)) -> 0 | J35: EQUIPMENT RENTALS | L35: {=_xll.ACC(DB,_xll.ArrayDPT($AA35:$AE35),_xll.ArrayCOA($AG35:$AZ35),YR,PRD,_xll.ArrayDIM($BB35:$BE35))} -> 0 | M35: =IF(L35=0,0,(L35*100/L$14)) -> 0 | N35: {=_xll.BCC(DB,_xll.ArrayDPT($AA35:$AE35),_xll.ArrayCOA($AG35:$AZ35),YR,PRD,RV,_xll.ArrayDIM($BB35:$BE35))} -> 0 | O35: =IF(N35=0,0,(N35*100/N$14)) -> 0 | P35: =+N35-L35 -> 0 | Q35: =IF(P35=0,0,(P35*100/P$14)) -> 0 | R35: {=_xll.ACC(DB,_xll.ArrayDPT($AA35:$AE35),_xll.ArrayCOA($AG35:$AZ35),YR-1,PRD,_xll.ArrayDIM($BB35:$BE35))} -> 0 | S35: =IF(R35=0,0,(R35*100/R$14)) -> 0 | AA35: 103 | AG35: 50035 | AH35: 50035
A36: {=_xll.AC(DB,_xll.ArrayDPT($AA36:$AE36),_xll.ArrayCOA($AG36:$AZ36),YR-1,PRD,_xll.ArrayDIM($BB36:$BE36))} -> 0 | B36: =IF(A36=0,0,(A36*100/A$14)) -> 0 | C36: =+E36-G36 -> 0 | D36: =IF(C36=0,0,(C36*100/C$14)) -> 0 | E36: {=_xll.BC(DB,_xll.ArrayDPT($AA36:$AE36),_xll.ArrayCOA($AG36:$AZ36),YR,PRD,RV,_xll.ArrayDIM($BB36:$BE36))} -> 0 | F36: =IF(E36=0,0,(E36*100/E$14)) -> 0 | G36: {=_xll.AC(DB,_xll.ArrayDPT($AA36:$AE36),_xll.ArrayCOA($AG36:$AZ36),YR,PRD,_xll.ArrayDIM($BB36:$BE36))} -> 0 | H36: =IF(G36=0,0,(G36*100/G$14)) -> 0 | J36: OE EXPENSES | L36: {=_xll.ACC(DB,_xll.ArrayDPT($AA36:$AE36),_xll.ArrayCOA($AG36:$AZ36),YR,PRD,_xll.ArrayDIM($BB36:$BE36))} -> 0 | M36: =IF(L36=0,0,(L36*100/L$14)) -> 0 | N36: {=_xll.BCC(DB,_xll.ArrayDPT($AA36:$AE36),_xll.ArrayCOA($AG36:$AZ36),YR,PRD,RV,_xll.ArrayDIM($BB36:$BE36))} -> 0 | O36: =IF(N36=0,0,(N36*100/N$14)) -> 0 | P36: =+N36-L36 -> 0 | Q36: =IF(P36=0,0,(P36*100/P$14)) -> 0 | R36: {=_xll.ACC(DB,_xll.ArrayDPT($AA36:$AE36),_xll.ArrayCOA($AG36:$AZ36),YR-1,PRD,_xll.ArrayDIM($BB36:$BE36))} -> 0 | S36: =IF(R36=0,0,(R36*100/R$14)) -> 0
A37: {=_xll.AC(DB,_xll.ArrayDPT($AA37:$AE37),_xll.ArrayCOA($AG37:$AZ37),YR-1,PRD,_xll.ArrayDIM($BB37:$BE37))} -> 0 | B37: =IF(A37=0,0,(A37*100/A$14)) -> 0 | C37: =+E37-G37 -> 0 | D37: =IF(C37=0,0,(C37*100/C$14)) -> 0 | E37: {=_xll.BC(DB,_xll.ArrayDPT($AA37:$AE37),_xll.ArrayCOA($AG37:$AZ37),YR,PRD,RV,_xll.ArrayDIM($BB37:$BE37))} -> 0 | F37: =IF(E37=0,0,(E37*100/E$14)) -> 0 | G37: {=_xll.AC(DB,_xll.ArrayDPT($AA37:$AE37),_xll.ArrayCOA($AG37:$AZ37),YR,PRD,_xll.ArrayDIM($BB37:$BE37))} -> 0 | H37: =IF(G37=0,0,(G37*100/G$14)) -> 0 | J37: - OE EXPENSES - UNIFORMS | L37: {=_xll.ACC(DB,_xll.ArrayDPT($AA37:$AE37),_xll.ArrayCOA($AG37:$AZ37),YR,PRD,_xll.ArrayDIM($BB37:$BE37))} -> 0 | M37: =IF(L37=0,0,(L37*100/L$14)) -> 0 | N37: {=_xll.BCC(DB,_xll.ArrayDPT($AA37:$AE37),_xll.ArrayCOA($AG37:$AZ37),YR,PRD,RV,_xll.ArrayDIM($BB37:$BE37))} -> 0 | O37: =IF(N37=0,0,(N37*100/N$14)) -> 0 | P37: =+N37-L37 -> 0 | Q37: =IF(P37=0,0,(P37*100/P$14)) -> 0 | R37: {=_xll.ACC(DB,_xll.ArrayDPT($AA37:$AE37),_xll.ArrayCOA($AG37:$AZ37),YR-1,PRD,_xll.ArrayDIM($BB37:$BE37))} -> 0 | S37: =IF(R37=0,0,(R37*100/R$14)) -> 0
A38: {=_xll.AC(DB,_xll.ArrayDPT($AA38:$AE38),_xll.ArrayCOA($AG38:$AZ38),YR-1,PRD,_xll.ArrayDIM($BB38:$BE38))} -> 0 | B38: =IF(A38=0,0,(A38*100/A$14)) -> 0 | C38: =+E38-G38 -> 0 | D38: =IF(C38=0,0,(C38*100/C$14)) -> 0 | E38: {=_xll.BC(DB,_xll.ArrayDPT($AA38:$AE38),_xll.ArrayCOA($AG38:$AZ38),YR,PRD,RV,_xll.ArrayDIM($BB38:$BE38))} -> 0 | F38: =IF(E38=0,0,(E38*100/E$14)) -> 0 | G38: {=_xll.AC(DB,_xll.ArrayDPT($AA38:$AE38),_xll.ArrayCOA($AG38:$AZ38),YR,PRD,_xll.ArrayDIM($BB38:$BE38))} -> 0 | H38: =IF(G38=0,0,(G38*100/G$14)) -> 0 | J38: - OE EXPENSES - CHINAWARE | L38: {=_xll.ACC(DB,_xll.ArrayDPT($AA38:$AE38),_xll.ArrayCOA($AG38:$AZ38),YR,PRD,_xll.ArrayDIM($BB38:$BE38))} -> 0 | M38: =IF(L38=0,0,(L38*100/L$14)) -> 0 | N38: {=_xll.BCC(DB,_xll.ArrayDPT($AA38:$AE38),_xll.ArrayCOA($AG38:$AZ38),YR,PRD,RV,_xll.ArrayDIM($BB38:$BE38))} -> 0 | O38: =IF(N38=0,0,(N38*100/N$14)) -> 0 | P38: =+N38-L38 -> 0 | Q38: =IF(P38=0,0,(P38*100/P$14)) -> 0 | R38: {=_xll.ACC(DB,_xll.ArrayDPT($AA38:$AE38),_xll.ArrayCOA($AG38:$AZ38),YR-1,PRD,_xll.ArrayDIM($BB38:$BE38))} -> 0 | S38: =IF(R38=0,0,(R38*100/R$14)) -> 0
A39: {=_xll.AC(DB,_xll.ArrayDPT($AA39:$AE39),_xll.ArrayCOA($AG39:$AZ39),YR-1,PRD,_xll.ArrayDIM($BB39:$BE39))} -> 0 | B39: =IF(A39=0,0,(A39*100/A$14)) -> 0 | C39: =+E39-G39 -> 0 | D39: =IF(C39=0,0,(C39*100/C$14)) -> 0 | E39: {=_xll.BC(DB,_xll.ArrayDPT($AA39:$AE39),_xll.ArrayCOA($AG39:$AZ39),YR,PRD,RV,_xll.ArrayDIM($BB39:$BE39))} -> 0 | F39: =IF(E39=0,0,(E39*100/E$14)) -> 0 | G39: {=_xll.AC(DB,_xll.ArrayDPT($AA39:$AE39),_xll.ArrayCOA($AG39:$AZ39),YR,PRD,_xll.ArrayDIM($BB39:$BE39))} -> 0 | H39: =IF(G39=0,0,(G39*100/G$14)) -> 0 | J39: - OE EXPENSES - GLASSWARE | L39: {=_xll.ACC(DB,_xll.ArrayDPT($AA39:$AE39),_xll.ArrayCOA($AG39:$AZ39),YR,PRD,_xll.ArrayDIM($BB39:$BE39))} -> 0 | M39: =IF(L39=0,0,(L39*100/L$14)) -> 0 | N39: {=_xll.BCC(DB,_xll.ArrayDPT($AA39:$AE39),_xll.ArrayCOA($AG39:$AZ39),YR,PRD,RV,_xll.ArrayDIM($BB39:$BE39))} -> 0 | O39: =IF(N39=0,0,(N39*100/N$14)) -> 0 | P39: =+N39-L39 -> 0 | Q39: =IF(P39=0,0,(P39*100/P$14)) -> 0 | R39: {=_xll.ACC(DB,_xll.ArrayDPT($AA39:$AE39),_xll.ArrayCOA($AG39:$AZ39),YR-1,PRD,_xll.ArrayDIM($BB39:$BE39))} -> 0 | S39: =IF(R39=0,0,(R39*100/R$14)) -> 0 | AA39: 101 | AB39: 103 | AG39: 48010 | AH39: 48010
A40: {=_xll.AC(DB,_xll.ArrayDPT($AA40:$AE40),_xll.ArrayCOA($AG40:$AZ40),YR-1,PRD,_xll.ArrayDIM($BB40:$BE40))} -> 0 | B40: =IF(A40=0,0,(A40*100/A$14)) -> 0 | C40: =+E40-G40 -> 0 | D40: =IF(C40=0,0,(C40*100/C$14)) -> 0 | E40: {=_xll.BC(DB,_xll.ArrayDPT($AA40:$AE40),_xll.ArrayCOA($AG40:$AZ40),YR,PRD,RV,_xll.ArrayDIM($BB40:$BE40))} -> 0 | F40: =IF(E40=0,0,(E40*100/E$14)) -> 0 | G40: {=_xll.AC(DB,_xll.ArrayDPT($AA40:$AE40),_xll.ArrayCOA($AG40:$AZ40),YR,PRD,_xll.ArrayDIM($BB40:$BE40))} -> 0 | H40: =IF(G40=0,0,(G40*100/G$14)) -> 0 | J40: - OE EXPENSES - SILVERWARE | L40: {=_xll.ACC(DB,_xll.ArrayDPT($AA40:$AE40),_xll.ArrayCOA($AG40:$AZ40),YR,PRD,_xll.ArrayDIM($BB40:$BE40))} -> 0 | M40: =IF(L40=0,0,(L40*100/L$14)) -> 0 | N40: {=_xll.BCC(DB,_xll.ArrayDPT($AA40:$AE40),_xll.ArrayCOA($AG40:$AZ40),YR,PRD,RV,_xll.ArrayDIM($BB40:$BE40))} -> 0 | O40: =IF(N40=0,0,(N40*100/N$14)) -> 0 | P40: =+N40-L40 -> 0 | Q40: =IF(P40=0,0,(P40*100/P$14)) -> 0 | R40: {=_xll.ACC(DB,_xll.ArrayDPT($AA40:$AE40),_xll.ArrayCOA($AG40:$AZ40),YR-1,PRD,_xll.ArrayDIM($BB40:$BE40))} -> 0 | S40: =IF(R40=0,0,(R40*100/R$14)) -> 0
A41: {=_xll.AC(DB,_xll.ArrayDPT($AA41:$AE41),_xll.ArrayCOA($AG41:$AZ41),YR-1,PRD,_xll.ArrayDIM($BB41:$BE41))} -> 0 | B41: =IF(A41=0,0,(A41*100/A$14)) -> 0 | C41: =+E41-G41 -> 0 | D41: =IF(C41=0,0,(C41*100/C$14)) -> 0 | E41: {=_xll.BC(DB,_xll.ArrayDPT($AA41:$AE41),_xll.ArrayCOA($AG41:$AZ41),YR,PRD,RV,_xll.ArrayDIM($BB41:$BE41))} -> 0 | F41: =IF(E41=0,0,(E41*100/E$14)) -> 0 | G41: {=_xll.AC(DB,_xll.ArrayDPT($AA41:$AE41),_xll.ArrayCOA($AG41:$AZ41),YR,PRD,_xll.ArrayDIM($BB41:$BE41))} -> 0 | H41: =IF(G41=0,0,(G41*100/G$14)) -> 0 | J41: - OE EXPENSES - LINEN | L41: {=_xll.ACC(DB,_xll.ArrayDPT($AA41:$AE41),_xll.ArrayCOA($AG41:$AZ41),YR,PRD,_xll.ArrayDIM($BB41:$BE41))} -> 0 | M41: =IF(L41=0,0,(L41*100/L$14)) -> 0 | N41: {=_xll.BCC(DB,_xll.ArrayDPT($AA41:$AE41),_xll.ArrayCOA($AG41:$AZ41),YR,PRD,RV,_xll.ArrayDIM($BB41:$BE41))} -> 0 | O41: =IF(N41=0,0,(N41*100/N$14)) -> 0 | P41: =+N41-L41 -> 0 | Q41: =IF(P41=0,0,(P41*100/P$14)) -> 0 | R41: {=_xll.ACC(DB,_xll.ArrayDPT($AA41:$AE41),_xll.ArrayCOA($AG41:$AZ41),YR-1,PRD,_xll.ArrayDIM($BB41:$BE41))} -> 0 | S41: =IF(R41=0,0,(R41*100/R$14)) -> 0
A42: {=_xll.AC(DB,_xll.ArrayDPT($AA42:$AE42),_xll.ArrayCOA($AG42:$AZ42),YR-1,PRD,_xll.ArrayDIM($BB42:$BE42))} -> 0 | B42: =IF(A42=0,0,(A42*100/A$14)) -> 0 | C42: =+E42-G42 -> 0 | D42: =IF(C42=0,0,(C42*100/C$14)) -> 0 | E42: {=_xll.BC(DB,_xll.ArrayDPT($AA42:$AE42),_xll.ArrayCOA($AG42:$AZ42),YR,PRD,RV,_xll.ArrayDIM($BB42:$BE42))} -> 0 | F42: =IF(E42=0,0,(E42*100/E$14)) -> 0 | G42: {=_xll.AC(DB,_xll.ArrayDPT($AA42:$AE42),_xll.ArrayCOA($AG42:$AZ42),YR,PRD,_xll.ArrayDIM($BB42:$BE42))} -> 0 | H42: =IF(G42=0,0,(G42*100/G$14)) -> 0 | J42: - OE EXPENSES - OE OTHER | L42: {=_xll.ACC(DB,_xll.ArrayDPT($AA42:$AE42),_xll.ArrayCOA($AG42:$AZ42),YR,PRD,_xll.ArrayDIM($BB42:$BE42))} -> 0 | M42: =IF(L42=0,0,(L42*100/L$14)) -> 0 | N42: {=_xll.BCC(DB,_xll.ArrayDPT($AA42:$AE42),_xll.ArrayCOA($AG42:$AZ42),YR,PRD,RV,_xll.ArrayDIM($BB42:$BE42))} -> 0 | O42: =IF(N42=0,0,(N42*100/N$14)) -> 0 | P42: =+N42-L42 -> 0 | Q42: =IF(P42=0,0,(P42*100/P$14)) -> 0 | R42: {=_xll.ACC(DB,_xll.ArrayDPT($AA42:$AE42),_xll.ArrayCOA($AG42:$AZ42),YR-1,PRD,_xll.ArrayDIM($BB42:$BE42))} -> 0 | S42: =IF(R42=0,0,(R42*100/R$14)) -> 0
